Workbook

Sheet Árbol de navegación
A1: Árbol de navegación por grupo, categoría y grupo de interés
A2: Nivel 1 = grupo de audiencia · Nivel 2 = categoría · Nivel 3 = grupo de la categoría. Los conteos se calculan desde cada hoja.
A4: Nivel 1 | B4: Nivel 2 · Categoría | C4: Nivel 3 · Grupo | D4: Páginas
A5: Contribuyentes | D5: =COUNTA(Contribuyentes!$G$5:$G$357)
B6: NIT sin Obligaciones | D6: =COUNTIF(Contribuyentes!$A$5:$A$357,B6)
C7: Todos los grupos | D7: =COUNTIFS(Contribuyentes!$A$5:$A$357,$B$6,Contribuyentes!$B$5:$B$357,C7)
B8: Pequeños Contribuyentes | D8: =COUNTIF(Contribuyentes!$A$5:$A$357,B8)
C9: Todos los grupos | D9: =COUNTIFS(Contribuyentes!$A$5:$A$357,$B$8,Contribuyentes!$B$5:$B$357,C9)
C10: Pequeño Contribuyente | D10: =COUNTIFS(Contribuyentes!$A$5:$A$357,$B$8,Contribuyentes!$B$5:$B$357,C10)
C11: Primario | D11: =COUNTIFS(Contribuyentes!$A$5:$A$357,$B$8,Contribuyentes!$B$5:$B$357,C11)
C12: Pecuario | D12: =COUNTIFS(Contribuyentes!$A$5:$A$357,$B$8,Contribuyentes!$B$5:$B$357,C12)
B13: Contribuyente General | D13: =COUNTIF(Contribuyentes!$A$5:$A$357,B13)
C14: Todos los grupos | D14: =COUNTIFS(Contribuyentes!$A$5:$A$357,$B$13,Contribuyentes!$B$5:$B$357,C14)
C15: Contribuyente General | D15: =COUNTIFS(Contribuyentes!$A$5:$A$357,$B$13,Contribuyentes!$B$5:$B$357,C15)
C16: Rep. Legales | D16: =COUNTIFS(Contribuyentes!$A$5:$A$357,$B$13,Contribuyentes!$B$5:$B$357,C16)
B17: Contribuyentes Especiales | D17: =COUNTIF(Contribuyentes!$A$5:$A$357,B17)
C18: Todos los grupos | D18: =COUNTIFS(Contribuyentes!$A$5:$A$357,$B$17,Contribuyentes!$B$5:$B$357,C18)
C19: Medianos | D19: =COUNTIFS(Contribuyentes!$A$5:$A$357,$B$17,Contribuyentes!$B$5:$B$357,C19)
C20: Grandes | D20: =COUNTIFS(Contribuyentes!$A$5:$A$357,$B$17,Contribuyentes!$B$5:$B$357,C20)
C21: Rep. Legales | D21: =COUNTIFS(Contribuyentes!$A$5:$A$357,$B$17,Contribuyentes!$B$5:$B$357,C21)
B22: Trámites comunes | D22: =COUNTIF(Contribuyentes!$A$5:$A$357,B22)
C23: Todos los grupos | D23: =COUNTIFS(Contribuyentes!$A$5:$A$357,$B$22,Contribuyentes!$B$5:$B$357,C23)
A24: Operadores de comercio exterior | D24: =COUNTA('Operadores de comercio exterior'!$F$5:$F$174)
B25: Importadores y Exportadores | D25: =COUNTIF('Operadores de comercio exterior'!$A$5:$A$174,B25)
C26: Todos los grupos | D26: =COUNTIFS('Operadores de comercio exterior'!$A$5:$A$174,$B$25,'Operadores de comercio exterior'!$B$5:$B$174,C26)
C27: Importadores | D27: =COUNTIFS('Operadores de comercio exterior'!$A$5:$A$174,$B$25,'Operadores de comercio exterior'!$B$5:$B$174,C27)
C28: OEA | D28: =COUNTIFS('Operadores de comercio exterior'!$A$5:$A$174,$B$25,'Operadores de comercio exterior'!$B$5:$B$174,C28)
C29: Exportadores | D29: =COUNTIFS('Operadores de comercio exterior'!$A$5:$A$174,$B$25,'Operadores de comercio exterior'!$B$5:$B$174,C29)
B30: Auxiliares de la Función Pública Aduanera | D30: =COUNTIF('Operadores de comercio exterior'!$A$5:$A$174,B30)
C31: Todos los grupos | D31: =COUNTIFS('Operadores de comercio exterior'!$A$5:$A$174,$B$30,'Operadores de comercio exterior'!$B$5:$B$174,C31)
C32: Courier | D32: =COUNTIFS('Operadores de comercio exterior'!$A$5:$A$174,$B$30,'Operadores de comercio exterior'!$B$5:$B$174,C32)
C33: Consolidadores y Desconsolidadores de Carga | D33: =COUNTIFS('Operadores de comercio exterior'!$A$5:$A$174,$B$30,'Operadores de comercio exterior'!$B$5:$B$174,C33)
C34: Almacenes Fiscales | D34: =COUNTIFS('Operadores de comercio exterior'!$A$5:$A$174,$B$30,'Operadores de comercio exterior'!$B$5:$B$174,C34)
C35: Almacenadoras | D35: =COUNTIFS('Operadores de comercio exterior'!$A$5:$A$174,$B$30,'Operadores de comercio exterior'!$B$5:$B$174,C35)
C36: Depósitos Aduaneros | D36: =COUNTIFS('Operadores de comercio exterior'!$A$5:$A$174,$B$30,'Operadores de comercio exterior'!$B$5:$B$174,C36)
C37: ZDEEP | D37: =COUNTIFS('Operadores de comercio exterior'!$A$5:$A$174,$B$30,'Operadores de comercio exterior'!$B$5:$B$174,C37)
C38: Agentes Aduaneros | D38: =COUNTIFS('Operadores de comercio exterior'!$A$5:$A$174,$B$30,'Operadores de comercio exterior'!$B$5:$B$174,C38)
C39: Transportistas | D39: =COUNTIFS('Operadores de comercio exterior'!$A$5:$A$174,$B$30,'Operadores de comercio exterior'!$B$5:$B$174,C39)
C40: Apoderado Especial Aduanero | D40: =COUNTIFS('Operadores de comercio exterior'!$A$5:$A$174,$B$30,'Operadores de comercio exterior'!$B$5:$B$174,C40)
B41: Trámites comunes | D41: =COUNTIF('Operadores de comercio exterior'!$A$5:$A$174,B41)
C42: Todos los grupos | D42: =COUNTIFS('Operadores de comercio exterior'!$A$5:$A$174,$B$41,'Operadores de comercio exterior'!$B$5:$B$174,C42)
A43: Profesionales | D43: =COUNTA(Profesionales!$F$5:$F$94)
B44: Terceras Personas | D44: =COUNTIF(Profesionales!$A$5:$A$94,B44)
C45: Todos los grupos | D45: =COUNTIFS(Profesionales!$A$5:$A$94,$B$44,Profesionales!$B$5:$B$94,C45)
C46: Gestores Tributarios | D46: =COUNTIFS(Profesionales!$A$5:$A$94,$B$44,Profesionales!$B$5:$B$94,C46)
C47: Auxiliar Tributario | D47: =COUNTIFS(Profesionales!$A$5:$A$94,$B$44,Profesionales!$B$5:$B$94,C47)
C48: Abogados y Notarios | D48: =COUNTIFS(Profesionales!$A$5:$A$94,$B$44,Profesionales!$B$5:$B$94,C48)
C49: Peritos Contadores | D49: =COUNTIFS(Profesionales!$A$5:$A$94,$B$44,Profesionales!$B$5:$B$94,C49)
C50: Auditores | D50: =COUNTIFS(Profesionales!$A$5:$A$94,$B$44,Profesionales!$B$5:$B$94,C50)
A51: Organismos especiales | D51: =COUNTA('Organismos especiales'!$F$5:$F$137)
B52: Exentos | D52: =COUNTIF('Organismos especiales'!$A$5:$A$137,B52)
C53: Todos los grupos | D53: =COUNTIFS('Organismos especiales'!$A$5:$A$137,$B$52,'Organismos especiales'!$B$5:$B$137,C53)
C54: Constitucionales | D54: =COUNTIFS('Organismos especiales'!$A$5:$A$137,$B$52,'Organismos especiales'!$B$5:$B$137,C54)
C55: No Lucrativos | D55: =COUNTIFS('Organismos especiales'!$A$5:$A$137,$B$52,'Organismos especiales'!$B$5:$B$137,C55)
C56: Decreto | D56: =COUNTIFS('Organismos especiales'!$A$5:$A$137,$B$52,'Organismos especiales'!$B$5:$B$137,C56)
C57: ZOLIC | D57: =COUNTIFS('Organismos especiales'!$A$5:$A$137,$B$52,'Organismos especiales'!$B$5:$B$137,C57)
C58: Municipalidades | D58: =COUNTIFS('Organismos especiales'!$A$5:$A$137,$B$52,'Organismos especiales'!$B$5:$B$137,C58)
B59: Entidades del Estado | D59: =COUNTIF('Organismos especiales'!$A$5:$A$137,B59)
C60: Todos los grupos | D60: =COUNTIFS('Organismos especiales'!$A$5:$A$137,$B$59,'Organismos especiales'!$B$5:$B$137,C60)
C61: Organismo Judicial | D61: =COUNTIFS('Organismos especiales'!$A$5:$A$137,$B$59,'Organismos especiales'!$B$5:$B$137,C61)
C62: Ministerio Público | D62: =COUNTIFS('Organismos especiales'!$A$5:$A$137,$B$59,'Organismos especiales'!$B$5:$B$137,C62)
C63: SENABED / CONABED | D63: =COUNTIFS('Organismos especiales'!$A$5:$A$137,$B$59,'Organismos especiales'!$B$5:$B$137,C63)
C64: Procuraduría de los Derechos Humanos | D64: =COUNTIFS('Organismos especiales'!$A$5:$A$137,$B$59,'Organismos especiales'!$B$5:$B$137,C64)
B65: Trámites comunes | D65: =COUNTIF('Organismos especiales'!$A$5:$A$137,B65)
C66: Todos los grupos | D66: =COUNTIFS('Organismos especiales'!$A$5:$A$137,$B$65,'Organismos especiales'!$B$5:$B$137,C66)
A67: Institucional – Transversal | D67: =COUNTA('Institucional – Transversal'!$E$5:$E$122)
A68: Total de filas | D68: =SUMIF($A$5:$A$67,"<>",$D$5:$D$67)
A69: Una misma página puede aparecer en varias hojas o grupos cuando la usan distintos grupos de interés.

Sheet Descripciones
A1: Descripciones de categorías y grupos
A2: Para qué sirve cada nivel desde el portal SAT y la base legal de referencia (verificar contra la versión vigente de cada ley).
A4: Nivel 1 | B4: Categoría | C4: Grupo | D4: Para quién es | E4: Base legal de referencia | F4: Páginas
A5: Contribuyentes | D5: Personas y empresas inscritas en el RTU: inscripción, declaraciones, facturas, vehículos, devoluciones y más. | E5: Código Tributario (Decreto 6-91): Registro Tributario Unificado. | F5: =COUNTA(Contribuyentes!$G$5:$G$357)
A6: Contribuyentes | B6: NIT sin Obligaciones | D6: Personas con NIT que no están afiliadas a impuestos: asalariados, personas que compran bienes o hacen trámites de vehículos y profesionales que registran su título. | E6: Código Tributario (RTU); Ley de Actualización Tributaria (Decreto 10-2012), ISR de rentas del trabajo. | F6: =COUNTIF(Contribuyentes!$A$5:$A$357,B6)
A7: Contribuyentes | B7: Pequeños Contribuyentes | D7: Contribuyentes de regímenes simplificados: pequeño contribuyente y los nuevos regímenes del sector primario y pecuario. | E7: Ley del IVA (Decreto 27-92), Régimen de Pequeño Contribuyente; Decreto 31-2024. | F7: =COUNTIF(Contribuyentes!$A$5:$A$357,B7)
A8: Contribuyentes | B8: Pequeños Contribuyentes | C8: Pequeño Contribuyente | D8: Personas con ingresos anuales de hasta Q150,000 que pagan una tarifa única sobre sus ventas (incluye el Régimen Electrónico). | E8: Ley del IVA (Decreto 27-92), Régimen de Pequeño Contribuyente; Decreto 7-2019 (régimen electrónico). | F8: =COUNTIFS(Contribuyentes!$A$5:$A$357,B8,Contribuyentes!$B$5:$B$357,C8)
A9: Contribuyentes | B9: Pequeños Contribuyentes | C9: Primario | D9: Productores agrícolas y artesanales del sector primario inscritos en el régimen especial, con pago del Impuesto a la Confianza Tributaria (ICT). | E9: Ley para la Integración del Sector Productivo Primario y Agropecuario (Decreto 31-2024). | F9: =COUNTIFS(Contribuyentes!$A$5:$A$357,B9,Contribuyentes!$B$5:$B$357,C9)
A10: Contribuyentes | B10: Pequeños Contribuyentes | C10: Pecuario | D10: Productores e intermediarios de ganado, acuicultura y apicultura sin transformación industrial, inscritos en el régimen pecuario (ICT). | E10: Decreto 31-2024, régimen pecuario. | F10: =COUNTIFS(Contribuyentes!$A$5:$A$357,B10,Contribuyentes!$B$5:$B$357,C10)
A11: Contribuyentes | B11: Contribuyente General | D11: Contribuyentes del Régimen General del IVA y del ISR de actividades lucrativas (sobre utilidades u opcional simplificado), incluidas personas jurídicas y entes. | E11: Ley del IVA (Decreto 27-92); Ley de Actualización Tributaria (Decreto 10-2012). | F11: =COUNTIF(Contribuyentes!$A$5:$A$357,B11)
A12: Contribuyentes | B12: Contribuyente General | C12: Contribuyente General | D12: Personas individuales y jurídicas con negocio en el Régimen General. | E12: Decreto 27-92 y Decreto 10-2012. | F12: =COUNTIFS(Contribuyentes!$A$5:$A$357,B12,Contribuyentes!$B$5:$B$357,C12)
A13: Contribuyentes | B13: Contribuyente General | C13: Rep. Legales | D13: Representantes legales que hacen gestiones en nombre de personas jurídicas. | E13: Código Tributario, responsables por representación; Código de Comercio. | F13: =COUNTIFS(Contribuyentes!$A$5:$A$357,B13,Contribuyentes!$B$5:$B$357,C13)
A14: Contribuyentes | B14: Contribuyentes Especiales | D14: Contribuyentes calificados por la SAT como especiales por su volumen de operaciones; atención en gerencias especializadas. | E14: Calificación por resolución de la SAT (Ley Orgánica de la SAT, Decreto 1-98). | F14: =COUNTIF(Contribuyentes!$A$5:$A$357,B14)
A15: Contribuyentes | B15: Contribuyentes Especiales | C15: Medianos | D15: Contribuyentes especiales medianos. | E15: Resolución de calificación de la SAT. | F15: =COUNTIFS(Contribuyentes!$A$5:$A$357,B15,Contribuyentes!$B$5:$B$357,C15)
A16: Contribuyentes | B16: Contribuyentes Especiales | C16: Grandes | D16: Contribuyentes especiales grandes. | E16: Resolución de calificación de la SAT. | F16: =COUNTIFS(Contribuyentes!$A$5:$A$357,B16,Contribuyentes!$B$5:$B$357,C16)
A17: Contribuyentes | B17: Contribuyentes Especiales | C17: Rep. Legales | D17: Representantes legales de contribuyentes especiales. | E17: Código Tributario, responsables por representación. | F17: =COUNTIFS(Contribuyentes!$A$5:$A$357,B17,Contribuyentes!$B$5:$B$357,C17)
A18: Operadores de comercio exterior | D18: Personas que importan, exportan o prestan servicios en las operaciones aduaneras. | E18: CAUCA y RECAUCA; Ley Nacional de Aduanas (Decreto 14-2013). | F18: =COUNTA('Operadores de comercio exterior'!$F$5:$F$174)
A19: Operadores de comercio exterior | B19: Importadores y Exportadores | D19: Personas y empresas que importan o exportan mercancías. | E19: CAUCA y RECAUCA; Ley del IVA (devolución de crédito fiscal). | F19: =COUNTIF('Operadores de comercio exterior'!$A$5:$A$174,B19)
A20: Operadores de comercio exterior | B20: Importadores y Exportadores | C20: Importadores | D20: Quienes ingresan mercancías o vehículos al país. | E20: CAUCA y RECAUCA. | F20: =COUNTIFS('Operadores de comercio exterior'!$A$5:$A$174,B20,'Operadores de comercio exterior'!$B$5:$B$174,C20)
A21: Operadores de comercio exterior | B21: Importadores y Exportadores | C21: OEA | D21: Operadores Económicos Autorizados: empresas certificadas por cumplir estándares de seguridad y bajo riesgo. | E21: CAUCA y RECAUCA; programa OEA de la SAT. | F21: =COUNTIFS('Operadores de comercio exterior'!$A$5:$A$174,B21,'Operadores de comercio exterior'!$B$5:$B$174,C21)
A22: Operadores de comercio exterior | B22: Importadores y Exportadores | C22: Exportadores | D22: Quienes venden mercancías al exterior: registro de exportadores y devolución del crédito fiscal del IVA. | E22: Ley del IVA (Decreto 27-92), regímenes de devolución de crédito fiscal. | F22: =COUNTIFS('Operadores de comercio exterior'!$A$5:$A$174,B22,'Operadores de comercio exterior'!$B$5:$B$174,C22)
A23: Operadores de comercio exterior | B23: Auxiliares de la Función Pública Aduanera | D23: Personas autorizadas por la SAT que intervienen en las operaciones aduaneras. | E23: CAUCA y RECAUCA, auxiliares de la función pública aduanera; Decreto 14-2013. | F23: =COUNTIF('Operadores de comercio exterior'!$A$5:$A$174,B23)
A24: Operadores de comercio exterior | B24: Auxiliares de la Función Pública Aduanera | C24: Courier | D24: Empresas de entrega rápida. | E24: RECAUCA. | F24: =COUNTIFS('Operadores de comercio exterior'!$A$5:$A$174,B24,'Operadores de comercio exterior'!$B$5:$B$174,C24)
A25: Operadores de comercio exterior | B25: Auxiliares de la Función Pública Aduanera | C25: Consolidadores y Desconsolidadores de Carga | D25: Agrupan o separan carga de varios consignatarios. | E25: RECAUCA. | F25: =COUNTIFS('Operadores de comercio exterior'!$A$5:$A$174,B25,'Operadores de comercio exterior'!$B$5:$B$174,C25)
A26: Operadores de comercio exterior | B26: Auxiliares de la Función Pública Aduanera | C26: Almacenes Fiscales | D26: Depositarios aduaneros que almacenan mercancías bajo control aduanero. | E26: RECAUCA. | F26: =COUNTIFS('Operadores de comercio exterior'!$A$5:$A$174,B26,'Operadores de comercio exterior'!$B$5:$B$174,C26)
A27: Operadores de comercio exterior | B27: Auxiliares de la Función Pública Aduanera | C27: Almacenadoras | D27: Almacenes generales de depósito autorizados. | E27: RECAUCA. | F27: =COUNTIFS('Operadores de comercio exterior'!$A$5:$A$174,B27,'Operadores de comercio exterior'!$B$5:$B$174,C27)
A28: Operadores de comercio exterior | B28: Auxiliares de la Función Pública Aduanera | C28: Depósitos Aduaneros | D28: Depósitos autorizados para mercancías en régimen suspensivo. | E28: RECAUCA. | F28: =COUNTIFS('Operadores de comercio exterior'!$A$5:$A$174,B28,'Operadores de comercio exterior'!$B$5:$B$174,C28)
A29: Operadores de comercio exterior | B29: Auxiliares de la Función Pública Aduanera | C29: ZDEEP | D29: Desarrolladores de Zonas de Desarrollo Económico Especial Públicas, registrados como auxiliares. | E29: Decreto 22-73 (ZOLIC), reformado por Decreto 30-2008. | F29: =COUNTIFS('Operadores de comercio exterior'!$A$5:$A$174,B29,'Operadores de comercio exterior'!$B$5:$B$174,C29)
A30: Operadores de comercio exterior | B30: Auxiliares de la Función Pública Aduanera | C30: Agentes Aduaneros | D30: Profesionales autorizados para presentar declaraciones de mercancías por cuenta de terceros. | E30: CAUCA y RECAUCA. | F30: =COUNTIFS('Operadores de comercio exterior'!$A$5:$A$174,B30,'Operadores de comercio exterior'!$B$5:$B$174,C30)
A31: Operadores de comercio exterior | B31: Auxiliares de la Función Pública Aduanera | C31: Transportistas | D31: Transportistas aduaneros: manifiestos, marchamo y tránsito. | E31: CAUCA y RECAUCA. | F31: =COUNTIFS('Operadores de comercio exterior'!$A$5:$A$174,B31,'Operadores de comercio exterior'!$B$5:$B$174,C31)
A32: Operadores de comercio exterior | B32: Auxiliares de la Función Pública Aduanera | C32: Apoderado Especial Aduanero | D32: Representante del importador o exportador en sus propias operaciones. | E32: Ley Nacional de Aduanas (Decreto 14-2013). | F32: =COUNTIFS('Operadores de comercio exterior'!$A$5:$A$174,B32,'Operadores de comercio exterior'!$B$5:$B$174,C32)
A33: Profesionales | D33: Personas que hacen gestiones ante la SAT por cuenta de otros. | F33: =COUNTA(Profesionales!$F$5:$F$94)
A34: Profesionales | B34: Terceras Personas | D34: Terceras personas autorizadas o registradas ante la SAT. | F34: =COUNTIF(Profesionales!$A$5:$A$94,B34)
A35: Profesionales | B35: Terceras Personas | C35: Gestores Tributarios | D35: Personas autorizadas por la SAT para hacer gestiones de terceros, principalmente de vehículos. | E35: Registro y autorización de la SAT. | F35: =COUNTIFS(Profesionales!$A$5:$A$94,B35,Profesionales!$B$5:$B$94,C35)
A36: Profesionales | B36: Terceras Personas | C36: Auxiliar Tributario | D36: Auxiliares de los gestores tributarios. | E36: Registro y autorización de la SAT. | F36: =COUNTIFS(Profesionales!$A$5:$A$94,B36,Profesionales!$B$5:$B$94,C36)
A37: Profesionales | B37: Terceras Personas | C37: Abogados y Notarios | D37: Registro de abogados y notarios, avisos notariales, traspasos electrónicos y especies fiscales. | E37: Código de Notariado (Decreto 314); Ley del Impuesto de Timbres Fiscales (Decreto 37-92). | F37: =COUNTIFS(Profesionales!$A$5:$A$94,B37,Profesionales!$B$5:$B$94,C37)
A38: Profesionales | B38: Terceras Personas | C38: Peritos Contadores | D38: Contadores inscritos que llevan la contabilidad de los contribuyentes. | E38: Decreto 10-2012 (contabilidad); Código de Comercio. | F38: =COUNTIFS(Profesionales!$A$5:$A$94,B38,Profesionales!$B$5:$B$94,C38)
A39: Profesionales | B39: Terceras Personas | C39: Auditores | D39: Contadores públicos y auditores que emiten dictámenes ante la SAT. | E39: Decreto 10-2012; Ley del IVA (dictamen para devolución de crédito fiscal). | F39: =COUNTIFS(Profesionales!$A$5:$A$94,B39,Profesionales!$B$5:$B$94,C39)
A40: Organismos especiales | D40: Entidades con régimen especial de exención y entidades del Estado. | F40: =COUNTA('Organismos especiales'!$F$5:$F$137)
A41: Organismos especiales | B41: Exentos | D41: Entidades exentas de impuestos según la Constitución o leyes específicas. | E41: Constitución Política; Decreto 10-2012, art. 11 (rentas exentas). | F41: =COUNTIF('Organismos especiales'!$A$5:$A$137,B41)
A42: Organismos especiales | B42: Exentos | C42: Constitucionales | D42: Exención que da la Constitución: universidades, centros educativos, iglesias y deporte federado. | E42: Constitución Política, arts. 37, 88, 91 y 92. | F42: =COUNTIFS('Organismos especiales'!$A$5:$A$137,B42,'Organismos especiales'!$B$5:$B$137,C42)
A43: Organismos especiales | B43: Exentos | C43: No Lucrativos | D43: Asociaciones, fundaciones, ONG, organizaciones comunitarias y sindicatos sin fines de lucro. | E43: Decreto 10-2012, art. 11; Ley de ONG para el Desarrollo. | F43: =COUNTIFS('Organismos especiales'!$A$5:$A$137,B43,'Organismos especiales'!$B$5:$B$137,C43)
A44: Organismos especiales | B44: Exentos | C44: Decreto | D44: Exentos por leyes específicas: cooperativas, maquilas, zonas francas, partidos políticos y misiones diplomáticas. | E44: Decretos 82-78, 29-89, 65-89 y 1-85; convenciones internacionales. | F44: =COUNTIFS('Organismos especiales'!$A$5:$A$137,B44,'Organismos especiales'!$B$5:$B$137,C44)
A45: Organismos especiales | B45: Exentos | C45: ZOLIC | D45: Usuarios de la Zona Libre de Industria y Comercio Santo Tomás de Castilla. | E45: Ley Orgánica de la ZOLIC (Decreto 22-73). | F45: =COUNTIFS('Organismos especiales'!$A$5:$A$137,B45,'Organismos especiales'!$B$5:$B$137,C45)
A46: Organismos especiales | B46: Exentos | C46: Municipalidades | D46: Municipalidades y sus gestiones de RTU, vehículos, FEL y retenciones. | E46: Constitución, art. 253 (autonomía); Decreto 10-2012, art. 11. | F46: =COUNTIFS('Organismos especiales'!$A$5:$A$137,B46,'Organismos especiales'!$B$5:$B$137,C46)
A47: Organismos especiales | B47: Entidades del Estado | D47: Entidades del Estado que piden gestiones a la SAT o coordinan con ella. | F47: =COUNTIF('Organismos especiales'!$A$5:$A$137,B47)
A48: Organismos especiales | B48: Entidades del Estado | C48: Organismo Judicial | D48: Órdenes judiciales sobre vehículos y registros. | F48: =COUNTIFS('Organismos especiales'!$A$5:$A$137,B48,'Organismos especiales'!$B$5:$B$137,C48)
A49: Organismos especiales | B49: Entidades del Estado | C49: Ministerio Público | D49: Activación e inactivación de vehículos por orden del MP. | F49: =COUNTIFS('Organismos especiales'!$A$5:$A$137,B49,'Organismos especiales'!$B$5:$B$137,C49)
A50: Organismos especiales | B50: Entidades del Estado | C50: SENABED / CONABED | D50: Bienes en extinción de dominio. | E50: Ley de Extinción de Dominio (Decreto 55-2010). | F50: =COUNTIFS('Organismos especiales'!$A$5:$A$137,B50,'Organismos especiales'!$B$5:$B$137,C50)
A51: Organismos especiales | B51: Entidades del Estado | C51: Procuraduría de los Derechos Humanos | D51: Gestiones y coordinación con la PDH. | F51: =COUNTIFS('Organismos especiales'!$A$5:$A$137,B51,'Organismos especiales'!$B$5:$B$137,C51)
A52: Trámites comunes | D52: En cada hoja, agrupa las páginas que usan varias categorías (por ejemplo Agencia Virtual, vehículos, solvencia fiscal o declaraciones).

Sheet Contribuyentes
A1: Contribuyentes
A2: Personas individuales y jurídicas inscritas en el RTU, ordenadas por categoría (régimen o tipo de contribuyente) y grupo. Orden: Categoría › Grupo › Tema › Página. «Todos los grupos» = la usan todos los grupos de la categoría. «Trámites comunes» = la usan varias categorías.
A4: Macro Grupos | B4: Grupo | C4: Sub grupo | D4: Tema | E4: Subtema | F4: Página / Trámite (nombre actual) | G4: Nombre de trámite sugerido | H4: Descripción de la página | I4: Usado por (según Grupos y categorías) | J4: Origen de la clasificación | K4: Motivo / referencia | L4: Sección actual del menú | M4: URL | N4: Nota / Revisar
A5: Contribuyente General | B5: Todos los grupos | D5: Devoluciones y créditos fiscales | E5: ISR (Impuesto Sobre la Renta) | F5: Devolución de ISR Asalariados (Retenciones en exceso o pago indebido) SAT-117 o 1431 | G5: Devolución de ISR si eres asalariado | H5: Información sobre: Devolución de ISR si eres asalariado. | J5: Análisis | K5: Asalariados: NIT sin obligaciones, ISR de rentas del trabajo | L5: SERVICIOS TRIBUTARIOS | M5: https://portal.sat.gob.gt/portal/requisitos-tramites-agencias/devolucion-del-impuesto-sobre-la-renta-asalariados-retenciones-en-exceso-o-pago-indebido/ | N5: Servicio/tema general para contribuyentes
A6: Contribuyentes | B6: NIT sin Obligaciones | D6: RTU Digital | E6: Inscripción | F6: Requisitos para la Inscripción RTU | G6: Inscripción de NIT sin Obligaciones | H6: Solicitud y requisitos para la obtención electrónica de NIT sin obligaciones tributarias por primera vez. | I6: Personas Individuales (Nacionales y Extranjeros sin actividad económica) | J6: Análisis de arquitectura transaccional | K6: Trámite inicial obligatorio para actos civiles, apertura de cuentas bancarias y recepción de remesas. | L6: Requisitos de personas / empresas | M6: https://portal.sat.gob.gt/portal/requisitos-de-personas-empresas/#1615485066841-639e67c5-51e3 | N6: Desvincular del listado de empresas/sociedades mercantiles; crear landing o ficha específica para personas individuales.
A7: Contribuyentes | B7: NIT sin Obligaciones | D7: RTU Digital | E7: Actualización | F7: Requisitos para la Actualización RTU | G7: Actualización de Datos y Transición de Régimen | H7: Requisitos y pasos para actualizar datos de identificación, domicilio fiscal o pasar al régimen con obligaciones tributarias. | I7: Personas que inician relación laboral o comercial | J7: Análisis de arquitectura transaccional | K7: Permite modificar datos personales o dar el salto formal a contribuyente afecto cuando la persona inicia actividades económicas. | L7: Requisitos de personas / empresas | M7: https://portal.sat.gob.gt/portal/requisitos-de-personas-empresas/#1541621044169-4198d06d-693f | N7: Aislar la opción de paso de 'sin obligaciones' a 'con obligaciones' sin obligar a navegar por requisitos corporativos.
A8: Contribuyentes | B8: NIT sin Obligaciones | D8: Sistemas Web | E8: Acceso y Seguridad | F8: Agencia Virtual | G8: Solicitud y Activación de Agencia Virtual | H8: Acceso a plataforma, activación de usuario, reinicio de contraseña y cambio de correo electrónico para personas sin obligaciones. | I8: Usuarios registrados con NIT | J8: Análisis de arquitectura transaccional | K8: Canal indispensable para descargar la constancia de RTU, consultar datos personales y dar seguimiento a solicitudes web. | L8: Menú Principal / Sistemas | M8: https://farm3.sat.gob.gt/menu/login.jsf | N8: Es un sistema de autenticación directa; la ficha informativa debe explicar cómo obtener el acceso inicial.
A9: Contribuyentes | B9: NIT sin Obligaciones | D9: Consultas Públicas | E9: Seguimiento | F9: Estado de Gestión de Agencia Virtual | G9: Consulta de Estado de Gestión de Agencia Virtual | H9: Herramienta de consulta para verificar el estado de aprobación de la solicitud de acceso a Agencia Virtual. | I9: Solicitantes de Agencia Virtual | J9: Análisis de arquitectura transaccional | K9: Permite validar si la solicitud de usuario o reseteo de clave fue aceptada, rechazada o requiere subsanar requisitos. | L9: Consultas Públicas | M9: https://portal.sat.gob.gt/portal/consulta-de-gestion-del-contribuyente/ | N9: Debe integrarse como paso de seguimiento dentro de la ficha de Agencia Virtual, no como enlace huérfano.
A10: Contribuyentes | B10: NIT sin Obligaciones | D10: Certificaciones | E10: Solvencias | F10: Solvencia Fiscal | G10: Solicitud y Emisión de Solvencia Fiscal (SOFI) | H10: Consulta, pago y descarga de la Solvencia Fiscal Electrónica para certificar ausencia de adeudos tributarios. | I10: Personas Individuales | J10: Análisis de arquitectura transaccional | K10: Exigida comúnmente a personas sin obligaciones para postulaciones laborales, trámites consulares/visas y contratos civiles. | L10: Consultas / Solvencias | M10: https://portal.sat.gob.gt/portal/solvencia-fiscal/ | N10: Para este perfil la emisión es automática, salvo que existan registros históricos de omisos o adeudos en el ISCV.
A11: Contribuyentes | B11: NIT sin Obligaciones | D11: Citas y Agencias | E11: Citas | F11: Requisitos para la Atención a través de Cita | G11: Cita Previa para Trámites Presenciales | H11: Información, requisitos y agenda electrónica para programar atención física en agencias tributarias. | I11: Casos especiales (menores o extranjeros) | J11: Análisis de arquitectura transaccional | K11: Aplica a personas sin obligaciones únicamente en validaciones biométricas presenciales o trámites mediante representante legal. | L11: Requisitos trámites agencias | M11: https://portal.sat.gob.gt/portal/requisitos-tramites-agencias/cita-controlada/ | N11: Condicional: solo debe desplegarse como alternativa si el trámite inicial no logra completarse 100% en línea.
A12: NIT sin Obligaciones | B12: Todos los grupos | D12: Otros servicios al contribuyente | E12: Títulos universitarios | F12: Títulos Universitarios | G12: Información sobre títulos universitarios | H12: Información sobre: Información sobre títulos universitarios. | J12: Análisis | K12: Profesionales que registran su título (NIT sin obligaciones) | L12: SERVICIOS TRIBUTARIOS | M12: https://portal.sat.gob.gt/portal/titulos-universitarios/ | N12: Servicio/tema general para contribuyentes
A13: NIT sin Obligaciones | B13: Todos los grupos | D13: Otros servicios al contribuyente | E13: Títulos universitarios | F13: Registro y Habilitación de Títulos Universitarios | G13: Registrar tu título universitario para ejercer | H13: Requisitos, pasos y documentos para registrar tu título universitario para ejercer. | I13: NIT sin Obligaciones | J13: Grupos y categorías | K13: Marcada «SI» en el archivo Grupos y categorías | L13: SERVICIOS TRIBUTARIOS | M13: https://portal.sat.gob.gt/portal/requisitos-tramites-agencias/registro-y-habilitacion-de-titulos-para-ejercer-profesion/ | N13: Servicio/tema general para contribuyentes
A14: NIT sin Obligaciones | B14: Todos los grupos | D14: Vehículos (como propietario) | E14: Requisitos y representantes | F14: Temas De Vehiculos | G14: Preguntas frecuentes sobre vehículos | H14: Respuestas a las preguntas más comunes sobre requisitos y representantes. | I14: NIT sin Obligaciones | J14: Grupos y categorías | K14: Marcada «SI» en el archivo Grupos y categorías | L14: CAPACITACIÓN | M14: https://portal.sat.gob.gt/portal/preguntas-frecuentes/temas-de-vehiculos/ | N14: Servicio/tema general para contribuyentes
A15: NIT sin Obligaciones | B15: Todos los grupos | D15: Vehículos (como propietario) | E15: Título y tarjeta de circulación | F15: Distintivos Electrónicos (Título de propiedad y Tarjeta de Circulación) | G15: Título y tarjeta de circulación electrónicos | H15: Información sobre: Título y tarjeta de circulación electrónicos. | I15: NIT sin Obligaciones | J15: Grupos y categorías | K15: Marcada «SI» en el archivo Grupos y categorías | L15: SERVICIOS TRIBUTARIOS | M15: https://portal.sat.gob.gt/portal/distintivos-electronicos/ | N15: Servicio/tema general para contribuyentes
A16: NIT sin Obligaciones | B16: Todos los grupos | D16: Agregada desde «Grupos y categorías» | G16: Libro Electrónico Tributario | H16: Pequeño Contribuyente | I16: NIT sin Obligaciones | J16: Grupos y categorías | K16: Marcada «SI» en el archivo Grupos y categorías | M16: https://portal.sat.gob.gt/portal/libro-electronico-tributario/pequeno-contribuyente/
A17: Pequeños Contribuyentes | B17: Todos los grupos | D17: Cultura tributaria y capacitación | E17: Leyes y normativa | F17: Legislación | G17: Legislación | H17: Información sobre: Legislación. | I17: Pequeños Contribuyentes | J17: Grupos y categorías | K17: Marcada «SI» en el archivo Grupos y categorías | L17: CAPACITACIÓN | M17: https://portal.sat.gob.gt/portal/biblioteca-en-linea-sat/legislacion/ | N17: Servicio/tema general para contribuyentes
A18: Pequeños Contribuyentes | B18: Todos los grupos | D18: Facturación electrónica y documentos tributarios | E18: Constancias de retención | F18: Constancias de Retención del IVA e ISR recibidos | G18: Consultar constancias de retención de IVA e ISR recibidas | H18: Servicio en línea para consultar constancias de retención de IVA e ISR recibidas. | I18: Pequeños Contribuyentes | J18: Grupos y categorías | K18: Marcada «SI» en el archivo Grupos y categorías | L18: SERVICIOS TRIBUTARIOS | M18: https://portal.sat.gob.gt/portal/retenciones-del-iva-consulta-de-constancias-de-retencion-del-iva-recibidas/ | N18: Servicio/tema general para contribuyentes
A19: Pequeños Contribuyentes | B19: Todos los grupos | D19: Importación | E19: Proceso de importación | F19: Despacho de distintivos de control de productos importados a los fabricantes o importadores domiciliados en el país y a las personas individuales y jurídicas que no sean fabricantes ni importadores | G19: Obtener distintivos de control de productos importados | H19: Requisitos, pasos y documentos para obtener distintivos de control de productos importados. | I19: Pequeños Contribuyentes | J19: Grupos y categorías | K19: Marcada «SI» en el archivo Grupos y categorías | L19: SERVICIOS TRIBUTARIOS | M19: https://portal.sat.gob.gt/portal/requisitos-tramites-agencias/despacho-de-distintivos-de-control-de-productos-importados-a-los-fabricantes-o-importadores-domiciliados-en-el-pais-y-a-las-personas-individuales-y-juridicas/ | N19: Coincide con palabra clave de comercio exterior/aduanas
A20: Pequeños Contribuyentes | B20: Todos los grupos | D20: Inscripción y actualización en el RTU | E20: Obtener o corregir tu NIT | F20: Solicitud Electrónica de NIT | G20: Solicitar tu NIT en línea | H20: Requisitos, pasos y documentos para solicitar tu NIT en línea. | I20: Pequeños Contribuyentes | J20: Grupos y categorías | K20: Marcada «SI» en el archivo Grupos y categorías | L20: SERVICIOS TRIBUTARIOS | M20: https://portal.sat.gob.gt/portal/solicitud-electronica-de-nit/ | N20: Servicio/tema general para contribuyentes
A21: Pequeños Contribuyentes | B21: Todos los grupos | D21: Otros servicios al contribuyente | E21: Sistemas de retención | F21: Asiste Hospitales Web | G21: Retenciones de hospitales (Asiste Hospitales Web) | H21: Información sobre: Retenciones de hospitales (Asiste Hospitales Web). | I21: Pequeños Contribuyentes | J21: Grupos y categorías | K21: Marcada «SI» en el archivo Grupos y categorías | L21: SERVICIOS TRIBUTARIOS | M21: https://portal.sat.gob.gt/portal/sistemas-web/asistehospitalesweb/ | N21: Servicio/tema general para contribuyentes
A22: Pequeños Contribuyentes | B22: Pequeño Contribuyente | D22: Cultura tributaria y capacitación | E22: Cursos por tipo de contribuyente | F22: Principales obligaciones tributarias de los pequeños contribuyentes | G22: Curso: obligaciones del pequeño contribuyente | H22: Capacitación virtual de la SAT sobre obligaciones del pequeño contribuyente. | J22: Análisis | K22: Régimen de Pequeño Contribuyente (Ley del IVA) | L22: CAPACITACIÓN | M22: https://sites.google.com/capacitacionessat.page/cultura-tributariad/cursos-virtuales-sat/impuesto-al-valor-agregado-iva/r%C3%A9gimen-del-peque%C3%B1o-contribuyente | N22: Servicio/tema general para contribuyentes
A23: Pequeños Contribuyentes | B23: Pequeño Contribuyente | D23: Devoluciones y créditos fiscales | E23: ISR (Impuesto Sobre la Renta) | F23: Devolución o Compensación del Impuesto Sobre la Renta Retenido al Pequeño Contribuyente del 5% | G23: Devolución del 5% de ISR retenido al pequeño contribuyente | H23: Información sobre: Devolución del 5% de ISR retenido al pequeño contribuyente. | J23: Análisis | K23: Retención de ISR al pequeño contribuyente | L23: SERVICIOS TRIBUTARIOS | M23: https://portal.sat.gob.gt/portal/requisitos-tramites-agencias/devolucion-acreditamiento-o-compensacion-de-impuesto-sobre-la-renta-retenido-indebidamente-a-pequeno-contribuyente-del-5/ | N23: Servicio/tema general para contribuyentes
A24: Pequeños Contribuyentes | B24: Pequeño Contribuyente | D24: Facturación electrónica y documentos tributarios | E24: Libro Electrónico Tributario (LET) | F24: Libro Electrónico Tributario para Pequeño contribuyente | G24: Curso: LET para pequeño contribuyente | H24: Capacitación virtual de la SAT sobre LET para pequeño contribuyente. | J24: Análisis | K24: Libro Electrónico Tributario del pequeño contribuyente | L24: CAPACITACIÓN | M24: https://sites.google.com/capacitacionessat.page/eventosenvivo/p%C3%A1gina-principal/libro-electr%C3%B3nico-tributario-para-peque%C3%B1o-contribuyente | N24: Servicio/tema general para contribuyentes
A25: Pequeños Contribuyentes | B25: Pequeño Contribuyente | D25: Otros servicios al contribuyente | E25: Libros, facturas y máquinas | F25: Autorización de documentos tributarios a pequeños contribuyentes | G25: Autorizar documentos para pequeños contribuyentes | H25: Requisitos, pasos y documentos para autorizar documentos para pequeños contribuyentes. | J25: Análisis | K25: Documentos del pequeño contribuyente | L25: SERVICIOS TRIBUTARIOS | M25: https://portal.sat.gob.gt/portal/requisitos-tramites-agencias/autorizacion-de-documentos-tributarios-a-pequenos-contribuyentes/ | N25: Servicio/tema general para contribuyentes
A26: Pequeños Contribuyentes | B26: Pequeño Contribuyente | D26: Regímenes tributarios | E26: Cambio de régimen | F26: Actualización de Cambio de Régimen de Pequeño Contribuyente a Régimen Electrónico de Pequeño Contribuyente | G26: Pasar a Régimen Electrónico de Pequeño Contribuyente | H26: Requisitos, pasos y documentos para pasar a Régimen Electrónico de Pequeño Contribuyente. | J26: Análisis | K26: Régimen de Pequeño Contribuyente (Ley del IVA) | L26: SERVICIOS TRIBUTARIOS | M26: https://portal.sat.gob.gt/portal/requisitos-tramites-agencias/requisitos-de-actualizacion-de-cambio-de-regimen-general-a-pequeno-contribuyente-persona/ | N26: Servicio/tema general para contribuyentes
A27: Pequeños Contribuyentes | B27: Pequeño Contribuyente | D27: Regímenes tributarios | E27: Cambio de régimen | F27: Actualización Cambio de Régimen de Pequeño Contribuyente a Régimen General del Impuesto al Valor Agregado | G27: Pasar de Pequeño Contribuyente a Régimen General del IVA | H27: Requisitos, pasos y documentos para pasar de Pequeño Contribuyente a Régimen General del IVA. | J27: Análisis | K27: Régimen de Pequeño Contribuyente (Ley del IVA) | L27: SERVICIOS TRIBUTARIOS | M27: https://portal.sat.gob.gt/portal/requisitos-tramites-agencias/actualizacion-cambio-de-regimen-de-pequeno-contribuyente-a-regimen-general-del-impuesto-al-valor-agregado/ | N27: Servicio/tema general para contribuyentes
A28: Pequeños Contribuyentes | B28: Pequeño Contribuyente | D28: Regímenes tributarios | E28: Pequeño Contribuyente | F28: Consulta NIT de Pequeño Contribuyente | G28: Consultar si un NIT es Pequeño Contribuyente | H28: Servicio en línea para consultar si un NIT es Pequeño Contribuyente. | J28: Análisis | K28: Régimen de Pequeño Contribuyente (Ley del IVA) | L28: SERVICIOS TRIBUTARIOS | M28: https://portal.sat.gob.gt/portal/consulta-regimen-de-pequeno-contribuyente/ | N28: Servicio/tema general para contribuyentes
A29: Pequeños Contribuyentes | B29: Pequeño Contribuyente | D29: Regímenes tributarios | E29: Pequeño Contribuyente | F29: Régimen Electrónico de Pequeño Contribuyente | G29: Curso: Régimen Electrónico de Pequeño Contribuyente | H29: Capacitación virtual de la SAT sobre Régimen Electrónico de Pequeño Contribuyente. | J29: Análisis | K29: Régimen de Pequeño Contribuyente (Ley del IVA) | L29: CAPACITACIÓN | M29: https://sites.google.com/capacitacionessat.page/cultura-tributariad/cursos-virtuales-sat/impuesto-al-valor-agregado-iva/r%C3%A9gimen-electr%C3%B3nico-de-peque%C3%B1o-contribuyente | N29: Servicio/tema general para contribuyentes
A30: Pequeños Contribuyentes | B30: Pequeño Contribuyente | D30: Regímenes tributarios | E30: Pequeño Contribuyente | F30: Régimen Electrónico del Pequeño Contribuyente | G30: Curso: Régimen Electrónico de Pequeño Contribuyente | H30: Capacitación virtual de la SAT sobre Régimen Electrónico de Pequeño Contribuyente. | J30: Análisis | K30: Régimen de Pequeño Contribuyente (Ley del IVA) | L30: CAPACITACIÓN | M30: https://sites.google.com/capacitacionessat.page/eventosenvivo/p%C3%A1gina-principal/r%C3%A9gimen-electr%C3%B3nico-del-peque%C3%B1o-contribuyente | N30: Servicio/tema general para contribuyentes
A31: Pequeños Contribuyentes | B31: Pequeño Contribuyente | D31: Regímenes tributarios | E31: Pequeño Contribuyente | F31: Régimen del pequeño contribuyente | G31: Curso: régimen de Pequeño Contribuyente | H31: Capacitación virtual de la SAT sobre régimen de Pequeño Contribuyente. | J31: Análisis | K31: Régimen de Pequeño Contribuyente (Ley del IVA) | L31: CAPACITACIÓN | M31: https://sites.google.com/capacitacionessat.page/cultura-tributariad/cursos-virtuales-sat/impuesto-al-valor-agregado/r%C3%A9gimen-del-peque%C3%B1o-contribuyente | N31: Servicio/tema general para contribuyentes
A32: Pequeños Contribuyentes | B32: Primario | D32: Consultas y verificadores | E32: Registros públicos | F32: Productores Inscritos: Consulta Productores | G32: Consultar productores inscritos | H32: Servicio en línea para consultar productores inscritos. | J32: Análisis | K32: Registro de productores | L32: SERVICIOS TRIBUTARIOS | M32: https://portal.sat.gob.gt/portal/consulta-productores/ | N32: Servicio/tema general para contribuyentes
A33: Pequeños Contribuyentes | B33: Primario | D33: Cultura tributaria y capacitación | E33: Cursos por tipo de contribuyente | F33: Productores de Productos Agropecuarios, Artesanales y Reciclados | G33: Curso: productores agropecuarios, artesanales y de reciclaje | H33: Capacitación virtual de la SAT sobre productores agropecuarios, artesanales y de reciclaje. | J33: Análisis | K33: Régimen agropecuario (Decreto 31-2024) | L33: CAPACITACIÓN | M33: https://sites.google.com/capacitacionessat.page/cultura-tributariad/cursos-virtuales-sat/impuesto-al-valor-agregado-iva/inscripci%C3%B3n-y-actualizaci%C3%B3n-de-productores | N33: Servicio/tema general para contribuyentes
... A42: Pequeños Contribuyentes | B42: Pecuario | D42: Regímenes tributarios | E42: Régimen Agropecuario | F42: Principales obligaciones tributarias del Régimen especial de Contribuyente Agropecuario (Convencional y Electrónico) | G42: Curso: obligaciones del Régimen Especial Agropecuario | H42: Capacitación virtual de la SAT sobre obligaciones del Régimen Especial Agropecuario. | J42: Análisis | K42: Régimen agropecuario (Decreto 31-2024) | L42: CAPACITACIÓN | M42: https://sites.google.com/capacitacionessat.page/cultura-tributariad/cursos-virtuales-sat/impuesto-al-valor-agregado-iva/principales-obligaciones-tributarias-del-r%C3%A9gimen-especial-de-contribuyente | N42: Servicio/tema general para contribuyentes
A43: Contribuyente General | B43: Todos los grupos | D43: Facturación electrónica y documentos tributarios | E43: Constancias de exención (CIVA y CAIS) | F43: Emisión Constancias de Adquisición de Insumos y Servicios -CAIS- | G43: Emitir constancias CAIS | H43: Requisitos, pasos y documentos para emitir constancias CAIS. | I43: Contribuyente General | J43: Grupos y categorías | K43: Marcada «SI» en el archivo Grupos y categorías | L43: SERVICIOS TRIBUTARIOS | M43: https://portal.sat.gob.gt/portal/emision-constancias-de-adquisicion-de-insumos-y-servicios-cais/ | N43: Servicio/tema general para contribuyentes
A44: Contribuyente General | B44: Todos los grupos | D44: Facturación electrónica y documentos tributarios | E44: Constancias de exención (CIVA y CAIS) | F44: Emisión Constancias de Exención de IVA -CIVA- | G44: Emitir constancias de exención de IVA (CIVA) | H44: Requisitos, pasos y documentos para emitir constancias de exención de IVA (CIVA). | I44: Contribuyente General | J44: Grupos y categorías | K44: Marcada «SI» en el archivo Grupos y categorías | L44: SERVICIOS TRIBUTARIOS | M44: https://portal.sat.gob.gt/portal/emision-constancias-de-exencion-de-iva-civa/ | N44: Servicio/tema general para contribuyentes
A45: Contribuyente General | B45: Todos los grupos | D45: Otros servicios al contribuyente | E45: Constancias y gestiones del RTU | F45: Requisitos de persona/empresa | G45: Requisitos para Abogados y Notarios | H45: Requisitos, listado de pasos, y casos especiales; para la inscripción/actualización, activación, confirmación de huella y Venta de Especies Fiscales para Abogados y Notarios. | I45: Contribuyente General | J45: Grupos y categorías | K45: Marcada «SI» en el archivo Grupos y categorías | L45: SERVICIOS TRIBUTARIOS | M45: https://portal.sat.gob.gt/portal/requisitos-de-personas-empresas/ | N45: Servicio/tema general para contribuyentes
A46: Contribuyente General | B46: Contribuyente General | D46: Consultas y verificadores | E46: Autorización y consulta | F46: Autorización de Máquinas en Agencia Virtual | G46: Autorizar máquinas registradoras en Agencia Virtual | H46: Requisitos, pasos y documentos para autorizar máquinas registradoras en Agencia Virtual. | J46: Análisis | K46: Máquinas registradoras | L46: SERVICIOS TRIBUTARIOS | M46: https://portal.sat.gob.gt/portal/requisitos-tramites-agencias/autorizacion-de-maquinas-en-agencia-virtual/ | N46: Servicio/tema general para contribuyentes
A47: Contribuyente General | B47: Contribuyente General | D47: Consultas y verificadores | E47: Autorización y consulta | F47: Consulta Autorización de Máquina | G47: Consultar si una máquina registradora está autorizada | H47: Servicio en línea para consultar si una máquina registradora está autorizada. | J47: Análisis | K47: Máquinas registradoras | L47: SERVICIOS TRIBUTARIOS | M47: https://portal.sat.gob.gt/portal/consulta-autorizacion-de-maquina/ | N47: Servicio/tema general para contribuyentes
A48: Contribuyente General | B48: Contribuyente General | D48: Cultura tributaria y capacitación | E48: Cursos por impuesto | F48: Regímenes para las Rentas de Actividades Lucrativas | G48: Curso: regímenes del ISR para negocios | H48: Capacitación virtual de la SAT sobre regímenes del ISR para negocios. | J48: Análisis | K48: Régimen General del IVA e ISR de actividades lucrativas | L48: CAPACITACIÓN | M48: https://sites.google.com/capacitacionessat.page/cultura-tributariad/cursos-virtuales-sat/impuesto-sobre-la-renta/reg%C3%ADmenes-para-las-rentas-de-actividades-lucrativas | N48: Servicio/tema general para contribuyentes
A49: Contribuyente General | B49: Contribuyente General | D49: Devoluciones y créditos fiscales | E49: ISR (Impuesto Sobre la Renta) | F49: Formulario Electrónico SAT-2350 (versión vigente) Solicitud de Devolución de Pagos en Exceso del ISR Anual | G49: Devolución de ISR anual pagado de más | H49: Información sobre: Devolución de ISR anual pagado de más. | J49: Análisis | K49: Devoluciones de ISR/IVA/ISO de actividades lucrativas | L49: SERVICIOS TRIBUTARIOS | M49: https://portal.sat.gob.gt/portal/requisitos-tramites-agencias/formulario-electronico-sat-2350-version-vigente-solicitud-de-pagos-en-exceso/ | N49: Servicio/tema general para contribuyentes
A50: Contribuyente General | B50: Contribuyente General | D50: Devoluciones y créditos fiscales | E50: ISR (Impuesto Sobre la Renta) | F50: Devolución o Compensación de ISR Opcional Mensual, SAT-1311 | G50: Devolución de ISR opcional mensual | H50: Información sobre: Devolución de ISR opcional mensual. | J50: Análisis | K50: Devoluciones de ISR/IVA/ISO de actividades lucrativas | L50: SERVICIOS TRIBUTARIOS | M50: https://portal.sat.gob.gt/portal/requisitos-tramites-agencias/devolucion-acreditamiento-o-compensacion-del-isr-opcional-mensual-sat-1311/ | N50: Servicio/tema general para contribuyentes
A51: Contribuyente General | B51: Contribuyente General | D51: Devoluciones y créditos fiscales | E51: ISR (Impuesto Sobre la Renta) | F51: Devolución o Compensación de Retenciones de ISR Retenido a Personas Residentes y no Residentes con Establecimiento Prmanente SAT-1331 | G51: Devolución de ISR retenido (con establecimiento permanente) | H51: Información sobre: Devolución de ISR retenido (con establecimiento permanente). | J51: Análisis | K51: Devoluciones de ISR/IVA/ISO de actividades lucrativas | L51: SERVICIOS TRIBUTARIOS | M51: https://portal.sat.gob.gt/portal/requisitos-tramites-agencias/devolucion-acreditamiento-o-compensacion-del-isr-retenido-a-personas-y-no-residentes-con-establecimiento-permanente-1331/ | N51: Servicio/tema general para contribuyentes
A52: Contribuyente General | B52: Contribuyente General | D52: Devoluciones y créditos fiscales | E52: ISR (Impuesto Sobre la Renta) | F52: Devolución o Compensación de Retenciones de ISR Retenido a Personas Residentes y no Residentes sin Establecimiento Permanente SAT-1352 | G52: Devolución de ISR retenido (sin establecimiento permanente) | H52: Información sobre: Devolución de ISR retenido (sin establecimiento permanente). | J52: Análisis | K52: Devoluciones de ISR/IVA/ISO de actividades lucrativas | L52: SERVICIOS TRIBUTARIOS | M52: https://portal.sat.gob.gt/portal/requisitos-tramites-agencias/devolucion-acreditamiento-o-compensacion-del-isr-retenido-a-personas-no-residentes-sin-establecimiento-permanente-sat-1352/ | N52: Servicio/tema general para contribuyentes
A53: Contribuyente General | B53: Contribuyente General | D53: Devoluciones y créditos fiscales | E53: ISR (Impuesto Sobre la Renta) | F53: Devolución de Retenciones de ISR por Repartición de Utilidades o Dividendos | G53: Devolución de ISR retenido por dividendos o utilidades | H53: Información sobre: Devolución de ISR retenido por dividendos o utilidades. | J53: Análisis | K53: Devoluciones de ISR/IVA/ISO de actividades lucrativas | L53: SERVICIOS TRIBUTARIOS | M53: https://portal.sat.gob.gt/portal/requisitos-tramites-agencias/devolucion-del-isr-por-reparticion-de-utilidades-o-dividendos/ | N53: Servicio/tema general para contribuyentes
A54: Contribuyente General | B54: Contribuyente General | D54: Devoluciones y créditos fiscales | E54: ISR (Impuesto Sobre la Renta) | F54: Devolución o Compensación de ISR Trimestral, SAT-1361 | G54: Devolución de ISR trimestral | H54: Información sobre: Devolución de ISR trimestral. | J54: Análisis | K54: Devoluciones de ISR/IVA/ISO de actividades lucrativas | L54: SERVICIOS TRIBUTARIOS | M54: https://portal.sat.gob.gt/portal/requisitos-tramites-agencias/devolucion-acreditamiento-o-compensacion-del-impuesto-sobre-la-rentatrimestral-sat-1361/ | N54: Servicio/tema general para contribuyentes
A55: Contribuyente General | B55: Contribuyente General | D55: Devoluciones y créditos fiscales | E55: IVA (Impuesto al Valor Agregado) | F55: Devolución o Compensación de IVA Facturas Especiales, SAT-2085 | G55: Devolución de IVA de facturas especiales | H55: Información sobre: Devolución de IVA de facturas especiales. | J55: Análisis | K55: Devoluciones de ISR/IVA/ISO de actividades lucrativas | L55: SERVICIOS TRIBUTARIOS | M55: https://portal.sat.gob.gt/portal/requisitos-tramites-agencias/devolucion-acreditamiento-o-compensacion-de-iva-facturas-especiales/ | N55: Servicio/tema general para contribuyentes
A56: Contribuyente General | B56: Contribuyente General | D56: Devoluciones y créditos fiscales | E56: IVA (Impuesto al Valor Agregado) | F56: Devolución de Retenciones del Impuesto al Valor Agregado, SAT-2219 | G56: Devolución de IVA retenido | H56: Información sobre: Devolución de IVA retenido. | J56: Análisis | K56: Devoluciones de ISR/IVA/ISO de actividades lucrativas | L56: SERVICIOS TRIBUTARIOS | M56: https://portal.sat.gob.gt/portal/requisitos-tramites-agencias/devolucion-de-retenciones-del-impuesto-al-valor-agregado-sat-2219/ | N56: Servicio/tema general para contribuyentes
A57: Contribuyente General | B57: Contribuyente General | D57: Devoluciones y créditos fiscales | E57: IVA (Impuesto al Valor Agregado) | F57: Acreditamiento en Cuenta de Remanente de Retenciones de IVA | G57: Usar el saldo a favor de retenciones de IVA | H57: Requisitos, pasos y documentos para usar el saldo a favor de retenciones de IVA. | J57: Análisis | K57: Devoluciones de ISR/IVA/ISO de actividades lucrativas | L57: SERVICIOS TRIBUTARIOS | M57: https://portal.sat.gob.gt/portal/requisitos-tramites-agencias/solicitud-de-acreditamiento-en-cuenta-de-remanente-por-retenciones-del-impuesto-al-valor-agregado/ | N57: Servicio/tema general para contribuyentes
... A94: Contribuyente General | B94: Contribuyente General | D94: Inscripción y actualización en el RTU | E94: Sociedades y empresas | F94: Inscripción de Sociedad | G94: Inscribir una sociedad o empresa | H94: Requisitos, pasos y documentos para inscribir una sociedad o empresa. | J94: Análisis | K94: Personas jurídicas y entes: Régimen General (IVA/ISR, Decreto 10-2012) | L94: SERVICIOS TRIBUTARIOS | M94: https://portal.sat.gob.gt/portal/requisitos-tramites-agencias/inscripcion-sociedades/ | N94: Servicio/tema general para contribuyentes
A95: Contribuyente General | B95: Contribuyente General | D95: Otros servicios al contribuyente | E95: Constancias y gestiones del RTU | F95: Requisitos de persona/empresa | G95: Requisitos sobre Formularios Electrónicos Solicitud Dev. C.F. Régimen Especial Electrónico y Régimen General | H95: Requisitos, listado de pasos, y casos especiales; para los formularios SAT-2125, SAT-2251 y SAT-2390. | I95: Contribuyente General: Contribuyente General | J95: Grupos y categorías | K95: Marcada «SI» en el archivo Grupos y categorías | L95: SERVICIOS TRIBUTARIOS | M95: https://portal.sat.gob.gt/portal/requisitos-de-personas-empresas/ | N95: Servicio/tema general para contribuyentes
A96: Contribuyente General | B96: Contribuyente General | D96: Otros servicios al contribuyente | E96: Libros, facturas y máquinas | F96: Anulación de Resolución de Documentos por Impresores en Agencia Virtual | G96: Anular resolución de documentos (imprentas) | H96: Requisitos, pasos y documentos para anular resolución de documentos (imprentas). | J96: Análisis | K96: Libros, documentos e imprentas | L96: SERVICIOS TRIBUTARIOS | M96: https://portal.sat.gob.gt/portal/requisitos-tramites-agencias/anulacion-de-resolucion-de-documentos-por-impresores-en-agencia-virtual/ | N96: Servicio/tema general para contribuyentes
A97: Contribuyente General | B97: Contribuyente General | D97: Otros servicios al contribuyente | E97: Libros, facturas y máquinas | F97: Autorización de Documentos para Espectáculos Públicos | G97: Autorizar documentos para espectáculos públicos | H97: Requisitos, pasos y documentos para autorizar documentos para espectáculos públicos. | J97: Análisis | K97: Libros, documentos e imprentas | L97: SERVICIOS TRIBUTARIOS | M97: https://portal.sat.gob.gt/portal/requisitos-tramites-agencias/autorizacion-de-documentos-para-espectaculos-publicos/ | N97: Servicio/tema general para contribuyentes
A98: Contribuyente General | B98: Contribuyente General | D98: Otros servicios al contribuyente | E98: Libros, facturas y máquinas | F98: Habilitación de Libros | G98: Habilitar libros contables | H98: Requisitos, pasos y documentos para habilitar libros contables. | J98: Análisis | K98: Libros, documentos e imprentas | L98: SERVICIOS TRIBUTARIOS | M98: https://portal.sat.gob.gt/portal/requisitos-tramites-agencias/habilitacion-de-libros/ | N98: Servicio/tema general para contribuyentes
A99: Contribuyente General | B99: Contribuyente General | D99: Otros servicios al contribuyente | E99: Libros, facturas y máquinas | F99: Informe de Servicios de Impresión en Agencia Virtual | G99: Informe de servicios de impresión (imprentas) | H99: Información sobre: Informe de servicios de impresión (imprentas). | J99: Análisis | K99: Libros, documentos e imprentas | L99: SERVICIOS TRIBUTARIOS | M99: https://portal.sat.gob.gt/portal/requisitos-tramites-agencias/informe-de-servicios-de-impresion-en-agencia-virtual/ | N99: Servicio/tema general para contribuyentes
A100: Contribuyente General | B100: Contribuyente General | D100: Regímenes tributarios | E100: Cambio de régimen | F100: Actualización del Impuesto Sobre la Renta, Régimen Opcional Simplificado, Opción Pago Directo | G100: Cambiar a ISR Opcional Simplificado con pago directo | H100: Requisitos, pasos y documentos para cambiar a ISR Opcional Simplificado con pago directo. | J100: Análisis | K100: Régimen General del IVA e ISR | L100: SERVICIOS TRIBUTARIOS | M100: https://portal.sat.gob.gt/portal/requisitos-tramites-agencias/actualizacion-del-impuesto-sobre-la-renta-regimen-opcional-simplificado-opcion-pago-directo/ | N100: Servicio/tema general para contribuyentes
A101: Contribuyente General | B101: Contribuyente General | D101: Regímenes tributarios | E101: Cambio de régimen | F101: Actualización Cambio de Régimen General del Impuesto al Valor Agregado a Pequeño Contribuyente | G101: Pasar de Régimen General a Pequeño Contribuyente | H101: Requisitos, pasos y documentos para pasar de Régimen General a Pequeño Contribuyente. | J101: Análisis | K101: Régimen General del IVA e ISR | L101: SERVICIOS TRIBUTARIOS | M101: https://portal.sat.gob.gt/portal/requisitos-tramites-agencias/actualizacion-cambio-de-regimen-general-del-impuesto-al-valor-agregado-a-pequeno-contribuyente/ | N101: Servicio/tema general para contribuyentes
A102: Contribuyente General | B102: Contribuyente General | D102: Regímenes tributarios | E102: ISR para negocios | F102: Régimen Opcional Simplificado sobre Ingresos de Actividades Lucrativas | G102: Curso: Régimen Opcional Simplificado | H102: Capacitación virtual de la SAT sobre Régimen Opcional Simplificado. | J102: Análisis | K102: Régimen General del IVA e ISR | L102: CAPACITACIÓN | M102: https://sites.google.com/capacitacionessat.page/cultura-tributariad/cursos-virtuales-sat/impuesto-sobre-la-renta-isr/5-r%C3%A9gimen-sobre-los-ingresos-de-actividades-lucrativas | N102: Servicio/tema general para contribuyentes
A103: Contribuyente General | B103: Contribuyente General | D103: Regímenes tributarios | E103: ISR para negocios | F103: Costos y gastos deducibles. Régimen sobre las utilidades de actividades lucrativas | G103: Curso: costos y gastos deducibles (régimen sobre utilidades) | H103: Capacitación virtual de la SAT sobre costos y gastos deducibles (régimen sobre utilidades). | J103: Análisis | K103: Régimen General del IVA e ISR | L103: CAPACITACIÓN | M103: https://sites.google.com/capacitacionessat.page/cultura-tributariad/cursos-virtuales-sat/impuesto-sobre-la-renta-isr/14-costos-y-gastos-deducibles-r%C3%A9gimen-sobre-las-utilidades-de-actividades | N103: Servicio/tema general para contribuyentes
A104: Contribuyente General | B104: Contribuyente General | D104: Regímenes tributarios | E104: ISR para negocios | F104: Régimen sobre las Utilidades de Actividades Lucrativas | G104: Curso: régimen sobre las utilidades | H104: Capacitación virtual de la SAT sobre régimen sobre las utilidades. | J104: Análisis | K104: Régimen General del IVA e ISR | L104: CAPACITACIÓN | M104: https://sites.google.com/capacitacionessat.page/cultura-tributariad/cursos-virtuales-sat/impuesto-sobre-la-renta-isr/12-r%C3%A9gimen-sobre-utilidades-de-rentas-de-actividades-lucrativa | N104: Servicio/tema general para contribuyentes
A105: Contribuyente General | B105: Contribuyente General | D105: Regímenes tributarios | E105: Régimen General del IVA | F105: Régimen General del IVA | G105: Curso: Régimen General del IVA | H105: Capacitación virtual de la SAT sobre Régimen General del IVA. | J105: Análisis | K105: Régimen General del IVA e ISR | L105: CAPACITACIÓN | M105: https://sites.google.com/capacitacionessat.page/cultura-tributariad/cursos-virtuales-sat/impuesto-al-valor-agregado/r%C3%A9gimen-general-del-iva | N105: Servicio/tema general para contribuyentes
A106: Contribuyente General | B106: Contribuyente General | D106: Regímenes tributarios | E106: Régimen General del IVA | F106: Principales errores e inconsistencias detectadas en la declaración mensual del IVA, régimen general | G106: Curso: errores comunes en la declaración mensual del IVA | H106: Capacitación virtual de la SAT sobre errores comunes en la declaración mensual del IVA. | J106: Análisis | K106: Régimen General del IVA e ISR | L106: CAPACITACIÓN | M106: https://sites.google.com/capacitacionessat.page/cultura-tributariad/cursos-virtuales-sat/impuesto-al-valor-agregado-iva/principales-errores-e-inconsistencias-detectadas-en-la-declaraci%C3%B3n-mensual | N106: Servicio/tema general para contribuyentes
A107: Contribuyente General | B107: Contribuyente General | D107: Regímenes tributarios | E107: Régimen General del IVA | F107: Régimen general del IVA (Principales obligaciones tributarias) | G107: Curso: obligaciones del Régimen General del IVA | H107: Capacitación virtual de la SAT sobre obligaciones del Régimen General del IVA. | J107: Análisis | K107: Régimen General del IVA e ISR | L107: CAPACITACIÓN | M107: https://sites.google.com/capacitacionessat.page/cultura-tributariad/cursos-virtuales-sat/impuesto-al-valor-agregado-iva/r%C3%A9gimen-general-del-iva-principales-obligaciones-tributarias | N107: Servicio/tema general para contribuyentes
... A110: Contribuyentes Especiales | B110: Todos los grupos | D110: Cultura tributaria y capacitación | E110: Cursos por impuesto | F110: Agentes de retención del ISR | G110: Curso: agentes de retención del ISR | H110: Capacitación virtual de la SAT sobre agentes de retención del ISR. | J110: Análisis | K110: Agentes de retención | L110: CAPACITACIÓN | M110: https://sites.google.com/capacitacionessat.page/cultura-tributariad/cursos-virtuales-sat/impuesto-sobre-la-renta-isr/21-agentes-de-retenci%C3%B3n-de-isr | N110: Servicio/tema general para contribuyentes
A111: Contribuyentes Especiales | B111: Todos los grupos | D111: Cultura tributaria y capacitación | E111: Preguntas frecuentes | F111: Contribuyentes Especiales | G111: Preguntas frecuentes: contribuyentes especiales | H111: Respuestas a las preguntas más comunes sobre contribuyentes especiales. | I111: Contribuyentes Especiales | J111: Grupos y categorías | K111: Marcada «SI» en el archivo Grupos y categorías | L111: CAPACITACIÓN | M111: https://portal.sat.gob.gt/portal/preguntas-frecuentes/contribuyentes-especiales/ | N111: Servicio/tema general para contribuyentes
A112: Contribuyentes Especiales | B112: Todos los grupos | D112: Declaraciones, pagos y solvencias | E112: Declaraciones | F112: Informe Electrónico de Compras y Ventas | G112: Informe electrónico de compras y ventas | H112: Información sobre: Informe electrónico de compras y ventas. | J112: Análisis | K112: Informe electrónico de compras y ventas | L112: SERVICIOS TRIBUTARIOS | M112: https://portal.sat.gob.gt/portal/informe-electronico-de-compras-y-venta/ | N112: Servicio/tema general para contribuyentes
A113: Contribuyentes Especiales | B113: Todos los grupos | D113: Gobierno y gestión institucional | E113: Información de referencia | F113: Tasas e Intereses | G113: Tasas e intereses vigentes | H113: Información sobre: Tasas e intereses vigentes. | I113: Contribuyentes Especiales | J113: Grupos y categorías | K113: Marcada «SI» en el archivo Grupos y categorías | L113: INSTITUCIONAL | M113: https://portal.sat.gob.gt/portal/tasas-e-intereses/ | N113: Contenido institucional/corporativo general (excluido por decisión del usuario)
A114: Contribuyentes Especiales | B114: Todos los grupos | D114: Inscripción y actualización en el RTU | E114: Registros especiales | F114: Solicitud de Inscripción como Agente de Retención del IVA | G114: Solicitar ser agente de retención del IVA | H114: Requisitos, pasos y documentos para solicitar ser agente de retención del IVA. | J114: Análisis | K114: Agentes de retención del IVA, designados en su mayoría entre contribuyentes especiales | L114: SERVICIOS TRIBUTARIOS | M114: https://portal.sat.gob.gt/portal/requisitos-tramites-agencias/solicitud-de-inscripcion-como-agente-de-retencion-del-iva/ | N114: Servicio/tema general para contribuyentes
A115: Contribuyentes Especiales | B115: Todos los grupos | D115: Otros servicios al contribuyente | E115: Constancias y gestiones del RTU | F115: RTU Digital | G115: RTU Digital: gestiones de tu registro en línea | H115: Información sobre: RTU Digital: gestiones de tu registro en línea. | I115: Contribuyentes Especiales | J115: Grupos y categorías | K115: Marcada «SI» en el archivo Grupos y categorías | L115: SERVICIOS TRIBUTARIOS | M115: https://portal.sat.gob.gt/portal/rtu-digital/ | N115: Servicio/tema general para contribuyentes
A116: Contribuyentes Especiales | B116: Todos los grupos | D116: Otros servicios al contribuyente | E116: Constancias y gestiones del RTU | F116: Requisitos de persona/empresa | G116: Requisitos para despacho de Distintivos | H116: Requisitos para despacho de distintivos de control de productos importados a los fabricantes o importadores domiciliados en el país y a las personas individuales y jurídicas que no sean fabricantes ni importadores | I116: Contribuyentes Especiales | J116: Grupos y categorías | K116: Marcada «SI» en el archivo Grupos y categorías | L116: SERVICIOS TRIBUTARIOS | M116: https://portal.sat.gob.gt/portal/requisitos-de-personas-empresas/ | N116: Servicio/tema general para contribuyentes
A117: Contribuyentes Especiales | B117: Todos los grupos | D117: Otros servicios al contribuyente | E117: Constancias y gestiones del RTU | F117: Requisitos de persona/empresa | G117: Requisitos sobre Trámites en Gerencias Especiales | H117: Requisitos para el registro y emisión de autorización de la SAT al impuesto a la distribución de petróleo crudo y combustible derivados del petróleo. | I117: Contribuyentes Especiales | J117: Grupos y categorías | K117: Marcada «SI» en el archivo Grupos y categorías | L117: SERVICIOS TRIBUTARIOS | M117: https://portal.sat.gob.gt/portal/requisitos-de-personas-empresas/ | N117: Servicio/tema general para contribuyentes
A118: Contribuyentes Especiales | B118: Todos los grupos | D118: Otros servicios al contribuyente | E118: Sistemas de retención | F118: Agentes de Retención IVA | G118: Información para agentes de retención del IVA | H118: Información sobre: Información para agentes de retención del IVA. | J118: Análisis | K118: Agentes de retención de IVA e ISR | L118: SERVICIOS TRIBUTARIOS | M118: https://portal.sat.gob.gt/portal/project/agentes-de-retencion-iva-2/ | N118: Servicio/tema general para contribuyentes
A119: Contribuyentes Especiales | B119: Todos los grupos | D119: Otros servicios al contribuyente | E119: Sistemas de retención | F119: Sistema Retenciones Web -ISR- | G119: Sistema de retenciones del ISR | H119: Información sobre: Sistema de retenciones del ISR. | I119: Contribuyentes Especiales | J119: Grupos y categorías | K119: Marcada «SI» en el archivo Grupos y categorías | L119: SERVICIOS TRIBUTARIOS | M119: https://portal.sat.gob.gt/portal/sistemas-web/retencioneswebisr/ | N119: Servicio/tema general para contribuyentes
A120: Contribuyentes Especiales | B120: Todos los grupos | D120: Agregada desde «Grupos y categorías» | G120: AsisteLight | H120: Información relacionada con la herramienta web, descarga y forma de uso. | I120: Contribuyentes Especiales | J120: Grupos y categorías | K120: Marcada «SI» en el archivo Grupos y categorías | M120: https://portal.sat.gob.gt/portal/biblioteca-en-linea-sat/software/asistelight/
A121: Contribuyentes Especiales | B121: Todos los grupos | D121: Agregada desde «Grupos y categorías» | G121: Precios de Transferencia | H121: Información relacionada a la declaración jurada anual del impuesto sobre la renta sobre partes relacionadas, guías técnicas y anexos. | I121: Contribuyentes Especiales | J121: Grupos y categorías | K121: Marcada «SI» en el archivo Grupos y categorías | M121: https://portal.sat.gob.gt/portal/precios-de-transferencia/
A122: Contribuyentes Especiales | B122: Grandes | D122: Devoluciones y créditos fiscales | E122: Otros impuestos | F122: Devolución o Compensación del Impuesto a la Distribución de Bebidas Alcohólicas y Otras, SAT-3035 | G122: Devolución del impuesto a bebidas alcohólicas | H122: Información sobre: Devolución del impuesto a bebidas alcohólicas. | J122: Análisis | K122: Fabricantes de bebidas alcohólicas | L122: SERVICIOS TRIBUTARIOS | M122: https://portal.sat.gob.gt/portal/requisitos-tramites-agencias/devolucion-acreditamiento-o-compensacion-del-impuesto-de-bebidas-alcoholicas/ | N122: Servicio/tema general para contribuyentes
A123: Contribuyentes Especiales | B123: Grandes | D123: Facturación electrónica y documentos tributarios | E123: Guías para llenar formularios | F123: Llenado del formulario de declaración anual del ISR, para contribuyentes que desarrollan actividades de transporte aéreo internacional | G123: Cómo llenar la declaración anual de ISR (transporte aéreo internacional) | H123: Guía paso a paso: cómo llenar la declaración anual de ISR (transporte aéreo internacional). | J123: Análisis | K123: Declaración anual de transporte aéreo internacional | L123: CAPACITACIÓN | M123: https://sites.google.com/capacitacionessat.page/eventosenvivo/p%C3%A1gina-principal/llenado-del-formulario-de-declaraci%C3%B3n-anual-del-isr-para-contribuyentes-qu | N123: Servicio/tema general para contribuyentes
A124: Contribuyentes Especiales | B124: Grandes | D124: Otros servicios al contribuyente | E124: Alcohol y combustibles | F124: Autorización de Fabricas de Alcohol y Bebidas Alcohólicas | G124: Autorizar una fábrica de alcohol o bebidas alcohólicas | H124: Requisitos, pasos y documentos para autorizar una fábrica de alcohol o bebidas alcohólicas. | J124: Análisis | K124: Fábricas de alcohol y bebidas alcohólicas | L124: SERVICIOS TRIBUTARIOS | M124: https://portal.sat.gob.gt/portal/requisitos-tramites-agencias/fabricas-de-alcoholes-y-bebidas-alcoholicas-y-fermentadas/ | N124: Servicio/tema general para contribuyentes
A125: Contribuyentes Especiales | B125: Grandes | D125: Otros servicios al contribuyente | E125: Alcohol y combustibles | F125: Solicitud de Alcoholes, Bebidas Alcohólicas y Fermentadas | G125: Solicitud para alcoholes y bebidas alcohólicas o fermentadas | H125: Información sobre: Solicitud para alcoholes y bebidas alcohólicas o fermentadas. | J125: Análisis | K125: Fábricas de alcohol y bebidas alcohólicas | L125: SERVICIOS TRIBUTARIOS | M125: https://portal.sat.gob.gt/portal/requisitos-tramites-agencias/solicitud-de-alcoholes-bebidas-alcoholicas-y-fermentadas/ | N125: Servicio/tema general para contribuyentes
A126: Contribuyentes Especiales | B126: Rep. Legales | D126: Inscripción y actualización en el RTU | E126: Representante legal | F126: Cancelación de Representante Legal solicitado por persona individual que finalizó relación laboral con la entidad | G126: Dejar de ser representante legal al terminar tu relación laboral | H126: Requisitos, pasos y documentos para dejar de ser representante legal al terminar tu relación laboral. | J126: Análisis | K126: Representación de personas jurídicas | L126: SERVICIOS TRIBUTARIOS | M126: https://portal.sat.gob.gt/portal/requisitos-tramites-agencias/requisitos-de-cancelacion-de-rl-solicitado-por-pi-que-finalizo-relacion-laboral/ | N126: Servicio/tema general para contribuyentes
A127: Contribuyentes Especiales | B127: Rep. Legales | D127: Inscripción y actualización en el RTU | E127: Representante legal | F127: Actualización o Cancelación de Representante Legal | G127: Nombrar, cambiar o cancelar al representante legal | H127: Información sobre: Nombrar, cambiar o cancelar al representante legal. | J127: Análisis | K127: Representación de personas jurídicas | L127: SERVICIOS TRIBUTARIOS | M127: https://portal.sat.gob.gt/portal/requisitos-tramites-agencias/actualizacion-o-cancelacion-de-representante-legal/ | N127: Servicio/tema general para contribuyentes
A128: Trámites comunes | B128: Todos los grupos | D128: Atención, quejas y denuncias | E128: Chat | F128: Chat en línea | G128: Chatear con la SAT | H128: Requisitos, pasos y documentos para chatear con la SAT. | I128: Varias categorías de contribuyentes | J128: Análisis | K128: Atención, quejas y denuncias | L128: CONTÁCTANOS | M128: https://portal.sat.gob.gt/portal/soporte-chat/ | N128: Servicio/tema general para contribuyentes
A129: Trámites comunes | B129: Todos los grupos | D129: Atención, quejas y denuncias | E129: Información pública | F129: Solicitud de Información Pública | G129: Solicitar información pública | H129: Requisitos, pasos y documentos para solicitar información pública. | I129: Varias categorías de contribuyentes | J129: Análisis | K129: Atención, quejas y denuncias | L129: CONTÁCTANOS | M129: https://portal.sat.gob.gt/portal/solicitud-informacion-publica/ | N129: Servicio/tema general para contribuyentes
A130: Trámites comunes | B130: Todos los grupos | D130: Atención, quejas y denuncias | E130: Quejas y denuncias | F130: Denuncias Tributarias | G130: Denunciar a quien no da factura | H130: Requisitos, pasos y documentos para denunciar a quien no da factura. | I130: Varias categorías de contribuyentes | J130: Análisis | K130: Atención, quejas y denuncias | L130: CONTÁCTANOS | M130: https://portal.sat.gob.gt/portal/contacto/denuncias-no-facturacion/ | N130: Servicio/tema general para contribuyentes
A131: Trámites comunes | B131: Todos los grupos | D131: Atención, quejas y denuncias | E131: Quejas y denuncias | F131: Corrupción e incumplimiento ético | G131: Denunciar corrupción o falta de ética | H131: Requisitos, pasos y documentos para denunciar corrupción o falta de ética. | I131: Varias categorías de contribuyentes | J131: Análisis | K131: Atención, quejas y denuncias | L131: CONTÁCTANOS | M131: https://portal.sat.gob.gt/portal/contacto/denuncias-por-corrupcion/ | N131: Servicio/tema general para contribuyentes
A132: Trámites comunes | B132: Todos los grupos | D132: Atención, quejas y denuncias | E132: Quejas y denuncias | F132: Quejas por mal servicio | G132: Presentar una queja por mal servicio | H132: Requisitos, pasos y documentos para presentar una queja por mal servicio. | I132: Varias categorías de contribuyentes | J132: Análisis | K132: Atención, quejas y denuncias | L132: CONTÁCTANOS | M132: https://portal.sat.gob.gt/portal/contacto/quejas-por-mal-servicio-o-servicio-no-conforme/ | N132: Servicio/tema general para contribuyentes
A133: Trámites comunes | B133: Todos los grupos | D133: Capacitación y orientación aduanera | E133: Legislación aduanera | F133: Legislación Aduanera | G133: Leyes aduaneras | H133: Información sobre: Leyes aduaneras. | I133: Contribuyente General, Contribuyentes Especiales | J133: Grupos y categorías | K133: Marcada «SI» en el archivo Grupos y categorías | L133: CAPACITACIÓN | M133: https://portal.sat.gob.gt/portal/biblioteca-en-linea-sat/legislacion-aduanera/ | N133: Coincide con palabra clave de comercio exterior/aduanas
A134: Trámites comunes | B134: Todos los grupos | D134: Consultas y verificadores | E134: Agencia Virtual | F134: Solicitud de Usuario Agencia Virtual | G134: Solicitar usuario de Agencia Virtual | H134: Requisitos, pasos y documentos para solicitar usuario de Agencia Virtual. | I134: Varias categorías de contribuyentes | J134: Análisis | K134: Consultas y verificadores | L134: SERVICIOS TRIBUTARIOS | M134: https://portal.sat.gob.gt/portal/solicitud-usuario-agencia-virtual/ | N134: Servicio/tema general para contribuyentes
A135: Trámites comunes | B135: Todos los grupos | D135: Consultas y verificadores | E135: Agencia Virtual | F135: Consulta Estado de Gestión de Agencia Virtual | G135: Ver el estado de tu gestión en Agencia Virtual | H135: Servicio en línea para ver el estado de tu gestión en Agencia Virtual. | I135: NIT sin Obligaciones, Contribuyente General | J135: Grupos y categorías | K135: Marcada «SI» en el archivo Grupos y categorías | L135: SERVICIOS TRIBUTARIOS | M135: https://portal.sat.gob.gt/portal/consulta-de-gestion-del-contribuyente/ | N135: Servicio/tema general para contribuyentes
A136: Trámites comunes | B136: Todos los grupos | D136: Consultas y verificadores | E136: Citas y quejas | F136: Consulta estado de cita | G136: Ver el estado de tu cita | H136: Servicio en línea para ver el estado de tu cita. | I136: Pequeños Contribuyentes, Contribuyente General | J136: Grupos y categorías | K136: Marcada «SI» en el archivo Grupos y categorías | L136: SERVICIOS TRIBUTARIOS | M136: https://portal.sat.gob.gt/portal/consulta-estado-de-cita/ | N136: Servicio/tema general para contribuyentes
A137: Trámites comunes | B137: Todos los grupos | D137: Consultas y verificadores | E137: Citas y quejas | F137: Consultar estado de la queja | G137: Ver el estado de tu queja | H137: Servicio en línea para ver el estado de tu queja. | I137: Varias categorías de contribuyentes | J137: Análisis | K137: Consultas y verificadores | L137: CONTÁCTANOS | M137: https://portal.sat.gob.gt/portal/contacto/consulta-estado-de-queja/ | N137: Servicio/tema general para contribuyentes
A138: Trámites comunes | B138: Todos los grupos | D138: Consultas y verificadores | E138: NIT y RTU | F138: Actualización de Datos | G138: Actualizar tus datos | H138: Requisitos, pasos y documentos para actualizar tus datos. | I138: Varias categorías de contribuyentes | J138: Análisis | K138: Consultas y verificadores | L138: SERVICIOS TRIBUTARIOS | M138: https://portal.sat.gob.gt/portal/project/actualizacion-de-datos/ | N138: Servicio/tema general para contribuyentes
A139: Trámites comunes | B139: Todos los grupos | D139: Consultas y verificadores | E139: NIT y RTU | F139: Consulta CUI / NIT | G139: Consultar tu NIT con tu DPI (CUI) | H139: Servicio en línea para consultar tu NIT con tu DPI (CUI). | I139: Varias categorías de contribuyentes | J139: Análisis | K139: Consultas y verificadores | L139: SERVICIOS TRIBUTARIOS | M139: https://portal.sat.gob.gt/portal/consulta-cui-nit/ | N139: Servicio/tema general para contribuyentes
... A357: Trámites comunes | B357: Todos los grupos | D357: Vehículos (como propietario) | E357: Título y tarjeta de circulación | F357: Reposición de Tarjeta de Circulación | G357: Reponer la tarjeta de circulación | H357: Requisitos, pasos y documentos para reponer la tarjeta de circulación. | I357: Varias categorías de contribuyentes | J357: Análisis | K357: Trámites de vehículos que usan todas las categorías | L357: SERVICIOS TRIBUTARIOS | M357: https://portal.sat.gob.gt/portal/requisitos-tramites-agencias/reposicion-de-tarjeta-de-circulacion-con-formulario-electronico-sat-8933/ | N357: Servicio/tema general para contribuyentes

Sheet Operadores de comercio exterior
A1: Operadores de comercio exterior
A2: Importadores, exportadores y auxiliares de la función pública aduanera que intervienen en operaciones de comercio exterior. Orden: Categoría › Grupo › Tema › Página. «Todos los grupos» = la usan todos los grupos de la categoría. «Trámites comunes» = la usan varias categorías.
A4: Macro-Grupo | B4: Actor / Rol | C4: Especialidad / Tema | D4: Área Funcional (Subtema) | E4: Nombre del Trámite | F4: Descripción (Lenguaje Ciudadano Activo) | G4: Control de Auditoría | H4: Etapa Ciclo ATO | I4: Tipo de Interacción | J4: Es Brecha | K4: Ruta de Navegación (Miga de Pan) | L4: URL Oficial SAT | M4: Notas / Justificación
A5: 2. Auxiliares de la Función Pública Aduanera (AFPA) | B5: Apoderados Especiales Aduaneros | C5: Apoderados Especiales Aduaneros | D5: Registro y acreditación | E5: Requisitos para la renovación de operación de auxiliares de la función pública | F5: Presenta la solicitud y cumple los requisitos oficiales ante la SAT para renovar tu autorización anual como Apoderados Especiales Aduaneros. | G5: APROBADO | H5: Empezar y registrarse | I5: Trámite / Aplicativo en Línea | J5: NO | K5: Operadores de Comercio Exterior > 2. Auxiliares de la Función Pública Aduanera (AFPA) > Apoderados Especiales Aduaneros > Registro y acreditación > Requisitos para la renovación de operación de auxiliares de la función pública | L5: https://portal.sat.gob.gt/portal/requisitos-de-aduanas/#1608063945646-f9ebd644-65ff
A6: 2. Auxiliares de la Función Pública Aduanera (AFPA) | B6: Apoderados Especiales Aduaneros | C6: Apoderados Especiales Aduaneros | D6: Registro y acreditación | E6: Auxiliares de la función pública aduanera (Carné, componente ActiveX PKI/DUA) | F6: Gestiona la emisión y actualización de tu carné oficial de identificación para ingresar a recintos aduaneros. | G6: APROBADO | H6: Empezar y registrarse | I6: Descarga de Documento / Software | J6: NO | K6: Operadores de Comercio Exterior > 2. Auxiliares de la Función Pública Aduanera (AFPA) > Apoderados Especiales Aduaneros > Registro y acreditación > Auxiliares de la función pública aduanera (Carné, componente ActiveX PKI/DUA) | L6: https://portal.sat.gob.gt/portal/procedimientos-aduanas/#1570112086149-de895ac7-a87c
A7: 2. Auxiliares de la Función Pública Aduanera (AFPA) | B7: Apoderados Especiales Aduaneros | C7: Apoderados Especiales Aduaneros | D7: Registro y acreditación | E7: Recepción de seguro de caución importación y admisión temporal | F7: Entrega y registra la póliza de fianza o seguro de caución exigido para garantizar tus operaciones aduaneras. | G7: APROBADO | H7: Empezar y registrarse | I7: Trámite / Aplicativo en Línea | J7: NO | K7: Operadores de Comercio Exterior > 2. Auxiliares de la Función Pública Aduanera (AFPA) > Apoderados Especiales Aduaneros > Registro y acreditación > Recepción de seguro de caución importación y admisión temporal | L7: https://portal.sat.gob.gt/portal/requisitos-tramites-agencias/recepcion-de-seguro-de-caucion-importacion-y-admision-temporal/
A8: 2. Auxiliares de la Función Pública Aduanera (AFPA) | B8: Apoderados Especiales Aduaneros | C8: Apoderados Especiales Aduaneros | D8: Registro y acreditación | E8: Solvencia fiscal (Requisito para renovación AFPA) | F8: Obtén tu solvencia fiscal en línea como requisito indispensable para operar y renovar tu acreditación como Apoderados Especiales Aduaneros. | G8: APROBADO | H8: Empezar y registrarse | I8: Trámite / Aplicativo en Línea | J8: NO | K8: Operadores de Comercio Exterior > 2. Auxiliares de la Función Pública Aduanera (AFPA) > Apoderados Especiales Aduaneros > Registro y acreditación > Solvencia fiscal (Requisito para renovación AFPA) | L8: https://portal.sat.gob.gt/portal/solvencia-fiscal/
A9: 2. Auxiliares de la Función Pública Aduanera (AFPA) | B9: Apoderados Especiales Aduaneros | C9: Apoderados Especiales Aduaneros | D9: Registro y acreditación | E9: Autorización inicial y registro de mandato de apoderado especial | F9: Presenta el mandato legal y solicita la autorización inicial ante la SAT para actuar como apoderado especial aduanero. | G9: PENDIENTE (Propuesta brecha) | H9: Empezar y registrarse | I9: Trámite / Aplicativo en Línea | J9: SÍ | K9: Operadores de Comercio Exterior > 2. Auxiliares de la Función Pública Aduanera (AFPA) > Apoderados Especiales Aduaneros > Registro y acreditación > Autorización inicial y registro de mandato de apoderado especial | L9: https://portal.sat.gob.gt/portal/requisitos-de-aduanas/ | M9: Propuesta de brecha normativa identificada para mesa técnica SAT.
A10: 2. Auxiliares de la Función Pública Aduanera (AFPA) | B10: Apoderados Especiales Aduaneros | C10: Apoderados Especiales Aduaneros | D10: Operaciones y trámites | E10: Declaración de mercancías (DUCA y Aduana sin papeles) | F10: Transmite electrónicamente la declaración de mercancías DUCA y gestiona el despacho aduanero ágil. | G10: APROBADO | H10: Operación y declaraciones | I10: Trámite / Aplicativo en Línea | J10: NO | K10: Operadores de Comercio Exterior > 2. Auxiliares de la Función Pública Aduanera (AFPA) > Apoderados Especiales Aduaneros > Operaciones y trámites > Declaración de mercancías (DUCA y Aduana sin papeles) | L10: https://portal.sat.gob.gt/portal/procedimientos-aduanas/
A11: 2. Auxiliares de la Función Pública Aduanera (AFPA) | B11: Apoderados Especiales Aduaneros | C11: Apoderados Especiales Aduaneros | D11: Operaciones y trámites | E11: Declaración anticipada | F11: Presenta tu declaración y paga tributos antes de que arribe el medio de transporte para agilizar el levante. | G11: APROBADO | H11: Operación y declaraciones | I11: Trámite / Aplicativo en Línea | J11: NO | K11: Operadores de Comercio Exterior > 2. Auxiliares de la Función Pública Aduanera (AFPA) > Apoderados Especiales Aduaneros > Operaciones y trámites > Declaración anticipada | L11: https://portal.sat.gob.gt/portal/facilitacion-de-comercio/#1559325573466-1284efd5-2d1b
A12: 2. Auxiliares de la Función Pública Aduanera (AFPA) | B12: Apoderados Especiales Aduaneros | C12: Apoderados Especiales Aduaneros | D12: Operaciones y trámites | E12: Sistema de franquicias electrónicas | F12: Aplica en línea a franquicias aduaneras para gestionar la exención o exoneración de tributos autorizados. | G12: APROBADO | H12: Operación y declaraciones | I12: Trámite / Aplicativo en Línea | J12: NO | K12: Operadores de Comercio Exterior > 2. Auxiliares de la Función Pública Aduanera (AFPA) > Apoderados Especiales Aduaneros > Operaciones y trámites > Sistema de franquicias electrónicas | L12: https://portal.sat.gob.gt/portal/franquicias-electronicas/
A13: 2. Auxiliares de la Función Pública Aduanera (AFPA) | B13: Apoderados Especiales Aduaneros | C13: Apoderados Especiales Aduaneros | D13: Consultas y seguimiento | E13: Consultas de aduanas (Rampa de revisión, revisores, retención/liberación, arancel) | F13: Consulta los aranceles DAI, gravámenes e impuestos del SAC y verifica los permisos no arancelarios exigibles. | G13: APROBADO | H13: Consultas y herramientas | I13: Consulta en Base de Datos | J13: NO | K13: Operadores de Comercio Exterior > 2. Auxiliares de la Función Pública Aduanera (AFPA) > Apoderados Especiales Aduaneros > Consultas y seguimiento > Consultas de aduanas (Rampa de revisión, revisores, retención/liberación, arancel) | L13: https://portal.sat.gob.gt/portal/consultas-aduanas/
A14: 2. Auxiliares de la Función Pública Aduanera (AFPA) | B14: Apoderados Especiales Aduaneros | C14: Apoderados Especiales Aduaneros | D14: Consultas y seguimiento | E14: Requisitos para consulta de expedientes de gestión aduanera | F14: Da seguimiento al estado de avance y resolución del expediente administrativo de tu gestión aduanera. | G14: APROBADO | H14: Consultas y herramientas | I14: Consulta en Base de Datos | J14: NO | K14: Operadores de Comercio Exterior > 2. Auxiliares de la Función Pública Aduanera (AFPA) > Apoderados Especiales Aduaneros > Consultas y seguimiento > Requisitos para consulta de expedientes de gestión aduanera | L14: https://portal.sat.gob.gt/portal/requisitos-de-aduanas/#1542142398181-8db4844a-6760
A15: 2. Auxiliares de la Función Pública Aduanera (AFPA) | B15: Apoderados Especiales Aduaneros | C15: Apoderados Especiales Aduaneros | D15: Consultas y seguimiento | E15: Unión aduanera (Procedimientos y resoluciones) | F15: Consulta los criterios de clasificación arancelaria y resoluciones anticipadas emitidas por la Intendencia de Aduanas. | G15: APROBADO | H15: Consultas y herramientas | I15: Trámite / Aplicativo en Línea | J15: NO | K15: Operadores de Comercio Exterior > 2. Auxiliares de la Función Pública Aduanera (AFPA) > Apoderados Especiales Aduaneros > Consultas y seguimiento > Unión aduanera (Procedimientos y resoluciones) | L15: https://portal.sat.gob.gt/portal/union-aduanera/
A16: 2. Auxiliares de la Función Pública Aduanera (AFPA) | B16: Apoderados Especiales Aduaneros | C16: Apoderados Especiales Aduaneros | D16: Normativa y recursos | E16: Procedimientos, instructivos, manuales y guías para gestiones aduaneras | F16: Desconsolida conocimientos de embarque y guías aéreas hijas para entregar bultos a sus consignatarios. | G16: APROBADO | H16: Normativa y asistencia | I16: Guía Informativa / Texto | J16: NO | K16: Operadores de Comercio Exterior > 2. Auxiliares de la Función Pública Aduanera (AFPA) > Apoderados Especiales Aduaneros > Normativa y recursos > Procedimientos, instructivos, manuales y guías para gestiones aduaneras | L16: https://portal.sat.gob.gt/portal/procedimientos-aduanas/#1571412473853-2ed0b43f-287f
A17: 2. Auxiliares de la Función Pública Aduanera (AFPA) | B17: Apoderados Especiales Aduaneros | C17: Apoderados Especiales Aduaneros | D17: Normativa y recursos | E17: Procedimientos administrativos de aduanas (Sanciones y recursos) | F17: Conoce el régimen de infracciones aduaneras y los procedimientos para interponer recursos de revocatoria. | G17: APROBADO | H17: Normativa y asistencia | I17: Guía Informativa / Texto | J17: NO | K17: Operadores de Comercio Exterior > 2. Auxiliares de la Función Pública Aduanera (AFPA) > Apoderados Especiales Aduaneros > Normativa y recursos > Procedimientos administrativos de aduanas (Sanciones y recursos) | L17: https://portal.sat.gob.gt/portal/procedimientos-aduanas/#1570112033454-be3581a4-383a
A18: 2. Auxiliares de la Función Pública Aduanera (AFPA) | B18: Apoderados Especiales Aduaneros | C18: Apoderados Especiales Aduaneros | D18: Normativa y recursos | E18: Legislación aduanera (Biblioteca en línea SAT) | F18: Descarga y consulta el marco legal, leyes nacionales, CAUCA y RECAUCA aplicables a Apoderados Especiales Aduaneros. | G18: APROBADO | H18: Normativa y asistencia | I18: Guía Informativa / Texto | J18: NO | K18: Operadores de Comercio Exterior > 2. Auxiliares de la Función Pública Aduanera (AFPA) > Apoderados Especiales Aduaneros > Normativa y recursos > Legislación aduanera (Biblioteca en línea SAT) | L18: https://portal.sat.gob.gt/portal/biblioteca-en-linea-sat/legislacion-aduanera/
A19: 2. Auxiliares de la Función Pública Aduanera (AFPA) | B19: Apoderados Especiales Aduaneros | C19: Apoderados Especiales Aduaneros | D19: Normativa y recursos | E19: Preguntas frecuentes sobre temas aduaneros | F19: Resuelve dudas frecuentes sobre normativa, requisitos y procedimientos aduaneros oficiales. | G19: APROBADO | H19: Normativa y asistencia | I19: Guía Informativa / Texto | J19: NO | K19: Operadores de Comercio Exterior > 2. Auxiliares de la Función Pública Aduanera (AFPA) > Apoderados Especiales Aduaneros > Normativa y recursos > Preguntas frecuentes sobre temas aduaneros | L19: https://portal.sat.gob.gt/portal/preguntas-frecuentes/temas-aduaneros/
A20: 2. Auxiliares de la Función Pública Aduanera (AFPA) | B20: Apoderados Especiales Aduaneros | C20: Apoderados Especiales Aduaneros | D20: Normativa y recursos | E20: Capacitaciones para auxiliares de la función pública | F20: Inscríbete en capacitaciones, talleres y diplomados aduaneros impartidos por la SAT para Apoderados Especiales Aduaneros. | G20: APROBADO | H20: Normativa y asistencia | I20: Guía Informativa / Texto | J20: NO | K20: Operadores de Comercio Exterior > 2. Auxiliares de la Función Pública Aduanera (AFPA) > Apoderados Especiales Aduaneros > Normativa y recursos > Capacitaciones para auxiliares de la función pública | L20: https://portal.sat.gob.gt/portal/#capacitacion
A21: 2. Auxiliares de la Función Pública Aduanera (AFPA) | B21: Depósitos Aduaneros | C21: Almacenes Fiscales | D21: Registro y acreditación | E21: Requisitos para la renovación de operación de auxiliares de la función pública | F21: Presenta la solicitud y cumple los requisitos oficiales ante la SAT para renovar tu autorización anual como Depósitos Aduaneros. | G21: APROBADO | H21: Empezar y registrarse | I21: Trámite / Aplicativo en Línea | J21: NO | K21: Operadores de Comercio Exterior > 2. Auxiliares de la Función Pública Aduanera (AFPA) > Depósitos Aduaneros > Almacenes Fiscales > Registro y acreditación > Requisitos para la renovación de operación de auxiliares de la función pública | L21: https://portal.sat.gob.gt/portal/requisitos-de-aduanas/#1608063945646-f9ebd644-65ff
... A24: 2. Auxiliares de la Función Pública Aduanera (AFPA) | B24: Depósitos Aduaneros | C24: Almacenes Fiscales | D24: Registro y acreditación | E24: Solvencia fiscal (Requisito indispensable de renovación AFPA) | F24: Obtén tu solvencia fiscal en línea como requisito indispensable para operar y renovar tu acreditación como Depósitos Aduaneros. | G24: APROBADO | H24: Empezar y registrarse | I24: Trámite / Aplicativo en Línea | J24: NO | K24: Operadores de Comercio Exterior > 2. Auxiliares de la Función Pública Aduanera (AFPA) > Depósitos Aduaneros > Almacenes Fiscales > Registro y acreditación > Solvencia fiscal (Requisito indispensable de renovación AFPA) | L24: https://portal.sat.gob.gt/portal/solvencia-fiscal/
A25: 2. Auxiliares de la Función Pública Aduanera (AFPA) | B25: Depósitos Aduaneros | C25: Almacenes Fiscales | D25: Registro y acreditación | E25: Requisitos para habilitación y ampliación de recintos de depósito fiscal | F25: Gestiona los requisitos y autorizaciones técnicas ante la SAT para habilitar o ampliar recintos de depósito fiscal. | G25: PENDIENTE (Propuesta brecha) | H25: Empezar y registrarse | I25: Trámite / Aplicativo en Línea | J25: SÍ | K25: Operadores de Comercio Exterior > 2. Auxiliares de la Función Pública Aduanera (AFPA) > Depósitos Aduaneros > Almacenes Fiscales > Registro y acreditación > Requisitos para habilitación y ampliación de recintos de depósito fiscal | L25: https://portal.sat.gob.gt/portal/requisitos-de-aduanas/ | M25: Propuesta de brecha normativa identificada para mesa técnica SAT.
A26: 2. Auxiliares de la Función Pública Aduanera (AFPA) | B26: Depósitos Aduaneros | C26: Almacenes Fiscales | D26: Operaciones y trámites | E26: Procedimientos, instructivos y guías para gestiones aduaneras de depósito | F26: Desconsolida conocimientos de embarque y guías aéreas hijas para entregar bultos a sus consignatarios. | G26: APROBADO | H26: Operación y declaraciones | I26: Guía Informativa / Texto | J26: NO | K26: Operadores de Comercio Exterior > 2. Auxiliares de la Función Pública Aduanera (AFPA) > Depósitos Aduaneros > Almacenes Fiscales > Operaciones y trámites > Procedimientos, instructivos y guías para gestiones aduaneras de depósito | L26: https://portal.sat.gob.gt/portal/procedimientos-aduanas/#1571412473853-2ed0b43f-287f
A27: 2. Auxiliares de la Función Pública Aduanera (AFPA) | B27: Depósitos Aduaneros | C27: Almacenes Fiscales | D27: Operaciones y trámites | E27: Declaración de mercancías (DUCA, tránsitos y aduana sin papeles) | F27: Transmite electrónicamente la declaración de mercancías DUCA y gestiona el despacho aduanero ágil. | G27: APROBADO | H27: Operación y declaraciones | I27: Trámite / Aplicativo en Línea | J27: NO | K27: Operadores de Comercio Exterior > 2. Auxiliares de la Función Pública Aduanera (AFPA) > Depósitos Aduaneros > Almacenes Fiscales > Operaciones y trámites > Declaración de mercancías (DUCA, tránsitos y aduana sin papeles) | L27: https://portal.sat.gob.gt/portal/procedimientos-aduanas/
A28: 2. Auxiliares de la Función Pública Aduanera (AFPA) | B28: Depósitos Aduaneros | C28: Almacenes Fiscales | D28: Operaciones y trámites | E28: Programa de modernización integral aduanera (MIAD) | F28: Conoce los lineamientos y avances del Programa de Modernización Integral Aduanera (MIAD) de la SAT. | G28: APROBADO | H28: Operación y declaraciones | I28: Guía Informativa / Texto | J28: NO | K28: Operadores de Comercio Exterior > 2. Auxiliares de la Función Pública Aduanera (AFPA) > Depósitos Aduaneros > Almacenes Fiscales > Operaciones y trámites > Programa de modernización integral aduanera (MIAD) | L28: https://portal.sat.gob.gt/portal/programa-miad/
A29: 2. Auxiliares de la Función Pública Aduanera (AFPA) | B29: Depósitos Aduaneros | C29: Almacenes Fiscales | D29: Operaciones y trámites | E29: Transmisión y control de inventarios bajo régimen de depósito aduanero | F29: Transmite los movimientos de entrada y salida para el control de inventarios de mercancías bajo régimen de depósito aduanero. | G29: PENDIENTE (Propuesta brecha) | H29: Operación y declaraciones | I29: Consulta en Base de Datos | J29: SÍ | K29: Operadores de Comercio Exterior > 2. Auxiliares de la Función Pública Aduanera (AFPA) > Depósitos Aduaneros > Almacenes Fiscales > Operaciones y trámites > Transmisión y control de inventarios bajo régimen de depósito aduanero | L29: https://portal.sat.gob.gt/portal/procedimientos-aduanas/ | M29: Propuesta de brecha normativa identificada para mesa técnica SAT.
A30: 2. Auxiliares de la Función Pública Aduanera (AFPA) | B30: Depósitos Aduaneros | C30: Almacenes Fiscales | D30: Consultas y seguimiento | E30: Consultas de aduanas (Retención, liberación, rampa y control de permanencia) | F30: Consulta el estado público de retención o liberación de mercancías en recintos portuarios y aduaneros. | G30: APROBADO | H30: Consultas y herramientas | I30: Consulta en Base de Datos | J30: NO | K30: Operadores de Comercio Exterior > 2. Auxiliares de la Función Pública Aduanera (AFPA) > Depósitos Aduaneros > Almacenes Fiscales > Consultas y seguimiento > Consultas de aduanas (Retención, liberación, rampa y control de permanencia) | L30: https://portal.sat.gob.gt/portal/consultas-aduanas/
A31: 2. Auxiliares de la Función Pública Aduanera (AFPA) | B31: Depósitos Aduaneros | C31: Almacenes Fiscales | D31: Consultas y seguimiento | E31: Requisitos para consulta de expedientes de gestión aduanera | F31: Da seguimiento al estado de avance y resolución del expediente administrativo de tu gestión aduanera. | G31: APROBADO | H31: Consultas y herramientas | I31: Consulta en Base de Datos | J31: NO | K31: Operadores de Comercio Exterior > 2. Auxiliares de la Función Pública Aduanera (AFPA) > Depósitos Aduaneros > Almacenes Fiscales > Consultas y seguimiento > Requisitos para consulta de expedientes de gestión aduanera | L31: https://portal.sat.gob.gt/portal/requisitos-de-aduanas/#1542142398181-8db4844a-6760
A32: 2. Auxiliares de la Función Pública Aduanera (AFPA) | B32: Depósitos Aduaneros | C32: Almacenes Fiscales | D32: Consultas y seguimiento | E32: Consulta y facilidades de pago de convenios tributarios | F32: Consulta el estado de cuotas y facilidades de pago autorizadas bajo convenios tributarios ante la SAT. | G32: APROBADO | H32: Consultas y herramientas | I32: Consulta en Base de Datos | J32: NO | K32: Operadores de Comercio Exterior > 2. Auxiliares de la Función Pública Aduanera (AFPA) > Depósitos Aduaneros > Almacenes Fiscales > Consultas y seguimiento > Consulta y facilidades de pago de convenios tributarios | L32: https://portal.sat.gob.gt/portal/consulta-movimiento-convenio/
A33: 2. Auxiliares de la Función Pública Aduanera (AFPA) | B33: Depósitos Aduaneros | C33: Almacenes Fiscales | D33: Normativa y recursos | E33: Legislación aduanera (RECAUCA Art. 119 y normativa de depósitos) | F33: Descarga y consulta el marco legal, leyes nacionales, CAUCA y RECAUCA aplicables a Depósitos Aduaneros. | G33: APROBADO | H33: Normativa y asistencia | I33: Guía Informativa / Texto | J33: NO | K33: Operadores de Comercio Exterior > 2. Auxiliares de la Función Pública Aduanera (AFPA) > Depósitos Aduaneros > Almacenes Fiscales > Normativa y recursos > Legislación aduanera (RECAUCA Art. 119 y normativa de depósitos) | L33: https://portal.sat.gob.gt/portal/biblioteca-en-linea-sat/legislacion-aduanera/
A34: 2. Auxiliares de la Función Pública Aduanera (AFPA) | B34: Depósitos Aduaneros | C34: Almacenes Fiscales | D34: Normativa y recursos | E34: Procedimientos administrativos de aduanas (Sanciones y recursos) | F34: Conoce el régimen de infracciones aduaneras y los procedimientos para interponer recursos de revocatoria. | G34: APROBADO | H34: Normativa y asistencia | I34: Guía Informativa / Texto | J34: NO | K34: Operadores de Comercio Exterior > 2. Auxiliares de la Función Pública Aduanera (AFPA) > Depósitos Aduaneros > Almacenes Fiscales > Normativa y recursos > Procedimientos administrativos de aduanas (Sanciones y recursos) | L34: https://portal.sat.gob.gt/portal/procedimientos-aduanas/#1570112033454-be3581a4-383a
A35: 2. Auxiliares de la Función Pública Aduanera (AFPA) | B35: Depósitos Aduaneros | C35: Almacenes Fiscales | D35: Normativa y recursos | E35: Preguntas frecuentes sobre temas aduaneros | F35: Resuelve dudas frecuentes sobre normativa, requisitos y procedimientos aduaneros oficiales. | G35: APROBADO | H35: Normativa y asistencia | I35: Guía Informativa / Texto | J35: NO | K35: Operadores de Comercio Exterior > 2. Auxiliares de la Función Pública Aduanera (AFPA) > Depósitos Aduaneros > Almacenes Fiscales > Normativa y recursos > Preguntas frecuentes sobre temas aduaneros | L35: https://portal.sat.gob.gt/portal/preguntas-frecuentes/temas-aduaneros/
A36: 2. Auxiliares de la Función Pública Aduanera (AFPA) | B36: Depósitos Aduaneros | C36: Almacenes Fiscales | D36: Normativa y recursos | E36: Capacitaciones para auxiliares de la función pública | F36: Inscríbete en capacitaciones, talleres y diplomados aduaneros impartidos por la SAT para Depósitos Aduaneros. | G36: APROBADO | H36: Normativa y asistencia | I36: Guía Informativa / Texto | J36: NO | K36: Operadores de Comercio Exterior > 2. Auxiliares de la Función Pública Aduanera (AFPA) > Depósitos Aduaneros > Almacenes Fiscales > Normativa y recursos > Capacitaciones para auxiliares de la función pública | L36: https://portal.sat.gob.gt/portal/#capacitacion
A37: 2. Auxiliares de la Función Pública Aduanera (AFPA) | B37: Depósitos Aduaneros | C37: Almacenes Generales de Depósito | D37: Registro y acreditación | E37: Requisitos para la renovación de operación de auxiliares de la función pública | F37: Presenta la solicitud y cumple los requisitos oficiales ante la SAT para renovar tu autorización anual como Depósitos Aduaneros. | G37: APROBADO | H37: Empezar y registrarse | I37: Trámite / Aplicativo en Línea | J37: NO | K37: Operadores de Comercio Exterior > 2. Auxiliares de la Función Pública Aduanera (AFPA) > Depósitos Aduaneros > Almacenes Generales de Depósito > Registro y acreditación > Requisitos para la renovación de operación de auxiliares de la función pública | L37: https://portal.sat.gob.gt/portal/requisitos-de-aduanas/#1608063945646-f9ebd644-65ff
A38: 2. Auxiliares de la Función Pública Aduanera (AFPA) | B38: Depósitos Aduaneros | C38: Almacenes Generales de Depósito | D38: Registro y acreditación | E38: Auxiliares de la función pública aduanera (Carné, componente ActiveX PKI/DUA) | F38: Gestiona la emisión y actualización de tu carné oficial de identificación para ingresar a recintos aduaneros. | G38: APROBADO | H38: Empezar y registrarse | I38: Descarga de Documento / Software | J38: NO | K38: Operadores de Comercio Exterior > 2. Auxiliares de la Función Pública Aduanera (AFPA) > Depósitos Aduaneros > Almacenes Generales de Depósito > Registro y acreditación > Auxiliares de la función pública aduanera (Carné, componente ActiveX PKI/DUA) | L38: https://portal.sat.gob.gt/portal/procedimientos-aduanas/#1570112086149-de895ac7-a87c
A39: 2. Auxiliares de la Función Pública Aduanera (AFPA) | B39: Depósitos Aduaneros | C39: Almacenes Generales de Depósito | D39: Registro y acreditación | E39: Recepción de seguro de caución y pólizas de garantía operativa | F39: Entrega y registra la póliza de fianza o seguro de caución exigido para garantizar tus operaciones aduaneras. | G39: APROBADO | H39: Empezar y registrarse | I39: Consulta en Base de Datos | J39: NO | K39: Operadores de Comercio Exterior > 2. Auxiliares de la Función Pública Aduanera (AFPA) > Depósitos Aduaneros > Almacenes Generales de Depósito > Registro y acreditación > Recepción de seguro de caución y pólizas de garantía operativa | L39: https://portal.sat.gob.gt/portal/requisitos-tramites-agencias/recepcion-de-seguro-de-caucion-importacion-y-admision-temporal/
A40: 2. Auxiliares de la Función Pública Aduanera (AFPA) | B40: Depósitos Aduaneros | C40: Almacenes Generales de Depósito | D40: Registro y acreditación | E40: Solvencia fiscal (Requisito indispensable de renovación AFPA) | F40: Obtén tu solvencia fiscal en línea como requisito indispensable para operar y renovar tu acreditación como Depósitos Aduaneros. | G40: APROBADO | H40: Empezar y registrarse | I40: Trámite / Aplicativo en Línea | J40: NO | K40: Operadores de Comercio Exterior > 2. Auxiliares de la Función Pública Aduanera (AFPA) > Depósitos Aduaneros > Almacenes Generales de Depósito > Registro y acreditación > Solvencia fiscal (Requisito indispensable de renovación AFPA) | L40: https://portal.sat.gob.gt/portal/solvencia-fiscal/
A41: 2. Auxiliares de la Función Pública Aduanera (AFPA) | B41: Depósitos Aduaneros | C41: Almacenes Generales de Depósito | D41: Registro y acreditación | E41: Registro y emisión de títulos de crédito (Certificados de depósito y bonos de prenda) | F41: Emite y registra formalmente certificados de depósito y bonos de prenda conforme a las disposiciones del Decreto 1236. | G41: PENDIENTE (Propuesta brecha) | H41: Empezar y registrarse | I41: Trámite / Aplicativo en Línea | J41: SÍ | K41: Operadores de Comercio Exterior > 2. Auxiliares de la Función Pública Aduanera (AFPA) > Depósitos Aduaneros > Almacenes Generales de Depósito > Registro y acreditación > Registro y emisión de títulos de crédito (Certificados de depósito y bonos de prenda) | L41: https://portal.sat.gob.gt/portal/requisitos-de-aduanas/ | M41: Propuesta de brecha normativa identificada para mesa técnica SAT.
A42: 2. Auxiliares de la Función Pública Aduanera (AFPA) | B42: Depósitos Aduaneros | C42: Almacenes Generales de Depósito | D42: Operaciones y trámites | E42: Procedimientos, instructivos y guías para gestiones aduaneras | F42: Desconsolida conocimientos de embarque y guías aéreas hijas para entregar bultos a sus consignatarios. | G42: APROBADO | H42: Operación y declaraciones | I42: Guía Informativa / Texto | J42: NO | K42: Operadores de Comercio Exterior > 2. Auxiliares de la Función Pública Aduanera (AFPA) > Depósitos Aduaneros > Almacenes Generales de Depósito > Operaciones y trámites > Procedimientos, instructivos y guías para gestiones aduaneras | L42: https://portal.sat.gob.gt/portal/procedimientos-aduanas/#1571412473853-2ed0b43f-287f
A43: 2. Auxiliares de la Función Pública Aduanera (AFPA) | B43: Depósitos Aduaneros | C43: Almacenes Generales de Depósito | D43: Operaciones y trámites | E43: Declaración de mercancías (DUCA y aduana sin papeles) | F43: Transmite electrónicamente la declaración de mercancías DUCA y gestiona el despacho aduanero ágil. | G43: APROBADO | H43: Operación y declaraciones | I43: Trámite / Aplicativo en Línea | J43: NO | K43: Operadores de Comercio Exterior > 2. Auxiliares de la Función Pública Aduanera (AFPA) > Depósitos Aduaneros > Almacenes Generales de Depósito > Operaciones y trámites > Declaración de mercancías (DUCA y aduana sin papeles) | L43: https://portal.sat.gob.gt/portal/procedimientos-aduanas/
A44: 2. Auxiliares de la Función Pública Aduanera (AFPA) | B44: Depósitos Aduaneros | C44: Almacenes Generales de Depósito | D44: Operaciones y trámites | E44: Programa de modernización integral aduanera (MIAD) | F44: Conoce los lineamientos y avances del Programa de Modernización Integral Aduanera (MIAD) de la SAT. | G44: APROBADO | H44: Operación y declaraciones | I44: Guía Informativa / Texto | J44: NO | K44: Operadores de Comercio Exterior > 2. Auxiliares de la Función Pública Aduanera (AFPA) > Depósitos Aduaneros > Almacenes Generales de Depósito > Operaciones y trámites > Programa de modernización integral aduanera (MIAD) | L44: https://portal.sat.gob.gt/portal/programa-miad/
A45: 2. Auxiliares de la Función Pública Aduanera (AFPA) | B45: Depósitos Aduaneros | C45: Almacenes Generales de Depósito | D45: Operaciones y trámites | E45: Reporte de saldos y existencias afianzadas ante SAT | F45: Presenta el reporte oficial de existencias y saldos de mercancías bajo fianza almacenadas en el recinto fiscal. | G45: PENDIENTE (Propuesta brecha) | H45: Operación y declaraciones | I45: Trámite / Aplicativo en Línea | J45: SÍ | K45: Operadores de Comercio Exterior > 2. Auxiliares de la Función Pública Aduanera (AFPA) > Depósitos Aduaneros > Almacenes Generales de Depósito > Operaciones y trámites > Reporte de saldos y existencias afianzadas ante SAT | L45: https://portal.sat.gob.gt/portal/procedimientos-aduanas/ | M45: Propuesta de brecha normativa identificada para mesa técnica SAT.
A46: 2. Auxiliares de la Función Pública Aduanera (AFPA) | B46: Depósitos Aduaneros | C46: Almacenes Generales de Depósito | D46: Consultas y seguimiento | E46: Consultas de aduanas (Retención y liberación de mercancías, arancel integrado) | F46: Consulta los aranceles DAI, gravámenes e impuestos del SAC y verifica los permisos no arancelarios exigibles. | G46: APROBADO | H46: Consultas y herramientas | I46: Consulta en Base de Datos | J46: NO | K46: Operadores de Comercio Exterior > 2. Auxiliares de la Función Pública Aduanera (AFPA) > Depósitos Aduaneros > Almacenes Generales de Depósito > Consultas y seguimiento > Consultas de aduanas (Retención y liberación de mercancías, arancel integrado) | L46: https://portal.sat.gob.gt/portal/consultas-aduanas/
A47: 2. Auxiliares de la Función Pública Aduanera (AFPA) | B47: Depósitos Aduaneros | C47: Almacenes Generales de Depósito | D47: Consultas y seguimiento | E47: Requisitos para consulta de expedientes de gestión aduanera | F47: Da seguimiento al estado de avance y resolución del expediente administrativo de tu gestión aduanera. | G47: APROBADO | H47: Consultas y herramientas | I47: Consulta en Base de Datos | J47: NO | K47: Operadores de Comercio Exterior > 2. Auxiliares de la Función Pública Aduanera (AFPA) > Depósitos Aduaneros > Almacenes Generales de Depósito > Consultas y seguimiento > Requisitos para consulta de expedientes de gestión aduanera | L47: https://portal.sat.gob.gt/portal/requisitos-de-aduanas/#1542142398181-8db4844a-6760
A48: 2. Auxiliares de la Función Pública Aduanera (AFPA) | B48: Depósitos Aduaneros | C48: Almacenes Generales de Depósito | D48: Consultas y seguimiento | E48: Consulta facilidades de pago y convenios | F48: Consulta el estado de cuotas y facilidades de pago autorizadas bajo convenios tributarios ante la SAT. | G48: APROBADO | H48: Consultas y herramientas | I48: Consulta en Base de Datos | J48: NO | K48: Operadores de Comercio Exterior > 2. Auxiliares de la Función Pública Aduanera (AFPA) > Depósitos Aduaneros > Almacenes Generales de Depósito > Consultas y seguimiento > Consulta facilidades de pago y convenios | L48: https://portal.sat.gob.gt/portal/consulta-movimiento-convenio/
A49: 2. Auxiliares de la Función Pública Aduanera (AFPA) | B49: Depósitos Aduaneros | C49: Almacenes Generales de Depósito | D49: Normativa y recursos | E49: Legislación aduanera y financiera (Decreto 1236 y RECAUCA) | F49: Descarga y consulta el marco legal, leyes nacionales, CAUCA y RECAUCA aplicables a Depósitos Aduaneros. | G49: APROBADO | H49: Normativa y asistencia | I49: Guía Informativa / Texto | J49: NO | K49: Operadores de Comercio Exterior > 2. Auxiliares de la Función Pública Aduanera (AFPA) > Depósitos Aduaneros > Almacenes Generales de Depósito > Normativa y recursos > Legislación aduanera y financiera (Decreto 1236 y RECAUCA) | L49: https://portal.sat.gob.gt/portal/biblioteca-en-linea-sat/legislacion-aduanera/
A50: 2. Auxiliares de la Función Pública Aduanera (AFPA) | B50: Depósitos Aduaneros | C50: Almacenes Generales de Depósito | D50: Normativa y recursos | E50: Procedimientos administrativos de aduanas (Sanciones y recursos) | F50: Conoce el régimen de infracciones aduaneras y los procedimientos para interponer recursos de revocatoria. | G50: APROBADO | H50: Normativa y asistencia | I50: Guía Informativa / Texto | J50: NO | K50: Operadores de Comercio Exterior > 2. Auxiliares de la Función Pública Aduanera (AFPA) > Depósitos Aduaneros > Almacenes Generales de Depósito > Normativa y recursos > Procedimientos administrativos de aduanas (Sanciones y recursos) | L50: https://portal.sat.gob.gt/portal/procedimientos-aduanas/#1570112033454-be3581a4-383a
A51: 2. Auxiliares de la Función Pública Aduanera (AFPA) | B51: Depósitos Aduaneros | C51: Almacenes Generales de Depósito | D51: Normativa y recursos | E51: Preguntas frecuentes sobre temas aduaneros | F51: Resuelve dudas frecuentes sobre normativa, requisitos y procedimientos aduaneros oficiales. | G51: APROBADO | H51: Normativa y asistencia | I51: Guía Informativa / Texto | J51: NO | K51: Operadores de Comercio Exterior > 2. Auxiliares de la Función Pública Aduanera (AFPA) > Depósitos Aduaneros > Almacenes Generales de Depósito > Normativa y recursos > Preguntas frecuentes sobre temas aduaneros | L51: https://portal.sat.gob.gt/portal/preguntas-frecuentes/temas-aduaneros/
A52: 2. Auxiliares de la Función Pública Aduanera (AFPA) | B52: Depósitos Aduaneros | C52: Almacenes Generales de Depósito | D52: Normativa y recursos | E52: Capacitaciones para auxiliares de la función pública | F52: Inscríbete en capacitaciones, talleres y diplomados aduaneros impartidos por la SAT para Depósitos Aduaneros. | G52: APROBADO | H52: Normativa y asistencia | I52: Guía Informativa / Texto | J52: NO | K52: Operadores de Comercio Exterior > 2. Auxiliares de la Función Pública Aduanera (AFPA) > Depósitos Aduaneros > Almacenes Generales de Depósito > Normativa y recursos > Capacitaciones para auxiliares de la función pública | L52: https://portal.sat.gob.gt/portal/#capacitacion
A53: 2. Auxiliares de la Función Pública Aduanera (AFPA) | B53: Depósitos Aduaneros | C53: Depósitos Aduaneros Temporales (DAT) | D53: Registro y acreditación | E53: Requisitos para la renovación de operación de auxiliares de la función pública | F53: Presenta la solicitud y cumple los requisitos oficiales ante la SAT para renovar tu autorización anual como Depósitos Aduaneros. | G53: APROBADO | H53: Empezar y registrarse | I53: Trámite / Aplicativo en Línea | J53: NO | K53: Operadores de Comercio Exterior > 2. Auxiliares de la Función Pública Aduanera (AFPA) > Depósitos Aduaneros > Depósitos Aduaneros Temporales (DAT) > Registro y acreditación > Requisitos para la renovación de operación de auxiliares de la función pública | L53: https://portal.sat.gob.gt/portal/requisitos-de-aduanas/#1608063945646-f9ebd644-65ff
A54: 2. Auxiliares de la Función Pública Aduanera (AFPA) | B54: Depósitos Aduaneros | C54: Depósitos Aduaneros Temporales (DAT) | D54: Registro y acreditación | E54: Auxiliares de la función pública aduanera (Carné, componente ActiveX PKI/DUA) | F54: Gestiona la emisión y actualización de tu carné oficial de identificación para ingresar a recintos aduaneros. | G54: APROBADO | H54: Empezar y registrarse | I54: Descarga de Documento / Software | J54: NO | K54: Operadores de Comercio Exterior > 2. Auxiliares de la Función Pública Aduanera (AFPA) > Depósitos Aduaneros > Depósitos Aduaneros Temporales (DAT) > Registro y acreditación > Auxiliares de la función pública aduanera (Carné, componente ActiveX PKI/DUA) | L54: https://portal.sat.gob.gt/portal/procedimientos-aduanas/#1570112086149-de895ac7-a87c
A55: 2. Auxiliares de la Función Pública Aduanera (AFPA) | B55: Depósitos Aduaneros | C55: Depósitos Aduaneros Temporales (DAT) | D55: Registro y acreditación | E55: Recepción de seguro de caución y pólizas de garantía operativa | F55: Entrega y registra la póliza de fianza o seguro de caución exigido para garantizar tus operaciones aduaneras. | G55: APROBADO | H55: Empezar y registrarse | I55: Consulta en Base de Datos | J55: NO | K55: Operadores de Comercio Exterior > 2. Auxiliares de la Función Pública Aduanera (AFPA) > Depósitos Aduaneros > Depósitos Aduaneros Temporales (DAT) > Registro y acreditación > Recepción de seguro de caución y pólizas de garantía operativa | L55: https://portal.sat.gob.gt/portal/requisitos-tramites-agencias/recepcion-de-seguro-de-caucion-importacion-y-admision-temporal/
A56: 2. Auxiliares de la Función Pública Aduanera (AFPA) | B56: Depósitos Aduaneros | C56: Depósitos Aduaneros Temporales (DAT) | D56: Registro y acreditación | E56: Solvencia fiscal (Requisito para renovación AFPA) | F56: Obtén tu solvencia fiscal en línea como requisito indispensable para operar y renovar tu acreditación como Depósitos Aduaneros. | G56: APROBADO | H56: Empezar y registrarse | I56: Trámite / Aplicativo en Línea | J56: NO | K56: Operadores de Comercio Exterior > 2. Auxiliares de la Función Pública Aduanera (AFPA) > Depósitos Aduaneros > Depósitos Aduaneros Temporales (DAT) > Registro y acreditación > Solvencia fiscal (Requisito para renovación AFPA) | L56: https://portal.sat.gob.gt/portal/solvencia-fiscal/
A57: 2. Auxiliares de la Función Pública Aduanera (AFPA) | B57: Depósitos Aduaneros | C57: Depósitos Aduaneros Temporales (DAT) | D57: Registro y acreditación | E57: Requisitos para habilitación y delimitación de recintos aduaneros temporales (DAT) | F57: Cumple los requisitos técnicos y perimetrales para la habilitación oficial de Depósitos Aduaneros Temporales ante la SAT. | G57: PENDIENTE (Propuesta brecha) | H57: Empezar y registrarse | I57: Trámite / Aplicativo en Línea | J57: SÍ | K57: Operadores de Comercio Exterior > 2. Auxiliares de la Función Pública Aduanera (AFPA) > Depósitos Aduaneros > Depósitos Aduaneros Temporales (DAT) > Registro y acreditación > Requisitos para habilitación y delimitación de recintos aduaneros temporales (DAT) | L57: https://portal.sat.gob.gt/portal/requisitos-de-aduanas/ | M57: Propuesta de brecha normativa identificada para mesa técnica SAT.
A58: 2. Auxiliares de la Función Pública Aduanera (AFPA) | B58: Depósitos Aduaneros | C58: Depósitos Aduaneros Temporales (DAT) | D58: Operaciones y trámites | E58: Registro de admisión temporal de contenedores terrestres y su ampliación | F58: Inscríbete en el registro oficial de la SAT cumpliendo los requisitos legales para operar como Depósitos Aduaneros. | G58: APROBADO | H58: Operación y declaraciones | I58: Trámite / Aplicativo en Línea | J58: NO | K58: Operadores de Comercio Exterior > 2. Auxiliares de la Función Pública Aduanera (AFPA) > Depósitos Aduaneros > Depósitos Aduaneros Temporales (DAT) > Operaciones y trámites > Registro de admisión temporal de contenedores terrestres y su ampliación | L58: https://portal.sat.gob.gt/portal/consultas-aduanas/
A59: 2. Auxiliares de la Función Pública Aduanera (AFPA) | B59: Depósitos Aduaneros | C59: Depósitos Aduaneros Temporales (DAT) | D59: Operaciones y trámites | E59: Procedimientos, instructivos y guías para gestiones aduaneras | F59: Desconsolida conocimientos de embarque y guías aéreas hijas para entregar bultos a sus consignatarios. | G59: APROBADO | H59: Operación y declaraciones | I59: Guía Informativa / Texto | J59: NO | K59: Operadores de Comercio Exterior > 2. Auxiliares de la Función Pública Aduanera (AFPA) > Depósitos Aduaneros > Depósitos Aduaneros Temporales (DAT) > Operaciones y trámites > Procedimientos, instructivos y guías para gestiones aduaneras | L59: https://portal.sat.gob.gt/portal/procedimientos-aduanas/#1571412473853-2ed0b43f-287f
A60: 2. Auxiliares de la Función Pública Aduanera (AFPA) | B60: Depósitos Aduaneros | C60: Depósitos Aduaneros Temporales (DAT) | D60: Operaciones y trámites | E60: Declaración de mercancías (DUCA y aduana sin papeles) | F60: Transmite electrónicamente la declaración de mercancías DUCA y gestiona el despacho aduanero ágil. | G60: APROBADO | H60: Operación y declaraciones | I60: Trámite / Aplicativo en Línea | J60: NO | K60: Operadores de Comercio Exterior > 2. Auxiliares de la Función Pública Aduanera (AFPA) > Depósitos Aduaneros > Depósitos Aduaneros Temporales (DAT) > Operaciones y trámites > Declaración de mercancías (DUCA y aduana sin papeles) | L60: https://portal.sat.gob.gt/portal/procedimientos-aduanas/
A61: 2. Auxiliares de la Función Pública Aduanera (AFPA) | B61: Depósitos Aduaneros | C61: Depósitos Aduaneros Temporales (DAT) | D61: Operaciones y trámites | E61: Control de descarga, ingreso de bultos y actas de recepción DAT | F61: Registra la recepción de bultos y emite las actas oficiales de descarga e ingreso de mercancías al recinto aduanero temporal. | G61: PENDIENTE (Propuesta brecha) | H61: Operación y declaraciones | I61: Trámite / Aplicativo en Línea | J61: SÍ | K61: Operadores de Comercio Exterior > 2. Auxiliares de la Función Pública Aduanera (AFPA) > Depósitos Aduaneros > Depósitos Aduaneros Temporales (DAT) > Operaciones y trámites > Control de descarga, ingreso de bultos y actas de recepción DAT | L61: https://portal.sat.gob.gt/portal/procedimientos-aduanas/ | M61: Propuesta de brecha normativa identificada para mesa técnica SAT.
A62: 2. Auxiliares de la Función Pública Aduanera (AFPA) | B62: Depósitos Aduaneros | C62: Depósitos Aduaneros Temporales (DAT) | D62: Consultas y seguimiento | E62: Consultas de aduanas (Asignación a rampa de revisión, revisores, retención y liberación) | F62: Consulta el estado público de retención o liberación de mercancías en recintos portuarios y aduaneros. | G62: APROBADO | H62: Consultas y herramientas | I62: Consulta en Base de Datos | J62: NO | K62: Operadores de Comercio Exterior > 2. Auxiliares de la Función Pública Aduanera (AFPA) > Depósitos Aduaneros > Depósitos Aduaneros Temporales (DAT) > Consultas y seguimiento > Consultas de aduanas (Asignación a rampa de revisión, revisores, retención y liberación) | L62: https://portal.sat.gob.gt/portal/consultas-aduanas/
A63: 2. Auxiliares de la Función Pública Aduanera (AFPA) | B63: Depósitos Aduaneros | C63: Depósitos Aduaneros Temporales (DAT) | D63: Consultas y seguimiento | E63: Sistema de cobro por permanencia en el país | F63: Calcula y consulta las tarifas por días de permanencia de mercancías bajo control fiscal antes del levante. | G63: APROBADO | H63: Consultas y herramientas | I63: Trámite / Aplicativo en Línea | J63: NO | K63: Operadores de Comercio Exterior > 2. Auxiliares de la Función Pública Aduanera (AFPA) > Depósitos Aduaneros > Depósitos Aduaneros Temporales (DAT) > Consultas y seguimiento > Sistema de cobro por permanencia en el país | L63: https://portal.sat.gob.gt/portal/consultas-aduanas/
A64: 2. Auxiliares de la Función Pública Aduanera (AFPA) | B64: Depósitos Aduaneros | C64: Depósitos Aduaneros Temporales (DAT) | D64: Consultas y seguimiento | E64: Monitoreo de sistemas informáticos de aduanas | F64: Verifica el estado operativo y disponibilidad de los sistemas informáticos y enlaces de la Intendencia de Aduanas. | G64: APROBADO | H64: Consultas y herramientas | I64: Consulta en Base de Datos | J64: NO | K64: Operadores de Comercio Exterior > 2. Auxiliares de la Función Pública Aduanera (AFPA) > Depósitos Aduaneros > Depósitos Aduaneros Temporales (DAT) > Consultas y seguimiento > Monitoreo de sistemas informáticos de aduanas | L64: https://portal.sat.gob.gt/portal/consultas-aduanas/
A65: 2. Auxiliares de la Función Pública Aduanera (AFPA) | B65: Depósitos Aduaneros | C65: Depósitos Aduaneros Temporales (DAT) | D65: Consultas y seguimiento | E65: Programa de modernización integral aduanera (MIAD) | F65: Conoce los lineamientos y avances del Programa de Modernización Integral Aduanera (MIAD) de la SAT. | G65: APROBADO | H65: Consultas y herramientas | I65: Guía Informativa / Texto | J65: NO | K65: Operadores de Comercio Exterior > 2. Auxiliares de la Función Pública Aduanera (AFPA) > Depósitos Aduaneros > Depósitos Aduaneros Temporales (DAT) > Consultas y seguimiento > Programa de modernización integral aduanera (MIAD) | L65: https://portal.sat.gob.gt/portal/programa-miad/
A66: 2. Auxiliares de la Función Pública Aduanera (AFPA) | B66: Depósitos Aduaneros | C66: Depósitos Aduaneros Temporales (DAT) | D66: Consultas y seguimiento | E66: Requisitos para consulta de expedientes de gestión aduanera | F66: Da seguimiento al estado de avance y resolución del expediente administrativo de tu gestión aduanera. | G66: APROBADO | H66: Consultas y herramientas | I66: Consulta en Base de Datos | J66: NO | K66: Operadores de Comercio Exterior > 2. Auxiliares de la Función Pública Aduanera (AFPA) > Depósitos Aduaneros > Depósitos Aduaneros Temporales (DAT) > Consultas y seguimiento > Requisitos para consulta de expedientes de gestión aduanera | L66: https://portal.sat.gob.gt/portal/requisitos-de-aduanas/#1542142398181-8db4844a-6760
A67: 2. Auxiliares de la Función Pública Aduanera (AFPA) | B67: Depósitos Aduaneros | C67: Depósitos Aduaneros Temporales (DAT) | D67: Normativa y recursos | E67: Legislación aduanera (RECAUCA Art. 119 - Disposiciones sobre depósitos) | F67: Descarga y consulta el marco legal, leyes nacionales, CAUCA y RECAUCA aplicables a Depósitos Aduaneros. | G67: APROBADO | H67: Normativa y asistencia | I67: Guía Informativa / Texto | J67: NO | K67: Operadores de Comercio Exterior > 2. Auxiliares de la Función Pública Aduanera (AFPA) > Depósitos Aduaneros > Depósitos Aduaneros Temporales (DAT) > Normativa y recursos > Legislación aduanera (RECAUCA Art. 119 - Disposiciones sobre depósitos) | L67: https://portal.sat.gob.gt/portal/biblioteca-en-linea-sat/legislacion-aduanera/
A68: 2. Auxiliares de la Función Pública Aduanera (AFPA) | B68: Depósitos Aduaneros | C68: Depósitos Aduaneros Temporales (DAT) | D68: Normativa y recursos | E68: Procedimientos administrativos de aduanas (Sanciones y recursos) | F68: Conoce el régimen de infracciones aduaneras y los procedimientos para interponer recursos de revocatoria. | G68: APROBADO | H68: Normativa y asistencia | I68: Guía Informativa / Texto | J68: NO | K68: Operadores de Comercio Exterior > 2. Auxiliares de la Función Pública Aduanera (AFPA) > Depósitos Aduaneros > Depósitos Aduaneros Temporales (DAT) > Normativa y recursos > Procedimientos administrativos de aduanas (Sanciones y recursos) | L68: https://portal.sat.gob.gt/portal/procedimientos-aduanas/#1570112033454-be3581a4-383a
A69: 2. Auxiliares de la Función Pública Aduanera (AFPA) | B69: Depósitos Aduaneros | C69: Depósitos Aduaneros Temporales (DAT) | D69: Normativa y recursos | E69: Preguntas frecuentes sobre temas aduaneros | F69: Resuelve dudas frecuentes sobre normativa, requisitos y procedimientos aduaneros oficiales. | G69: APROBADO | H69: Normativa y asistencia | I69: Guía Informativa / Texto | J69: NO | K69: Operadores de Comercio Exterior > 2. Auxiliares de la Función Pública Aduanera (AFPA) > Depósitos Aduaneros > Depósitos Aduaneros Temporales (DAT) > Normativa y recursos > Preguntas frecuentes sobre temas aduaneros | L69: https://portal.sat.gob.gt/portal/preguntas-frecuentes/temas-aduaneros/
A70: 2. Auxiliares de la Función Pública Aduanera (AFPA) | B70: Depósitos Aduaneros | C70: Depósitos Aduaneros Temporales (DAT) | D70: Normativa y recursos | E70: Capacitaciones para auxiliares de la función pública | F70: Inscríbete en capacitaciones, talleres y diplomados aduaneros impartidos por la SAT para Depósitos Aduaneros. | G70: APROBADO | H70: Normativa y asistencia | I70: Guía Informativa / Texto | J70: NO | K70: Operadores de Comercio Exterior > 2. Auxiliares de la Función Pública Aduanera (AFPA) > Depósitos Aduaneros > Depósitos Aduaneros Temporales (DAT) > Normativa y recursos > Capacitaciones para auxiliares de la función pública | L70: https://portal.sat.gob.gt/portal/#capacitacion
A71: 3. Regímenes Territoriales y Zonas Especiales | B71: ZDEEP - Entidades Administradoras | C71: ZDEEP - Entidades Administradoras | D71: Registro y acreditación | E71: Requisitos para habilitación y delimitación perimetral del polígono ZDEEP | F71: Presenta los requisitos de infraestructura y delimitación física del polígono ZDEEP para su reconocimiento formal ante SAT. | G71: PENDIENTE (Propuesta brecha) | H71: Empezar y registrarse | I71: Trámite / Aplicativo en Línea | J71: SÍ | K71: Operadores de Comercio Exterior > 3. Regímenes Territoriales y Zonas Especiales > ZDEEP - Entidades Administradoras > Registro y acreditación > Requisitos para habilitación y delimitación perimetral del polígono ZDEEP | L71: https://portal.sat.gob.gt/portal/requisitos-de-aduanas/ | M71: Propuesta de brecha normativa identificada para mesa técnica SAT.
A72: 3. Regímenes Territoriales y Zonas Especiales | B72: ZDEEP - Entidades Administradoras | C72: ZDEEP - Entidades Administradoras | D72: Registro y acreditación | E72: Registro y control de garitas aduaneras e infraestructura perimetral | F72: Registra las garitas de acceso y acredita el cumplimiento de seguridad e infraestructura perimetral del recinto ZDEEP. | G72: PENDIENTE (Propuesta brecha) | H72: Empezar y registrarse | I72: Trámite / Aplicativo en Línea | J72: SÍ | K72: Operadores de Comercio Exterior > 3. Regímenes Territoriales y Zonas Especiales > ZDEEP - Entidades Administradoras > Registro y acreditación > Registro y control de garitas aduaneras e infraestructura perimetral | L72: https://portal.sat.gob.gt/portal/procedimientos-aduanas/ | M72: Propuesta de brecha normativa identificada para mesa técnica SAT.
A73: 3. Regímenes Territoriales y Zonas Especiales | B73: ZDEEP - Entidades Administradoras | C73: ZDEEP - Entidades Administradoras | D73: Registro y acreditación | E73: Solvencia fiscal (Requisito institucional de cumplimiento) | F73: Obtén tu solvencia fiscal en línea como requisito indispensable para operar y renovar tu acreditación como ZDEEP - Entidades Administradoras. | G73: APROBADO | H73: Empezar y registrarse | I73: Trámite / Aplicativo en Línea | J73: NO | K73: Operadores de Comercio Exterior > 3. Regímenes Territoriales y Zonas Especiales > ZDEEP - Entidades Administradoras > Registro y acreditación > Solvencia fiscal (Requisito institucional de cumplimiento) | L73: https://portal.sat.gob.gt/portal/solvencia-fiscal/
A74: 3. Regímenes Territoriales y Zonas Especiales | B74: ZDEEP - Entidades Administradoras | C74: ZDEEP - Entidades Administradoras | D74: Operaciones y trámites | E74: Procedimientos, instructivos y guías para gestiones aduaneras | F74: Desconsolida conocimientos de embarque y guías aéreas hijas para entregar bultos a sus consignatarios. | G74: APROBADO | H74: Operación y declaraciones | I74: Guía Informativa / Texto | J74: NO | K74: Operadores de Comercio Exterior > 3. Regímenes Territoriales y Zonas Especiales > ZDEEP - Entidades Administradoras > Operaciones y trámites > Procedimientos, instructivos y guías para gestiones aduaneras | L74: https://portal.sat.gob.gt/portal/procedimientos-aduanas/#1571412473853-2ed0b43f-287f
A75: 3. Regímenes Territoriales y Zonas Especiales | B75: ZDEEP - Entidades Administradoras | C75: ZDEEP - Entidades Administradoras | D75: Operaciones y trámites | E75: Procedimiento de control para ingreso y egreso de carga en garita ZDEEP | F75: Aplica el procedimiento oficial de control y verificación automatizada para el ingreso y salida de carga en garitas ZDEEP. | G75: PENDIENTE (Propuesta brecha) | H75: Operación y declaraciones | I75: Trámite / Aplicativo en Línea | J75: SÍ | K75: Operadores de Comercio Exterior > 3. Regímenes Territoriales y Zonas Especiales > ZDEEP - Entidades Administradoras > Operaciones y trámites > Procedimiento de control para ingreso y egreso de carga en garita ZDEEP | L75: https://portal.sat.gob.gt/portal/procedimientos-aduanas/ | M75: Propuesta de brecha normativa identificada para mesa técnica SAT.
A76: 3. Regímenes Territoriales y Zonas Especiales | B76: ZDEEP - Entidades Administradoras | C76: ZDEEP - Entidades Administradoras | D76: Operaciones y trámites | E76: Programa de modernización integral aduanera (MIAD) | F76: Conoce los lineamientos y avances del Programa de Modernización Integral Aduanera (MIAD) de la SAT. | G76: APROBADO | H76: Operación y declaraciones | I76: Guía Informativa / Texto | J76: NO | K76: Operadores de Comercio Exterior > 3. Regímenes Territoriales y Zonas Especiales > ZDEEP - Entidades Administradoras > Operaciones y trámites > Programa de modernización integral aduanera (MIAD) | L76: https://portal.sat.gob.gt/portal/programa-miad/
A77: 3. Regímenes Territoriales y Zonas Especiales | B77: ZDEEP - Entidades Administradoras | C77: ZDEEP - Entidades Administradoras | D77: Consultas y seguimiento | E77: Consultas de aduanas (Retención, liberación, rampa y manifiestos de transporte) | F77: Consulta el estado público de retención o liberación de mercancías en recintos portuarios y aduaneros. | G77: APROBADO | H77: Consultas y herramientas | I77: Consulta en Base de Datos | J77: NO | K77: Operadores de Comercio Exterior > 3. Regímenes Territoriales y Zonas Especiales > ZDEEP - Entidades Administradoras > Consultas y seguimiento > Consultas de aduanas (Retención, liberación, rampa y manifiestos de transporte) | L77: https://portal.sat.gob.gt/portal/consultas-aduanas/
A78: 3. Regímenes Territoriales y Zonas Especiales | B78: ZDEEP - Entidades Administradoras | C78: ZDEEP - Entidades Administradoras | D78: Consultas y seguimiento | E78: Monitoreo de sistemas informáticos de aduanas | F78: Verifica el estado operativo y disponibilidad de los sistemas informáticos y enlaces de la Intendencia de Aduanas. | G78: APROBADO | H78: Consultas y herramientas | I78: Consulta en Base de Datos | J78: NO | K78: Operadores de Comercio Exterior > 3. Regímenes Territoriales y Zonas Especiales > ZDEEP - Entidades Administradoras > Consultas y seguimiento > Monitoreo de sistemas informáticos de aduanas | L78: https://portal.sat.gob.gt/portal/consultas-aduanas/
A79: 3. Regímenes Territoriales y Zonas Especiales | B79: ZDEEP - Entidades Administradoras | C79: ZDEEP - Entidades Administradoras | D79: Consultas y seguimiento | E79: Puestos de control interinstitucional (PCI) y rutas fiscales | F79: Ubica los Puestos de Control Interinstitucional (PCI) y conoce los puntos de inspección en rutas fiscales. | G79: APROBADO | H79: Consultas y herramientas | I79: Trámite / Aplicativo en Línea | J79: NO | K79: Operadores de Comercio Exterior > 3. Regímenes Territoriales y Zonas Especiales > ZDEEP - Entidades Administradoras > Consultas y seguimiento > Puestos de control interinstitucional (PCI) y rutas fiscales | L79: https://portal.sat.gob.gt/portal/puestos-de-control-interinstitucional-pci/
A80: 3. Regímenes Territoriales y Zonas Especiales | B80: ZDEEP - Entidades Administradoras | C80: ZDEEP - Entidades Administradoras | D80: Consultas y seguimiento | E80: Requisitos para consulta de expedientes de gestión aduanera | F80: Da seguimiento al estado de avance y resolución del expediente administrativo de tu gestión aduanera. | G80: APROBADO | H80: Consultas y herramientas | I80: Consulta en Base de Datos | J80: NO | K80: Operadores de Comercio Exterior > 3. Regímenes Territoriales y Zonas Especiales > ZDEEP - Entidades Administradoras > Consultas y seguimiento > Requisitos para consulta de expedientes de gestión aduanera | L80: https://portal.sat.gob.gt/portal/requisitos-de-aduanas/#1542142398181-8db4844a-6760
A81: 3. Regímenes Territoriales y Zonas Especiales | B81: ZDEEP - Entidades Administradoras | C81: ZDEEP - Entidades Administradoras | D81: Consultas y seguimiento | E81: Consulta facilidades de pago y convenios tributarios | F81: Consulta el estado de cuotas y facilidades de pago autorizadas bajo convenios tributarios ante la SAT. | G81: APROBADO | H81: Consultas y herramientas | I81: Consulta en Base de Datos | J81: NO | K81: Operadores de Comercio Exterior > 3. Regímenes Territoriales y Zonas Especiales > ZDEEP - Entidades Administradoras > Consultas y seguimiento > Consulta facilidades de pago y convenios tributarios | L81: https://portal.sat.gob.gt/portal/consulta-movimiento-convenio/
A82: 3. Regímenes Territoriales y Zonas Especiales | B82: ZDEEP - Entidades Administradoras | C82: ZDEEP - Entidades Administradoras | D82: Normativa y recursos | E82: Legislación aduanera y régimen especial ZDEEP (Decreto 22-73 y reformas) | F82: Descarga y consulta el marco legal, leyes nacionales, CAUCA y RECAUCA aplicables a ZDEEP - Entidades Administradoras. | G82: APROBADO | H82: Normativa y asistencia | I82: Guía Informativa / Texto | J82: NO | K82: Operadores de Comercio Exterior > 3. Regímenes Territoriales y Zonas Especiales > ZDEEP - Entidades Administradoras > Normativa y recursos > Legislación aduanera y régimen especial ZDEEP (Decreto 22-73 y reformas) | L82: https://portal.sat.gob.gt/portal/biblioteca-en-linea-sat/legislacion-aduanera/
A83: 3. Regímenes Territoriales y Zonas Especiales | B83: ZDEEP - Entidades Administradoras | C83: ZDEEP - Entidades Administradoras | D83: Normativa y recursos | E83: Procedimientos administrativos de aduanas (Sanciones y recursos) | F83: Conoce el régimen de infracciones aduaneras y los procedimientos para interponer recursos de revocatoria. | G83: APROBADO | H83: Normativa y asistencia | I83: Guía Informativa / Texto | J83: NO | K83: Operadores de Comercio Exterior > 3. Regímenes Territoriales y Zonas Especiales > ZDEEP - Entidades Administradoras > Normativa y recursos > Procedimientos administrativos de aduanas (Sanciones y recursos) | L83: https://portal.sat.gob.gt/portal/procedimientos-aduanas/#1570112033454-be3581a4-383a
A84: 3. Regímenes Territoriales y Zonas Especiales | B84: ZDEEP - Entidades Administradoras | C84: ZDEEP - Entidades Administradoras | D84: Normativa y recursos | E84: Preguntas frecuentes sobre temas aduaneros | F84: Resuelve dudas frecuentes sobre normativa, requisitos y procedimientos aduaneros oficiales. | G84: APROBADO | H84: Normativa y asistencia | I84: Guía Informativa / Texto | J84: NO | K84: Operadores de Comercio Exterior > 3. Regímenes Territoriales y Zonas Especiales > ZDEEP - Entidades Administradoras > Normativa y recursos > Preguntas frecuentes sobre temas aduaneros | L84: https://portal.sat.gob.gt/portal/preguntas-frecuentes/temas-aduaneros/
A85: 3. Regímenes Territoriales y Zonas Especiales | B85: ZDEEP - Entidades Administradoras | C85: ZDEEP - Entidades Administradoras | D85: Normativa y recursos | E85: Capacitaciones institucionales y cultura tributaria | F85: Inscríbete en capacitaciones, talleres y diplomados aduaneros impartidos por la SAT para ZDEEP - Entidades Administradoras. | G85: APROBADO | H85: Normativa y asistencia | I85: Guía Informativa / Texto | J85: NO | K85: Operadores de Comercio Exterior > 3. Regímenes Territoriales y Zonas Especiales > ZDEEP - Entidades Administradoras > Normativa y recursos > Capacitaciones institucionales y cultura tributaria | L85: https://portal.sat.gob.gt/portal/#capacitacion
A86: 3. Regímenes Territoriales y Zonas Especiales | B86: ZDEEP - Empresas Usuarias | C86: ZDEEP - Empresas Usuarias | D86: Registro y acreditación | E86: Registro de empresas usuarias calificadas en ZDEEP ante SAT | F86: Inscribe tu empresa calificada en ZDEEP ante la SAT para gozar de los incentivos fiscales y aduaneros autorizados por ley. | G86: PENDIENTE (Propuesta brecha) | H86: Empezar y registrarse | I86: Trámite / Aplicativo en Línea | J86: SÍ | K86: Operadores de Comercio Exterior > 3. Regímenes Territoriales y Zonas Especiales > ZDEEP - Empresas Usuarias > Registro y acreditación > Registro de empresas usuarias calificadas en ZDEEP ante SAT | L86: https://portal.sat.gob.gt/portal/requisitos-de-aduanas/ | M86: Propuesta de brecha normativa identificada para mesa técnica SAT.
A87: 3. Regímenes Territoriales y Zonas Especiales | B87: ZDEEP - Empresas Usuarias | C87: ZDEEP - Empresas Usuarias | D87: Registro y acreditación | E87: Solvencia fiscal (Requisito obligatorio para goce de incentivos tributarios) | F87: Obtén tu solvencia fiscal en línea como requisito indispensable para operar y renovar tu acreditación como ZDEEP - Empresas Usuarias. | G87: APROBADO | H87: Empezar y registrarse | I87: Trámite / Aplicativo en Línea | J87: NO | K87: Operadores de Comercio Exterior > 3. Regímenes Territoriales y Zonas Especiales > ZDEEP - Empresas Usuarias > Registro y acreditación > Solvencia fiscal (Requisito obligatorio para goce de incentivos tributarios) | L87: https://portal.sat.gob.gt/portal/solvencia-fiscal/
A88: 3. Regímenes Territoriales y Zonas Especiales | B88: ZDEEP - Empresas Usuarias | C88: ZDEEP - Empresas Usuarias | D88: Registro y acreditación | E88: Régimen de factura electrónica en línea (FEL) | F88: Emite facturas electrónicas FEL y gestiona tus documentos tributarios en línea desde la Agencia Virtual. | G88: APROBADO | H88: Empezar y registrarse | I88: Trámite / Aplicativo en Línea | J88: NO | K88: Operadores de Comercio Exterior > 3. Regímenes Territoriales y Zonas Especiales > ZDEEP - Empresas Usuarias > Registro y acreditación > Régimen de factura electrónica en línea (FEL) | L88: https://portal.sat.gob.gt/portal/efactura/
A89: 3. Regímenes Territoriales y Zonas Especiales | B89: ZDEEP - Empresas Usuarias | C89: ZDEEP - Empresas Usuarias | D89: Operaciones y trámites | E89: Declaración de mercancías (DUCA, tránsitos aduaneros y aduana sin papeles) | F89: Transmite electrónicamente la declaración de mercancías DUCA y gestiona el despacho aduanero ágil. | G89: APROBADO | H89: Operación y declaraciones | I89: Trámite / Aplicativo en Línea | J89: NO | K89: Operadores de Comercio Exterior > 3. Regímenes Territoriales y Zonas Especiales > ZDEEP - Empresas Usuarias > Operaciones y trámites > Declaración de mercancías (DUCA, tránsitos aduaneros y aduana sin papeles) | L89: https://portal.sat.gob.gt/portal/procedimientos-aduanas/
A90: 3. Regímenes Territoriales y Zonas Especiales | B90: ZDEEP - Empresas Usuarias | C90: ZDEEP - Empresas Usuarias | D90: Operaciones y trámites | E90: Procedimiento aduanero de traslado de mercancías hacia y desde ZDEEP | F90: Gestiona las declaraciones y traslados de materias primas y mercancías entre aduanas y la ZDEEP con custodia fiscal. | G90: PENDIENTE (Propuesta brecha) | H90: Operación y declaraciones | I90: Trámite / Aplicativo en Línea | J90: SÍ | K90: Operadores de Comercio Exterior > 3. Regímenes Territoriales y Zonas Especiales > ZDEEP - Empresas Usuarias > Operaciones y trámites > Procedimiento aduanero de traslado de mercancías hacia y desde ZDEEP | L90: https://portal.sat.gob.gt/portal/procedimientos-aduanas/ | M90: Propuesta de brecha normativa identificada para mesa técnica SAT.
A91: 3. Regímenes Territoriales y Zonas Especiales | B91: ZDEEP - Empresas Usuarias | C91: ZDEEP - Empresas Usuarias | D91: Operaciones y trámites | E91: Control, descargo y reporte periódico de inventarios de transformación | F91: Presenta los reportes periódicos y registra el descargo de inventarios de materias primas transformadas en el régimen ZDEEP. | G91: PENDIENTE (Propuesta brecha) | H91: Operación y declaraciones | I91: Consulta en Base de Datos | J91: SÍ | K91: Operadores de Comercio Exterior > 3. Regímenes Territoriales y Zonas Especiales > ZDEEP - Empresas Usuarias > Operaciones y trámites > Control, descargo y reporte periódico de inventarios de transformación | L91: https://portal.sat.gob.gt/portal/procedimientos-aduanas/ | M91: Propuesta de brecha normativa identificada para mesa técnica SAT.
A92: 3. Regímenes Territoriales y Zonas Especiales | B92: ZDEEP - Empresas Usuarias | C92: ZDEEP - Empresas Usuarias | D92: Operaciones y trámites | E92: Procedimientos, instructivos y guías para gestiones aduaneras | F92: Desconsolida conocimientos de embarque y guías aéreas hijas para entregar bultos a sus consignatarios. | G92: APROBADO | H92: Operación y declaraciones | I92: Guía Informativa / Texto | J92: NO | K92: Operadores de Comercio Exterior > 3. Regímenes Territoriales y Zonas Especiales > ZDEEP - Empresas Usuarias > Operaciones y trámites > Procedimientos, instructivos y guías para gestiones aduaneras | L92: https://portal.sat.gob.gt/portal/procedimientos-aduanas/#1571412473853-2ed0b43f-287f
A93: 3. Regímenes Territoriales y Zonas Especiales | B93: ZDEEP - Empresas Usuarias | C93: ZDEEP - Empresas Usuarias | D93: Consultas y seguimiento | E93: Consultas de aduanas (Arancel integrado, rampa de revisión, retención y liberación) | F93: Consulta los aranceles DAI, gravámenes e impuestos del SAC y verifica los permisos no arancelarios exigibles. | G93: APROBADO | H93: Consultas y herramientas | I93: Consulta en Base de Datos | J93: NO | K93: Operadores de Comercio Exterior > 3. Regímenes Territoriales y Zonas Especiales > ZDEEP - Empresas Usuarias > Consultas y seguimiento > Consultas de aduanas (Arancel integrado, rampa de revisión, retención y liberación) | L93: https://portal.sat.gob.gt/portal/consultas-aduanas/
A94: 3. Regímenes Territoriales y Zonas Especiales | B94: ZDEEP - Empresas Usuarias | C94: ZDEEP - Empresas Usuarias | D94: Consultas y seguimiento | E94: Declaración anticipada de mercancías | F94: Presenta tu declaración y paga tributos antes de que arribe el medio de transporte para agilizar el levante. | G94: APROBADO | H94: Consultas y herramientas | I94: Trámite / Aplicativo en Línea | J94: NO | K94: Operadores de Comercio Exterior > 3. Regímenes Territoriales y Zonas Especiales > ZDEEP - Empresas Usuarias > Consultas y seguimiento > Declaración anticipada de mercancías | L94: https://portal.sat.gob.gt/portal/facilitacion-de-comercio/#1559325573466-1284efd5-2d1b/
A95: 3. Regímenes Territoriales y Zonas Especiales | B95: ZDEEP - Empresas Usuarias | C95: ZDEEP - Empresas Usuarias | D95: Consultas y seguimiento | E95: Requisitos para consulta de expedientes de gestión aduanera | F95: Da seguimiento al estado de avance y resolución del expediente administrativo de tu gestión aduanera. | G95: APROBADO | H95: Consultas y herramientas | I95: Consulta en Base de Datos | J95: NO | K95: Operadores de Comercio Exterior > 3. Regímenes Territoriales y Zonas Especiales > ZDEEP - Empresas Usuarias > Consultas y seguimiento > Requisitos para consulta de expedientes de gestión aduanera | L95: https://portal.sat.gob.gt/portal/requisitos-de-aduanas/#1542142398181-8db4844a-6760
A96: 3. Regímenes Territoriales y Zonas Especiales | B96: ZDEEP - Empresas Usuarias | C96: ZDEEP - Empresas Usuarias | D96: Consultas y seguimiento | E96: Consulta y facilidades de pago de convenios | F96: Consulta el estado de cuotas y facilidades de pago autorizadas bajo convenios tributarios ante la SAT. | G96: APROBADO | H96: Consultas y herramientas | I96: Consulta en Base de Datos | J96: NO | K96: Operadores de Comercio Exterior > 3. Regímenes Territoriales y Zonas Especiales > ZDEEP - Empresas Usuarias > Consultas y seguimiento > Consulta y facilidades de pago de convenios | L96: https://portal.sat.gob.gt/portal/consulta-movimiento-convenio/
A97: 3. Regímenes Territoriales y Zonas Especiales | B97: ZDEEP - Empresas Usuarias | C97: ZDEEP - Empresas Usuarias | D97: Normativa y recursos | E97: Legislación aduanera y tributaria (Exenciones y marco legal ZDEEP) | F97: Descarga y consulta el marco legal, leyes nacionales, CAUCA y RECAUCA aplicables a ZDEEP - Empresas Usuarias. | G97: APROBADO | H97: Normativa y asistencia | I97: Guía Informativa / Texto | J97: NO | K97: Operadores de Comercio Exterior > 3. Regímenes Territoriales y Zonas Especiales > ZDEEP - Empresas Usuarias > Normativa y recursos > Legislación aduanera y tributaria (Exenciones y marco legal ZDEEP) | L97: https://portal.sat.gob.gt/portal/biblioteca-en-linea-sat/legislacion-aduanera/
A98: 3. Regímenes Territoriales y Zonas Especiales | B98: ZDEEP - Empresas Usuarias | C98: ZDEEP - Empresas Usuarias | D98: Normativa y recursos | E98: Procedimientos administrativos de aduanas (Sanciones y recursos) | F98: Conoce el régimen de infracciones aduaneras y los procedimientos para interponer recursos de revocatoria. | G98: APROBADO | H98: Normativa y asistencia | I98: Guía Informativa / Texto | J98: NO | K98: Operadores de Comercio Exterior > 3. Regímenes Territoriales y Zonas Especiales > ZDEEP - Empresas Usuarias > Normativa y recursos > Procedimientos administrativos de aduanas (Sanciones y recursos) | L98: https://portal.sat.gob.gt/portal/procedimientos-aduanas/#1570112033454-be3581a4-383a
A99: 3. Regímenes Territoriales y Zonas Especiales | B99: ZDEEP - Empresas Usuarias | C99: ZDEEP - Empresas Usuarias | D99: Normativa y recursos | E99: Preguntas frecuentes sobre temas aduaneros y cumplimiento | F99: Resuelve dudas frecuentes sobre normativa, requisitos y procedimientos aduaneros oficiales. | G99: APROBADO | H99: Normativa y asistencia | I99: Guía Informativa / Texto | J99: NO | K99: Operadores de Comercio Exterior > 3. Regímenes Territoriales y Zonas Especiales > ZDEEP - Empresas Usuarias > Normativa y recursos > Preguntas frecuentes sobre temas aduaneros y cumplimiento | L99: https://portal.sat.gob.gt/portal/preguntas-frecuentes/temas-aduaneros/
A100: 3. Regímenes Territoriales y Zonas Especiales | B100: ZDEEP - Empresas Usuarias | C100: ZDEEP - Empresas Usuarias | D100: Normativa y recursos | E100: Capacitaciones aduaneras y tributarias | F100: Inscríbete en capacitaciones, talleres y diplomados aduaneros impartidos por la SAT para ZDEEP - Empresas Usuarias. | G100: APROBADO | H100: Normativa y asistencia | I100: Guía Informativa / Texto | J100: NO | K100: Operadores de Comercio Exterior > 3. Regímenes Territoriales y Zonas Especiales > ZDEEP - Empresas Usuarias > Normativa y recursos > Capacitaciones aduaneras y tributarias | L100: https://portal.sat.gob.gt/portal/#capacitacion
A101: 1. Importadores y Exportadores | B101: Importadores y Exportadores (Compartido) | C101: Importadores y Exportadores (Compartido) | D101: Registro y acreditación | E101: Actualización de datos en RTU Digital y régimen de comercio exterior | F101: Actualiza tus datos en el RTU Digital para mantener habilitadas tus operaciones y gestiones aduaneras. | G101: APROBADO | H101: Empezar y registrarse | I101: Trámite / Aplicativo en Línea | J101: NO | K101: Operadores de Comercio Exterior > 1. Importadores y Exportadores > Importadores y Exportadores (Compartido) > Registro y acreditación > Actualización de datos en RTU Digital y régimen de comercio exterior | L101: https://portal.sat.gob.gt/portal/tramites-registro-tributario/
A102: 1. Importadores y Exportadores | B102: Importadores y Exportadores (Compartido) | C102: Importadores y Exportadores (Compartido) | D102: Registro y acreditación | E102: Solvencia fiscal (Requisito habilitante para operaciones aduaneras) | F102: Obtén tu solvencia fiscal en línea como requisito indispensable para operar y renovar tu acreditación como Importadores y Exportadores (Compartido). | G102: APROBADO | H102: Empezar y registrarse | I102: Trámite / Aplicativo en Línea | J102: NO | K102: Operadores de Comercio Exterior > 1. Importadores y Exportadores > Importadores y Exportadores (Compartido) > Registro y acreditación > Solvencia fiscal (Requisito habilitante para operaciones aduaneras) | L102: https://portal.sat.gob.gt/portal/solvencia-fiscal/
A103: 1. Importadores y Exportadores | B103: Importadores y Exportadores (Compartido) | C103: Importadores y Exportadores (Compartido) | D103: Registro y acreditación | E103: Registro y acreditación de operadores de comercio exterior habituales | F103: Inscríbete y acredita tu personería en el registro de operadores habituales de comercio exterior de la SAT. | G103: PENDIENTE (Propuesta brecha) | H103: Empezar y registrarse | I103: Trámite / Aplicativo en Línea | J103: SÍ | K103: Operadores de Comercio Exterior > 1. Importadores y Exportadores > Importadores y Exportadores (Compartido) > Registro y acreditación > Registro y acreditación de operadores de comercio exterior habituales | L103: https://portal.sat.gob.gt/portal/requisitos-de-aduanas/ | M103: Propuesta de brecha normativa identificada para mesa técnica SAT.
...

Sheet Institucional – Transversal
A1: 5. Institucional – Transversal
A2: Información sobre la SAT: transparencia, estadísticas y gestión institucional.
A4: Categoría propuesta | B4: Subcategoría 1 | C4: Subcategoría 2 | D4: Página / Trámite | E4: Nombre de trámite sugerido | F4: Descripción de la página | G4: Sección actual del menú | H4: URL | I4: Confianza | J4: Nota / Revisar | K4: Observación de reorganización | L4: Subcategoría anterior (referencia)
A5: Transparencia e información pública | B5: Acceso a la información pública | C5: Ley de Acceso a la Información | D5: Acceso a la Información Pública | E5: Acceso a la información pública | F5: Información sobre: Acceso a la información pública. | G5: INSTITUCIONAL | H5: https://portal.sat.gob.gt/portal/libre-acceso-la-informacion-publica/ | I5: Alta | J5: Contenido institucional/corporativo general (excluido por decisión del usuario) | K5: Categoría propuesta nueva; Posible duplicado: misma URL que otra fila de esta hoja
A6: Transparencia e información pública | B6: Acceso a la información pública | C6: Ley de Acceso a la Información | D6: Acceso a la Información Pública | E6: Acceso a la información pública | F6: Información sobre: Acceso a la información pública. | G6: MENÚ FLOTANTE | H6: https://portal.sat.gob.gt/portal/libre-acceso-la-informacion-publica/ | I6: Alta | J6: Contenido institucional/corporativo general (excluido por decisión del usuario) | K6: Categoría propuesta nueva; Posible duplicado: misma URL que otra fila de esta hoja
A7: Transparencia e información pública | B7: Acceso a la información pública | C7: Ley de Acceso a la Información | D7: Ley de Acceso a la Información Pública (Decreto 57-2008, Artículo 10) Indice de Información de oficio | E7: Índice de información pública de oficio | F7: Publicación de información pública: Índice de información pública de oficio. | G7: INSTITUCIONAL | H7: https://portal.sat.gob.gt/portal/libre-acceso-la-informacion-publica/menu-ley-info-publica/ | I7: Alta | J7: Contenido institucional/corporativo general (excluido por decisión del usuario) | K7: Categoría propuesta nueva
A8: Transparencia e información pública | B8: Acceso a la información pública | C8: Ley de Acceso a la Información | D8: Articulo 10. Información pública de oficio | E8: Información pública de oficio (Artículo 10) | F8: Publicación de información pública: Información pública de oficio (Artículo 10). | G8: INSTITUCIONAL | H8: https://portal.sat.gob.gt/portal/transparencia-fiscal-gobernanza-sat/articulo-10-informacion-publica-de-oficio/ | I8: Alta | J8: Contenido institucional/corporativo general (excluido por decisión del usuario) | K8: Categoría propuesta nueva
A9: Transparencia e información pública | B9: Acceso a la información pública | C9: Ley de Acceso a la Información | D9: Estadísticas de solicitudes de Información Pública atendida | E9: Estadísticas de solicitudes de información atendidas | F9: Información sobre: Estadísticas de solicitudes de información atendidas. | G9: INSTITUCIONAL | H9: https://portal.sat.gob.gt/portal/estadisticas-de-solicitudes-de-informacion-publica-atendidas/ | I9: Alta | J9: Contenido institucional/corporativo general (excluido por decisión del usuario) | K9: Categoría propuesta nueva
A10: Transparencia e información pública | B10: Acceso a la información pública | C10: Información de oficio por numeral (Art. 10) | D10: Numeral 1. Estructura Orgánica y Funciones de las Dependencias, Incluyendo su Marco Normativo | E10: Numeral 1: Estructura y funciones | F10: Publicación de información pública: Numeral 1: Estructura y funciones. | G10: INSTITUCIONAL | H10: https://portal.sat.gob.gt/portal/libre-acceso-la-informacion-publica/menu-ley-info-publica/funciones-y-dependencias-sat/ | I10: Alta | J10: Contenido institucional/corporativo general (excluido por decisión del usuario) | K10: Categoría propuesta nueva
A11: Transparencia e información pública | B11: Acceso a la información pública | C11: Información de oficio por numeral (Art. 10) | D11: Numeral 2. Dirección y Teléfonos de sus Dependencias | E11: Numeral 2: Direcciones y teléfonos | F11: Publicación de información pública: Numeral 2: Direcciones y teléfonos. | G11: INSTITUCIONAL | H11: https://portal.sat.gob.gt/portal/libre-acceso-la-informacion-publica/menu-ley-info-publica/numeral-2-direccion-telefonos-dependencias/ | I11: Alta | J11: Contenido institucional/corporativo general (excluido por decisión del usuario) | K11: Categoría propuesta nueva
A12: Transparencia e información pública | B12: Acceso a la información pública | C12: Información de oficio por numeral (Art. 10) | D12: Numeral 3. Directorio de Empleados, Números Telefónicos y Direcciones de Correo Electrónico Oficiales | E12: Numeral 3: Directorio de empleados | F12: Publicación de información pública: Numeral 3: Directorio de empleados. | G12: INSTITUCIONAL | H12: https://portal.sat.gob.gt/portal/libre-acceso-la-informacion-publica/menu-ley-info-publica/numeral-3-directorio-empleados-numeros-telefonicos-direcciones-correo-electronico-oficiales/ | I12: Alta | J12: Contenido institucional/corporativo general (excluido por decisión del usuario) | K12: Categoría propuesta nueva
A13: Transparencia e información pública | B13: Acceso a la información pública | C13: Información de oficio por numeral (Art. 10) | D13: Numeral 4. Número y Nombre de Puestos y Plazas de la SAT | E13: Numeral 4: Puestos y plazas | F13: Publicación de información pública: Numeral 4: Puestos y plazas. | G13: INSTITUCIONAL | H13: https://portal.sat.gob.gt/portal/libre-acceso-la-informacion-publica/menu-ley-info-publica/numeral-4-numero-nombre-puestos-plazas-sat/ | I13: Alta | J13: Contenido institucional/corporativo general (excluido por decisión del usuario) | K13: Categoría propuesta nueva
A14: Transparencia e información pública | B14: Acceso a la información pública | C14: Información de oficio por numeral (Art. 10) | D14: Numeral 5. Misión y Objetivos de la Institución, Plan Operativo y Resultados Obtenidos | E14: Numeral 5: Misión, objetivos y plan operativo | F14: Publicación de información pública: Numeral 5: Misión, objetivos y plan operativo. | G14: INSTITUCIONAL | H14: https://portal.sat.gob.gt/portal/libre-acceso-la-informacion-publica/menu-ley-info-publica/numeral-5-mision-objetivos-institucion-plan-operativo-resultados-obtenidos/ | I14: Alta | J14: Contenido institucional/corporativo general (excluido por decisión del usuario) | K14: Categoría propuesta nueva
A15: Transparencia e información pública | B15: Acceso a la información pública | C15: Información de oficio por numeral (Art. 10) | D15: Numeral 6. Manuales de Procedimientos Administrativos y Operativos | E15: Numeral 6: Manuales de procedimientos | F15: Publicación de información pública: Numeral 6: Manuales de procedimientos. | G15: INSTITUCIONAL | H15: https://portal.sat.gob.gt/portal/libre-acceso-la-informacion-publica/menu-ley-info-publica/numeral-6-manuales-procedimientos-administrativos-operativos/ | I15: Alta | J15: Contenido institucional/corporativo general (excluido por decisión del usuario) | K15: Categoría propuesta nueva
A16: Transparencia e información pública | B16: Acceso a la información pública | C16: Información de oficio por numeral (Art. 10) | D16: Numeral 7. Presupuesto de Ingresos y Egresos, Programas a Cargo, Incluyendo Transferencias | E16: Numeral 7: Presupuesto de ingresos y egresos | F16: Publicación de información pública: Numeral 7: Presupuesto de ingresos y egresos. | G16: INSTITUCIONAL | H16: https://portal.sat.gob.gt/portal/libre-acceso-la-informacion-publica/menu-ley-info-publica/numeral-7-presupuesto-ingresos-egresos-programas-cargo-incluyendo-transferencias/ | I16: Alta | J16: Contenido institucional/corporativo general (excluido por decisión del usuario) | K16: Categoría propuesta nueva
... A122: Gobierno y gestión institucional | B122: Páginas de navegación | C122: Menús | D122: PORTAL | E122: Página de inicio del portal | F122: Información sobre: Página de inicio del portal. | G122: PORTAL | H122: https://portal.sat.gob.gt/portal/ | I122: Alta | J122: Contenido institucional/corporativo general (excluido por decisión del usuario) | K122: Categoría propuesta nueva; Página de menú, no es contenido

Sheet Profesionales
A1: Profesionales
A2: Terceras personas que hacen gestiones ante la SAT en nombre de otros: gestores, abogados y notarios, contadores y auditores. Orden: Categoría › Grupo › Tema › Página. «Todos los grupos» = la usan todos los grupos de la categoría. «Trámites comunes» = la usan varias categorías.
A4: Categoría | B4: Grupo | C4: Tema | D4: Subtema | E4: Página / Trámite (nombre actual) | F4: Nombre de trámite sugerido | G4: Descripción de la página | H4: Usado por (según Grupos y categorías) | I4: Origen de la clasificación | J4: Motivo / referencia | K4: Sección actual del menú | L4: URL | M4: Nota / Revisar
A5: Terceras Personas | B5: Todos los grupos | C5: Consultas legales | D5: Consultas | E5: Consultas Legales | F5: Hacer una consulta legal | G5: Requisitos, pasos y documentos para hacer una consulta legal. | H5: Terceras Personas | I5: Grupos y categorías | J5: Marcada «SI» en el archivo Grupos y categorías | K5: CONTÁCTANOS | L5: https://portal.sat.gob.gt/portal/contacto/consultas-legales/ | M5: Rol profesional (agente aduanero, notario, abogado, gestor, tercero autorizado)
A6: Terceras Personas | B6: Todos los grupos | C6: Cultura tributaria y capacitación | D6: Biblioteca virtual y descargas | E6: Descarga de Aplicaciones | F6: Descargar aplicaciones de la SAT | G6: Requisitos, pasos y documentos para descargar aplicaciones de la SAT. | H6: Terceras Personas | I6: Grupos y categorías | J6: Marcada «SI» en el archivo Grupos y categorías | K6: CAPACITACIÓN | L6: https://portal.sat.gob.gt/portal/biblioteca-en-linea-sat/software/ | M6: Servicio/tema general para contribuyentes
A7: Terceras Personas | B7: Todos los grupos | C7: Cultura tributaria y capacitación | D7: Información institucional | E7: Memoria de Labores SAT | F7: Memoria de labores | G7: Información sobre: Memoria de labores. | H7: Terceras Personas | I7: Grupos y categorías | J7: Marcada «SI» en el archivo Grupos y categorías | K7: CAPACITACIÓN | L7: https://portal.sat.gob.gt/portal/memoria-de-labores/ | M7: Servicio/tema general para contribuyentes
A8: Terceras Personas | B8: Todos los grupos | C8: Cultura tributaria y capacitación | D8: Leyes y normativa | E8: Criterios Institucionales | F8: Criterios institucionales | G8: Información sobre: Criterios institucionales. | H8: Terceras Personas | I8: Grupos y categorías | J8: Marcada «SI» en el archivo Grupos y categorías | K8: CAPACITACIÓN | L8: https://portal.sat.gob.gt/portal/criterios-institucionales/ | M8: Servicio/tema general para contribuyentes
A9: Terceras Personas | B9: Todos los grupos | C9: Cultura tributaria y capacitación | D9: Leyes y normativa | E9: Legislación | F9: Legislación | G9: Información sobre: Legislación. | H9: Terceras Personas | I9: Grupos y categorías | J9: Marcada «SI» en el archivo Grupos y categorías | K9: CAPACITACIÓN | L9: https://portal.sat.gob.gt/portal/biblioteca-en-linea-sat/legislacion/ | M9: Servicio/tema general para contribuyentes
A10: Terceras Personas | B10: Todos los grupos | C10: Cultura tributaria y capacitación | D10: Leyes y normativa | E10: Orientacion Legal | F10: Orientación legal | G10: Información sobre: Orientación legal. | H10: Terceras Personas | I10: Grupos y categorías | J10: Marcada «SI» en el archivo Grupos y categorías | K10: CAPACITACIÓN | L10: https://portal.sat.gob.gt/portal/orientacion-legal/ | M10: Servicio/tema general para contribuyentes
A11: Terceras Personas | B11: Todos los grupos | C11: Cultura tributaria y capacitación | D11: Preguntas frecuentes | E11: Preguntas Frecuentes | F11: Preguntas frecuentes | G11: Respuestas a las preguntas más comunes sobre preguntas frecuentes. | H11: Terceras Personas | I11: Grupos y categorías | J11: Marcada «SI» en el archivo Grupos y categorías | K11: CAPACITACIÓN | L11: https://portal.sat.gob.gt/portal/preguntas-frecuentes/ | M11: Servicio/tema general para contribuyentes
A12: Terceras Personas | B12: Todos los grupos | C12: Declaraciones, pagos y solvencias | D12: Formas de pago y convenios | E12: Consulta Movimiento de Pago: Facilidades de pago | F12: Consultar pagos de tu convenio | G12: Servicio en línea para consultar pagos de tu convenio. | H12: Terceras Personas | I12: Grupos y categorías | J12: Marcada «SI» en el archivo Grupos y categorías | K12: SERVICIOS TRIBUTARIOS | L12: https://portal.sat.gob.gt/portal/consulta-movimiento-convenio/ | M12: Servicio/tema general para contribuyentes
A13: Terceras Personas | B13: Todos los grupos | C13: Declaraciones, pagos y solvencias | D13: Formas de pago y convenios | E13: Otras Formas de Pago | F13: Formas de pago de impuestos | G13: Información sobre: Formas de pago de impuestos. | H13: Terceras Personas | I13: Grupos y categorías | J13: Marcada «SI» en el archivo Grupos y categorías | K13: SERVICIOS TRIBUTARIOS | L13: https://portal.sat.gob.gt/portal/forma-de-pago/ | M13: Servicio/tema general para contribuyentes
A14: Terceras Personas | B14: Todos los grupos | C14: Declaraciones, pagos y solvencias | D14: Solvencia fiscal | E14: Falta Solvencia Fiscal | F14: ¿Por qué no tengo solvencia fiscal? | G14: Información general: ¿Por qué no tengo solvencia fiscal? | H14: Terceras Personas | I14: Grupos y categorías | J14: Marcada «SI» en el archivo Grupos y categorías | K14: SERVICIOS TRIBUTARIOS | L14: https://portal.sat.gob.gt/portal/solvencia-fiscal/ | M14: Servicio/tema general para contribuyentes
A15: Terceras Personas | B15: Todos los grupos | C15: Estadísticas y estudios | D15: Estadísticas e indicadores | E15: Estadísticas Tributarias SAT | F15: Estadísticas tributarias | G15: Información sobre: Estadísticas tributarias. | H15: Terceras Personas | I15: Grupos y categorías | J15: Marcada «SI» en el archivo Grupos y categorías | K15: ESTADÍSTICAS | L15: https://portal.sat.gob.gt/portal/estadisticas-tributarias-sat/ | M15: Contenido institucional/corporativo general (excluido por decisión del usuario)
... A56: Terceras Personas | B56: Todos los grupos | C56: Vehículos (como propietario) | D56: Requisitos y representantes | E56: Requisitos Gestiones Vehículos para Propietarios: Requisitos de Vehiculos | F56: Requisitos sobre Traspaso Electrónico de Vehículos a través de Notarios | G56: Información sobre traspaso electrónico de vehículos por notario con anexo del certificado de propiedad emitido vía Declaraguate en Agencia Virtual, entrega de documentos de traspaso electrónico en Agencia Virtual y Requisitos para remitir documentación electrónica o digital de TEV. | H56: Terceras Personas | I56: Grupos y categorías | J56: Marcada «SI» en el archivo Grupos y categorías | K56: SERVICIOS TRIBUTARIOS | L56: https://portal.sat.gob.gt/portal/requisitos-de-vehiculos/ | M56: Servicio/tema general para contribuyentes
A57: Terceras Personas | B57: Gestores Tributarios | C57: Gestores tributarios y terceros autorizados | D57: Registro y gafete | E57: Actualización de Información y Renovación del Gafete de Gestor Tributario y/o Auxiliar de Gestor Tributario | F57: Actualizar tus datos y renovar tu gafete de gestor | G57: Requisitos, pasos y documentos para actualizar tus datos y renovar tu gafete de gestor. | I57: Análisis | J57: Gestores tributarios y sus auxiliares | K57: SERVICIOS TRIBUTARIOS | L57: https://portal.sat.gob.gt/portal/requisitos-tramites-agencias/actualizacion-de-informacion-y-renovacion-del-gafete-de-gestor-tributario-y-o-auxiliar-de-gestor-tributario/ | M57: Rol profesional (agente aduanero, notario, abogado, gestor, tercero autorizado)
A58: Terceras Personas | B58: Gestores Tributarios | C58: Gestores tributarios y terceros autorizados | D58: Registro y gafete | E58: Terceros Autorizados: Consulta de Datos del Gestor Tributario o Auxiliar de Gestor Tributario | F58: Consultar los datos de un gestor tributario | G58: Servicio en línea para consultar los datos de un gestor tributario. | I58: Análisis | J58: Gestores tributarios | K58: SERVICIOS TRIBUTARIOS | L58: https://portal.sat.gob.gt/portal/consulta-de-datos-del-gestor-tributario-o-auxiliar-de-gestor-tributario/ | M58: Rol profesional (agente aduanero, notario, abogado, gestor, tercero autorizado)
A59: Terceras Personas | B59: Gestores Tributarios | C59: Gestores tributarios y terceros autorizados | D59: Registro y gafete | E59: Habilitación e Inhabilitación Temporal o Permanente de Gestor Tributario y/o Auxiliar de Gestor Tributario | F59: Habilitar o inhabilitar a un gestor tributario | G59: Requisitos, pasos y documentos para habilitar o inhabilitar a un gestor tributario. | I59: Análisis | J59: Gestores tributarios | K59: SERVICIOS TRIBUTARIOS | L59: https://portal.sat.gob.gt/portal/requisitos-tramites-agencias/habilitacion-e-inhabilitacion-temporal-o-permanente-de-gestor-tributario-y-o-auxiliar-de-gestor-tributario/ | M59: Rol profesional (agente aduanero, notario, abogado, gestor, tercero autorizado)
A60: Terceras Personas | B60: Gestores Tributarios | C60: Gestores tributarios y terceros autorizados | D60: Registro y gafete | E60: Reposición del Gafete de Gestor Tributario y/o Auxiliares de Gestor Tributario por Extravió, Robo, Hurto o Deterioro | F60: Reponer tu gafete de gestor tributario | G60: Requisitos, pasos y documentos para reponer tu gafete de gestor tributario. | I60: Análisis | J60: Gestores tributarios y sus auxiliares | K60: SERVICIOS TRIBUTARIOS | L60: https://portal.sat.gob.gt/portal/requisitos-tramites-agencias/reposicion-del-gafete-de-gestor-tributario-y-o-auxiliares-de-gestor-tributario-por-extravio-robo-hurto-o-deterioro/ | M60: Rol profesional (agente aduanero, notario, abogado, gestor, tercero autorizado)
A61: Terceras Personas | B61: Gestores Tributarios | C61: Gestores tributarios y terceros autorizados | D61: Registro y gafete | E61: Requisitos para las solicitudes de Gestor Tributario o Auxiliar de Gestor Tributario | F61: Requisitos para ser gestor tributario o auxiliar | G61: Lista de requisitos y documentos: requisitos para ser gestor tributario o auxiliar. | I61: Análisis | J61: Gestores tributarios y sus auxiliares | K61: SERVICIOS TRIBUTARIOS | L61: https://portal.sat.gob.gt/portal/requisitos-tramites-agencias/requisitos-para-las-solicitudes-de-gestor-tributario-o-auxiliar-de-gestor-tributario/ | M61: Rol profesional (agente aduanero, notario, abogado, gestor, tercero autorizado)
A62: Terceras Personas | B62: Auxiliar Tributario | C62: Gestores tributarios y terceros autorizados | D62: Registro y gafete | E62: Actualización de Información y Renovación del Gafete de Gestor Tributario y/o Auxiliar de Gestor Tributario | F62: Actualizar tus datos y renovar tu gafete de gestor | G62: Requisitos, pasos y documentos para actualizar tus datos y renovar tu gafete de gestor. | I62: Análisis | J62: Gestores tributarios y sus auxiliares | K62: SERVICIOS TRIBUTARIOS | L62: https://portal.sat.gob.gt/portal/requisitos-tramites-agencias/actualizacion-de-informacion-y-renovacion-del-gafete-de-gestor-tributario-y-o-auxiliar-de-gestor-tributario/ | M62: Rol profesional (agente aduanero, notario, abogado, gestor, tercero autorizado)
A63: Terceras Personas | B63: Auxiliar Tributario | C63: Gestores tributarios y terceros autorizados | D63: Registro y gafete | E63: Reposición del Gafete de Gestor Tributario y/o Auxiliares de Gestor Tributario por Extravió, Robo, Hurto o Deterioro | F63: Reponer tu gafete de gestor tributario | G63: Requisitos, pasos y documentos para reponer tu gafete de gestor tributario. | I63: Análisis | J63: Gestores tributarios y sus auxiliares | K63: SERVICIOS TRIBUTARIOS | L63: https://portal.sat.gob.gt/portal/requisitos-tramites-agencias/reposicion-del-gafete-de-gestor-tributario-y-o-auxiliares-de-gestor-tributario-por-extravio-robo-hurto-o-deterioro/ | M63: Rol profesional (agente aduanero, notario, abogado, gestor, tercero autorizado)
A64: Terceras Personas | B64: Auxiliar Tributario | C64: Gestores tributarios y terceros autorizados | D64: Registro y gafete | E64: Requisitos para las solicitudes de Gestor Tributario o Auxiliar de Gestor Tributario | F64: Requisitos para ser gestor tributario o auxiliar | G64: Lista de requisitos y documentos: requisitos para ser gestor tributario o auxiliar. | I64: Análisis | J64: Gestores tributarios y sus auxiliares | K64: SERVICIOS TRIBUTARIOS | L64: https://portal.sat.gob.gt/portal/requisitos-tramites-agencias/requisitos-para-las-solicitudes-de-gestor-tributario-o-auxiliar-de-gestor-tributario/ | M64: Rol profesional (agente aduanero, notario, abogado, gestor, tercero autorizado)
A65: Terceras Personas | B65: Abogados y Notarios | C65: Cultura tributaria y capacitación | D65: Preguntas frecuentes | E65: Contribuyentes Especiales | F65: Preguntas frecuentes: contribuyentes especiales | G65: Respuestas a las preguntas más comunes sobre contribuyentes especiales. | H65: Terceras Personas: Abogados y Notarios, Peritos Contadores, Auditores | I65: Grupos y categorías | J65: Marcada «SI» en el archivo Grupos y categorías | K65: CAPACITACIÓN | L65: https://portal.sat.gob.gt/portal/preguntas-frecuentes/contribuyentes-especiales/ | M65: Servicio/tema general para contribuyentes
A66: Terceras Personas | B66: Abogados y Notarios | C66: Notarios | D66: Especies fiscales | E66: Venta de Especies Fiscales a Notarios y Patentados | F66: Comprar especies fiscales (notarios y patentados) | G66: Requisitos, pasos y documentos para comprar especies fiscales (notarios y patentados). | I66: Análisis | J66: Abogados y notarios (Código de Notariado; Ley de Timbres Fiscales) | K66: SERVICIOS TRIBUTARIOS | L66: https://portal.sat.gob.gt/portal/requisitos-tramites-agencias/venta-de-especies-fiscales-a-notarios-y-patentados/ | M66: Rol profesional (agente aduanero, notario, abogado, gestor, tercero autorizado)
A67: Terceras Personas | B67: Abogados y Notarios | C67: Notarios | D67: Registro | E67: Activacion de abogados | F67: Activarte como abogado | G67: Requisitos, pasos y documentos para activarte como abogado. | I67: Análisis | J67: Abogados y notarios (Código de Notariado; Ley de Timbres Fiscales) | K67: SERVICIOS TRIBUTARIOS | L67: https://portal.sat.gob.gt/portal/requisitos-tramites-agencias/activacion-de-abogados/ | M67: Rol profesional (agente aduanero, notario, abogado, gestor, tercero autorizado)
A68: Terceras Personas | B68: Abogados y Notarios | C68: Notarios | D68: Registro | E68: Confirmación de Huella en el Registro de Abogados y Notarios | F68: Confirmar tu huella en el registro de abogados y notarios | G68: Requisitos, pasos y documentos para confirmar tu huella en el registro de abogados y notarios. | I68: Análisis | J68: Abogados y notarios (Código de Notariado; Ley de Timbres Fiscales) | K68: SERVICIOS TRIBUTARIOS | L68: https://portal.sat.gob.gt/portal/sin-categoria/requisitos-de-actualizacion-de-impresion-dactilar-para-abogados-y-notarios-que-realizan-traspasos-electronicos-a-traves-de-agencia-virtual/ | M68: Rol profesional (agente aduanero, notario, abogado, gestor, tercero autorizado)
A69: Terceras Personas | B69: Abogados y Notarios | C69: Notarios | D69: Registro | E69: Confirmación de Huella en el Registro de Abogados y Notarios | F69: Confirmar tu huella en el registro de abogados y notarios | G69: Requisitos, pasos y documentos para confirmar tu huella en el registro de abogados y notarios. | I69: Análisis | J69: Abogados y notarios (Código de Notariado; Ley de Timbres Fiscales) | K69: SERVICIOS TRIBUTARIOS | L69: https://portal.sat.gob.gt/portal/requisitos-tramites-agencias/requisitos-de-actualizacion-de-impresion-dactilar-para-abogados-y-notarios-que-realizan-traspasos-electronicos-a-traves-de-agencia-virtual/ | M69: Rol profesional (agente aduanero, notario, abogado, gestor, tercero autorizado)
A70: Terceras Personas | B70: Abogados y Notarios | C70: Notarios | D70: Registro | E70: Inscripción / Actualización de Abogado y Notario | F70: Inscribirte o actualizar tus datos como abogado y notario | G70: Requisitos, pasos y documentos para inscribirte o actualizar tus datos como abogado y notario. | I70: Análisis | J70: Abogados y notarios (Código de Notariado; Ley de Timbres Fiscales) | K70: SERVICIOS TRIBUTARIOS | L70: https://portal.sat.gob.gt/portal/requisitos-tramites-agencias/inscripcion-actualizacion-de-abogado-y-notario/ | M70: Rol profesional (agente aduanero, notario, abogado, gestor, tercero autorizado)
A71: Terceras Personas | B71: Abogados y Notarios | C71: Notarios | D71: Traspasos y avisos | E71: Tercera Persona Autorizada en el Registro Fiscal de Vehículos | F71: Autorizar a otra persona en el registro de vehículos | G71: Requisitos, pasos y documentos para autorizar a otra persona en el registro de vehículos. | I71: Análisis | J71: Abogados y notarios (Código de Notariado; Ley de Timbres Fiscales) | K71: SERVICIOS TRIBUTARIOS | L71: https://portal.sat.gob.gt/portal/requisitos-tramites-agencias/tercera-persona-autorizada-en-el-registro-fiscal-de-vehiculos/ | M71: Rol profesional (agente aduanero, notario, abogado, gestor, tercero autorizado)
A72: Terceras Personas | B72: Abogados y Notarios | C72: Notarios | D72: Traspasos y avisos | E72: Aviso de Legalización de Firmas en Certificado de Propiedad de Vehículos | F72: Avisar la legalización de firmas en un título de propiedad | G72: Requisitos, pasos y documentos para avisar la legalización de firmas en un título de propiedad. | I72: Análisis | J72: Abogados y notarios (Código de Notariado; Ley de Timbres Fiscales) | K72: SERVICIOS TRIBUTARIOS | L72: https://portal.sat.gob.gt/portal/requisitos-tramites-agencias/aviso-de-legalizacion-de-firmas-en-certificado-de-propiedad-de-vehiculos/ | M72: Rol profesional (agente aduanero, notario, abogado, gestor, tercero autorizado)
A73: Terceras Personas | B73: Abogados y Notarios | C73: Notarios | D73: Traspasos y avisos | E73: Aviso de Transferencia de Dominio de Vehículos | F73: Avisar una transferencia de dominio de vehículo | G73: Requisitos, pasos y documentos para avisar una transferencia de dominio de vehículo. | I73: Análisis | J73: Abogados y notarios (Código de Notariado; Ley de Timbres Fiscales) | K73: SERVICIOS TRIBUTARIOS | L73: https://portal.sat.gob.gt/portal/requisitos-tramites-agencias/aviso-de-transferencia-de-dominio-de-vehiculos/ | M73: Rol profesional (agente aduanero, notario, abogado, gestor, tercero autorizado)
A74: Terceras Personas | B74: Abogados y Notarios | C74: Notarios | D74: Traspasos y avisos | E74: Registro en la Modalidad de Traspaso Electrónico por Notario | F74: Registrarte para hacer traspasos electrónicos | G74: Requisitos, pasos y documentos para registrarte para hacer traspasos electrónicos. | I74: Análisis | J74: Abogados y notarios (Código de Notariado; Ley de Timbres Fiscales) | K74: SERVICIOS TRIBUTARIOS | L74: https://portal.sat.gob.gt/portal/requisitos-tramites-agencias/registro-en-la-modalidad-de-traspaso-electronico-por-notario/ | M74: Rol profesional (agente aduanero, notario, abogado, gestor, tercero autorizado)
A75: Terceras Personas | B75: Abogados y Notarios | C75: Notarios | D75: Traspasos y avisos | E75: Requisitos Gestiones Vehículos para Notarios: Requisitos para Trámites de Notarios | F75: Requisitos de trámites de vehículos para notarios | G75: Requisitos gestiones vehículos para Notarios Verifica los requisitos indispensables como notario para realizar tus gestiones | H75: Terceras Personas: Abogados y Notarios | I75: Grupos y categorías | J75: Marcada «SI» en el archivo Grupos y categorías | K75: SERVICIOS TRIBUTARIOS | L75: https://portal.sat.gob.gt/portal/requisitos-tramites-notarios/ | M75: Rol profesional (agente aduanero, notario, abogado, gestor, tercero autorizado)
A76: Terceras Personas | B76: Abogados y Notarios | C76: Otros servicios al contribuyente | D76: Alcohol y combustibles | E76: Requisitos para el Registro y Emisión de Autorización de la Superintendencia de Administración Tributaria al Impuesto a la Distribución de Petróleo Crudo y Combustible Derivados del Petróleo | F76: Registro de exentos del impuesto a combustibles | G76: Información sobre: Registro de exentos del impuesto a combustibles. | H76: Terceras Personas: Abogados y Notarios, Peritos Contadores, Auditores | I76: Grupos y categorías | J76: Marcada «SI» en el archivo Grupos y categorías | K76: SERVICIOS TRIBUTARIOS | L76: https://portal.sat.gob.gt/portal/requisitos-tramites-agencias/solicitud-de-registro-de-personas-exentas-del-impuesto-a-la-distribucion-de-petroleo-crudo-y-combustibles-derivados-del-petroleo/ | M76: Servicio/tema general para contribuyentes
A77: Terceras Personas | B77: Abogados y Notarios | C77: Otros servicios al contribuyente | D77: Constancias y gestiones del RTU | E77: RTU Digital | F77: RTU Digital: gestiones de tu registro en línea | G77: Información sobre: RTU Digital: gestiones de tu registro en línea. | H77: Terceras Personas: Abogados y Notarios, Peritos Contadores, Auditores | I77: Grupos y categorías | J77: Marcada «SI» en el archivo Grupos y categorías | K77: SERVICIOS TRIBUTARIOS | L77: https://portal.sat.gob.gt/portal/rtu-digital/ | M77: Servicio/tema general para contribuyentes
A78: Terceras Personas | B78: Abogados y Notarios | C78: Agregada desde «Grupos y categorías» | F78: Sistema Retenciones Web -ICT- | G78: Información y documentación de soporte sobre el sistema que tienen a disposición todas las personas individuales o jurídicas afiliadas al Impuesto a la Confianza Tributaria. | H78: Terceras Personas: Abogados y Notarios, Peritos Contadores, Auditores | I78: Grupos y categorías | J78: Marcada «SI» en el archivo Grupos y categorías | L78: https://portal.sat.gob.gt/portal/sistemas-web/retencioneswebict/
A79: Terceras Personas | B79: Peritos Contadores | C79: Cultura tributaria y capacitación | D79: Preguntas frecuentes | E79: Contribuyentes Especiales | F79: Preguntas frecuentes: contribuyentes especiales | G79: Respuestas a las preguntas más comunes sobre contribuyentes especiales. | H79: Terceras Personas: Abogados y Notarios, Peritos Contadores, Auditores | I79: Grupos y categorías | J79: Marcada «SI» en el archivo Grupos y categorías | K79: CAPACITACIÓN | L79: https://portal.sat.gob.gt/portal/preguntas-frecuentes/contribuyentes-especiales/ | M79: Servicio/tema general para contribuyentes
A80: Terceras Personas | B80: Peritos Contadores | C80: Inscripción y actualización en el RTU | D80: Contadores, auditores y gestores | E80: Actualización de Peritos Contadores | F80: Actualizar tus datos como perito contador | G80: Requisitos, pasos y documentos para actualizar tus datos como perito contador. | I80: Análisis | J80: Registro de contadores | K80: SERVICIOS TRIBUTARIOS | L80: https://portal.sat.gob.gt/portal/requisitos-tramites-agencias/actualizacion-al-registro-de-peritos-contadores-o-contadores-publicos-y-auditores/ | M80: Servicio/tema general para contribuyentes
A81: Terceras Personas | B81: Peritos Contadores | C81: Inscripción y actualización en el RTU | D81: Contadores, auditores y gestores | E81: Aviso de Baja como Contador Registrado en Agencia Virtual | F81: Darte de baja como contador en Agencia Virtual | G81: Requisitos, pasos y documentos para darte de baja como contador en Agencia Virtual. | I81: Análisis | J81: Registro de contadores | K81: SERVICIOS TRIBUTARIOS | L81: https://portal.sat.gob.gt/portal/aviso-de-baja-como-contador-registrado-en-agencia-virtual/ | M81: Servicio/tema general para contribuyentes
A82: Terceras Personas | B82: Peritos Contadores | C82: Inscripción y actualización en el RTU | D82: Contadores, auditores y gestores | E82: Inscripción de Peritos Contadores | F82: Inscribirte como perito contador | G82: Requisitos, pasos y documentos para inscribirte como perito contador. | I82: Análisis | J82: Registro de contadores | K82: SERVICIOS TRIBUTARIOS | L82: https://portal.sat.gob.gt/portal/requisitos-tramites-agencias/inscripcion-de-peritos-contadores/ | M82: Servicio/tema general para contribuyentes
A83: Terceras Personas | B83: Peritos Contadores | C83: Inscripción y actualización en el RTU | D83: Contadores, auditores y gestores | E83: Registro de Contadores En Agencia Virtual | F83: Registrarte como contador en Agencia Virtual | G83: Requisitos, pasos y documentos para registrarte como contador en Agencia Virtual. | I83: Análisis | J83: Registro de contadores | K83: SERVICIOS TRIBUTARIOS | L83: https://portal.sat.gob.gt/portal/registro-de-contadores-en-agencia-virtual/ | M83: Servicio/tema general para contribuyentes
A84: Terceras Personas | B84: Peritos Contadores | C84: Otros servicios al contribuyente | D84: Alcohol y combustibles | E84: Requisitos para el Registro y Emisión de Autorización de la Superintendencia de Administración Tributaria al Impuesto a la Distribución de Petróleo Crudo y Combustible Derivados del Petróleo | F84: Registro de exentos del impuesto a combustibles | G84: Información sobre: Registro de exentos del impuesto a combustibles. | H84: Terceras Personas: Abogados y Notarios, Peritos Contadores, Auditores | I84: Grupos y categorías | J84: Marcada «SI» en el archivo Grupos y categorías | K84: SERVICIOS TRIBUTARIOS | L84: https://portal.sat.gob.gt/portal/requisitos-tramites-agencias/solicitud-de-registro-de-personas-exentas-del-impuesto-a-la-distribucion-de-petroleo-crudo-y-combustibles-derivados-del-petroleo/ | M84: Servicio/tema general para contribuyentes
A85: Terceras Personas | B85: Peritos Contadores | C85: Otros servicios al contribuyente | D85: Constancias y gestiones del RTU | E85: RTU Digital | F85: RTU Digital: gestiones de tu registro en línea | G85: Información sobre: RTU Digital: gestiones de tu registro en línea. | H85: Terceras Personas: Abogados y Notarios, Peritos Contadores, Auditores | I85: Grupos y categorías | J85: Marcada «SI» en el archivo Grupos y categorías | K85: SERVICIOS TRIBUTARIOS | L85: https://portal.sat.gob.gt/portal/rtu-digital/ | M85: Servicio/tema general para contribuyentes
A86: Terceras Personas | B86: Peritos Contadores | C86: Agregada desde «Grupos y categorías» | F86: Sistema Retenciones Web -ICT- | G86: Información y documentación de soporte sobre el sistema que tienen a disposición todas las personas individuales o jurídicas afiliadas al Impuesto a la Confianza Tributaria. | H86: Terceras Personas: Abogados y Notarios, Peritos Contadores, Auditores | I86: Grupos y categorías | J86: Marcada «SI» en el archivo Grupos y categorías | L86: https://portal.sat.gob.gt/portal/sistemas-web/retencioneswebict/
A87: Terceras Personas | B87: Auditores | C87: Cultura tributaria y capacitación | D87: Preguntas frecuentes | E87: Contribuyentes Especiales | F87: Preguntas frecuentes: contribuyentes especiales | G87: Respuestas a las preguntas más comunes sobre contribuyentes especiales. | H87: Terceras Personas: Abogados y Notarios, Peritos Contadores, Auditores | I87: Grupos y categorías | J87: Marcada «SI» en el archivo Grupos y categorías | K87: CAPACITACIÓN | L87: https://portal.sat.gob.gt/portal/preguntas-frecuentes/contribuyentes-especiales/ | M87: Servicio/tema general para contribuyentes
A88: Terceras Personas | B88: Auditores | C88: Devoluciones y créditos fiscales | D88: Contador que emite el dictamen | E88: Actualización de Contador Público y Auditor para emisión de Dictámenes de Devolución de Crédito Fiscal Régimen Optativo | F88: Actualizar tus datos como contador que emite dictámenes de devolución | G88: Requisitos, pasos y documentos para actualizar tus datos como contador que emite dictámenes de devolución. | I88: Análisis | J88: Dictamen de contador público y auditor | K88: SERVICIOS TRIBUTARIOS | L88: https://portal.sat.gob.gt/portal/requisitos-tramites-agencias/actualizacion-de-contador-publico-y-auditor-para-emision-de-dictamenes-de-devolucion-de-credito-fiscal-regimen-optativo/ | M88: Servicio/tema general para contribuyentes
A89: Terceras Personas | B89: Auditores | C89: Devoluciones y créditos fiscales | D89: Contador que emite el dictamen | E89: Inscripción de Contador Público y Auditor para emisión de Dictámenes de Devolución de Crédito Fiscal Régimen Optativo | F89: Inscribirte como contador para emitir dictámenes de devolución | G89: Requisitos, pasos y documentos para inscribirte como contador para emitir dictámenes de devolución. | I89: Análisis | J89: Dictamen de contador público y auditor | K89: SERVICIOS TRIBUTARIOS | L89: https://portal.sat.gob.gt/portal/requisitos-tramites-agencias/inscripcion-de-contador-publico-y-auditor-emisor-de-dictamenes/ | M89: Servicio/tema general para contribuyentes
A90: Terceras Personas | B90: Auditores | C90: Inscripción y actualización en el RTU | D90: Contadores, auditores y gestores | E90: Actualización de Auditores | F90: Actualizar tus datos como auditor | G90: Requisitos, pasos y documentos para actualizar tus datos como auditor. | I90: Análisis | J90: Registro de auditores | K90: SERVICIOS TRIBUTARIOS | L90: https://portal.sat.gob.gt/portal/requisitos-tramites-agencias/actualizacion-de-auditores/ | M90: Servicio/tema general para contribuyentes
A91: Terceras Personas | B91: Auditores | C91: Inscripción y actualización en el RTU | D91: Contadores, auditores y gestores | E91: Inscripcion de Auditores | F91: Inscribirte como auditor | G91: Requisitos, pasos y documentos para inscribirte como auditor. | I91: Análisis | J91: Registro de auditores | K91: SERVICIOS TRIBUTARIOS | L91: https://portal.sat.gob.gt/portal/requisitos-tramites-agencias/inscripcion-de-auditores/ | M91: Servicio/tema general para contribuyentes
A92: Terceras Personas | B92: Auditores | C92: Otros servicios al contribuyente | D92: Alcohol y combustibles | E92: Requisitos para el Registro y Emisión de Autorización de la Superintendencia de Administración Tributaria al Impuesto a la Distribución de Petróleo Crudo y Combustible Derivados del Petróleo | F92: Registro de exentos del impuesto a combustibles | G92: Información sobre: Registro de exentos del impuesto a combustibles. | H92: Terceras Personas: Abogados y Notarios, Peritos Contadores, Auditores | I92: Grupos y categorías | J92: Marcada «SI» en el archivo Grupos y categorías | K92: SERVICIOS TRIBUTARIOS | L92: https://portal.sat.gob.gt/portal/requisitos-tramites-agencias/solicitud-de-registro-de-personas-exentas-del-impuesto-a-la-distribucion-de-petroleo-crudo-y-combustibles-derivados-del-petroleo/ | M92: Servicio/tema general para contribuyentes
A93: Terceras Personas | B93: Auditores | C93: Otros servicios al contribuyente | D93: Constancias y gestiones del RTU | E93: RTU Digital | F93: RTU Digital: gestiones de tu registro en línea | G93: Información sobre: RTU Digital: gestiones de tu registro en línea. | H93: Terceras Personas: Abogados y Notarios, Peritos Contadores, Auditores | I93: Grupos y categorías | J93: Marcada «SI» en el archivo Grupos y categorías | K93: SERVICIOS TRIBUTARIOS | L93: https://portal.sat.gob.gt/portal/rtu-digital/ | M93: Servicio/tema general para contribuyentes
A94: Terceras Personas | B94: Auditores | C94: Agregada desde «Grupos y categorías» | F94: Sistema Retenciones Web -ICT- | G94: Información y documentación de soporte sobre el sistema que tienen a disposición todas las personas individuales o jurídicas afiliadas al Impuesto a la Confianza Tributaria. | H94: Terceras Personas: Abogados y Notarios, Peritos Contadores, Auditores | I94: Grupos y categorías | J94: Marcada «SI» en el archivo Grupos y categorías | L94: https://portal.sat.gob.gt/portal/sistemas-web/retencioneswebict/

Sheet Organismos especiales
A1: Organismos especiales
A2: Entidades exentas y entidades del Estado que se relacionan con la SAT por régimen especial o por coordinación institucional. Orden: Categoría › Grupo › Tema › Página. «Todos los grupos» = la usan todos los grupos de la categoría. «Trámites comunes» = la usan varias categorías.
A4: Categoría | B4: Grupo | C4: Tema | D4: Subtema | E4: Página / Trámite (nombre actual) | F4: Nombre de trámite sugerido | G4: Descripción de la página | H4: Usado por (según Grupos y categorías) | I4: Origen de la clasificación | J4: Motivo / referencia | K4: Sección actual del menú | L4: URL | M4: Nota / Revisar
A5: Exentos | B5: Todos los grupos | C5: Facturación electrónica y documentos tributarios | D5: Constancias de exención (CIVA y CAIS) | E5: Habilitación para emisión de CIVA | F5: Habilitarte para emitir constancias de exención de IVA (CIVA) | G5: Requisitos, pasos y documentos para habilitarte para emitir constancias de exención de IVA (CIVA). | I5: Análisis | J5: Constancias de exención de IVA que emiten los entes exentos | K5: SERVICIOS TRIBUTARIOS | L5: https://portal.sat.gob.gt/portal/requisitos-tramites-agencias/habilitacion-para-la-emision-de-constancias-de-exencion-de-iva-civa/ | M5: Servicio/tema general para contribuyentes
A6: Exentos | B6: Constitucionales | C6: Declaraciones, pagos y solvencias | D6: Formas de pago y convenios | E6: Consulta Movimiento de Pago: Facilidades de pago | F6: Consultar pagos de tu convenio | G6: Servicio en línea para consultar pagos de tu convenio. | H6: Exentos: Constitucionales, No Lucrativos, Decreto, Municipalidades | I6: Grupos y categorías | J6: Marcada «SI» en el archivo Grupos y categorías | K6: SERVICIOS TRIBUTARIOS | L6: https://portal.sat.gob.gt/portal/consulta-movimiento-convenio/ | M6: Servicio/tema general para contribuyentes
A7: Exentos | B7: Constitucionales | C7: Declaraciones, pagos y solvencias | D7: Solvencia fiscal | E7: Bitácora de Solvencia Fiscal | F7: Historial de solvencias fiscales | G7: Información sobre: Historial de solvencias fiscales. | H7: Exentos: Constitucionales, No Lucrativos, Decreto, Municipalidades | I7: Grupos y categorías | J7: Marcada «SI» en el archivo Grupos y categorías | K7: SERVICIOS TRIBUTARIOS | L7: https://portal.sat.gob.gt/portal/bitacora-de-solvencia-fiscal/ | M7: Servicio/tema general para contribuyentes
A8: Exentos | B8: Constitucionales | C8: Declaraciones, pagos y solvencias | D8: Solvencia fiscal | E8: Falta Solvencia Fiscal | F8: ¿Por qué no tengo solvencia fiscal? | G8: Información general: ¿Por qué no tengo solvencia fiscal? | H8: Exentos: Constitucionales, No Lucrativos, Decreto, Municipalidades | I8: Grupos y categorías | J8: Marcada «SI» en el archivo Grupos y categorías | K8: SERVICIOS TRIBUTARIOS | L8: https://portal.sat.gob.gt/portal/solvencia-fiscal/ | M8: Servicio/tema general para contribuyentes
A9: Exentos | B9: Constitucionales | C9: Gestiones y consultas aduaneras | D9: Centros educativos | E9: Actualización Centros Educativos, Centros Educativos Públicos Comunitarios | F9: Actualizar los datos de un centro educativo | G9: Requisitos, pasos y documentos para actualizar los datos de un centro educativo. | I9: Análisis | J9: Centros educativos (Constitución, art. 88) | K9: SERVICIOS TRIBUTARIOS | L9: https://portal.sat.gob.gt/portal/requisitos-tramites-agencias/actualizacion-centros-educativos-centros-educativos-publicos-comunitarios/ | M9: Coincide con palabra clave de comercio exterior/aduanas
A10: Exentos | B10: Constitucionales | C10: Gestiones y consultas aduaneras | D10: Centros educativos | E10: Obligaciones Tributarias para Centros Educativos | F10: Curso: obligaciones tributarias de centros educativos | G10: Capacitación virtual de la SAT sobre obligaciones tributarias de centros educativos. | I10: Análisis | J10: Centros educativos (Constitución, art. 88) | K10: CAPACITACIÓN | L10: https://sites.google.com/capacitacionessat.page/cultura-tributariad/cursos-virtuales-sat/temas-varios/28-obligaciones-tributarias-para-los-centros-educativos | M10: Coincide con palabra clave de comercio exterior/aduanas
A11: Exentos | B11: Constitucionales | C11: Gestiones y consultas aduaneras | D11: Centros educativos | E11: Inscripción de Centros Educativos, Centros Educativos Públicos Comunitarios | F11: Inscribir un centro educativo | G11: Requisitos, pasos y documentos para inscribir un centro educativo. | I11: Análisis | J11: Centros educativos (Constitución, art. 88) | K11: SERVICIOS TRIBUTARIOS | L11: https://portal.sat.gob.gt/portal/requisitos-tramites-agencias/inscripcion-centros-educativos-centros-educativos-publicos-comunitarios-asociacion-educativa/ | M11: Coincide con palabra clave de comercio exterior/aduanas
A12: Exentos | B12: Constitucionales | C12: Gestiones y consultas aduaneras | D12: Centros educativos | E12: Solicitud de Actividades: Solicitud para llevar a cabo en centros educativos actividades de Cultura Tributaria | F12: Solicitar actividades de cultura tributaria en tu centro educativo | G12: Requisitos, pasos y documentos para solicitar actividades de cultura tributaria en tu centro educativo. | I12: Análisis | J12: Centros educativos (Constitución, art. 88) | K12: CAPACITACIÓN | L12: https://docs.google.com/forms/d/e/1FAIpQLScCxvGsehcWigqXjUu4yH5KwFZF-HDCrOwY-zL8SqwWhuZ-fQ/viewform | M12: Coincide con palabra clave de comercio exterior/aduanas
A13: Exentos | B13: Constitucionales | C13: Inscripción y actualización en el RTU | D13: Clubes y federaciones deportivas | E13: Actualización de Federaciones Deportivas | F13: Actualizar los datos de una federación deportiva | G13: Requisitos, pasos y documentos para actualizar los datos de una federación deportiva. | I13: Análisis | J13: Deporte federado autónomo (Constitución, arts. 91-92) | K13: SERVICIOS TRIBUTARIOS | L13: https://portal.sat.gob.gt/portal/requisitos-tramites-agencias/actualizacion-de-federaciones-deportivas/ | M13: Servicio/tema general para contribuyentes
A14: Exentos | B14: Constitucionales | C14: Inscripción y actualización en el RTU | D14: Iglesia Católica | E14: Actualización Iglesia Católica | F14: Actualizar los datos de una entidad de la Iglesia Católica | G14: Requisitos, pasos y documentos para actualizar los datos de una entidad de la Iglesia Católica. | I14: Análisis | J14: Exención constitucional (Constitución, arts. 37 y 88) | K14: SERVICIOS TRIBUTARIOS | L14: https://portal.sat.gob.gt/portal/requisitos-tramites-agencias/actualizacion-iglesia-catolica/ | M14: Servicio/tema general para contribuyentes
A15: Exentos | B15: Constitucionales | C15: Inscripción y actualización en el RTU | D15: Iglesia Católica | E15: Cancelación de nombramiento de representante legal de iglesia católica | F15: Cancelar al representante legal de una entidad de la Iglesia Católica | G15: Requisitos, pasos y documentos para cancelar al representante legal de una entidad de la Iglesia Católica. | I15: Análisis | J15: Exención constitucional (Constitución, arts. 37 y 88) | K15: SERVICIOS TRIBUTARIOS | L15: https://portal.sat.gob.gt/portal/requisitos-tramites-agencias/cancelacion-de-nombramiento-de-representante-legal-de-iglesia-catolica/ | M15: Servicio/tema general para contribuyentes
A16: Exentos | B16: Constitucionales | C16: Inscripción y actualización en el RTU | D16: Iglesia Católica | E16: Inscripción de Iglesia Católica | F16: Inscribir una entidad de la Iglesia Católica | G16: Requisitos, pasos y documentos para inscribir una entidad de la Iglesia Católica. | I16: Análisis | J16: Exención constitucional (Constitución, arts. 37 y 88) | K16: SERVICIOS TRIBUTARIOS | L16: https://portal.sat.gob.gt/portal/requisitos-tramites-agencias/inscripcion-iglesia-catolica/ | M16: Servicio/tema general para contribuyentes
A17: Exentos | B17: Constitucionales | C17: Inscripción y actualización en el RTU | D17: Universidades privadas | E17: Actualización Universidad Privada Empresa/Organización (Persona Jurídica) | F17: Actualizar los datos de una universidad privada | G17: Requisitos, pasos y documentos para actualizar los datos de una universidad privada. | I17: Análisis | J17: Exención constitucional (Constitución, arts. 37 y 88) | K17: SERVICIOS TRIBUTARIOS | L17: https://portal.sat.gob.gt/portal/requisitos-tramites-agencias/actualizacion-universidad-privada-empresa-organizacion-persona-juridica/ | M17: Servicio/tema general para contribuyentes
A18: Exentos | B18: Constitucionales | C18: Inscripción y actualización en el RTU | D18: Universidades privadas | E18: Inscripción de Universidad Privada | F18: Inscribir una universidad privada | G18: Requisitos, pasos y documentos para inscribir una universidad privada. | I18: Análisis | J18: Exención constitucional (Constitución, arts. 37 y 88) | K18: SERVICIOS TRIBUTARIOS | L18: https://portal.sat.gob.gt/portal/requisitos-tramites-agencias/inscripcion-universidad-privada/ | M18: Servicio/tema general para contribuyentes
A19: Exentos | B19: Constitucionales | C19: Notarios | D19: Traspasos y avisos | E19: Requisitos Gestiones Vehículos para Notarios: Requisitos para Trámites de Notarios | F19: Requisitos para Avisos de Notarios | G19: Requisitos para el aviso de legalización de firmas en certificado de propiedad de vehículos y aviso de transferencia de dominio de vehículos. | H19: Exentos: Constitucionales, No Lucrativos, Decreto, Municipalidades | I19: Grupos y categorías | J19: Marcada «SI» en el archivo Grupos y categorías | K19: SERVICIOS TRIBUTARIOS | L19: https://portal.sat.gob.gt/portal/requisitos-tramites-notarios/ | M19: Rol profesional (agente aduanero, notario, abogado, gestor, tercero autorizado)
A20: Exentos | B20: Constitucionales | C20: Otros servicios al contribuyente | D20: Constancias y gestiones del RTU | E20: Tercera Persona Autorizada en Gestiones de RTU | F20: Autorizar a otra persona para gestiones del RTU | G20: Requisitos, pasos y documentos para autorizar a otra persona para gestiones del RTU. | H20: Exentos: Constitucionales, No Lucrativos, Decreto, Municipalidades | I20: Grupos y categorías | J20: Marcada «SI» en el archivo Grupos y categorías | K20: SERVICIOS TRIBUTARIOS | L20: https://portal.sat.gob.gt/portal/requisitos-tramites-agencias/tercera-persona-autorizada-rtu/ | M20: Servicio/tema general para contribuyentes
