Workbook

Sheet Resumen Arquitectura
B2: SUPERINTENDENCIA DE ADMINISTRACIÓN TRIBUTARIA — SAT GUATEMALA
B4: ARQUITECTURA DE INFORMACIÓN DEL PORTAL WEB — DEFINICIÓN DE SEGMENTOS, LEAD TEXT Y BASE JURÍDICA
B6: =COUNTA('Matriz Maestra (676)'!A2:A677) | C6: =COUNTIF('Matriz Maestra (676)'!C2:C677, "Contribuyentes") | D6: =COUNTIF('Matriz Maestra (676)'!C2:C677, "Operadores de Comercio Exterior") | F6: =COUNTIF('Matriz Maestra (676)'!C2:C677, "Profesionales") | G6: =COUNTIF('Matriz Maestra (676)'!C2:C677, "Entes Exentos")
B9: 1. SEGMENTOS PRINCIPALES DEL PORTAL (NIVEL 1) — DEFINICIONES INSTITUCIONALES
B10: No. | C10: Segmento (Nivel 1) | D10: Qué es: (Definición Operativa) | E10: Lead text: (Texto Orientador de Interfaz) | F10: Base jurídica: (Fundamento Legal Oficial: CAUCA, RECAUCA, Leyes) | G10: Total Contenidos | H10: % del Portal
B11: 1 | C11: Operadores de Comercio Exterior | D11: Son todas las personas individuales o jurídicas que intervienen en el ingreso, permanencia, traslado y salida de mercancías del territorio aduanero nacional. Comprende tanto a los dueños de las mercancías (importadores y exportadores) como a los prestadores de servicios logísticos autorizados (auxiliares de la función pública, transportistas, depósitos) y empresas que operan bajo regímenes territoriales especiales. | E11: Servicios e información aduanera para la importación, exportación y logística. | F11: Código Tributario (Dto. 6-91), CAUCA IV (Resolución 223-2008 COMIECO) y RECAUCA (Resolución 224-2008 COMIECO). | G11: =COUNTIF('Matriz Maestra (676)'!C2:C677, "Operadores de Comercio Exterior") | H11: =G11/COUNTA('Matriz Maestra (676)'!A2:A677)
B12: 2 | C12: Contribuyentes | D12: Son las personas individuales, jurídicas, patrimonios o entes afectos al cumplimiento de obligaciones tributarias internas en el territorio guatemalteco. Abarca a ciudadanos sin actividad económica activa, asalariados en relación de dependencia, pequeños contribuyentes, contribuyentes del régimen general del IVA e ISR, propietarios de vehículos y grandes/medianos contribuyentes especiales calificados. | E12: Información y servicios tributarios para personas y empresas. | F12: Constitución Política (Art. 135d), Código Tributario (Dto. 6-91), Ley del IVA (Dto. 27-92), Ley de Actualización Tributaria (Dto. 10-2012), Ley del ISCV (Dto. 70-94) y Ley de Simplificación Tributaria (Dto. 7-2019 / Dto. 31-2024). | G12: =COUNTIF('Matriz Maestra (676)'!C2:C677, "Contribuyentes") | H12: =G12/COUNTA('Matriz Maestra (676)'!A2:A677)
B13: 3 | C13: Profesionales | D13: Son las personas individuales colegiadas activas o técnicos acreditados ante la SAT que ejercen liberalmente su profesión o actúan como auxiliares técnicos en materia tributaria, mercantil y notarial. Comprende a abogados y notarios (traspasos vehiculares electrónicos y fe pública), peritos contadores, contadores públicos y auditores (CPA) y gestores tributarios acreditados. | E13: Herramientas y servicios especializados para profesionales tributarios y auxiliares. | F13: Código de Notariado (Dto. 314), Ley de Colegiación Profesional Obligatoria (Dto. 72-2001), Decreto 2450 (Normas de la Profesión Contable), Ley de Timbres Fiscales (Dto. 37-92) y Código Tributario (Art. 57 "A" y 112). | G13: =COUNTIF('Matriz Maestra (676)'!C2:C677, "Profesionales") | H13: =G13/COUNTA('Matriz Maestra (676)'!A2:A677)
B14: 4 | C14: Entes Exentos | D14: Son las personas jurídicas, entidades del sector público, organismos diplomáticos y organizaciones de la sociedad civil que, por mandato constitucional o ley específica ordinaria, gozan de exención total o parcial de tributos y aranceles en el territorio nacional. Incluye centros educativos, universidades, comunidades religiosas, ONGs, fundaciones sin fines de lucro, municipalidades y ministerios de Estado. | E14: Información y gestiones tributarias para entidades públicas y organizaciones no lucrativas. | F14: Constitución Política (Arts. 37, 73, 88 y 257), Ley de ONGs (Dto. 02-2003), Ley del IVA (Dto. 27-92, Art. 8), Ley de Actualización Tributaria (Dto. 10-2012, Art. 11), Código Municipal (Dto. 12-2002) y Ley Orgánica del Presupuesto (Dto. 101-97). | G14: =COUNTIF('Matriz Maestra (676)'!C2:C677, "Entes Exentos") | H14: =G14/COUNTA('Matriz Maestra (676)'!A2:A677)
C15: TOTAL PORTAL WEB SAT | D15: Universo total de fichas y servicios | G15: =SUM(G11:G14) | H15: =SUM(H11:H14)
B17: 2. CICLO DE VIDA ATO (AUSTRALIA) - SIN NÚMEROS VISIBLES
B18: Etapa ATO | C18: Descripción Funcional | G18: Total Contenidos | H18: %
B19: Empezar y registrarse | C19: Primer NIT, RTU Digital, padrones de importación/exportación y habilitación inicial | G19: =COUNTIF('Matriz Maestra (676)'!K2:K677, "Empezar y registrarse") | H19: =G19/COUNTA('Matriz Maestra (676)'!A2:A677)
B20: Operación y declaraciones | C20: Facturación FEL, Declaraguate, DUCAs, retenciones, transferencias y pagos | G20: =COUNTIF('Matriz Maestra (676)'!K2:K677, "Operación y declaraciones") | H20: =G20/COUNTA('Matriz Maestra (676)'!A2:A677)
B21: Consultas y herramientas | C21: Verificadores en tiempo real, solvencia, selectivo aduanero, rampa y SAC | G21: =COUNTIF('Matriz Maestra (676)'!K2:K677, "Consultas y herramientas") | H21: =G21/COUNTA('Matriz Maestra (676)'!A2:A677)
B22: Modificaciones y cierre | C22: Actualización de RTU, traspaso vehicular, prórrogas, cese de actividades y subastas | G22: =COUNTIF('Matriz Maestra (676)'!K2:K677, "Modificaciones y cierre") | H22: =G22/COUNTA('Matriz Maestra (676)'!A2:A677)
B23: Normativa y asistencia | C23: Marco legal aduanero y tributario, devoluciones, criterios institucionales y cursos | G23: =COUNTIF('Matriz Maestra (676)'!K2:K677, "Normativa y asistencia") | H23: =G23/COUNTA('Matriz Maestra (676)'!A2:A677)
B24: TOTAL POR CICLO ATO | C24: 100% de contenidos clasificados según ciclo de vida | G24: =SUM(G19:G23) | H24: =SUM(H19:H23)
B26: 3. TIPOS DE INTERACCIÓN (CÓMO RESUELVE EL CIUDADANO)
B27: Tipo de Interacción | C27: Modalidad Operativa | G27: Total Contenidos | H27: %
B28: Guía Informativa / Texto | C28: Páginas explicativas, requisitos de trámites presenciales o mixtos | G28: =COUNTIF('Matriz Maestra (676)'!L2:L677, "Guía Informativa / Texto") | H28: =G28/COUNTA('Matriz Maestra (676)'!A2:A677)
B29: Trámite / Aplicativo en Línea | C29: Servicios digitales transaccionales (Agencia Virtual, Declaraguate, TEV, FEL) | G29: =COUNTIF('Matriz Maestra (676)'!L2:L677, "Trámite / Aplicativo en Línea") | H29: =G29/COUNTA('Matriz Maestra (676)'!A2:A677)
B30: Consulta en Base de Datos | C30: Herramientas de verificación sin autenticación previa (RTU público, solvencias) | G30: =COUNTIF('Matriz Maestra (676)'!L2:L677, "Consulta en Base de Datos") | H30: =G30/COUNTA('Matriz Maestra (676)'!A2:A677)
B31: Descarga de Documento / Software | C31: Descarga de formularios en PDF/Excel, software, manuales o legislación | G31: =COUNTIF('Matriz Maestra (676)'!L2:L677, "Descarga de Documento / Software") | H31: =G31/COUNTA('Matriz Maestra (676)'!A2:A677)
B32: TOTAL INTERACCIONES | C32: 100% de contenidos catalogados | G32: =SUM(G28:G31) | H32: =SUM(H28:H31)

Sheet Matriz Maestra (676)
A1: No. | B1: ID Trámite | C1: Segmento (L1) | D1: Régimen / Área (L2) | E1: Nivel 3: Grupo de Actor | F1: Nivel 4: Actor Específico / Recinto | G1: Materia / Tema | H1: Subtema / Tipo de Gestión | I1: Nombre del Trámite / Servicio (Lenguaje Claro) | J1: Ruta de Navegación (Miga de Pan) | K1: Etapa Ciclo de Vida ATO | L1: Tipo de Interacción | M1: Tipología de Contenido | N1: Plataforma / Sistema | O1: Canal | P1: Control de Auditoría | Q1: ¿Para qué sirve? (Descripción Operativa) | R1: Base Legal / Fundamento Jurídico (En base a qué: CAUCA, RECAUCA, Leyes) | S1: Ruta de Procesos Asociada | T1: Estado Normativo | U1: URL Portal SAT
A2: 1 | B2: profesionales-38 | C2: Profesionales | D2: Servicios Profesionales y Terceras Personas | E2: Abogados y Notarios | F2: — | G2: Constancias y gestiones del RTU | H2: Requisitos de persona/empresa | I2: Acreditación de procurador o tercero para retiro de especies fiscales | J2: Profesionales > Servicios Profesionales y Terceras Personas > Abogados y Notarios > Constancias y gestiones del RTU > Requisitos de persona/empresa > Acreditación de procurador o tercero para retiro de especies fiscales | K2: Empezar y registrarse | L2: Guía Informativa / Texto | M2: Guía de Requisitos y Pasos | N2: Portal Web SAT | O2: 100% Digital | P2: APROBADO | Q2: Carta de autorización notarial, boleta SAT-2000 y requisitos para que un procurador retire papel sellado o timbres en agencia. | R2: Decreto 37-92 (Ley del Impuesto de Timbres Fiscales y de Papel Sellado Especial para Protocolos). | S2: N/A | T2: Vigente | U2: https://portal.sat.gob.gt/portal/requisitos-tramites-agencias/venta-de-especies-fiscales-a-notarios-y-patentados/
A3: 2 | B3: profesionales-70 | C3: Profesionales | D3: Servicios Profesionales y Terceras Personas | E3: Abogados y Notarios | F3: — | G3: Registro | H3: Inscripción / Actualización de Abogado y Notario | I3: Inscripción y actualización de Abogado y Notario en el Registro Tributario Unificado (RTU) | J3: Profesionales > Servicios Profesionales y Terceras Personas > Abogados y Notarios > Registro > Inscripción / Actualización de Abogado y Notario > Inscripción y actualización de Abogado y Notario en RTU | K3: Modificaciones y cierre | L3: Trámite / Aplicativo en Línea | M3: Guía de Requisitos y Pasos | N3: Portal Web SAT | O3: 100% Digital | P3: APROBADO | Q3: Requisitos, colegiado activo (CANG) y pasos para inscribir o actualizar tus datos profesionales como Abogado y Notario en el RTU. | R3: Decreto 37-92 (Ley del Impuesto de Timbres Fiscales y de Papel Sellado Especial para Protocolos). | S3: N/A | T3: Vigente | U3: https://portal.sat.gob.gt/portal/requisitos-de-personas-empresas/
A4: 3 | B4: profesionales-71 | C4: Profesionales | D4: Servicios Profesionales y Terceras Personas | E4: Abogados y Notarios | F4: — | G4: Traspasos y avisos | H4: Tercera Persona Autorizada en el Registro Fiscal de Vehículos | I4: Autorización notarial de tercera persona en el Registro Fiscal de Vehículos | J4: Profesionales > Servicios Profesionales y Terceras Personas > Abogados y Notarios > Traspasos y avisos > Tercera Persona Autorizada en el Registro Fiscal de Vehículos > Autorización notarial de tercera persona en el Registro Fiscal de Vehículos | K4: Operación y declaraciones | L4: Guía Informativa / Texto | M4: Guía de Requisitos y Pasos | N4: Portal Web SAT | O4: 100% Digital | P4: APROBADO | Q4: Acta notarial de legalización para que un tercero o apoderado realice gestiones vehiculares presenciales en nombre del propietario. | R4: Decreto 37-92 (Ley del Impuesto de Timbres Fiscales y de Papel Sellado Especial para Protocolos). | S4: N/A | T4: Vigente | U4: https://portal.sat.gob.gt/portal/requisitos-de-personas-empresas/
A5: 4 | B5: profesionales-32 | C5: Profesionales | D5: Servicios Profesionales y Terceras Personas | E5: Abogados y Notarios | F5: — | G5: Traspasos y avisos | H5: Traspaso Electrónico de Vehículos por Notario con Anexo del Certificado de Propiedad emitido vía Declaraguate en Agencia Virtual | I5: Formalización notarial de traspaso electrónico de vehículos en línea | J5: Profesionales > Servicios Profesionales y Terceras Personas > Abogados y Notarios > Traspasos y avisos > Traspaso Electrónico de Vehículos por Notario con Anexo del Certificado de Propiedad emitido vía Declaraguate en Agencia Virtual > Formalización notarial de traspaso electrónico de vehículos en línea | K5: Operación y declaraciones | L5: Trámite / Aplicativo en Línea | M5: Guía de Requisitos y Pasos | N5: Portal Web SAT | O5: 100% Digital | P5: APROBADO | Q5: Proceso notarial para autorizar la compraventa vehicular, validar autorizaciones de comprador/vendedor y generar distintivos electrónicos. | R5: Decreto 37-92 (Ley del Impuesto de Timbres Fiscales y de Papel Sellado Especial para Protocolos). | S5: N/A | T5: Vigente | U5: https://portal.sat.gob.gt/portal/requisitos-de-vehiculos/
A6: 5 | B6: profesionales-56 | C6: Profesionales | D6: Servicios Profesionales y Terceras Personas | E6: Abogados y Notarios | F6: — | G6: Requisitos y representantes | H6: Requisitos Gestiones Vehículos para Propietarios: Requisitos de Vehiculos | I6: Carga y remisión de expedientes digitales de traspaso con firma avanzada | J6: Profesionales > Servicios Profesionales y Terceras Personas > Abogados y Notarios > Requisitos y representantes > Requisitos Gestiones Vehículos para Propietarios: Requisitos de Vehiculos > Carga y remisión de expedientes digitales de traspaso con firma avanzada | K6: Operación y declaraciones | L6: Trámite / Aplicativo en Línea | M6: Guía de Requisitos y Pasos | N6: Portal Web SAT | O6: 100% Digital | P6: APROBADO | Q6: Envío de archivos digitalizados en formato PDF firmados electrónicamente por el notario para concluir el cambio de propietario. | R6: Decreto 37-92 (Ley del Impuesto de Timbres Fiscales y de Papel Sellado Especial para Protocolos). | S6: N/A | T6: Vigente | U6: https://portal.sat.gob.gt/portal/requisitos-de-vehiculos/
A7: 6 | B7: contribuyentes-44 | C7: Profesionales | D7: Servicios Profesionales y Terceras Personas | E7: Abogados y Notarios | F7: — | G7: Otros servicios al contribuyente | H7: Constancias y gestiones del RTU | I7: Devolución y canje de timbres fiscales y papel sellado inutilizado | J7: Profesionales > Servicios Profesionales y Terceras Personas > Abogados y Notarios > Otros servicios al contribuyente > Constancias y gestiones del RTU > Devolución y canje de timbres fiscales y papel sellado inutilizado | K7: Operación y declaraciones | L7: Guía Informativa / Texto | M7: Guía de Requisitos y Pasos | N7: Portal Web SAT | O7: 100% Digital | P7: APROBADO | Q7: Procedimiento para solicitar la reposición o devolución monetaria de especies fiscales deterioradas o no utilizadas conforme a ley. | R7: Decreto 37-92 (Ley del Impuesto de Timbres Fiscales y de Papel Sellado Especial para Protocolos). | S7: Proc #42 (Requisitos por trámite) | T7: Vigente | U7: https://portal.sat.gob.gt/portal/requisitos-de-personas-empresas/
A8: 7 | B8: profesionales-33 | C8: Profesionales | D8: Servicios Profesionales y Terceras Personas | E8: Abogados y Notarios | F8: — | G8: Traspasos y avisos | H8: Requisitos Gestiones Vehículos para Notarios: Requisitos para Trámites de Notarios | I8: Consulta de avisos notariales y estado de legalizaciones registradas | J8: Profesionales > Servicios Profesionales y Terceras Personas > Abogados y Notarios > Traspasos y avisos > Requisitos Gestiones Vehículos para Notarios: Requisitos para Trámites de Notarios > Consulta de avisos notariales y estado de legalizaciones registradas | K8: Consultas y herramientas | L8: Consulta en Base de Datos | M8: Guía de Requisitos y Pasos | N8: Portal Web SAT | O8: 100% Digital | P8: APROBADO | Q8: Verifica el historial, recepción oficial y confirmación de los avisos notariales emitidos a través de tu Agencia Virtual. | R8: Decreto 37-92 (Ley del Impuesto de Timbres Fiscales y de Papel Sellado Especial para Protocolos). | S8: N/A | T8: Vigente | U8: https://portal.sat.gob.gt/portal/requisitos-tramites-agencias/aviso-de-legalizacion-de-firmas-en-certificado-de-propiedad-de-vehiculos/
A9: 8 | B9: profesionales-34 | C9: Profesionales | D9: Servicios Profesionales y Terceras Personas | E9: Abogados y Notarios | F9: — | G9: Traspasos y avisos | H9: Requisitos Gestiones Vehículos para Notarios: Requisitos para Trámites de Notarios | I9: Calendario y plazos de obligaciones notariales ante la SAT | J9: Profesionales > Servicios Profesionales y Terceras Personas > Abogados y Notarios > Traspasos y avisos > Requisitos Gestiones Vehículos para Notarios: Requisitos para Trámites de Notarios > Calendario y plazos de obligaciones notariales ante la SAT | K9: Operación y declaraciones | L9: Guía Informativa / Texto | M9: Guía de Requisitos y Pasos | N9: Portal Web SAT | O9: 100% Digital | P9: APROBADO | Q9: Guía de plazos legales para la presentación de avisos de legalización, testimonios especiales afectos y prevención de sanciones. | R9: Decreto 37-92 (Ley del Impuesto de Timbres Fiscales y de Papel Sellado Especial para Protocolos). | S9: N/A | T9: Vigente | U9: https://portal.sat.gob.gt/portal/requisitos-tramites-notarios/
A10: 9 | B10: profesionales-76 | C10: Entes Exentos | D10: Organizaciones No Lucrativas (Exentas) | E10: Iglesias y Comunidades Religiosas | F10: — | G10: Alcohol y combustibles | H10: Requisitos para el Registro y Emisión de Autorización de la Superintendencia de Administración Tributaria al Impuesto a la Distribución de Petróleo Crudo y Combustible Derivados del Petróleo | I10: Información sobre: Registro de exentos del impuesto a combustibles. | J10: Entes Exentos > Organizaciones No Lucrativas (Exentas) > Iglesias y Comunidades Religiosas > Alcohol y combustibles > Requisitos para el Registro y Emisión de Autorización de la Superintendencia de Administración Tributaria al Impuesto a la Distribución de Petróleo Crudo y Combustible Derivados del Petróleo > Información sobre: Registro de exentos del impuesto a combustibles. | K10: Operación y declaraciones | L10: Guía Informativa / Texto | M10: Guía de Requisitos y Pasos | N10: Portal Web SAT | O10: 100% Digital | P10: APROBADO | Q10: Terceras Personas: Abogados y Notarios, Peritos Contadores, Auditores | R10: Decreto Legislativo de Exención / Fomento Específico y Código Tributario. | S10: N/A | T10: Vigente | U10: https://portal.sat.gob.gt/portal/requisitos-tramites-agencias/solicitud-de-registro-de-personas-exentas-del-impuesto-a-la-distribucion-de-petroleo-crudo-y-combustibles-derivados-del-petroleo/
A11: 10 | B11: profesionales-77 | C11: Profesionales | D11: Servicios Profesionales y Terceras Personas | E11: Abogados y Notarios | F11: — | G11: Constancias y gestiones del RTU | H11: RTU Digital | I11: Ratificación anual de datos de Abogado y Notario en el Registro Tributario Unificado (RTU) Digital | J11: Profesionales > Servicios Profesionales y Terceras Personas > Abogados y Notarios > Constancias y gestiones del RTU > RTU Digital > Ratificación anual de datos de Abogado y Notario en RTU Digital | K11: Empezar y registrarse | L11: Guía Informativa / Texto | M11: Guía de Requisitos y Pasos | N11: Portal Web SAT | O11: 100% Digital | P11: APROBADO | Q11: Actualización anual obligatoria de dirección de bufete o domicilio fiscal para mantener habilitada la compra de especies y trámites en línea. | R11: Decreto 37-92 (Ley del Impuesto de Timbres Fiscales y de Papel Sellado Especial para Protocolos). | S11: N/A | T11: Vigente | U11: https://portal.sat.gob.gt/portal/rtu-digital/
A12: 11 | B12: profesionales-78 | C12: Profesionales | D12: Servicios Profesionales y Terceras Personas | E12: Profesionales Habilitados | F12: — | G12: Sistemas de Retención en la Fuente | H12: Gestión Profesional | I12: Información y documentación de soporte sobre el sistema que tienen a disposición todas las personas individuales o jurídicas afiliadas al Impuesto a la Confianza Tributaria. | J12: Profesionales > Servicios Profesionales y Terceras Personas > Profesionales Habilitados > Sistemas de Retención en la Fuente > Gestión Profesional > Información y documentación de soporte sobre el sistema que tienen a disposición todas las personas individuales o jurídicas afiliadas al Impuesto a la Confianza Tributaria. | K12: Consultas y herramientas | L12: Trámite / Aplicativo en Línea | M12: Guía de Requisitos y Pasos | N12: Portal Web SAT | O12: 100% Digital | P12: APROBADO | Q12: Terceras Personas: Abogados y Notarios, Peritos Contadores, Auditores | R12: Código de Comercio, Código Tributario y Leyes Profesionales Aplicables. | S12: N/A | T12: Vigente | U12: https://portal.sat.gob.gt/
A13: 12 | B13: profesionales-66 | C13: Profesionales | D13: Servicios Profesionales y Terceras Personas | E13: Abogados y Notarios | F13: — | G13: Especies fiscales | H13: Venta de Especies Fiscales a Notarios y Patentados | I13: Adquisición de Papel Sellado Especial para Protocolos y Timbres Fiscales (SAT-7130) | J13: Profesionales > Servicios Profesionales y Terceras Personas > Abogados y Notarios > Especies fiscales > Venta de Especies Fiscales a Notarios y Patentados > Adquisición de Papel Sellado Especial para Protocolos y Timbres Fiscales (SAT-7130) | K13: Operación y declaraciones | L13: Trámite / Aplicativo en Línea | M13: Guía de Requisitos y Pasos | N13: Portal Web SAT | O13: 100% Digital | P13: APROBADO | Q13: Pago y compra de hojas de papel de protocolo (lotes de 50 hojas) y timbres fiscales físicos en agencias tributarias mediante Declaraguate. | R13: Decreto 37-92 (Ley del Impuesto de Timbres Fiscales y de Papel Sellado Especial para Protocolos). | S13: N/A | T13: Vigente | U13: https://portal.sat.gob.gt/portal/requisitos-de-personas-empresas/
... A677: 676 | B677: contribuyentes-rtu-tercera-persona | C677: Contribuyentes | D677: Contribuyente General | E677: Personas Individuales con Negocio | F677: — | G677: Constancias y gestiones del RTU | H677: Tercera Persona Autorizada en Gestiones de RTU | I677: Requisitos, pasos y documentos para autorizar a otra persona para gestiones del Registro Tributario Unificado (RTU). | J677: Contribuyentes > Contribuyente General > RTU Digital y Agencia Virtual > Operaciones y trámites > Autorización a tercera persona para gestiones del RTU | K677: Operación y declaraciones | L677: Guía Informativa / Texto | M677: Guía de Requisitos y Pasos | N677: Portal Web SAT | O677: Presencial / Mixto | P677: APROBADO | Q677: Exentos: Constitucionales, No Lucrativos, Decreto, Municipalidades | R677: Código Tributario, Decreto 6-91 (Arts. 112 y 120) y Acuerdo de Directorio SAT 08-2020. | S677: N/A | T677: Vigente | U677: https://portal.sat.gob.gt/portal/requisitos-tramites-agencias/tercera-persona-autorizada-rtu/

Sheet Comercio Exterior (204)
A1: No. | B1: Régimen / Área Aduanera | C1: Grupo de Actor | D1: Actor Específico / Recinto | E1: Materia / Tema | F1: Subtema / Tipo de Gestión | G1: Nombre del Trámite / Servicio (Lenguaje Claro) | H1: Ruta de Navegación (Miga de Pan) | I1: Etapa Ciclo de Vida ATO | J1: Tipo de Interacción | K1: Tipología de Contenido | L1: Plataforma / Sistema | M1: Control de Auditoría | N1: ¿Para qué sirve? (Descripción Operativa) | O1: Base Legal / Fundamento Jurídico (En base a qué: CAUCA, RECAUCA, Leyes) | P1: Ruta de Proceso | Q1: Estado Normativo | R1: URL Portal SAT
A2: 1 | B2: 2. Auxiliares de la Función Pública Aduanera (AFPA) | C2: Apoderados Especiales Aduaneros | D2: Apoderados Especiales Aduaneros | E2: Apoderados Especiales Aduaneros | F2: Registro y acreditación | G2: Requisitos para la renovación de operación de auxiliares de la función pública | H2: Operadores de Comercio Exterior > 2. Auxiliares de la Función Pública Aduanera (AFPA) > Apoderados Especiales Aduaneros > Registro y acreditación > Requisitos para la renovación de operación de auxiliares de la función pública | I2: Empezar y registrarse | J2: Trámite / Aplicativo en Línea | K2: Trámite / Aplicativo en Línea | L2: Portal Web SAT | M2: APROBADO | N2: Presenta la solicitud y cumple los requisitos oficiales ante la SAT para renovar tu autorización anual como Apoderados Especiales Aduaneros. | O2: CAUCA IV y RECAUCA IV (Arts. 86 al 90, Apoderados Especiales Aduaneros). | P2: N/A | Q2: Vigente | R2: https://portal.sat.gob.gt/portal/requisitos-de-aduanas/#1608063945646-f9ebd644-65ff
A3: 2 | B3: 2. Auxiliares de la Función Pública Aduanera (AFPA) | C3: Apoderados Especiales Aduaneros | D3: Apoderados Especiales Aduaneros | E3: Apoderados Especiales Aduaneros | F3: Registro y acreditación | G3: Auxiliares de la función pública aduanera (Carné, firma electrónica PKI y Declaración Aduanera DUA) | H3: Operadores de Comercio Exterior > 2. Auxiliares de la Función Pública Aduanera (AFPA) > Apoderados Especiales Aduaneros > Registro y acreditación > Auxiliares de la función pública aduanera (Carné, componente ActiveX PKI/DUA) | I3: Empezar y registrarse | J3: Descarga de Documento / Software | K3: Descarga de Documento / Software | L3: Portal Web SAT | M3: APROBADO | N3: Gestiona la emisión y actualización de tu carné oficial de identificación para ingresar a recintos aduaneros. | O3: CAUCA IV y RECAUCA IV (Arts. 86 al 90, Apoderados Especiales Aduaneros). | P3: N/A | Q3: Vigente | R3: https://portal.sat.gob.gt/portal/procedimientos-aduanas/#1570112086149-de895ac7-a87c
A4: 3 | B4: 2. Auxiliares de la Función Pública Aduanera (AFPA) | C4: Apoderados Especiales Aduaneros | D4: Apoderados Especiales Aduaneros | E4: Apoderados Especiales Aduaneros | F4: Registro y acreditación | G4: Recepción de seguro de caución importación y admisión temporal | H4: Operadores de Comercio Exterior > 2. Auxiliares de la Función Pública Aduanera (AFPA) > Apoderados Especiales Aduaneros > Registro y acreditación > Recepción de seguro de caución importación y admisión temporal | I4: Empezar y registrarse | J4: Trámite / Aplicativo en Línea | K4: Trámite / Aplicativo en Línea | L4: Portal Web SAT | M4: APROBADO | N4: Entrega y registra la póliza de fianza o seguro de caución exigido para garantizar tus operaciones aduaneras. | O4: CAUCA IV y RECAUCA IV (Arts. 86 al 90, Apoderados Especiales Aduaneros). | P4: N/A | Q4: Vigente | R4: https://portal.sat.gob.gt/portal/requisitos-tramites-agencias/recepcion-de-seguro-de-caucion-importacion-y-admision-temporal/
A5: 4 | B5: 2. Auxiliares de la Función Pública Aduanera (AFPA) | C5: Apoderados Especiales Aduaneros | D5: Apoderados Especiales Aduaneros | E5: Apoderados Especiales Aduaneros | F5: Registro y acreditación | G5: Solvencia fiscal (Requisito para renovación de Auxiliares de la Función Pública Aduanera (AFPA)) | H5: Operadores de Comercio Exterior > 2. Auxiliares de la Función Pública Aduanera (AFPA) > Apoderados Especiales Aduaneros > Registro y acreditación > Solvencia fiscal (Requisito para renovación AFPA) | I5: Empezar y registrarse | J5: Trámite / Aplicativo en Línea | K5: Trámite / Aplicativo en Línea | L5: Portal Web SAT | M5: APROBADO | N5: Obtén tu solvencia fiscal en línea como requisito indispensable para operar y renovar tu acreditación como Apoderados Especiales Aduaneros. | O5: CAUCA IV y RECAUCA IV (Arts. 86 al 90, Apoderados Especiales Aduaneros). | P5: N/A | Q5: Vigente | R5: https://portal.sat.gob.gt/portal/solvencia-fiscal/
A6: 5 | B6: 2. Auxiliares de la Función Pública Aduanera (AFPA) | C6: Apoderados Especiales Aduaneros | D6: Apoderados Especiales Aduaneros | E6: Apoderados Especiales Aduaneros | F6: Registro y acreditación | G6: Autorización inicial y registro de mandato de apoderado especial | H6: Operadores de Comercio Exterior > 2. Auxiliares de la Función Pública Aduanera (AFPA) > Apoderados Especiales Aduaneros > Registro y acreditación > Autorización inicial y registro de mandato de apoderado especial | I6: Empezar y registrarse | J6: Trámite / Aplicativo en Línea | K6: Trámite / Aplicativo en Línea | L6: Portal Web SAT | M6: PENDIENTE (Propuesta brecha) | N6: Presenta el mandato legal y solicita la autorización inicial ante la SAT para actuar como apoderado especial aduanero. | O6: CAUCA IV y RECAUCA IV (Arts. 86 al 90, Apoderados Especiales Aduaneros). | P6: N/A | Q6: Brecha Propuesta | R6: https://portal.sat.gob.gt/portal/requisitos-de-aduanas/
A7: 6 | B7: 2. Auxiliares de la Función Pública Aduanera (AFPA) | C7: Apoderados Especiales Aduaneros | D7: Apoderados Especiales Aduaneros | E7: Apoderados Especiales Aduaneros | F7: Operaciones y trámites | G7: Declaración de mercancías (Declaración Única Centroamericana - DUCA y Aduana sin papeles) | H7: Operadores de Comercio Exterior > 2. Auxiliares de la Función Pública Aduanera (AFPA) > Apoderados Especiales Aduaneros > Operaciones y trámites > Declaración de mercancías (DUCA y Aduana sin papeles) | I7: Operación y declaraciones | J7: Trámite / Aplicativo en Línea | K7: Trámite / Aplicativo en Línea | L7: Portal Web SAT | M7: APROBADO | N7: Transmite electrónicamente la declaración de mercancías DUCA y gestiona el despacho aduanero ágil. | O7: CAUCA IV y RECAUCA IV (Arts. 86 al 90, Apoderados Especiales Aduaneros). | P7: N/A | Q7: Vigente | R7: https://portal.sat.gob.gt/portal/procedimientos-aduanas/
A8: 7 | B8: 2. Auxiliares de la Función Pública Aduanera (AFPA) | C8: Apoderados Especiales Aduaneros | D8: Apoderados Especiales Aduaneros | E8: Apoderados Especiales Aduaneros | F8: Operaciones y trámites | G8: Declaración anticipada | H8: Operadores de Comercio Exterior > 2. Auxiliares de la Función Pública Aduanera (AFPA) > Apoderados Especiales Aduaneros > Operaciones y trámites > Declaración anticipada | I8: Operación y declaraciones | J8: Trámite / Aplicativo en Línea | K8: Trámite / Aplicativo en Línea | L8: Portal Web SAT | M8: APROBADO | N8: Presenta tu declaración y paga tributos antes de que arribe el medio de transporte para agilizar el levante. | O8: CAUCA IV y RECAUCA IV (Arts. 86 al 90, Apoderados Especiales Aduaneros). | P8: N/A | Q8: Vigente | R8: https://portal.sat.gob.gt/portal/facilitacion-de-comercio/#1559325573466-1284efd5-2d1b
A9: 8 | B9: 2. Auxiliares de la Función Pública Aduanera (AFPA) | C9: Apoderados Especiales Aduaneros | D9: Apoderados Especiales Aduaneros | E9: Apoderados Especiales Aduaneros | F9: Operaciones y trámites | G9: Sistema de franquicias electrónicas | H9: Operadores de Comercio Exterior > 2. Auxiliares de la Función Pública Aduanera (AFPA) > Apoderados Especiales Aduaneros > Operaciones y trámites > Sistema de franquicias electrónicas | I9: Operación y declaraciones | J9: Trámite / Aplicativo en Línea | K9: Trámite / Aplicativo en Línea | L9: Portal Web SAT | M9: APROBADO | N9: Aplica en línea a franquicias aduaneras para gestionar la exención o exoneración de tributos autorizados. | O9: CAUCA IV y RECAUCA IV (Arts. 86 al 90, Apoderados Especiales Aduaneros). | P9: N/A | Q9: Vigente | R9: https://portal.sat.gob.gt/portal/franquicias-electronicas/
A10: 9 | B10: 2. Auxiliares de la Función Pública Aduanera (AFPA) | C10: Apoderados Especiales Aduaneros | D10: Apoderados Especiales Aduaneros | E10: Apoderados Especiales Aduaneros | F10: Consultas y seguimiento | G10: Consultas de aduanas (Rampa de revisión, revisores, retención/liberación, arancel) | H10: Operadores de Comercio Exterior > 2. Auxiliares de la Función Pública Aduanera (AFPA) > Apoderados Especiales Aduaneros > Consultas y seguimiento > Consultas de aduanas (Rampa de revisión, revisores, retención/liberación, arancel) | I10: Consultas y herramientas | J10: Consulta en Base de Datos | K10: Consulta en Base de Datos | L10: Portal Web SAT | M10: APROBADO | N10: Consulta los aranceles DAI, gravámenes e impuestos del SAC y verifica los permisos no arancelarios exigibles. | O10: CAUCA IV y RECAUCA IV (Arts. 86 al 90, Apoderados Especiales Aduaneros). | P10: N/A | Q10: Vigente | R10: https://portal.sat.gob.gt/portal/consultas-aduanas/
A11: 10 | B11: 2. Auxiliares de la Función Pública Aduanera (AFPA) | C11: Apoderados Especiales Aduaneros | D11: Apoderados Especiales Aduaneros | E11: Apoderados Especiales Aduaneros | F11: Consultas y seguimiento | G11: Requisitos para consulta de expedientes de gestión aduanera | H11: Operadores de Comercio Exterior > 2. Auxiliares de la Función Pública Aduanera (AFPA) > Apoderados Especiales Aduaneros > Consultas y seguimiento > Requisitos para consulta de expedientes de gestión aduanera | I11: Consultas y herramientas | J11: Consulta en Base de Datos | K11: Consulta en Base de Datos | L11: Portal Web SAT | M11: APROBADO | N11: Da seguimiento al estado de avance y resolución del expediente administrativo de tu gestión aduanera. | O11: CAUCA IV y RECAUCA IV (Arts. 86 al 90, Apoderados Especiales Aduaneros). | P11: N/A | Q11: Vigente | R11: https://portal.sat.gob.gt/portal/requisitos-de-aduanas/#1542142398181-8db4844a-6760
A12: 11 | B12: 2. Auxiliares de la Función Pública Aduanera (AFPA) | C12: Apoderados Especiales Aduaneros | D12: Apoderados Especiales Aduaneros | E12: Apoderados Especiales Aduaneros | F12: Consultas y seguimiento | G12: Unión aduanera (Procedimientos y resoluciones) | H12: Operadores de Comercio Exterior > 2. Auxiliares de la Función Pública Aduanera (AFPA) > Apoderados Especiales Aduaneros > Consultas y seguimiento > Unión aduanera (Procedimientos y resoluciones) | I12: Consultas y herramientas | J12: Trámite / Aplicativo en Línea | K12: Trámite / Aplicativo en Línea | L12: Portal Web SAT | M12: APROBADO | N12: Consulta los criterios de clasificación arancelaria y resoluciones anticipadas emitidas por la Intendencia de Aduanas. | O12: CAUCA IV y RECAUCA IV (Arts. 86 al 90, Apoderados Especiales Aduaneros). | P12: N/A | Q12: Vigente | R12: https://portal.sat.gob.gt/portal/union-aduanera/
A13: 12 | B13: 2. Auxiliares de la Función Pública Aduanera (AFPA) | C13: Apoderados Especiales Aduaneros | D13: Apoderados Especiales Aduaneros | E13: Apoderados Especiales Aduaneros | F13: Normativa y recursos | G13: Procedimientos, instructivos, manuales y guías para gestiones aduaneras | H13: Operadores de Comercio Exterior > 2. Auxiliares de la Función Pública Aduanera (AFPA) > Apoderados Especiales Aduaneros > Normativa y recursos > Procedimientos, instructivos, manuales y guías para gestiones aduaneras | I13: Normativa y asistencia | J13: Guía Informativa / Texto | K13: Guía Informativa / Texto | L13: Portal Web SAT | M13: APROBADO | N13: Desconsolida conocimientos de embarque y guías aéreas hijas para entregar bultos a sus consignatarios. | O13: CAUCA IV y RECAUCA IV (Arts. 86 al 90, Apoderados Especiales Aduaneros). | P13: N/A | Q13: Vigente | R13: https://portal.sat.gob.gt/portal/procedimientos-aduanas/#1571412473853-2ed0b43f-287f
... A205: 204 | B205: Contribuyente General | C205: Personas Individuales con Negocio | D205: — | E205: Opina sobre los procedimientos | F205: Objeciones y Recomendaciones a los procedimientos de la Intendencia de Aduanas | G205: Espacio para opinar sobre procedimientos de Aduanas y enviar tus recomendaciones. | H205: Operadores de Comercio Exterior > 1. Titulares de Mercancías > Importadores y Exportadores (Compartido) > Normativa y recursos > Objeciones y recomendaciones a procedimientos de la Intendencia de Aduanas | I205: Operación y declaraciones | J205: Guía Informativa / Texto | K205: Guía de Requisitos y Pasos | L205: Portal Web SAT | M205: APROBADO | N205: Importadores y Exportadores, Auxiliares de la Función Pública Aduanera | O205: Código Tributario, Decreto 6-91 del Congreso de la República y Leyes Tributarias Específicas. | P205: N/A | Q205: Vigente | R205: https://portal.sat.gob.gt/portal/recepcion-de-objeciones-y-recomendaciones-procedimientos-de-la-sat/objeciones-y-recomendaciones-a-los-procedimientos-de-la-intendencia-de-aduanas/

Sheet Brechas Normativas (24)
A1: No. | B1: Actor / Rol Aduanero Afectado | C1: Área Funcional / Subtema | D1: Trámite Propuesto (Brecha) | E1: Descripción / Situación Operativa | F1: Pregunta Formal para Mesa Técnica de Aduanas
A2: 1 | B2: Apoderados Especiales Aduaneros | C2: Registro y acreditación | D2: Autorización inicial y registro de mandato de apoderado especial | E2: El portal actual solo publica renovación. | F2: ¿Cuáles son los requisitos exactos para el primer nombramiento de un empleado de empresa como apoderado aduanero exclusivo?
A3: 2 | B3: Depósitos Aduaneros | C3: Registro y acreditación | D3: Requisitos para habilitación y ampliación de recintos de depósito fiscal | E3: Falta el procedimiento para abrir un nuevo recinto o nave fiscal. | F3: ¿Qué dictamen de infraestructura y fianza inicial exige la Intendencia de Aduanas?
A4: 3 | B4: Depósitos Aduaneros | C4: Operaciones y trámites | D4: Transmisión y control de inventarios bajo régimen de depósito aduanero | E4: No hay guía pública para interconectar el sistema WMS del almacén con SAT. | F4: ¿Cuáles son las especificaciones de API / Web Service para el reporte periódico de inventarios?
A5: 4 | B5: Depósitos Aduaneros | C5: Registro y acreditación | D5: Registro y emisión de títulos de crédito (Certificados de depósito y bonos de prenda) | E5: Emite y registra formalmente certificados de depósito y bonos de prenda conforme a las disposiciones del Decreto 1236. | F5: ¿Existe acuerdo de directorio o resolución que formalice el requisito digital para 'Registro y emisión de títulos de crédito (Certificados de depósito y bonos de prenda)' ante SAT?
A6: 5 | B6: Depósitos Aduaneros | C6: Operaciones y trámites | D6: Reporte de saldos y existencias afianzadas ante SAT | E6: Exigido en auditorías aduaneras pero sin formato descargable. | F6: ¿Qué periodicidad y formato oficial aplica para el informe de saldos bajo fianza?
A7: 6 | B7: Depósitos Aduaneros | C7: Registro y acreditación | D7: Requisitos para habilitación y delimitación de recintos aduaneros temporales (DAT) | E7: Requisito portuario/aeroportuario no publicado como ficha de servicio. | F7: ¿Qué requisitos perimetrales y de aduana sin papeles aplican para autorizar un DAT?
A8: 7 | B8: Depósitos Aduaneros | C8: Operaciones y trámites | D8: Control de descarga, ingreso de bultos y actas de recepción en Depósito Aduanero Temporal (DAT) | E8: Registra la recepción de bultos y emite las actas oficiales de descarga e ingreso de mercancías al recinto aduanero temporal. | F8: ¿Existe acuerdo de directorio o resolución que formalice el requisito digital para 'Control de descarga, ingreso de bultos y actas de recepción en Depósito Aduanero Temporal (DAT)' ante SAT?
A9: 8 | B9: ZDEEP - Entidades Administradoras | C9: Registro y acreditación | D9: Requisitos para habilitación y delimitación perimetral del polígono de Zona de Desarrollo Económico Especial Público (ZDEEP) | E9: Presenta los requisitos de infraestructura y delimitación física del polígono ZDEEP para su reconocimiento formal ante SAT. | F9: ¿Existe acuerdo de directorio o resolución que formalice el requisito digital para 'Requisitos para habilitación y delimitación perimetral del polígono de Zona de Desarrollo Económico Especial Público (ZDEEP)' ante SAT?
A10: 9 | B10: ZDEEP - Entidades Administradoras | C10: Registro y acreditación | D10: Registro y control de garitas aduaneras e infraestructura perimetral | E10: Homologación de sistemas tecnológicos. | F10: ¿Qué requisitos mínimos de circuito cerrado (CCTV) y básculas exige SAT en las garitas de ZDEEP?
A11: 10 | B11: ZDEEP - Entidades Administradoras | C11: Operaciones y trámites | D11: Procedimiento de control para ingreso y egreso de carga en garita de Zona de Desarrollo Económico Especial Público (ZDEEP) | E11: Aplica el procedimiento oficial de control y verificación automatizada para el ingreso y salida de carga en garitas ZDEEP. | F11: ¿Existe acuerdo de directorio o resolución que formalice el requisito digital para 'Procedimiento de control para ingreso y egreso de carga en garita de Zona de Desarrollo Económico Especial Público (ZDEEP)' ante SAT?
A12: 11 | B12: ZDEEP - Empresas Usuarias | C12: Registro y acreditación | D12: Registro de empresas usuarias calificadas en Zona de Desarrollo Económico Especial Público (ZDEEP) ante SAT | E12: Inscribe tu empresa calificada en ZDEEP ante la SAT para gozar de los incentivos fiscales y aduaneros autorizados por ley. | F12: ¿Existe acuerdo de directorio o resolución que formalice el requisito digital para 'Registro de empresas usuarias calificadas en Zona de Desarrollo Económico Especial Público (ZDEEP) ante SAT' ante SAT?
A13: 12 | B13: ZDEEP - Empresas Usuarias | C13: Operaciones y trámites | D13: Procedimiento aduanero de traslado de mercancías hacia y desde Zona de Desarrollo Económico Especial Público (ZDEEP) | E13: Gestiona las declaraciones y traslados de materias primas y mercancías entre aduanas y la ZDEEP con custodia fiscal. | F13: ¿Existe acuerdo de directorio o resolución que formalice el requisito digital para 'Procedimiento aduanero de traslado de mercancías hacia y desde Zona de Desarrollo Económico Especial Público (ZDEEP)' ante SAT?
... A25: 24 | B25: Consolidadores y Desconsolidadores de Carga | C25: Operaciones y trámites | D25: Registro de justificación de sobrantes, faltantes y daños en bultos desconsolidados | E25: Reporta y justifica formalmente ante la autoridad aduanera las discrepancias de bultos sobrantes, faltantes o averiados. | F25: ¿Existe acuerdo de directorio o resolución que formalice el requisito digital para 'Registro de justificación de sobrantes, faltantes y daños en bultos desconsolidados' ante SAT?
