Workbook

Sheet Procesos
A1: Lista de procesos
A2: Un renglón por proceso: a quién va dirigido, en qué categorías y grupos aparece y su ruta de pasos.
A4: No. | B4: Proceso | C4: Grupo de audiencia | D4: Etapa | E4: Para quién | F4: Categorías y grupos donde aparece | G4: Pasos | H4: Páginas | I4: Ruta de pasos
A5: 1 | B5: Obtener mi primer NIT | C5: Contribuyentes | D5: Empezar | E5: Persona individual que nunca ha tenido NIT | F5: NIT sin Obligaciones › Todos los grupos Trámites comunes › Todos los grupos | G5: 7 | H5: =COUNTIFS('Rutas por proceso'!$A$5:$A$575,A5,'Rutas por proceso'!$C$5:$C$575,">0") -> 18 | I5: 1. Verifica si ya tienes NIT 2. Elige tu caso 3. Solicita tu NIT 4. Da seguimiento 5. Activa tu cuenta en Agencia Virtual 6. Descarga tu constancia 7. Si hay un error
A6: 2 | B6: Abrir mi negocio (persona individual) | C6: Contribuyentes | D6: Empezar | E6: Emprendedor o profesional independiente | F6: Pequeños Contribuyentes › Pequeño Contribuyente Contribuyente General › Contribuyente General | G6: 7 | H6: =COUNTIFS('Rutas por proceso'!$A$5:$A$575,A6,'Rutas por proceso'!$C$5:$C$575,">0") -> 20 | I6: 1. Conoce los regímenes y elige el tuyo 2. Inscribe tu negocio 3. Activa tu cuenta en Agencia Virtual 4. Nombra a tu contador (si aplica) 5. Prepárate para facturar 6. Habilita tus libros 7. Conoce tus fechas para declarar
A7: 3 | B7: Constituir una empresa o sociedad | C7: Contribuyentes | D7: Empezar | E7: Socios, representantes legales y contadores | F7: Contribuyente General › Contribuyente General Contribuyente General › Rep. Legales | G7: 6 | H7: =COUNTIFS('Rutas por proceso'!$A$5:$A$575,A7,'Rutas por proceso'!$C$5:$C$575,">0") -> 13 | I7: 1. Inscribe la empresa 2. Registra al representante legal 3. Nombra al contador 4. Define impuestos y actividades 5. Prepárate para facturar y llevar libros 6. Activa la cuenta en Agencia Virtual
A8: 4 | B8: Inscribir una entidad sin fines de lucro u otra organización | C8: Organismos especiales | D8: Empezar | E8: Asociaciones, ONG, cooperativas, iglesias, comités, condominios, etc. | F8: Exentos › Todos los grupos | G8: 7 | H8: =COUNTIFS('Rutas por proceso'!$A$5:$A$575,A8,'Rutas por proceso'!$C$5:$C$575,">0") -> 24 | I8: 1. Asociaciones, fundaciones y ONG 2. Cooperativas, iglesias y universidades 3. Organizaciones sociales, deportivas y políticas 4. Bienes y negocios compartidos 5. Sector público 6. Registra al representante legal 7. Si emitirás constancias de exención
A9: 5 | B9: Emitir facturas | C9: Contribuyentes | D9: Cumplir | E9: Cualquier contribuyente con negocio | F9: Trámites comunes › Todos los grupos | G9: 6 | H9: =COUNTIFS('Rutas por proceso'!$A$5:$A$575,A9,'Rutas por proceso'!$C$5:$C$575,">0") -> 17 | I9: 1. Factura electrónica (FEL) 2. Facturas impresas (si aún aplica) 3. Máquinas registradoras y sistemas 4. Casos especiales 5. Anular o corregir documentos 6. Verificar una factura recibida
A10: 6 | B10: Declarar y pagar mis impuestos | C10: Contribuyentes | D10: Cumplir | E10: Contribuyentes inscritos en algún impuesto | F10: Trámites comunes › Todos los grupos | G10: 7 | H10: =COUNTIFS('Rutas por proceso'!$A$5:$A$575,A10,'Rutas por proceso'!$C$5:$C$575,">0") -> 20 | I10: 1. Revisa tus fechas 2. Prepara tu declaración 3. Declara 4. Paga 5. Si no puedes pagar todo 6. Si te equivocaste 7. Dudas
A11: 7 | B11: Obtener mi solvencia fiscal | C11: Contribuyentes | D11: Cumplir | E11: Quien necesita demostrar que está al día | F11: Trámites comunes › Todos los grupos | G11: 4 | H11: =COUNTIFS('Rutas por proceso'!$A$5:$A$575,A11,'Rutas por proceso'!$C$5:$C$575,">0") -> 7 | I11: 1. Revisa los requisitos 2. Solicítala 3. Si te la niegan 4. Consulta solvencias anteriores
A12: 8 | B12: Soy asalariado: ISR de mi salario | C12: Contribuyentes | D12: Cumplir | E12: Empleados en relación de dependencia | F12: NIT sin Obligaciones › Todos los grupos | G12: 4 | H12: =COUNTIFS('Rutas por proceso'!$A$5:$A$575,A12,'Rutas por proceso'!$C$5:$C$575,">0") -> 4 | I12: 1. Obtén tu NIT 2. Calcula tu ISR 3. Revisa tus retenciones 4. Pide devolución si te retuvieron de más
A13: 9 | B13: Actualizar mis datos | C13: Contribuyentes | D13: Cambiar | E13: Cualquier contribuyente | F13: Trámites comunes › Todos los grupos | G13: 5 | H13: =COUNTIFS('Rutas por proceso'!$A$5:$A$575,A13,'Rutas por proceso'!$C$5:$C$575,">0") -> 12 | I13: 1. Datos personales 2. Datos del negocio 3. Contador y representantes 4. Confirmación anual 5. Verifica el cambio
A14: 10 | B14: Actualizar datos de una empresa o entidad | C14: Contribuyentes | D14: Cambiar | E14: Representantes legales y contadores | F14: Contribuyente General › Rep. Legales Contribuyentes Especiales › Rep. Legales Exentos › Todos los grupos (Organismos especiales) | G14: 6 | H14: =COUNTIFS('Rutas por proceso'!$A$5:$A$575,A14,'Rutas por proceso'!$C$5:$C$575,">0") -> 23 | I14: 1. Empresas 2. Representante legal 3. Entidades sin fines de lucro 4. Organizaciones sociales y deportivas 5. Bienes compartidos 6. Sector público e internacional
A15: 11 | B15: Cambiar de régimen | C15: Contribuyentes | D15: Cambiar | E15: Negocios que crecen o cambian de tamaño | F15: Pequeños Contribuyentes › Pequeño Contribuyente Pequeños Contribuyentes › Primario Pequeños Contribuyentes › Pecuario Contribuyente General › Contribuyente General | G15: 4 | H15: =COUNTIFS('Rutas por proceso'!$A$5:$A$575,A15,'Rutas por proceso'!$C$5:$C$575,">0") -> 12 | I15: 1. Averigua tu régimen actual 2. Compara regímenes 3. Haz el cambio 4. Ajusta tu facturación
A16: 12 | B16: Suspender o cerrar mi negocio (persona individual) | C16: Contribuyentes | D16: Cerrar | E16: Persona individual con negocio inscrito | F16: Pequeños Contribuyentes › Pequeño Contribuyente Contribuyente General › Contribuyente General | G16: 5 | H16: =COUNTIFS('Rutas por proceso'!$A$5:$A$575,A16,'Rutas por proceso'!$C$5:$C$575,">0") -> 14 | I16: 1. Ponte al día antes de cerrar 2. Elige: suspender o cerrar 3. Da de baja documentos y equipos 4. Verifica el cierre 5. Si quieres volver a operar
... A53: 49 | B53: Coordinación y convenios con la SAT | C53: Organismos especiales | D53: Coordinación | E53: Instituciones públicas aliadas | F53: Entidades del Estado › Todos los grupos | G53: 3 | H53: =COUNTIFS('Rutas por proceso'!$A$5:$A$575,A53,'Rutas por proceso'!$C$5:$C$575,">0") -> 5 | I53: 1. Convenios 2. Operativos conjuntos 3. Control interno

Sheet Rutas por proceso
A1: Rutas por proceso
A2: Cada proceso con sus pasos en orden y las páginas de cada paso. «Ubicación en el árbol» dice dónde está hoy la página en este archivo.
A4: No. | B4: Proceso | C4: Paso | D4: Qué hacer en este paso | E4: Página | F4: Ubicación en el árbol | G4: URL
A5: 1 | B5: Obtener mi primer NIT | D5: Para: Persona individual que nunca ha tenido NIT
A6: 1 | B6: Obtener mi primer NIT | C6: 1 | D6: Verifica si ya tienes NIT | E6: Consultar tu NIT con tu DPI (CUI) | F6: Contribuyentes › Trámites comunes › Todos los grupos | G6: https://portal.sat.gob.gt/portal/consulta-cui-nit/
A7: 1 | B7: Obtener mi primer NIT | C7: 2 | D7: Elige tu caso | E7: Obtener tu NIT por primera vez | F7: Contribuyentes › Trámites comunes › Todos los grupos | G7: https://portal.sat.gob.gt/portal/rtu-digital/inscripcion-solicitud-de-nit/
A8: 1 | B8: Obtener mi primer NIT | C8: 2 | D8: Elige tu caso | E8: Obtener NIT sin tener negocio (sin obligaciones) | F8: Contribuyentes › NIT sin Obligaciones › Todos los grupos | G8: https://portal.sat.gob.gt/portal/requisitos-tramites-agencias/inscripcion-nit-sin-obligaciones-tributarias/
A9: 1 | B9: Obtener mi primer NIT | C9: 2 | D9: Elige tu caso | E9: Obtener NIT para tener un negocio (con obligaciones) | F9: Contribuyentes › Trámites comunes › Todos los grupos | G9: https://portal.sat.gob.gt/portal/requisitos-tramites-agencias/inscripcion-nit-con-obligaciones-tributarias/
A10: 1 | B10: Obtener mi primer NIT | C10: 2 | D10: Elige tu caso | E10: Obtener NIT si vives en el extranjero y vas a comprar un inmueble | F10: Contribuyentes › NIT sin Obligaciones › Todos los grupos | G10: https://portal.sat.gob.gt/portal/requisitos-tramites-agencias/inscripcion-nit-sin-obligaciones-para-guatemaltecos-residentes-en-el-extranjero/
A11: 1 | B11: Obtener mi primer NIT | C11: 2 | D11: Elige tu caso | E11: Obtener NIT para personas con discapacidad | F11: Contribuyentes › NIT sin Obligaciones › Todos los grupos | G11: https://portal.sat.gob.gt/portal/requisitos-tramites-agencias/inscripcion-nit-sin-obligaciones-para-personas-con-discapacidad/
A12: 1 | B12: Obtener mi NIT | C12: 2 | D12: Elige tu caso | E12: Obtener NIT para personas con invalidez física | F12: Contribuyentes › NIT sin Obligaciones › Todos los grupos | G12: https://portal.sat.gob.gt/portal/requisitos-tramites-agencias/inscripcion-nit-sin-obligaciones-para-personas-con-invalidez-fisica/
A13: 1 | B13: Obtener mi primer NIT | C13: 3 | D13: Solicita tu NIT | E13: Solicitar tu NIT en línea | F13: Contribuyentes › Pequeños Contribuyentes › Todos los grupos | G13: https://portal.sat.gob.gt/portal/solicitud-electronica-de-nit/
A14: 1 | B14: Obtener mi primer NIT | C14: 3 | D14: Solicita tu NIT | E14: Agendar cita para obtener tu NIT | F14: Contribuyentes › Trámites comunes › Todos los grupos | G14: https://portal.sat.gob.gt/portal/citas-solicitud-de-NIT/
A15: 1 | B15: Obtener mi primer NIT | C15: 3 | D15: Solicita tu NIT | E15: Ubicar agencias de la SAT | F15: Contribuyentes › Trámites comunes › Todos los grupos | G15: https://portal.sat.gob.gt/portal/contacto/
A16: 1 | B16: Obtener mi primer NIT | C16: 4 | D16: Da seguimiento | E16: Ver el estado de tu gestión de RTU Digital | F16: Contribuyentes › Trámites comunes › Todos los grupos | G16: https://portal.sat.gob.gt/portal/estado-de-gestion-de-rtu-digital/
A17: 1 | B17: Obtener mi primer NIT | C17: 5 | D17: Activa tu cuenta en Agencia Virtual | E17: Solicitar usuario de Agencia Virtual | F17: Contribuyentes › Trámites comunes › Todos los grupos | G17: https://portal.sat.gob.gt/portal/solicitud-usuario-agencia-virtual/
... A23: 1 | B23: Obtener mi primer NIT | C23: 7 | D23: Si hay un error | E23: Actualizar tus datos de identificación por primera vez | F23: Contribuyentes › Trámites comunes › Todos los grupos | G23: https://portal.sat.gob.gt/portal/requisitos-tramites-agencias/primera-actualizacion-de-datos-de-identificacion/
A24: 2 | B24: Abrir mi negocio (persona individual) | D24: Para: Emprendedor o profesional independiente
A25: 2 | B25: Abrir mi negocio (persona individual) | C25: 1 | D25: Conoce los regímenes y elige el tuyo | E25: Curso: régimen de Pequeño Contribuyente | F25: Contribuyentes › Pequeños Contribuyentes › Pequeño Contribuyente | G25: https://sites.google.com/capacitacionessat.page/cultura-tributariad/cursos-virtuales-sat/impuesto-al-valor-agregado/r%C3%A9gimen-del-peque%C3%B1o-contribuyente
A26: 2 | B26: Abrir mi negocio (persona individual) | C26: 1 | D26: Conoce los regímenes y elige el tuyo | E26: Curso: Régimen General del IVA | F26: Contribuyentes › Contribuyente General › Contribuyente General | G26: https://sites.google.com/capacitacionessat.page/cultura-tributariad/cursos-virtuales-sat/impuesto-al-valor-agregado/r%C3%A9gimen-general-del-iva
A27: 2 | B27: Abrir mi negocio (persona individual) | C27: 1 | D27: Conoce los regímenes y elige el tuyo | E27: Curso: régimen sobre las utilidades | F27: Contribuyentes › Contribuyente General › Contribuyente General | G27: https://sites.google.com/capacitacionessat.page/cultura-tributariad/cursos-virtuales-sat/impuesto-sobre-la-renta-isr/12-r%C3%A9gimen-sobre-utilidades-de-rentas-de-actividades-lucrativa
A28: 2 | B28: Abrir mi negocio (persona individual) | C28: 1 | D28: Conoce los regímenes y elige el tuyo | E28: Curso: Régimen Opcional Simplificado | F28: Contribuyentes › Contribuyente General › Contribuyente General | G28: https://sites.google.com/capacitacionessat.page/cultura-tributariad/cursos-virtuales-sat/impuesto-sobre-la-renta-isr/5-r%C3%A9gimen-sobre-los-ingresos-de-actividades-lucrativas
A29: 2 | B29: Abrir mi negocio (persona individual) | C29: 1 | D29: Conoce los regímenes y elige el tuyo | E29: Curso: regímenes del ISR para negocios | F29: Contribuyentes › Contribuyente General › Contribuyente General | G29: https://sites.google.com/capacitacionessat.page/cultura-tributariad/cursos-virtuales-sat/impuesto-sobre-la-renta/reg%C3%ADmenes-para-las-rentas-de-actividades-lucrativas
A30: 2 | B30: Abrir mi negocio (persona individual) | C30: 2 | D30: Inscribe tu negocio | E30: Obtener NIT para tener un negocio (con obligaciones) | F30: Contribuyentes › Trámites comunes › Todos los grupos | G30: https://portal.sat.gob.gt/portal/requisitos-tramites-agencias/inscripcion-nit-con-obligaciones-tributarias/
A31: 2 | B31: Abrir mi negocio (persona individual) | C31: 2 | D31: Inscribe tu negocio | E31: Consultar códigos de actividades económicas | F31: Contribuyentes › Trámites comunes › Todos los grupos | G31: https://portal.sat.gob.gt/portal/actividades-economicas/
A32: 2 | B32: Abrir mi negocio (persona individual) | C32: 2 | D32: Inscribe tu negocio | E32: Actualizar los datos de tu negocio o establecimiento | F32: Contribuyentes › Trámites comunes › Todos los grupos | G32: https://portal.sat.gob.gt/portal/requisitos-tramites-agencias/actualizacion-datos-del-establecimiento/
A33: 2 | B33: Abrir mi negocio (persona individual) | C33: 2 | D33: Inscribe tu negocio | E33: Agregar o quitar impuestos a los que estás inscrito | F33: Contribuyentes › Trámites comunes › Todos los grupos | G33: https://portal.sat.gob.gt/portal/requisitos-tramites-agencias/actualizacion-afiliaciones/
A34: 2 | B34: Abrir mi negocio (persona individual) | C34: 3 | D34: Activa tu cuenta en Agencia Virtual | E34: Solicitar usuario de Agencia Virtual | F34: Contribuyentes › Trámites comunes › Todos los grupos | G34: https://portal.sat.gob.gt/portal/solicitud-usuario-agencia-virtual/
A35: 2 | B35: Abrir mi negocio (persona individual) | C35: 3 | D35: Activa tu cuenta en Agencia Virtual | E35: Activar tu usuario de Agencia Virtual | F35: Contribuyentes › Trámites comunes › Todos los grupos | G35: https://portal.sat.gob.gt/portal/requisitos-tramites-agencias/activacion-de-usuario-de-agencia-virtual/
A36: 2 | B36: Abrir mi negocio (persona individual) | C36: 4 | D36: Nombra a tu contador (si aplica) | E36: Nombrar o cambiar al contador de tu negocio | F36: Contribuyentes › Trámites comunes › Todos los grupos | G36: https://portal.sat.gob.gt/portal/requisitos-tramites-agencias/actualizacion-nombramiento-o-cambio-de-perito-contador/
... A44: 2 | B44: Abrir mi negocio (persona individual) | C44: 7 | D44: Conoce tus fechas para declarar | E44: Declarar y pagar en Declaraguate | F44: Contribuyentes › Trámites comunes › Todos los grupos | G44: https://declaraguate.sat.gob.gt/declaraguate-web/
A45: 3 | B45: Constituir una empresa o sociedad | D45: Para: Socios, representantes legales y contadores
A46: 3 | B46: Constituir una empresa o sociedad | C46: 1 | D46: Inscribe la empresa | E46: Inscribir una sociedad o empresa | F46: Contribuyentes › Contribuyente General › Contribuyente General | G46: https://portal.sat.gob.gt/portal/requisitos-tramites-agencias/inscripcion-sociedades/
A47: 3 | B47: Constituir una empresa o sociedad | C47: 1 | D47: Inscribe la empresa | E47: Inscribir una Sociedad de Emprendimiento | F47: Contribuyentes › Contribuyente General › Contribuyente General | G47: https://portal.sat.gob.gt/portal/requisitos-tramites-agencias/sociedad-de-emprendimiento/
A48: 3 | B48: Constituir una empresa o sociedad | C48: 1 | D48: Inscribe la empresa | E48: Inscribir la sucursal de una empresa extranjera | F48: Contribuyentes › Contribuyente General › Contribuyente General | G48: https://portal.sat.gob.gt/portal/requisitos-tramites-agencias/inscripcion-de-sucursal-empresa-extranjera/
A49: 3 | B49: Constituir una empresa o sociedad | C49: 2 | D49: Registra al representante legal | E49: Nombrar, cambiar o cancelar al representante legal | F49: Contribuyentes › Contribuyente General › Rep. Legales | G49: https://portal.sat.gob.gt/portal/requisitos-tramites-agencias/actualizacion-o-cancelacion-de-representante-legal/
A50: 3 | B50: Constituir una empresa o sociedad | C50: 3 | D50: Nombra al contador | E50: Nombrar o cambiar al contador de tu negocio | F50: Contribuyentes › Trámites comunes › Todos los grupos | G50: https://portal.sat.gob.gt/portal/requisitos-tramites-agencias/actualizacion-nombramiento-o-cambio-de-perito-contador/
A51: 3 | B51: Constituir una empresa o sociedad | C51: 4 | D51: Define impuestos y actividades | E51: Consultar códigos de actividades económicas | F51: Contribuyentes › Trámites comunes › Todos los grupos | G51: https://portal.sat.gob.gt/portal/actividades-economicas/
A52: 3 | B52: Constituir una empresa o sociedad | C52: 4 | D52: Define impuestos y actividades | E52: Agregar o quitar impuestos a los que estás inscrito | F52: Contribuyentes › Trámites comunes › Todos los grupos | G52: https://portal.sat.gob.gt/portal/requisitos-tramites-agencias/actualizacion-afiliaciones/
A53: 3 | B53: Constituir una empresa o sociedad | C53: 4 | D53: Define impuestos y actividades | E53: Curso: régimen sobre las utilidades | F53: Contribuyentes › Contribuyente General › Contribuyente General | G53: https://sites.google.com/capacitacionessat.page/cultura-tributariad/cursos-virtuales-sat/impuesto-sobre-la-renta-isr/12-r%C3%A9gimen-sobre-utilidades-de-rentas-de-actividades-lucrativa
A54: 3 | B54: Constituir una empresa o sociedad | C54: 4 | D54: Define impuestos y actividades | E54: Curso: costos y gastos deducibles (régimen sobre utilidades) | F54: Contribuyentes › Contribuyente General › Contribuyente General | G54: https://sites.google.com/capacitacionessat.page/cultura-tributariad/cursos-virtuales-sat/impuesto-sobre-la-renta-isr/14-costos-y-gastos-deducibles-r%C3%A9gimen-sobre-las-utilidades-de-actividades
A55: 3 | B55: Constituir una empresa o sociedad | C55: 5 | D55: Prepárate para facturar y llevar libros | E55: Factura Electrónica en Línea (FEL) | F55: Contribuyentes › Trámites comunes › Todos los grupos | G55: https://portal.sat.gob.gt/portal/efactura/
A56: 3 | B56: Constituir una empresa o sociedad | C56: 5 | D56: Prepárate para facturar y llevar libros | E56: Habilitar libros contables | F56: Contribuyentes › Contribuyente General › Contribuyente General | G56: https://portal.sat.gob.gt/portal/requisitos-tramites-agencias/habilitacion-de-libros/
A57: 3 | B57: Constituir una empresa o sociedad | C57: 6 | D57: Activa la cuenta en Agencia Virtual | E57: Solicitar usuario de Agencia Virtual | F57: Contribuyentes › Trámites comunes › Todos los grupos | G57: https://portal.sat.gob.gt/portal/solicitud-usuario-agencia-virtual/
A58: 3 | B58: Constituir una empresa o sociedad | C58: 6 | D58: Activa la cuenta en Agencia Virtual | E58: Activar tu usuario de Agencia Virtual | F58: Contribuyentes › Trámites comunes › Todos los grupos | G58: https://portal.sat.gob.gt/portal/requisitos-tramites-agencias/activacion-de-usuario-de-agencia-virtual/
A59: 4 | B59: Inscribir una entidad sin fines de lucro u otra organización | D59: Para: Asociaciones, ONG, cooperativas, iglesias, comités, condominios, etc.
A60: 4 | B60: Inscribir una entidad sin fines de lucro u otra organización | C60: 1 | D60: Asociaciones, fundaciones y ONG | E60: Inscribir una fundación, asociación o entidad religiosa | F60: Organismos especiales › Exentos › No Lucrativos | G60: https://portal.sat.gob.gt/portal/requisitos-tramites-agencias/inscripcion-de-fundacion-otra-entidad-religiosa-asociacion/
A61: 4 | B61: Inscribir una entidad sin fines de lucro u otra organización | C61: 1 | D61: Asociaciones, fundaciones y ONG | E61: Inscribir una fundación, asociación o entidad religiosa extranjera | F61: Organismos especiales › Exentos › No Lucrativos | G61: https://portal.sat.gob.gt/portal/requisitos-tramites-agencias/inscripcion-de-fundacion-otra-entidad-religiosa-asociacion-extranjeras/
A62: 4 | B62: Inscribir una entidad sin fines de lucro u otra organización | C62: 1 | D62: Asociaciones, fundaciones y ONG | E62: Inscribir una ONG registrada antes del 3 de agosto de 2022 | F62: Organismos especiales › Exentos › No Lucrativos | G62: https://portal.sat.gob.gt/portal/requisitos-tramites-agencias/inscripcion-de-organizacion-no-gubernamental-ong-inscritas-en-el-registro-de-personas-juridicas-repeju-antes-del-3-de-agosto-2022/
A63: 4 | B63: Inscribir una entidad sin fines de lucro u otra organización | C63: 1 | D63: Asociaciones, fundaciones y ONG | E63: Inscribir una ONG registrada desde el 3 de agosto de 2022 | F63: Organismos especiales › Exentos › No Lucrativos | G63: https://portal.sat.gob.gt/portal/requisitos-tramites-agencias/inscripcion-de-organizacion-no-gubernamental-ong-inscritas-en-el-registro-de-personas-juridicas-repeju-a-partir-del-3-de-agosto-2022/
A64: 4 | B64: Inscribir una entidad sin fines de lucro u otra organización | C64: 2 | D64: Cooperativas, iglesias y universidades | E64: Inscribir una cooperativa | F64: Organismos especiales › Exentos › Decreto | G64: https://portal.sat.gob.gt/portal/requisitos-tramites-agencias/inscripcion-de-cooperativa/
A65: 4 | B65: Inscribir una entidad sin fines de lucro u otra organización | C65: 2 | D65: Cooperativas, iglesias y universidades | E65: Inscribir una entidad de la Iglesia Católica | F65: Organismos especiales › Exentos › Constitucionales | G65: https://portal.sat.gob.gt/portal/requisitos-tramites-agencias/inscripcion-iglesia-catolica/
A66: 4 | B66: Inscribir una entidad sin fines de lucro u otra organización | C66: 2 | D66: Cooperativas, iglesias y universidades | E66: Inscribir una universidad privada | F66: Organismos especiales › Exentos › Constitucionales | G66: https://portal.sat.gob.gt/portal/requisitos-tramites-agencias/inscripcion-universidad-privada/
A67: 4 | B67: Inscribir una entidad sin fines de lucro u otra organización | C67: 2 | D67: Cooperativas, iglesias y universidades | E67: Inscribir un centro educativo | F67: Organismos especiales › Exentos › Constitucionales | G67: https://portal.sat.gob.gt/portal/requisitos-tramites-agencias/inscripcion-centros-educativos-centros-educativos-publicos-comunitarios-asociacion-educativa/
A68: 4 | B68: Inscribir una entidad sin fines de lucro u otra organización | C68: 3 | D68: Organizaciones sociales, deportivas y políticas | E68: Inscribir una organización comunitaria | F68: Organismos especiales › Exentos › No Lucrativos | G68: https://portal.sat.gob.gt/portal/requisitos-tramites-agencias/inscripcion-organizaciones-comunitarias/
A69: 4 | B69: Inscribir una entidad sin fines de lucro u otra organización | C69: 3 | D69: Organizaciones sociales, deportivas y políticas | E69: Inscribir una Organización de Padres de Familia (OPF) | F69: Organismos especiales › Exentos › No Lucrativos | G69: https://portal.sat.gob.gt/portal/requisitos-tramites-agencias/organizacion-de-padres-de-familia-opf/
A70: 4 | B70: Inscribir una entidad sin fines de lucro u otra organización | C70: 3 | D70: Organizaciones sociales, deportivas y políticas | E70: Inscribir un sindicato | F70: Organismos especiales › Exentos › No Lucrativos | G70: https://portal.sat.gob.gt/portal/requisitos-tramites-agencias/inscripcion-sindicato/
A71: 4 | B71: Inscribir una entidad sin fines de lucro u otra organización | C71: 3 | D71: Organizaciones sociales, deportivas y políticas | E71: Inscribir un club deportivo | F71: Contribuyentes › Contribuyente General › Contribuyente General | G71: https://portal.sat.gob.gt/portal/requisitos-tramites-agencias/inscripcion-de-club-deportivo-con-finalidad-lucrativa/
... A83: 4 | B83: Inscribir una entidad sin fines de lucro u otra organización | C83: 7 | D83: Si emitirás constancias de exención | E83: Habilitarte para emitir constancias CAIS | F83: Organismos especiales › Exentos › Decreto | G83: https://portal.sat.gob.gt/portal/requisitos-tramites-agencia-virtual/habilitacion-emision-cais/
A84: 5 | B84: Emitir facturas | D84: Para: Cualquier contribuyente con negocio
A85: 5 | B85: Emitir facturas | C85: 1 | D85: Factura electrónica (FEL) | E85: Factura Electrónica en Línea (FEL) | F85: Contribuyentes › Trámites comunes › Todos los grupos | G85: https://portal.sat.gob.gt/portal/efactura/
A86: 5 | B86: Emitir facturas | C86: 1 | D86: Factura electrónica (FEL) | E86: Curso: Factura Electrónica en Línea | F86: Contribuyentes › Trámites comunes › Todos los grupos | G86: https://sites.google.com/capacitacionessat.page/cultura-tributariad/cursos-virtuales-sat/factura-electr%C3%B3nica-en-l%C3%ADnea/31-factura-electr%C3%B3nica-en-l%C3%ADnea-fel
A87: 5 | B87: Emitir facturas | C87: 1 | D87: Factura electrónica (FEL) | E87: Curso: FEL para entidades del Estado | F87: Organismos especiales › Entidades del Estado › Todos los grupos | G87: https://sites.google.com/capacitacionessat.page/cultura-tributariad/cursos-virtuales-sat/factura-electr%C3%B3nica-en-l%C3%ADnea/implementaci%C3%B3n-de-fel-en-entidades-ejecutoras-del-estado
A88: 5 | B88: Emitir facturas | C88: 2 | D88: Facturas impresas (si aún aplica) | E88: Autorizar facturas y otros documentos | F88: Contribuyentes › Contribuyente General › Contribuyente General | G88: https://portal.sat.gob.gt/portal/requisitos-tramites-agencias/autorizacion-de-documentos-y-formularios/
A89: 5 | B89: Emitir facturas | C89: 2 | D89: Facturas impresas (si aún aplica) | E89: Autorizar facturas si las imprimes tú mismo | F89: Contribuyentes › Contribuyente General › Contribuyente General | G89: https://portal.sat.gob.gt/portal/requisitos-tramites-agencias/autorizacion-de-facturas-auto-impresores-en-agencia-virtual/
A90: 5 | B90: Emitir facturas | C90: 2 | D90: Facturas impresas (si aún aplica) | E90: Autorizar facturas impresas por una imprenta | F90: Contribuyentes › Contribuyente General › Contribuyente General | G90: https://portal.sat.gob.gt/portal/requisitos-tramites-agencias/autorizacion-de-facturas-y-otros-documentos-de-imprentas-en-agencia-virtual/
A91: 5 | B91: Emitir facturas | C91: 2 | D91: Facturas impresas (si aún aplica) | E91: Consultar imprentas autorizadas | F91: Contribuyentes › Contribuyente General › Contribuyente General | G91: https://portal.sat.gob.gt/portal/imprentas-inscritas/
A92: 5 | B92: Emitir facturas | C92: 3 | D92: Máquinas registradoras y sistemas | E92: Autorizar un sistema computarizado o máquina registradora | F92: Contribuyentes › Contribuyente General › Contribuyente General | G92: https://portal.sat.gob.gt/portal/requisitos-tramites-agencias/autorizacion-de-sistema-computarizado-como-maquina-registradora-sistema-computarizado-integrado-de-contabilidad/
A93: 5 | B93: Emitir facturas | C93: 3 | D93: Máquinas registradoras y sistemas | E93: Autorizar máquinas registradoras en Agencia Virtual | F93: Contribuyentes › Contribuyente General › Contribuyente General | G93: https://portal.sat.gob.gt/portal/requisitos-tramites-agencias/autorizacion-de-maquinas-en-agencia-virtual/
A94: 5 | B94: Emitir facturas | C94: 3 | D94: Máquinas registradoras y sistemas | E94: Trasladar o actualizar una máquina registradora | F94: Contribuyentes › Contribuyente General › Contribuyente General | G94: https://portal.sat.gob.gt/portal/requisitos-tramites-agencias/traslado-y-actualizacion-de-maquina-registradora/
A95: 5 | B95: Emitir facturas | C95: 4 | D95: Casos especiales | E95: Autorizar documentos para pequeños contribuyentes | F95: Contribuyentes › Pequeños Contribuyentes › Pequeño Contribuyente | G95: https://portal.sat.gob.gt/portal/requisitos-tramites-agencias/autorizacion-de-documentos-tributarios-a-pequenos-contribuyentes/
A96: 5 | B96: Emitir facturas | C96: 4 | D96: Casos especiales | E96: Autorizar documentos para espectáculos públicos | F96: Contribuyentes › Contribuyente General › Contribuyente General | G96: https://portal.sat.gob.gt/portal/requisitos-tramites-agencias/autorizacion-de-documentos-para-espectaculos-publicos/
... A101: 5 | B101: Emitir facturas | C101: 6 | D101: Verificar una factura recibida | E101: Denunciar a quien no da factura | F101: Contribuyentes › Trámites comunes › Todos los grupos | G101: https://portal.sat.gob.gt/portal/contacto/denuncias-no-facturacion/
A102: 6 | B102: Declarar y pagar mis impuestos | D102: Para: Contribuyentes inscritos en algún impuesto
A103: 6 | B103: Declarar y pagar mis impuestos | C103: 1 | D103: Revisa tus fechas | E103: Consultar fechas de vencimiento (calendario tributario) | F103: Contribuyentes › Trámites comunes › Todos los grupos | G103: https://portal.sat.gob.gt/portal/calendario-tributario/
A104: 6 | B104: Declarar y pagar mis impuestos | C104: 2 | D104: Prepara tu declaración | E104: Ver todos los formularios | F104: Profesionales › Terceras Personas › Todos los grupos | G104: https://portal.sat.gob.gt/portal/lista-general-de-formularios/
A105: 6 | B105: Declarar y pagar mis impuestos | C105: 2 | D105: Prepara tu declaración | E105: Cómo llenar el formulario SAT-1411 (ISR anual) | F105: Contribuyentes › Trámites comunes › Todos los grupos | G105: https://sites.google.com/capacitacionessat.page/eventosenvivo/p%C3%A1gina-principal/llenado-del-formulario-sat-1411-declaraci%C3%B3n-anual-del-isr-r%C3%A9gimen-sobre-la
A106: 6 | B106: Declarar y pagar mis impuestos | C106: 2 | D106: Prepara tu declaración | E106: Curso: cómo usar Declaraguate | F106: Contribuyentes › Trámites comunes › Todos los grupos | G106: https://sites.google.com/capacitacionessat.page/cultura-tributariad/cursos-virtuales-sat/herramientas-electr%C3%B3nicas/19-declaraguate-uso-y-manejo
A107: 6 | B107: Declarar y pagar mis impuestos | C107: 2 | D107: Prepara tu declaración | E107: Planilla del IVA en FEL | F107: Contribuyentes › Trámites comunes › Todos los grupos | G107: https://portal.sat.gob.gt/portal/planilla-iva-fel/
A108: 6 | B108: Declarar y pagar mis impuestos | C108: 2 | D108: Prepara tu declaración | E108: Consultar constancias de retención de IVA e ISR recibidas | F108: Contribuyentes › Pequeños Contribuyentes › Todos los grupos | G108: https://portal.sat.gob.gt/portal/retenciones-del-iva-consulta-de-constancias-de-retencion-del-iva-recibidas/
A109: 6 | B109: Declarar y pagar mis impuestos | C109: 3 | D109: Declara | E109: Declarar y pagar en Declaraguate | F109: Contribuyentes › Trámites comunes › Todos los grupos | G109: https://declaraguate.sat.gob.gt/declaraguate-web/
A110: 6 | B110: Declarar y pagar mis impuestos | C110: 3 | D110: Declara | E110: Presentar declaración sin movimiento (valor cero) | F110: Contribuyentes › Trámites comunes › Todos los grupos | G110: https://portal.sat.gob.gt/portal/declaracion-valor-cero/
A111: 6 | B111: Declarar y pagar mis impuestos | C111: 3 | D111: Declara | E111: Informe electrónico de compras y ventas | F111: Contribuyentes › Contribuyentes Especiales › Todos los grupos | G111: https://portal.sat.gob.gt/portal/informe-electronico-de-compras-y-venta/
A112: 6 | B112: Declarar y pagar mis impuestos | C112: 4 | D112: Paga | E112: Formas de pago de impuestos | F112: Contribuyentes › Trámites comunes › Todos los grupos | G112: https://portal.sat.gob.gt/portal/forma-de-pago/
A113: 6 | B113: Declarar y pagar mis impuestos | C113: 4 | D113: Paga | E113: Pagar timbres fiscales en línea (razón electrónica) | F113: Contribuyentes › Trámites comunes › Todos los grupos | G113: https://portal.sat.gob.gt/portal/razon-electronica-timbres-fiscales/
A114: 6 | B114: Declarar y pagar mis impuestos | C114: 5 | D114: Si no puedes pagar todo | E114: Solicitar facilidades de pago (convenio) | F114: Contribuyentes › Trámites comunes › Todos los grupos | G114: https://portal.sat.gob.gt/portal/requisitos-tramites-agencias/solicitud-de-facilidad-de-pago/
... A122: 6 | B122: Declarar y pagar mis impuestos | C122: 7 | D122: Dudas | E122: Curso: errores comunes en la declaración mensual del IVA | F122: Contribuyentes › Contribuyente General › Contribuyente General | G122: https://sites.google.com/capacitacionessat.page/cultura-tributariad/cursos-virtuales-sat/impuesto-al-valor-agregado-iva/principales-errores-e-inconsistencias-detectadas-en-la-declaraci%C3%B3n-mensual
A123: 7 | B123: Obtener mi solvencia fiscal | D123: Para: Quien necesita demostrar que está al día
A124: 7 | B124: Obtener mi solvencia fiscal | C124: 1 | D124: Revisa los requisitos | E124: Requisitos para la solvencia fiscal (SOFI) | F124: Contribuyentes › Trámites comunes › Todos los grupos | G124: https://portal.sat.gob.gt/portal/requisitos-sofi/
A125: 7 | B125: Obtener mi solvencia fiscal | C125: 2 | D125: Solicítala | E125: Obtener tu solvencia fiscal | F125: Contribuyentes › Trámites comunes › Todos los grupos | G125: https://portal.sat.gob.gt/portal/requisitos-tramites-agencias/solvencia-fiscal/
A126: 7 | B126: Obtener mi solvencia fiscal | C126: 3 | D126: Si te la niegan | E126: ¿Por qué no tengo solvencia fiscal? | F126: Contribuyentes › Trámites comunes › Todos los grupos | G126: https://portal.sat.gob.gt/portal/solvencia-fiscal/
A127: 7 | B127: Obtener mi solvencia fiscal | C127: 3 | D127: Si te la niegan | E127: Declarar y pagar en Declaraguate | F127: Contribuyentes › Trámites comunes › Todos los grupos | G127: https://declaraguate.sat.gob.gt/declaraguate-web/
A128: 7 | B128: Obtener mi solvencia fiscal | C128: 3 | D128: Si te la niegan | E128: Solicitar facilidades de pago en línea | F128: Contribuyentes › Trámites comunes › Todos los grupos | G128: https://portal.sat.gob.gt/portal/requisitos-tramites-agencias/facilidades-de-pago/
A129: 7 | B129: Obtener mi solvencia fiscal | C129: 3 | D129: Si te la niegan | E129: Confirmar tus datos cada año (ratificación anual) | F129: Contribuyentes › Trámites comunes › Todos los grupos | G129: https://portal.sat.gob.gt/portal/requisitos-tramites-agencias/ratificacion-o-confirmacion-anual-de-datos/
A130: 7 | B130: Obtener mi solvencia fiscal | C130: 4 | D130: Consulta solvencias anteriores | E130: Historial de solvencias fiscales | F130: Organismos especiales › Exentos › Constitucionales | G130: https://portal.sat.gob.gt/portal/bitacora-de-solvencia-fiscal/
A131: 8 | B131: Soy asalariado: ISR de mi salario | D131: Para: Empleados en relación de dependencia
A132: 8 | B132: Soy asalariado: ISR de mi salario | C132: 1 | D132: Obtén tu NIT | E132: Obtener NIT sin tener negocio (sin obligaciones) | F132: Contribuyentes › NIT sin Obligaciones › Todos los grupos | G132: https://portal.sat.gob.gt/portal/requisitos-tramites-agencias/inscripcion-nit-sin-obligaciones-tributarias/
A133: 8 | B133: Soy asalariado: ISR de mi salario | C133: 2 | D133: Calcula tu ISR | E133: Calcular el ISR de tu salario | F133: Contribuyentes › NIT sin Obligaciones › Todos los grupos | G133: https://portal.sat.gob.gt/portal/calculo-isr-asalariados/
A134: 8 | B134: Soy asalariado: ISR de mi salario | C134: 3 | D134: Revisa tus retenciones | E134: Consultar constancias de retención de IVA e ISR recibidas | F134: Contribuyentes › Pequeños Contribuyentes › Todos los grupos | G134: https://portal.sat.gob.gt/portal/retenciones-del-iva-consulta-de-constancias-de-retencion-del-iva-recibidas/
A135: 8 | B135: Soy asalariado: ISR de mi salario | C135: 4 | D135: Pide devolución si te retuvieron de más | E135: Devolución de ISR si eres asalariado | F135: Contribuyentes › NIT sin Obligaciones › Todos los grupos | G135: https://portal.sat.gob.gt/portal/requisitos-tramites-agencias/devolucion-del-impuesto-sobre-la-renta-asalariados-retenciones-en-exceso-o-pago-indebido/
...
