Workbook

Sheet Árbol de navegación
A1: Árbol de navegación por grupo, categoría y grupo de interés
A2: Nivel 1 = grupo de audiencia · Nivel 2 = categoría · Nivel 3 = grupo de la categoría. Los conteos se calculan desde cada hoja.
A4: Nivel 1 | B4: Nivel 2 · Categoría | C4: Nivel 3 · Grupo | D4: Páginas
A5: Contribuyentes | D5: =COUNTA(Contribuyentes!$G$5:$G$357) -> 353
B6: NIT sin Obligaciones | D6: =COUNTIF(Contribuyentes!$A$5:$A$357,B6) -> 5
C7: Todos los grupos | D7: =COUNTIFS(Contribuyentes!$A$5:$A$357,$B$6,Contribuyentes!$B$5:$B$357,C7) -> 5
B8: Pequeños Contribuyentes | D8: =COUNTIF(Contribuyentes!$A$5:$A$357,B8) -> 26
C9: Todos los grupos | D9: =COUNTIFS(Contribuyentes!$A$5:$A$357,$B$8,Contribuyentes!$B$5:$B$357,C9) -> 5
C10: Pequeño Contribuyente | D10: =COUNTIFS(Contribuyentes!$A$5:$A$357,$B$8,Contribuyentes!$B$5:$B$357,C10) -> 10
C11: Primario | D11: =COUNTIFS(Contribuyentes!$A$5:$A$357,$B$8,Contribuyentes!$B$5:$B$357,C11) -> 8
C12: Pecuario | D12: =COUNTIFS(Contribuyentes!$A$5:$A$357,$B$8,Contribuyentes!$B$5:$B$357,C12) -> 3
B13: Contribuyente General | D13: =COUNTIF(Contribuyentes!$A$5:$A$357,B13) -> 68
C14: Todos los grupos | D14: =COUNTIFS(Contribuyentes!$A$5:$A$357,$B$13,Contribuyentes!$B$5:$B$357,C14) -> 4
C15: Contribuyente General | D15: =COUNTIFS(Contribuyentes!$A$5:$A$357,$B$13,Contribuyentes!$B$5:$B$357,C15) -> 62
C16: Rep. Legales | D16: =COUNTIFS(Contribuyentes!$A$5:$A$357,$B$13,Contribuyentes!$B$5:$B$357,C16) -> 2
B17: Contribuyentes Especiales | D17: =COUNTIF(Contribuyentes!$A$5:$A$357,B17) -> 18
C18: Todos los grupos | D18: =COUNTIFS(Contribuyentes!$A$5:$A$357,$B$17,Contribuyentes!$B$5:$B$357,C18) -> 12
C19: Medianos | D19: =COUNTIFS(Contribuyentes!$A$5:$A$357,$B$17,Contribuyentes!$B$5:$B$357,C19) -> 0
C20: Grandes | D20: =COUNTIFS(Contribuyentes!$A$5:$A$357,$B$17,Contribuyentes!$B$5:$B$357,C20) -> 4
C21: Rep. Legales | D21: =COUNTIFS(Contribuyentes!$A$5:$A$357,$B$17,Contribuyentes!$B$5:$B$357,C21) -> 2
B22: Trámites comunes | D22: =COUNTIF(Contribuyentes!$A$5:$A$357,B22) -> 230
C23: Todos los grupos | D23: =COUNTIFS(Contribuyentes!$A$5:$A$357,$B$22,Contribuyentes!$B$5:$B$357,C23) -> 230
A24: Operadores de comercio exterior | D24: =COUNTA('Operadores de comercio exterior'!$F$5:$F$188) -> 184
B25: Importadores y Exportadores | D25: =COUNTIF('Operadores de comercio exterior'!$A$5:$A$188,B25) -> 75
C26: Todos los grupos | D26: =COUNTIFS('Operadores de comercio exterior'!$A$5:$A$188,$B$25,'Operadores de comercio exterior'!$B$5:$B$188,C26) -> 22
C27: Importadores | D27: =COUNTIFS('Operadores de comercio exterior'!$A$5:$A$188,$B$25,'Operadores de comercio exterior'!$B$5:$B$188,C27) -> 27
C28: OEA | D28: =COUNTIFS('Operadores de comercio exterior'!$A$5:$A$188,$B$25,'Operadores de comercio exterior'!$B$5:$B$188,C28) -> 5
C29: Exportadores | D29: =COUNTIFS('Operadores de comercio exterior'!$A$5:$A$188,$B$25,'Operadores de comercio exterior'!$B$5:$B$188,C29) -> 21
B30: Auxiliares de la Función Pública Aduanera | D30: =COUNTIF('Operadores de comercio exterior'!$A$5:$A$188,B30) -> 35
C31: Todos los grupos | D31: =COUNTIFS('Operadores de comercio exterior'!$A$5:$A$188,$B$30,'Operadores de comercio exterior'!$B$5:$B$188,C31) -> 8
C32: Courier | D32: =COUNTIFS('Operadores de comercio exterior'!$A$5:$A$188,$B$30,'Operadores de comercio exterior'!$B$5:$B$188,C32) -> 3
C33: Consolidadores y Desconsolidadores de Carga | D33: =COUNTIFS('Operadores de comercio exterior'!$A$5:$A$188,$B$30,'Operadores de comercio exterior'!$B$5:$B$188,C33) -> 2
C34: Almacenes Fiscales | D34: =COUNTIFS('Operadores de comercio exterior'!$A$5:$A$188,$B$30,'Operadores de comercio exterior'!$B$5:$B$188,C34) -> 1
C35: Almacenadoras | D35: =COUNTIFS('Operadores de comercio exterior'!$A$5:$A$188,$B$30,'Operadores de comercio exterior'!$B$5:$B$188,C35) -> 1
C36: Depósitos Aduaneros | D36: =COUNTIFS('Operadores de comercio exterior'!$A$5:$A$188,$B$30,'Operadores de comercio exterior'!$B$5:$B$188,C36) -> 1
C37: ZDEEP | D37: =COUNTIFS('Operadores de comercio exterior'!$A$5:$A$188,$B$30,'Operadores de comercio exterior'!$B$5:$B$188,C37) -> 0
C38: Agentes Aduaneros | D38: =COUNTIFS('Operadores de comercio exterior'!$A$5:$A$188,$B$30,'Operadores de comercio exterior'!$B$5:$B$188,C38) -> 6
C39: Transportistas | D39: =COUNTIFS('Operadores de comercio exterior'!$A$5:$A$188,$B$30,'Operadores de comercio exterior'!$B$5:$B$188,C39) -> 13
C40: Apoderado Especial Aduanero | D40: =COUNTIFS('Operadores de comercio exterior'!$A$5:$A$188,$B$30,'Operadores de comercio exterior'!$B$5:$B$188,C40) -> 0
B41: Trámites comunes | D41: =COUNTIF('Operadores de comercio exterior'!$A$5:$A$188,B41) -> 74
C42: Todos los grupos | D42: =COUNTIFS('Operadores de comercio exterior'!$A$5:$A$188,$B$41,'Operadores de comercio exterior'!$B$5:$B$188,C42) -> 74
A43: Profesionales | D43: =COUNTA(Profesionales!$F$5:$F$95) -> 91
B44: Terceras Personas | D44: =COUNTIF(Profesionales!$A$5:$A$95,B44) -> 91
C45: Todos los grupos | D45: =COUNTIFS(Profesionales!$A$5:$A$95,$B$44,Profesionales!$B$5:$B$95,C45) -> 53
C46: Gestores Tributarios | D46: =COUNTIFS(Profesionales!$A$5:$A$95,$B$44,Profesionales!$B$5:$B$95,C46) -> 5
C47: Auxiliar Tributario | D47: =COUNTIFS(Profesionales!$A$5:$A$95,$B$44,Profesionales!$B$5:$B$95,C47) -> 3
C48: Abogados y Notarios | D48: =COUNTIFS(Profesionales!$A$5:$A$95,$B$44,Profesionales!$B$5:$B$95,C48) -> 14
C49: Peritos Contadores | D49: =COUNTIFS(Profesionales!$A$5:$A$95,$B$44,Profesionales!$B$5:$B$95,C49) -> 8
C50: Auditores | D50: =COUNTIFS(Profesionales!$A$5:$A$95,$B$44,Profesionales!$B$5:$B$95,C50) -> 8
A51: Organismos especiales | D51: =COUNTA('Organismos especiales'!$F$5:$F$138) -> 134
B52: Exentos | D52: =COUNTIF('Organismos especiales'!$A$5:$A$138,B52) -> 99
C53: Todos los grupos | D53: =COUNTIFS('Organismos especiales'!$A$5:$A$138,$B$52,'Organismos especiales'!$B$5:$B$138,C53) -> 1
C54: Constitucionales | D54: =COUNTIFS('Organismos especiales'!$A$5:$A$138,$B$52,'Organismos especiales'!$B$5:$B$138,C54) -> 22
C55: No Lucrativos | D55: =COUNTIFS('Organismos especiales'!$A$5:$A$138,$B$52,'Organismos especiales'!$B$5:$B$138,C55) -> 24
C56: Decreto | D56: =COUNTIFS('Organismos especiales'!$A$5:$A$138,$B$52,'Organismos especiales'!$B$5:$B$138,C56) -> 31
C57: ZOLIC | D57: =COUNTIFS('Organismos especiales'!$A$5:$A$138,$B$52,'Organismos especiales'!$B$5:$B$138,C57) -> 6
C58: Municipalidades | D58: =COUNTIFS('Organismos especiales'!$A$5:$A$138,$B$52,'Organismos especiales'!$B$5:$B$138,C58) -> 15
B59: Entidades del Estado | D59: =COUNTIF('Organismos especiales'!$A$5:$A$138,B59) -> 13
C60: Todos los grupos | D60: =COUNTIFS('Organismos especiales'!$A$5:$A$138,$B$59,'Organismos especiales'!$B$5:$B$138,C60) -> 9
C61: Organismo Judicial | D61: =COUNTIFS('Organismos especiales'!$A$5:$A$138,$B$59,'Organismos especiales'!$B$5:$B$138,C61) -> 1
C62: Ministerio Público | D62: =COUNTIFS('Organismos especiales'!$A$5:$A$138,$B$59,'Organismos especiales'!$B$5:$B$138,C62) -> 2
C63: SENABED / CONABED | D63: =COUNTIFS('Organismos especiales'!$A$5:$A$138,$B$59,'Organismos especiales'!$B$5:$B$138,C63) -> 1
C64: Procuraduría de los Derechos Humanos | D64: =COUNTIFS('Organismos especiales'!$A$5:$A$138,$B$59,'Organismos especiales'!$B$5:$B$138,C64) -> 0
B65: Trámites comunes | D65: =COUNTIF('Organismos especiales'!$A$5:$A$138,B65) -> 22
C66: Todos los grupos | D66: =COUNTIFS('Organismos especiales'!$A$5:$A$138,$B$65,'Organismos especiales'!$B$5:$B$138,C66) -> 22
A67: Institucional – Transversal | D67: =COUNTA('Institucional – Transversal'!$E$5:$E$123) -> 119
A68: Total de filas | D68: =SUMIF($A$5:$A$67,"<>",$D$5:$D$67) -> 881
A69: Una misma página puede aparecer en varias hojas o grupos cuando la usan distintos grupos de interés.

Sheet Descripciones
A1: Descripciones de categorías y grupos
A2: Para qué sirve cada nivel desde el portal SAT y la base legal de referencia (verificar contra la versión vigente de cada ley).
A4: Nivel 1 | B4: Categoría | C4: Grupo | D4: Para quién es | E4: Base legal de referencia | F4: Páginas
A5: Contribuyentes | D5: Personas y empresas inscritas en el RTU: inscripción, declaraciones, facturas, vehículos, devoluciones y más. | E5: Código Tributario (Decreto 6-91): Registro Tributario Unificado. | F5: =COUNTA(Contribuyentes!$G$5:$G$357) -> 353
A6: Contribuyentes | B6: NIT sin Obligaciones | D6: Personas con NIT que no están afiliadas a impuestos: asalariados, personas que compran bienes o hacen trámites de vehículos y profesionales que registran su título. | E6: Código Tributario (RTU); Ley de Actualización Tributaria (Decreto 10-2012), ISR de rentas del trabajo. | F6: =COUNTIF(Contribuyentes!$A$5:$A$357,B6) -> 5
A7: Contribuyentes | B7: Pequeños Contribuyentes | D7: Contribuyentes de regímenes simplificados: pequeño contribuyente y los nuevos regímenes del sector primario y pecuario. | E7: Ley del IVA (Decreto 27-92), Régimen de Pequeño Contribuyente; Decreto 31-2024. | F7: =COUNTIF(Contribuyentes!$A$5:$A$357,B7) -> 26
A8: Contribuyentes | B8: Pequeños Contribuyentes | C8: Pequeño Contribuyente | D8: Personas con ingresos anuales de hasta Q150,000 que pagan una tarifa única sobre sus ventas (incluye el Régimen Electrónico). | E8: Ley del IVA (Decreto 27-92), Régimen de Pequeño Contribuyente; Decreto 7-2019 (régimen electrónico). | F8: =COUNTIFS(Contribuyentes!$A$5:$A$357,B8,Contribuyentes!$B$5:$B$357,C8) -> 10
A9: Contribuyentes | B9: Pequeños Contribuyentes | C9: Primario | D9: Productores agrícolas y artesanales del sector primario inscritos en el régimen especial, con pago del Impuesto a la Confianza Tributaria (ICT). | E9: Ley para la Integración del Sector Productivo Primario y Agropecuario (Decreto 31-2024). | F9: =COUNTIFS(Contribuyentes!$A$5:$A$357,B9,Contribuyentes!$B$5:$B$357,C9) -> 8
A10: Contribuyentes | B10: Pequeños Contribuyentes | C10: Pecuario | D10: Productores e intermediarios de ganado, acuicultura y apicultura sin transformación industrial, inscritos en el régimen pecuario (ICT). | E10: Decreto 31-2024, régimen pecuario. | F10: =COUNTIFS(Contribuyentes!$A$5:$A$357,B10,Contribuyentes!$B$5:$B$357,C10) -> 3
A11: Contribuyentes | B11: Contribuyente General | D11: Contribuyentes del Régimen General del IVA y del ISR de actividades lucrativas (sobre utilidades u opcional simplificado), incluidas personas jurídicas y entes. | E11: Ley del IVA (Decreto 27-92); Ley de Actualización Tributaria (Decreto 10-2012). | F11: =COUNTIF(Contribuyentes!$A$5:$A$357,B11) -> 68
A12: Contribuyentes | B12: Contribuyente General | C12: Contribuyente General | D12: Personas individuales y jurídicas con negocio en el Régimen General. | E12: Decreto 27-92 y Decreto 10-2012. | F12: =COUNTIFS(Contribuyentes!$A$5:$A$357,B12,Contribuyentes!$B$5:$B$357,C12) -> 62
A13: Contribuyentes | B13: Contribuyente General | C13: Rep. Legales | D13: Representantes legales que hacen gestiones en nombre de personas jurídicas. | E13: Código Tributario, responsables por representación; Código de Comercio. | F13: =COUNTIFS(Contribuyentes!$A$5:$A$357,B13,Contribuyentes!$B$5:$B$357,C13) -> 2
A14: Contribuyentes | B14: Contribuyentes Especiales | D14: Contribuyentes calificados por la SAT como especiales por su volumen de operaciones; atención en gerencias especializadas. | E14: Calificación por resolución de la SAT (Ley Orgánica de la SAT, Decreto 1-98). | F14: =COUNTIF(Contribuyentes!$A$5:$A$357,B14) -> 18
A15: Contribuyentes | B15: Contribuyentes Especiales | C15: Medianos | D15: Contribuyentes especiales medianos. | E15: Resolución de calificación de la SAT. | F15: =COUNTIFS(Contribuyentes!$A$5:$A$357,B15,Contribuyentes!$B$5:$B$357,C15) -> 0
A16: Contribuyentes | B16: Contribuyentes Especiales | C16: Grandes | D16: Contribuyentes especiales grandes. | E16: Resolución de calificación de la SAT. | F16: =COUNTIFS(Contribuyentes!$A$5:$A$357,B16,Contribuyentes!$B$5:$B$357,C16) -> 4
A17: Contribuyentes | B17: Contribuyentes Especiales | C17: Rep. Legales | D17: Representantes legales de contribuyentes especiales. | E17: Código Tributario, responsables por representación. | F17: =COUNTIFS(Contribuyentes!$A$5:$A$357,B17,Contribuyentes!$B$5:$B$357,C17) -> 2
A18: Operadores de comercio exterior | D18: Personas que importan, exportan o prestan servicios en las operaciones aduaneras. | E18: CAUCA y RECAUCA; Ley Nacional de Aduanas (Decreto 14-2013). | F18: =COUNTA('Operadores de comercio exterior'!$F$5:$F$188) -> 184
A19: Operadores de comercio exterior | B19: Importadores y Exportadores | D19: Personas y empresas que importan o exportan mercancías. | E19: CAUCA y RECAUCA; Ley del IVA (devolución de crédito fiscal). | F19: =COUNTIF('Operadores de comercio exterior'!$A$5:$A$188,B19) -> 75
A20: Operadores de comercio exterior | B20: Importadores y Exportadores | C20: Importadores | D20: Quienes ingresan mercancías o vehículos al país. | E20: CAUCA y RECAUCA. | F20: =COUNTIFS('Operadores de comercio exterior'!$A$5:$A$188,B20,'Operadores de comercio exterior'!$B$5:$B$188,C20) -> 27
A21: Operadores de comercio exterior | B21: Importadores y Exportadores | C21: OEA | D21: Operadores Económicos Autorizados: empresas certificadas por cumplir estándares de seguridad y bajo riesgo. | E21: CAUCA y RECAUCA; programa OEA de la SAT. | F21: =COUNTIFS('Operadores de comercio exterior'!$A$5:$A$188,B21,'Operadores de comercio exterior'!$B$5:$B$188,C21) -> 5
A22: Operadores de comercio exterior | B22: Importadores y Exportadores | C22: Exportadores | D22: Quienes venden mercancías al exterior: registro de exportadores y devolución del crédito fiscal del IVA. | E22: Ley del IVA (Decreto 27-92), regímenes de devolución de crédito fiscal. | F22: =COUNTIFS('Operadores de comercio exterior'!$A$5:$A$188,B22,'Operadores de comercio exterior'!$B$5:$B$188,C22) -> 21
A23: Operadores de comercio exterior | B23: Auxiliares de la Función Pública Aduanera | D23: Personas autorizadas por la SAT que intervienen en las operaciones aduaneras. | E23: CAUCA y RECAUCA, auxiliares de la función pública aduanera; Decreto 14-2013. | F23: =COUNTIF('Operadores de comercio exterior'!$A$5:$A$188,B23) -> 35
A24: Operadores de comercio exterior | B24: Auxiliares de la Función Pública Aduanera | C24: Courier | D24: Empresas de entrega rápida. | E24: RECAUCA. | F24: =COUNTIFS('Operadores de comercio exterior'!$A$5:$A$188,B24,'Operadores de comercio exterior'!$B$5:$B$188,C24) -> 3
A25: Operadores de comercio exterior | B25: Auxiliares de la Función Pública Aduanera | C25: Consolidadores y Desconsolidadores de Carga | D25: Agrupan o separan carga de varios consignatarios. | E25: RECAUCA. | F25: =COUNTIFS('Operadores de comercio exterior'!$A$5:$A$188,B25,'Operadores de comercio exterior'!$B$5:$B$188,C25) -> 2
A26: Operadores de comercio exterior | B26: Auxiliares de la Función Pública Aduanera | C26: Almacenes Fiscales | D26: Depositarios aduaneros que almacenan mercancías bajo control aduanero. | E26: RECAUCA. | F26: =COUNTIFS('Operadores de comercio exterior'!$A$5:$A$188,B26,'Operadores de comercio exterior'!$B$5:$B$188,C26) -> 1
A27: Operadores de comercio exterior | B27: Auxiliares de la Función Pública Aduanera | C27: Almacenadoras | D27: Almacenes generales de depósito autorizados. | E27: RECAUCA. | F27: =COUNTIFS('Operadores de comercio exterior'!$A$5:$A$188,B27,'Operadores de comercio exterior'!$B$5:$B$188,C27) -> 1
A28: Operadores de comercio exterior | B28: Auxiliares de la Función Pública Aduanera | C28: Depósitos Aduaneros | D28: Depósitos autorizados para mercancías en régimen suspensivo. | E28: RECAUCA. | F28: =COUNTIFS('Operadores de comercio exterior'!$A$5:$A$188,B28,'Operadores de comercio exterior'!$B$5:$B$188,C28) -> 1
A29: Operadores de comercio exterior | B29: Auxiliares de la Función Pública Aduanera | C29: ZDEEP | D29: Desarrolladores de Zonas de Desarrollo Económico Especial Públicas, registrados como auxiliares. | E29: Decreto 22-73 (ZOLIC), reformado por Decreto 30-2008. | F29: =COUNTIFS('Operadores de comercio exterior'!$A$5:$A$188,B29,'Operadores de comercio exterior'!$B$5:$B$188,C29) -> 0
A30: Operadores de comercio exterior | B30: Auxiliares de la Función Pública Aduanera | C30: Agentes Aduaneros | D30: Profesionales autorizados para presentar declaraciones de mercancías por cuenta de terceros. | E30: CAUCA y RECAUCA. | F30: =COUNTIFS('Operadores de comercio exterior'!$A$5:$A$188,B30,'Operadores de comercio exterior'!$B$5:$B$188,C30) -> 6
A31: Operadores de comercio exterior | B31: Auxiliares de la Función Pública Aduanera | C31: Transportistas | D31: Transportistas aduaneros: manifiestos, marchamo y tránsito. | E31: CAUCA y RECAUCA. | F31: =COUNTIFS('Operadores de comercio exterior'!$A$5:$A$188,B31,'Operadores de comercio exterior'!$B$5:$B$188,C31) -> 13
A32: Operadores de comercio exterior | B32: Auxiliares de la Función Pública Aduanera | C32: Apoderado Especial Aduanero | D32: Representante del importador o exportador en sus propias operaciones. | E32: Ley Nacional de Aduanas (Decreto 14-2013). | F32: =COUNTIFS('Operadores de comercio exterior'!$A$5:$A$188,B32,'Operadores de comercio exterior'!$B$5:$B$188,C32) -> 0
A33: Profesionales | D33: Personas que hacen gestiones ante la SAT por cuenta de otros. | F33: =COUNTA(Profesionales!$F$5:$F$95) -> 91
A34: Profesionales | B34: Terceras Personas | D34: Terceras personas autorizadas o registradas ante la SAT. | F34: =COUNTIF(Profesionales!$A$5:$A$95,B34) -> 91
A35: Profesionales | B35: Terceras Personas | C35: Gestores Tributarios | D35: Personas autorizadas por la SAT para hacer gestiones de terceros, principalmente de vehículos. | E35: Registro y autorización de la SAT. | F35: =COUNTIFS(Profesionales!$A$5:$A$95,B35,Profesionales!$B$5:$B$95,C35) -> 5
A36: Profesionales | B36: Terceras Personas | C36: Auxiliar Tributario | D36: Auxiliares de los gestores tributarios. | E36: Registro y autorización de la SAT. | F36: =COUNTIFS(Profesionales!$A$5:$A$95,B36,Profesionales!$B$5:$B$95,C36) -> 3
A37: Profesionales | B37: Terceras Personas | C37: Abogados y Notarios | D37: Registro de abogados y notarios, avisos notariales, traspasos electrónicos y especies fiscales. | E37: Código de Notariado (Decreto 314); Ley del Impuesto de Timbres Fiscales (Decreto 37-92). | F37: =COUNTIFS(Profesionales!$A$5:$A$95,B37,Profesionales!$B$5:$B$95,C37) -> 14
A38: Profesionales | B38: Terceras Personas | C38: Peritos Contadores | D38: Contadores inscritos que llevan la contabilidad de los contribuyentes. | E38: Decreto 10-2012 (contabilidad); Código de Comercio. | F38: =COUNTIFS(Profesionales!$A$5:$A$95,B38,Profesionales!$B$5:$B$95,C38) -> 8
A39: Profesionales | B39: Terceras Personas | C39: Auditores | D39: Contadores públicos y auditores que emiten dictámenes ante la SAT. | E39: Decreto 10-2012; Ley del IVA (dictamen para devolución de crédito fiscal). | F39: =COUNTIFS(Profesionales!$A$5:$A$95,B39,Profesionales!$B$5:$B$95,C39) -> 8
A40: Organismos especiales | D40: Entidades con régimen especial de exención y entidades del Estado. | F40: =COUNTA('Organismos especiales'!$F$5:$F$138) -> 134
A41: Organismos especiales | B41: Exentos | D41: Entidades exentas de impuestos según la Constitución o leyes específicas. | E41: Constitución Política; Decreto 10-2012, art. 11 (rentas exentas). | F41: =COUNTIF('Organismos especiales'!$A$5:$A$138,B41) -> 99
A42: Organismos especiales | B42: Exentos | C42: Constitucionales | D42: Exención que da la Constitución: universidades, centros educativos, iglesias y deporte federado. | E42: Constitución Política, arts. 37, 88, 91 y 92. | F42: =COUNTIFS('Organismos especiales'!$A$5:$A$138,B42,'Organismos especiales'!$B$5:$B$138,C42) -> 22
A43: Organismos especiales | B43: Exentos | C43: No Lucrativos | D43: Asociaciones, fundaciones, ONG, organizaciones comunitarias y sindicatos sin fines de lucro. | E43: Decreto 10-2012, art. 11; Ley de ONG para el Desarrollo. | F43: =COUNTIFS('Organismos especiales'!$A$5:$A$138,B43,'Organismos especiales'!$B$5:$B$138,C43) -> 24
A44: Organismos especiales | B44: Exentos | C44: Decreto | D44: Exentos por leyes específicas: cooperativas, maquilas, zonas francas, partidos políticos y misiones diplomáticas. | E44: Decretos 82-78, 29-89, 65-89 y 1-85; convenciones internacionales. | F44: =COUNTIFS('Organismos especiales'!$A$5:$A$138,B44,'Organismos especiales'!$B$5:$B$138,C44) -> 31
A45: Organismos especiales | B45: Exentos | C45: ZOLIC | D45: Usuarios de la Zona Libre de Industria y Comercio Santo Tomás de Castilla. | E45: Ley Orgánica de la ZOLIC (Decreto 22-73). | F45: =COUNTIFS('Organismos especiales'!$A$5:$A$138,B45,'Organismos especiales'!$B$5:$B$138,C45) -> 6
A46: Organismos especiales | B46: Exentos | C46: Municipalidades | D46: Municipalidades y sus gestiones de RTU, vehículos, FEL y retenciones. | E46: Constitución, art. 253 (autonomía); Decreto 10-2012, art. 11. | F46: =COUNTIFS('Organismos especiales'!$A$5:$A$138,B46,'Organismos especiales'!$B$5:$B$138,C46) -> 15
A47: Organismos especiales | B47: Entidades del Estado | D47: Entidades del Estado que piden gestiones a la SAT o coordinan con ella. | F47: =COUNTIF('Organismos especiales'!$A$5:$A$138,B47) -> 13
A48: Organismos especiales | B48: Entidades del Estado | C48: Organismo Judicial | D48: Órdenes judiciales sobre vehículos y registros. | F48: =COUNTIFS('Organismos especiales'!$A$5:$A$138,B48,'Organismos especiales'!$B$5:$B$138,C48) -> 1
A49: Organismos especiales | B49: Entidades del Estado | C49: Ministerio Público | D49: Activación e inactivación de vehículos por orden del MP. | F49: =COUNTIFS('Organismos especiales'!$A$5:$A$138,B49,'Organismos especiales'!$B$5:$B$138,C49) -> 2
A50: Organismos especiales | B50: Entidades del Estado | C50: SENABED / CONABED | D50: Bienes en extinción de dominio. | E50: Ley de Extinción de Dominio (Decreto 55-2010). | F50: =COUNTIFS('Organismos especiales'!$A$5:$A$138,B50,'Organismos especiales'!$B$5:$B$138,C50) -> 1
A51: Organismos especiales | B51: Entidades del Estado | C51: Procuraduría de los Derechos Humanos | D51: Gestiones y coordinación con la PDH. | F51: =COUNTIFS('Organismos especiales'!$A$5:$A$138,B51,'Organismos especiales'!$B$5:$B$138,C51) -> 0
A52: Trámites comunes | D52: En cada hoja, agrupa las páginas que usan varias categorías (por ejemplo Agencia Virtual, vehículos, solvencia fiscal o declaraciones).

Sheet Contribuyentes
A1: Contribuyentes
A2: Personas individuales y jurídicas inscritas en el RTU, ordenadas por categoría (régimen o tipo de contribuyente) y grupo. Orden: Categoría › Grupo › Tema › Página. «Todos los grupos» = la usan todos los grupos de la categoría. «Trámites comunes» = la usan varias categorías.
A4: Macro Grupos | B4: Grupo | C4: Sub grupo | D4: Tema | E4: Subtema | F4: Página / Trámite (nombre actual) | G4: Nombre de trámite sugerido | H4: Descripción de la página | I4: Usado por (según Grupos y categorías) | J4: Origen de la clasificación | K4: Motivo / referencia | L4: Sección actual del menú | M4: URL | N4: Nota / Revisar
A5: Contribuyente General | B5: Todos los grupos | D5: Devoluciones y créditos fiscales | E5: ISR (Impuesto Sobre la Renta) | F5: Devolución de ISR Asalariados (Retenciones en exceso o pago indebido) SAT-117 o 1431 | G5: Devolución de ISR si eres asalariado | H5: Información sobre: Devolución de ISR si eres asalariado. | J5: Análisis | K5: Asalariados: NIT sin obligaciones, ISR de rentas del trabajo | L5: SERVICIOS TRIBUTARIOS | M5: https://portal.sat.gob.gt/portal/requisitos-tramites-agencias/devolucion-del-impuesto-sobre-la-renta-asalariados-retenciones-en-exceso-o-pago-indebido/ | N5: Servicio/tema general para contribuyentes
A6: Contribuyentes | B6: NIT sin Obligaciones | D6: RTU Digital | E6: Inscripción | F6: Requisitos para la Inscripción RTU | G6: Inscripción de NIT sin Obligaciones | H6: Solicitud y requisitos para la obtención electrónica de NIT sin obligaciones tributarias por primera vez. | I6: Personas Individuales (Nacionales y Extranjeros sin actividad económica) | J6: Análisis de arquitectura transaccional | K6: Trámite inicial obligatorio para actos civiles, apertura de cuentas bancarias y recepción de remesas. | L6: Requisitos de personas / empresas | M6: https://portal.sat.gob.gt/portal/requisitos-de-personas-empresas/#1615485066841-639e67c5-51e3 | N6: Desvincular del listado de empresas/sociedades mercantiles; crear landing o ficha específica para personas individuales.
A7: Contribuyentes | B7: NIT sin Obligaciones | D7: RTU Digital | E7: Actualización | F7: Requisitos para la Actualización RTU | G7: Actualización de Datos y Transición de Régimen | H7: Requisitos y pasos para actualizar datos de identificación, domicilio fiscal o pasar al régimen con obligaciones tributarias. | I7: Personas que inician relación laboral o comercial | J7: Análisis de arquitectura transaccional | K7: Permite modificar datos personales o dar el salto formal a contribuyente afecto cuando la persona inicia actividades económicas. | L7: Requisitos de personas / empresas | M7: https://portal.sat.gob.gt/portal/requisitos-de-personas-empresas/#1541621044169-4198d06d-693f | N7: Aislar la opción de paso de 'sin obligaciones' a 'con obligaciones' sin obligar a navegar por requisitos corporativos.
A8: Contribuyentes | B8: NIT sin Obligaciones | D8: Sistemas Web | E8: Acceso y Seguridad | F8: Agencia Virtual | G8: Solicitud y Activación de Agencia Virtual | H8: Acceso a plataforma, activación de usuario, reinicio de contraseña y cambio de correo electrónico para personas sin obligaciones. | I8: Usuarios registrados con NIT | J8: Análisis de arquitectura transaccional | K8: Canal indispensable para descargar la constancia de RTU, consultar datos personales y dar seguimiento a solicitudes web. | L8: Menú Principal / Sistemas | M8: https://farm3.sat.gob.gt/menu/login.jsf | N8: Es un sistema de autenticación directa; la ficha informativa debe explicar cómo obtener el acceso inicial.
A9: Contribuyentes | B9: NIT sin Obligaciones | D9: Consultas Públicas | E9: Seguimiento | F9: Estado de Gestión de Agencia Virtual | G9: Consulta de Estado de Gestión de Agencia Virtual | H9: Herramienta de consulta para verificar el estado de aprobación de la solicitud de acceso a Agencia Virtual. | I9: Solicitantes de Agencia Virtual | J9: Análisis de arquitectura transaccional | K9: Permite validar si la solicitud de usuario o reseteo de clave fue aceptada, rechazada o requiere subsanar requisitos. | L9: Consultas Públicas | M9: https://portal.sat.gob.gt/portal/consulta-de-gestion-del-contribuyente/ | N9: Debe integrarse como paso de seguimiento dentro de la ficha de Agencia Virtual, no como enlace huérfano.
A10: Contribuyentes | B10: NIT sin Obligaciones | D10: Certificaciones | E10: Solvencias | F10: Solvencia Fiscal | G10: Solicitud y Emisión de Solvencia Fiscal (SOFI) | H10: Consulta, pago y descarga de la Solvencia Fiscal Electrónica para certificar ausencia de adeudos tributarios. | I10: Personas Individuales | J10: Análisis de arquitectura transaccional | K10: Exigida comúnmente a personas sin obligaciones para postulaciones laborales, trámites consulares/visas y contratos civiles. | L10: Consultas / Solvencias | M10: https://portal.sat.gob.gt/portal/solvencia-fiscal/ | N10: Para este perfil la emisión es automática, salvo que existan registros históricos de omisos o adeudos en el ISCV.
A11: Contribuyentes | B11: NIT sin Obligaciones | D11: Citas y Agencias | E11: Citas | F11: Requisitos para la Atención a través de Cita | G11: Cita Previa para Trámites Presenciales | H11: Información, requisitos y agenda electrónica para programar atención física en agencias tributarias. | I11: Casos especiales (menores o extranjeros) | J11: Análisis de arquitectura transaccional | K11: Aplica a personas sin obligaciones únicamente en validaciones biométricas presenciales o trámites mediante representante legal. | L11: Requisitos trámites agencias | M11: https://portal.sat.gob.gt/portal/requisitos-tramites-agencias/cita-controlada/ | N11: Condicional: solo debe desplegarse como alternativa si el trámite inicial no logra completarse 100% en línea.
A12: NIT sin Obligaciones | B12: Todos los grupos | D12: Otros servicios al contribuyente | E12: Títulos universitarios | F12: Títulos Universitarios | G12: Información sobre títulos universitarios | H12: Información sobre: Información sobre títulos universitarios. | J12: Análisis | K12: Profesionales que registran su título (NIT sin obligaciones) | L12: SERVICIOS TRIBUTARIOS | M12: https://portal.sat.gob.gt/portal/titulos-universitarios/ | N12: Servicio/tema general para contribuyentes
A13: NIT sin Obligaciones | B13: Todos los grupos | D13: Otros servicios al contribuyente | E13: Títulos universitarios | F13: Registro y Habilitación de Títulos Universitarios | G13: Registrar tu título universitario para ejercer | H13: Requisitos, pasos y documentos para registrar tu título universitario para ejercer. | I13: NIT sin Obligaciones | J13: Grupos y categorías | K13: Marcada «SI» en el archivo Grupos y categorías | L13: SERVICIOS TRIBUTARIOS | M13: https://portal.sat.gob.gt/portal/requisitos-tramites-agencias/registro-y-habilitacion-de-titulos-para-ejercer-profesion/ | N13: Servicio/tema general para contribuyentes
A14: NIT sin Obligaciones | B14: Todos los grupos | D14: Vehículos (como propietario) | E14: Requisitos y representantes | F14: Temas De Vehiculos | G14: Preguntas frecuentes sobre vehículos | H14: Respuestas a las preguntas más comunes sobre requisitos y representantes. | I14: NIT sin Obligaciones | J14: Grupos y categorías | K14: Marcada «SI» en el archivo Grupos y categorías | L14: CAPACITACIÓN | M14: https://portal.sat.gob.gt/portal/preguntas-frecuentes/temas-de-vehiculos/ | N14: Servicio/tema general para contribuyentes
A15: NIT sin Obligaciones | B15: Todos los grupos | D15: Vehículos (como propietario) | E15: Título y tarjeta de circulación | F15: Distintivos Electrónicos (Título de propiedad y Tarjeta de Circulación) | G15: Título y tarjeta de circulación electrónicos | H15: Información sobre: Título y tarjeta de circulación electrónicos. | I15: NIT sin Obligaciones | J15: Grupos y categorías | K15: Marcada «SI» en el archivo Grupos y categorías | L15: SERVICIOS TRIBUTARIOS | M15: https://portal.sat.gob.gt/portal/distintivos-electronicos/ | N15: Servicio/tema general para contribuyentes
A16: NIT sin Obligaciones | B16: Todos los grupos | D16: Agregada desde «Grupos y categorías» | G16: Libro Electrónico Tributario | H16: Pequeño Contribuyente | I16: NIT sin Obligaciones | J16: Grupos y categorías | K16: Marcada «SI» en el archivo Grupos y categorías | M16: https://portal.sat.gob.gt/portal/libro-electronico-tributario/pequeno-contribuyente/
A17: Pequeños Contribuyentes | B17: Todos los grupos | D17: Cultura tributaria y capacitación | E17: Leyes y normativa | F17: Legislación | G17: Legislación | H17: Información sobre: Legislación. | I17: Pequeños Contribuyentes | J17: Grupos y categorías | K17: Marcada «SI» en el archivo Grupos y categorías | L17: CAPACITACIÓN | M17: https://portal.sat.gob.gt/portal/biblioteca-en-linea-sat/legislacion/ | N17: Servicio/tema general para contribuyentes
A18: Pequeños Contribuyentes | B18: Todos los grupos | D18: Facturación electrónica y documentos tributarios | E18: Constancias de retención | F18: Constancias de Retención del IVA e ISR recibidos | G18: Consultar constancias de retención de IVA e ISR recibidas | H18: Servicio en línea para consultar constancias de retención de IVA e ISR recibidas. | I18: Pequeños Contribuyentes | J18: Grupos y categorías | K18: Marcada «SI» en el archivo Grupos y categorías | L18: SERVICIOS TRIBUTARIOS | M18: https://portal.sat.gob.gt/portal/retenciones-del-iva-consulta-de-constancias-de-retencion-del-iva-recibidas/ | N18: Servicio/tema general para contribuyentes
A19: Pequeños Contribuyentes | B19: Todos los grupos | D19: Importación | E19: Proceso de importación | F19: Despacho de distintivos de control de productos importados a los fabricantes o importadores domiciliados en el país y a las personas individuales y jurídicas que no sean fabricantes ni importadores | G19: Obtener distintivos de control de productos importados | H19: Requisitos, pasos y documentos para obtener distintivos de control de productos importados. | I19: Pequeños Contribuyentes | J19: Grupos y categorías | K19: Marcada «SI» en el archivo Grupos y categorías | L19: SERVICIOS TRIBUTARIOS | M19: https://portal.sat.gob.gt/portal/requisitos-tramites-agencias/despacho-de-distintivos-de-control-de-productos-importados-a-los-fabricantes-o-importadores-domiciliados-en-el-pais-y-a-las-personas-individuales-y-juridicas/ | N19: Coincide con palabra clave de comercio exterior/aduanas
A20: Pequeños Contribuyentes | B20: Todos los grupos | D20: Inscripción y actualización en el RTU | E20: Obtener o corregir tu NIT | F20: Solicitud Electrónica de NIT | G20: Solicitar tu NIT en línea | H20: Requisitos, pasos y documentos para solicitar tu NIT en línea. | I20: Pequeños Contribuyentes | J20: Grupos y categorías | K20: Marcada «SI» en el archivo Grupos y categorías | L20: SERVICIOS TRIBUTARIOS | M20: https://portal.sat.gob.gt/portal/solicitud-electronica-de-nit/ | N20: Servicio/tema general para contribuyentes
A21: Pequeños Contribuyentes | B21: Todos los grupos | D21: Otros servicios al contribuyente | E21: Sistemas de retención | F21: Asiste Hospitales Web | G21: Retenciones de hospitales (Asiste Hospitales Web) | H21: Información sobre: Retenciones de hospitales (Asiste Hospitales Web). | I21: Pequeños Contribuyentes | J21: Grupos y categorías | K21: Marcada «SI» en el archivo Grupos y categorías | L21: SERVICIOS TRIBUTARIOS | M21: https://portal.sat.gob.gt/portal/sistemas-web/asistehospitalesweb/ | N21: Servicio/tema general para contribuyentes
A22: Pequeños Contribuyentes | B22: Pequeño Contribuyente | D22: Cultura tributaria y capacitación | E22: Cursos por tipo de contribuyente | F22: Principales obligaciones tributarias de los pequeños contribuyentes | G22: Curso: obligaciones del pequeño contribuyente | H22: Capacitación virtual de la SAT sobre obligaciones del pequeño contribuyente. | J22: Análisis | K22: Régimen de Pequeño Contribuyente (Ley del IVA) | L22: CAPACITACIÓN | M22: https://sites.google.com/capacitacionessat.page/cultura-tributariad/cursos-virtuales-sat/impuesto-al-valor-agregado-iva/r%C3%A9gimen-del-peque%C3%B1o-contribuyente | N22: Servicio/tema general para contribuyentes
A23: Pequeños Contribuyentes | B23: Pequeño Contribuyente | D23: Devoluciones y créditos fiscales | E23: ISR (Impuesto Sobre la Renta) | F23: Devolución o Compensación del Impuesto Sobre la Renta Retenido al Pequeño Contribuyente del 5% | G23: Devolución del 5% de ISR retenido al pequeño contribuyente | H23: Información sobre: Devolución del 5% de ISR retenido al pequeño contribuyente. | J23: Análisis | K23: Retención de ISR al pequeño contribuyente | L23: SERVICIOS TRIBUTARIOS | M23: https://portal.sat.gob.gt/portal/requisitos-tramites-agencias/devolucion-acreditamiento-o-compensacion-de-impuesto-sobre-la-renta-retenido-indebidamente-a-pequeno-contribuyente-del-5/ | N23: Servicio/tema general para contribuyentes
A24: Pequeños Contribuyentes | B24: Pequeño Contribuyente | D24: Facturación electrónica y documentos tributarios | E24: Libro Electrónico Tributario (LET) | F24: Libro Electrónico Tributario para Pequeño contribuyente | G24: Curso: LET para pequeño contribuyente | H24: Capacitación virtual de la SAT sobre LET para pequeño contribuyente. | J24: Análisis | K24: Libro Electrónico Tributario del pequeño contribuyente | L24: CAPACITACIÓN | M24: https://sites.google.com/capacitacionessat.page/eventosenvivo/p%C3%A1gina-principal/libro-electr%C3%B3nico-tributario-para-peque%C3%B1o-contribuyente | N24: Servicio/tema general para contribuyentes
A25: Pequeños Contribuyentes | B25: Pequeño Contribuyente | D25: Otros servicios al contribuyente | E25: Libros, facturas y máquinas | F25: Autorización de documentos tributarios a pequeños contribuyentes | G25: Autorizar documentos para pequeños contribuyentes | H25: Requisitos, pasos y documentos para autorizar documentos para pequeños contribuyentes. | J25: Análisis | K25: Documentos del pequeño contribuyente | L25: SERVICIOS TRIBUTARIOS | M25: https://portal.sat.gob.gt/portal/requisitos-tramites-agencias/autorizacion-de-documentos-tributarios-a-pequenos-contribuyentes/ | N25: Servicio/tema general para contribuyentes
A26: Pequeños Contribuyentes | B26: Pequeño Contribuyente | D26: Regímenes tributarios | E26: Cambio de régimen | F26: Actualización de Cambio de Régimen de Pequeño Contribuyente a Régimen Electrónico de Pequeño Contribuyente | G26: Pasar a Régimen Electrónico de Pequeño Contribuyente | H26: Requisitos, pasos y documentos para pasar a Régimen Electrónico de Pequeño Contribuyente. | J26: Análisis | K26: Régimen de Pequeño Contribuyente (Ley del IVA) | L26: SERVICIOS TRIBUTARIOS | M26: https://portal.sat.gob.gt/portal/requisitos-tramites-agencias/requisitos-de-actualizacion-de-cambio-de-regimen-general-a-pequeno-contribuyente-persona/ | N26: Servicio/tema general para contribuyentes
A27: Pequeños Contribuyentes | B27: Pequeño Contribuyente | D27: Regímenes tributarios | E27: Cambio de régimen | F27: Actualización Cambio de Régimen de Pequeño Contribuyente a Régimen General del Impuesto al Valor Agregado | G27: Pasar de Pequeño Contribuyente a Régimen General del IVA | H27: Requisitos, pasos y documentos para pasar de Pequeño Contribuyente a Régimen General del IVA. | J27: Análisis | K27: Régimen de Pequeño Contribuyente (Ley del IVA) | L27: SERVICIOS TRIBUTARIOS | M27: https://portal.sat.gob.gt/portal/requisitos-tramites-agencias/actualizacion-cambio-de-regimen-de-pequeno-contribuyente-a-regimen-general-del-impuesto-al-valor-agregado/ | N27: Servicio/tema general para contribuyentes
A28: Pequeños Contribuyentes | B28: Pequeño Contribuyente | D28: Regímenes tributarios | E28: Pequeño Contribuyente | F28: Consulta NIT de Pequeño Contribuyente | G28: Consultar si un NIT es Pequeño Contribuyente | H28: Servicio en línea para consultar si un NIT es Pequeño Contribuyente. | J28: Análisis | K28: Régimen de Pequeño Contribuyente (Ley del IVA) | L28: SERVICIOS TRIBUTARIOS | M28: https://portal.sat.gob.gt/portal/consulta-regimen-de-pequeno-contribuyente/ | N28: Servicio/tema general para contribuyentes
A29: Pequeños Contribuyentes | B29: Pequeño Contribuyente | D29: Regímenes tributarios | E29: Pequeño Contribuyente | F29: Régimen Electrónico de Pequeño Contribuyente | G29: Curso: Régimen Electrónico de Pequeño Contribuyente | H29: Capacitación virtual de la SAT sobre Régimen Electrónico de Pequeño Contribuyente. | J29: Análisis | K29: Régimen de Pequeño Contribuyente (Ley del IVA) | L29: CAPACITACIÓN | M29: https://sites.google.com/capacitacionessat.page/cultura-tributariad/cursos-virtuales-sat/impuesto-al-valor-agregado-iva/r%C3%A9gimen-electr%C3%B3nico-de-peque%C3%B1o-contribuyente | N29: Servicio/tema general para contribuyentes
A30: Pequeños Contribuyentes | B30: Pequeño Contribuyente | D30: Regímenes tributarios | E30: Pequeño Contribuyente | F30: Régimen Electrónico del Pequeño Contribuyente | G30: Curso: Régimen Electrónico de Pequeño Contribuyente | H30: Capacitación virtual de la SAT sobre Régimen Electrónico de Pequeño Contribuyente. | J30: Análisis | K30: Régimen de Pequeño Contribuyente (Ley del IVA) | L30: CAPACITACIÓN | M30: https://sites.google.com/capacitacionessat.page/eventosenvivo/p%C3%A1gina-principal/r%C3%A9gimen-electr%C3%B3nico-del-peque%C3%B1o-contribuyente | N30: Servicio/tema general para contribuyentes
A31: Pequeños Contribuyentes | B31: Pequeño Contribuyente | D31: Regímenes tributarios | E31: Pequeño Contribuyente | F31: Régimen del pequeño contribuyente | G31: Curso: régimen de Pequeño Contribuyente | H31: Capacitación virtual de la SAT sobre régimen de Pequeño Contribuyente. | J31: Análisis | K31: Régimen de Pequeño Contribuyente (Ley del IVA) | L31: CAPACITACIÓN | M31: https://sites.google.com/capacitacionessat.page/cultura-tributariad/cursos-virtuales-sat/impuesto-al-valor-agregado/r%C3%A9gimen-del-peque%C3%B1o-contribuyente | N31: Servicio/tema general para contribuyentes
A32: Pequeños Contribuyentes | B32: Primario | D32: Consultas y verificadores | E32: Registros públicos | F32: Productores Inscritos: Consulta Productores | G32: Consultar productores inscritos | H32: Servicio en línea para consultar productores inscritos. | J32: Análisis | K32: Registro de productores | L32: SERVICIOS TRIBUTARIOS | M32: https://portal.sat.gob.gt/portal/consulta-productores/ | N32: Servicio/tema general para contribuyentes
A33: Pequeños Contribuyentes | B33: Primario | D33: Cultura tributaria y capacitación | E33: Cursos por tipo de contribuyente | F33: Productores de Productos Agropecuarios, Artesanales y Reciclados | G33: Curso: productores agropecuarios, artesanales y de reciclaje | H33: Capacitación virtual de la SAT sobre productores agropecuarios, artesanales y de reciclaje. | J33: Análisis | K33: Régimen agropecuario (Decreto 31-2024) | L33: CAPACITACIÓN | M33: https://sites.google.com/capacitacionessat.page/cultura-tributariad/cursos-virtuales-sat/impuesto-al-valor-agregado-iva/inscripci%C3%B3n-y-actualizaci%C3%B3n-de-productores | N33: Servicio/tema general para contribuyentes
... A42: Pequeños Contribuyentes | B42: Pecuario | D42: Regímenes tributarios | E42: Régimen Agropecuario | F42: Principales obligaciones tributarias del Régimen especial de Contribuyente Agropecuario (Convencional y Electrónico) | G42: Curso: obligaciones del Régimen Especial Agropecuario | H42: Capacitación virtual de la SAT sobre obligaciones del Régimen Especial Agropecuario. | J42: Análisis | K42: Régimen agropecuario (Decreto 31-2024) | L42: CAPACITACIÓN | M42: https://sites.google.com/capacitacionessat.page/cultura-tributariad/cursos-virtuales-sat/impuesto-al-valor-agregado-iva/principales-obligaciones-tributarias-del-r%C3%A9gimen-especial-de-contribuyente | N42: Servicio/tema general para contribuyentes
A43: Contribuyente General | B43: Todos los grupos | D43: Facturación electrónica y documentos tributarios | E43: Constancias de exención (CIVA y CAIS) | F43: Emisión Constancias de Adquisición de Insumos y Servicios -CAIS- | G43: Emitir constancias CAIS | H43: Requisitos, pasos y documentos para emitir constancias CAIS. | I43: Contribuyente General | J43: Grupos y categorías | K43: Marcada «SI» en el archivo Grupos y categorías | L43: SERVICIOS TRIBUTARIOS | M43: https://portal.sat.gob.gt/portal/emision-constancias-de-adquisicion-de-insumos-y-servicios-cais/ | N43: Servicio/tema general para contribuyentes
A44: Contribuyente General | B44: Todos los grupos | D44: Facturación electrónica y documentos tributarios | E44: Constancias de exención (CIVA y CAIS) | F44: Emisión Constancias de Exención de IVA -CIVA- | G44: Emitir constancias de exención de IVA (CIVA) | H44: Requisitos, pasos y documentos para emitir constancias de exención de IVA (CIVA). | I44: Contribuyente General | J44: Grupos y categorías | K44: Marcada «SI» en el archivo Grupos y categorías | L44: SERVICIOS TRIBUTARIOS | M44: https://portal.sat.gob.gt/portal/emision-constancias-de-exencion-de-iva-civa/ | N44: Servicio/tema general para contribuyentes
A45: Contribuyente General | B45: Todos los grupos | D45: Otros servicios al contribuyente | E45: Constancias y gestiones del RTU | F45: Requisitos de persona/empresa | G45: Requisitos para Abogados y Notarios | H45: Requisitos, listado de pasos, y casos especiales; para la inscripción/actualización, activación, confirmación de huella y Venta de Especies Fiscales para Abogados y Notarios. | I45: Contribuyente General | J45: Grupos y categorías | K45: Marcada «SI» en el archivo Grupos y categorías | L45: SERVICIOS TRIBUTARIOS | M45: https://portal.sat.gob.gt/portal/requisitos-de-personas-empresas/ | N45: Servicio/tema general para contribuyentes
A46: Contribuyente General | B46: Contribuyente General | D46: Consultas y verificadores | E46: Autorización y consulta | F46: Autorización de Máquinas en Agencia Virtual | G46: Autorizar máquinas registradoras en Agencia Virtual | H46: Requisitos, pasos y documentos para autorizar máquinas registradoras en Agencia Virtual. | J46: Análisis | K46: Máquinas registradoras | L46: SERVICIOS TRIBUTARIOS | M46: https://portal.sat.gob.gt/portal/requisitos-tramites-agencias/autorizacion-de-maquinas-en-agencia-virtual/ | N46: Servicio/tema general para contribuyentes
A47: Contribuyente General | B47: Contribuyente General | D47: Consultas y verificadores | E47: Autorización y consulta | F47: Consulta Autorización de Máquina | G47: Consultar si una máquina registradora está autorizada | H47: Servicio en línea para consultar si una máquina registradora está autorizada. | J47: Análisis | K47: Máquinas registradoras | L47: SERVICIOS TRIBUTARIOS | M47: https://portal.sat.gob.gt/portal/consulta-autorizacion-de-maquina/ | N47: Servicio/tema general para contribuyentes
A48: Contribuyente General | B48: Contribuyente General | D48: Cultura tributaria y capacitación | E48: Cursos por impuesto | F48: Regímenes para las Rentas de Actividades Lucrativas | G48: Curso: regímenes del ISR para negocios | H48: Capacitación virtual de la SAT sobre regímenes del ISR para negocios. | J48: Análisis | K48: Régimen General del IVA e ISR de actividades lucrativas | L48: CAPACITACIÓN | M48: https://sites.google.com/capacitacionessat.page/cultura-tributariad/cursos-virtuales-sat/impuesto-sobre-la-renta/reg%C3%ADmenes-para-las-rentas-de-actividades-lucrativas | N48: Servicio/tema general para contribuyentes
A49: Contribuyente General | B49: Contribuyente General | D49: Devoluciones y créditos fiscales | E49: ISR (Impuesto Sobre la Renta) | F49: Formulario Electrónico SAT-2350 (versión vigente) Solicitud de Devolución de Pagos en Exceso del ISR Anual | G49: Devolución de ISR anual pagado de más | H49: Información sobre: Devolución de ISR anual pagado de más. | J49: Análisis | K49: Devoluciones de ISR/IVA/ISO de actividades lucrativas | L49: SERVICIOS TRIBUTARIOS | M49: https://portal.sat.gob.gt/portal/requisitos-tramites-agencias/formulario-electronico-sat-2350-version-vigente-solicitud-de-pagos-en-exceso/ | N49: Servicio/tema general para contribuyentes
A50: Contribuyente General | B50: Contribuyente General | D50: Devoluciones y créditos fiscales | E50: ISR (Impuesto Sobre la Renta) | F50: Devolución o Compensación de ISR Opcional Mensual, SAT-1311 | G50: Devolución de ISR opcional mensual | H50: Información sobre: Devolución de ISR opcional mensual. | J50: Análisis | K50: Devoluciones de ISR/IVA/ISO de actividades lucrativas | L50: SERVICIOS TRIBUTARIOS | M50: https://portal.sat.gob.gt/portal/requisitos-tramites-agencias/devolucion-acreditamiento-o-compensacion-del-isr-opcional-mensual-sat-1311/ | N50: Servicio/tema general para contribuyentes
A51: Contribuyente General | B51: Contribuyente General | D51: Devoluciones y créditos fiscales | E51: ISR (Impuesto Sobre la Renta) | F51: Devolución o Compensación de Retenciones de ISR Retenido a Personas Residentes y no Residentes con Establecimiento Prmanente SAT-1331 | G51: Devolución de ISR retenido (con establecimiento permanente) | H51: Información sobre: Devolución de ISR retenido (con establecimiento permanente). | J51: Análisis | K51: Devoluciones de ISR/IVA/ISO de actividades lucrativas | L51: SERVICIOS TRIBUTARIOS | M51: https://portal.sat.gob.gt/portal/requisitos-tramites-agencias/devolucion-acreditamiento-o-compensacion-del-isr-retenido-a-personas-y-no-residentes-con-establecimiento-permanente-1331/ | N51: Servicio/tema general para contribuyentes
A52: Contribuyente General | B52: Contribuyente General | D52: Devoluciones y créditos fiscales | E52: ISR (Impuesto Sobre la Renta) | F52: Devolución o Compensación de Retenciones de ISR Retenido a Personas Residentes y no Residentes sin Establecimiento Permanente SAT-1352 | G52: Devolución de ISR retenido (sin establecimiento permanente) | H52: Información sobre: Devolución de ISR retenido (sin establecimiento permanente). | J52: Análisis | K52: Devoluciones de ISR/IVA/ISO de actividades lucrativas | L52: SERVICIOS TRIBUTARIOS | M52: https://portal.sat.gob.gt/portal/requisitos-tramites-agencias/devolucion-acreditamiento-o-compensacion-del-isr-retenido-a-personas-no-residentes-sin-establecimiento-permanente-sat-1352/ | N52: Servicio/tema general para contribuyentes
A53: Contribuyente General | B53: Contribuyente General | D53: Devoluciones y créditos fiscales | E53: ISR (Impuesto Sobre la Renta) | F53: Devolución de Retenciones de ISR por Repartición de Utilidades o Dividendos | G53: Devolución de ISR retenido por dividendos o utilidades | H53: Información sobre: Devolución de ISR retenido por dividendos o utilidades. | J53: Análisis | K53: Devoluciones de ISR/IVA/ISO de actividades lucrativas | L53: SERVICIOS TRIBUTARIOS | M53: https://portal.sat.gob.gt/portal/requisitos-tramites-agencias/devolucion-del-isr-por-reparticion-de-utilidades-o-dividendos/ | N53: Servicio/tema general para contribuyentes
A54: Contribuyente General | B54: Contribuyente General | D54: Devoluciones y créditos fiscales | E54: ISR (Impuesto Sobre la Renta) | F54: Devolución o Compensación de ISR Trimestral, SAT-1361 | G54: Devolución de ISR trimestral | H54: Información sobre: Devolución de ISR trimestral. | J54: Análisis | K54: Devoluciones de ISR/IVA/ISO de actividades lucrativas | L54: SERVICIOS TRIBUTARIOS | M54: https://portal.sat.gob.gt/portal/requisitos-tramites-agencias/devolucion-acreditamiento-o-compensacion-del-impuesto-sobre-la-rentatrimestral-sat-1361/ | N54: Servicio/tema general para contribuyentes
A55: Contribuyente General | B55: Contribuyente General | D55: Devoluciones y créditos fiscales | E55: IVA (Impuesto al Valor Agregado) | F55: Devolución o Compensación de IVA Facturas Especiales, SAT-2085 | G55: Devolución de IVA de facturas especiales | H55: Información sobre: Devolución de IVA de facturas especiales. | J55: Análisis | K55: Devoluciones de ISR/IVA/ISO de actividades lucrativas | L55: SERVICIOS TRIBUTARIOS | M55: https://portal.sat.gob.gt/portal/requisitos-tramites-agencias/devolucion-acreditamiento-o-compensacion-de-iva-facturas-especiales/ | N55: Servicio/tema general para contribuyentes
A56: Contribuyente General | B56: Contribuyente General | D56: Devoluciones y créditos fiscales | E56: IVA (Impuesto al Valor Agregado) | F56: Devolución de Retenciones del Impuesto al Valor Agregado, SAT-2219 | G56: Devolución de IVA retenido | H56: Información sobre: Devolución de IVA retenido. | J56: Análisis | K56: Devoluciones de ISR/IVA/ISO de actividades lucrativas | L56: SERVICIOS TRIBUTARIOS | M56: https://portal.sat.gob.gt/portal/requisitos-tramites-agencias/devolucion-de-retenciones-del-impuesto-al-valor-agregado-sat-2219/ | N56: Servicio/tema general para contribuyentes
A57: Contribuyente General | B57: Contribuyente General | D57: Devoluciones y créditos fiscales | E57: IVA (Impuesto al Valor Agregado) | F57: Acreditamiento en Cuenta de Remanente de Retenciones de IVA | G57: Usar el saldo a favor de retenciones de IVA | H57: Requisitos, pasos y documentos para usar el saldo a favor de retenciones de IVA. | J57: Análisis | K57: Devoluciones de ISR/IVA/ISO de actividades lucrativas | L57: SERVICIOS TRIBUTARIOS | M57: https://portal.sat.gob.gt/portal/requisitos-tramites-agencias/solicitud-de-acreditamiento-en-cuenta-de-remanente-por-retenciones-del-impuesto-al-valor-agregado/ | N57: Servicio/tema general para contribuyentes
... A94: Contribuyente General | B94: Contribuyente General | D94: Inscripción y actualización en el RTU | E94: Sociedades y empresas | F94: Inscripción de Sociedad | G94: Inscribir una sociedad o empresa | H94: Requisitos, pasos y documentos para inscribir una sociedad o empresa. | J94: Análisis | K94: Personas jurídicas y entes: Régimen General (IVA/ISR, Decreto 10-2012) | L94: SERVICIOS TRIBUTARIOS | M94: https://portal.sat.gob.gt/portal/requisitos-tramites-agencias/inscripcion-sociedades/ | N94: Servicio/tema general para contribuyentes
A95: Contribuyente General | B95: Contribuyente General | D95: Otros servicios al contribuyente | E95: Constancias y gestiones del RTU | F95: Requisitos de persona/empresa | G95: Requisitos sobre Formularios Electrónicos Solicitud Dev. C.F. Régimen Especial Electrónico y Régimen General | H95: Requisitos, listado de pasos, y casos especiales; para los formularios SAT-2125, SAT-2251 y SAT-2390. | I95: Contribuyente General: Contribuyente General | J95: Grupos y categorías | K95: Marcada «SI» en el archivo Grupos y categorías | L95: SERVICIOS TRIBUTARIOS | M95: https://portal.sat.gob.gt/portal/requisitos-de-personas-empresas/ | N95: Servicio/tema general para contribuyentes
A96: Contribuyente General | B96: Contribuyente General | D96: Otros servicios al contribuyente | E96: Libros, facturas y máquinas | F96: Anulación de Resolución de Documentos por Impresores en Agencia Virtual | G96: Anular resolución de documentos (imprentas) | H96: Requisitos, pasos y documentos para anular resolución de documentos (imprentas). | J96: Análisis | K96: Libros, documentos e imprentas | L96: SERVICIOS TRIBUTARIOS | M96: https://portal.sat.gob.gt/portal/requisitos-tramites-agencias/anulacion-de-resolucion-de-documentos-por-impresores-en-agencia-virtual/ | N96: Servicio/tema general para contribuyentes
A97: Contribuyente General | B97: Contribuyente General | D97: Otros servicios al contribuyente | E97: Libros, facturas y máquinas | F97: Autorización de Documentos para Espectáculos Públicos | G97: Autorizar documentos para espectáculos públicos | H97: Requisitos, pasos y documentos para autorizar documentos para espectáculos públicos. | J97: Análisis | K97: Libros, documentos e imprentas | L97: SERVICIOS TRIBUTARIOS | M97: https://portal.sat.gob.gt/portal/requisitos-tramites-agencias/autorizacion-de-documentos-para-espectaculos-publicos/ | N97: Servicio/tema general para contribuyentes
A98: Contribuyente General | B98: Contribuyente General | D98: Otros servicios al contribuyente | E98: Libros, facturas y máquinas | F98: Habilitación de Libros | G98: Habilitar libros contables | H98: Requisitos, pasos y documentos para habilitar libros contables. | J98: Análisis | K98: Libros, documentos e imprentas | L98: SERVICIOS TRIBUTARIOS | M98: https://portal.sat.gob.gt/portal/requisitos-tramites-agencias/habilitacion-de-libros/ | N98: Servicio/tema general para contribuyentes
A99: Contribuyente General | B99: Contribuyente General | D99: Otros servicios al contribuyente | E99: Libros, facturas y máquinas | F99: Informe de Servicios de Impresión en Agencia Virtual | G99: Informe de servicios de impresión (imprentas) | H99: Información sobre: Informe de servicios de impresión (imprentas). | J99: Análisis | K99: Libros, documentos e imprentas | L99: SERVICIOS TRIBUTARIOS | M99: https://portal.sat.gob.gt/portal/requisitos-tramites-agencias/informe-de-servicios-de-impresion-en-agencia-virtual/ | N99: Servicio/tema general para contribuyentes
A100: Contribuyente General | B100: Contribuyente General | D100: Regímenes tributarios | E100: Cambio de régimen | F100: Actualización del Impuesto Sobre la Renta, Régimen Opcional Simplificado, Opción Pago Directo | G100: Cambiar a ISR Opcional Simplificado con pago directo | H100: Requisitos, pasos y documentos para cambiar a ISR Opcional Simplificado con pago directo. | J100: Análisis | K100: Régimen General del IVA e ISR | L100: SERVICIOS TRIBUTARIOS | M100: https://portal.sat.gob.gt/portal/requisitos-tramites-agencias/actualizacion-del-impuesto-sobre-la-renta-regimen-opcional-simplificado-opcion-pago-directo/ | N100: Servicio/tema general para contribuyentes
A101: Contribuyente General | B101: Contribuyente General | D101: Regímenes tributarios | E101: Cambio de régimen | F101: Actualización Cambio de Régimen General del Impuesto al Valor Agregado a Pequeño Contribuyente | G101: Pasar de Régimen General a Pequeño Contribuyente | H101: Requisitos, pasos y documentos para pasar de Régimen General a Pequeño Contribuyente. | J101: Análisis | K101: Régimen General del IVA e ISR | L101: SERVICIOS TRIBUTARIOS | M101: https://portal.sat.gob.gt/portal/requisitos-tramites-agencias/actualizacion-cambio-de-regimen-general-del-impuesto-al-valor-agregado-a-pequeno-contribuyente/ | N101: Servicio/tema general para contribuyentes
A102: Contribuyente General | B102: Contribuyente General | D102: Regímenes tributarios | E102: ISR para negocios | F102: Régimen Opcional Simplificado sobre Ingresos de Actividades Lucrativas | G102: Curso: Régimen Opcional Simplificado | H102: Capacitación virtual de la SAT sobre Régimen Opcional Simplificado. | J102: Análisis | K102: Régimen General del IVA e ISR | L102: CAPACITACIÓN | M102: https://sites.google.com/capacitacionessat.page/cultura-tributariad/cursos-virtuales-sat/impuesto-sobre-la-renta-isr/5-r%C3%A9gimen-sobre-los-ingresos-de-actividades-lucrativas | N102: Servicio/tema general para contribuyentes
A103: Contribuyente General | B103: Contribuyente General | D103: Regímenes tributarios | E103: ISR para negocios | F103: Costos y gastos deducibles. Régimen sobre las utilidades de actividades lucrativas | G103: Curso: costos y gastos deducibles (régimen sobre utilidades) | H103: Capacitación virtual de la SAT sobre costos y gastos deducibles (régimen sobre utilidades). | J103: Análisis | K103: Régimen General del IVA e ISR | L103: CAPACITACIÓN | M103: https://sites.google.com/capacitacionessat.page/cultura-tributariad/cursos-virtuales-sat/impuesto-sobre-la-renta-isr/14-costos-y-gastos-deducibles-r%C3%A9gimen-sobre-las-utilidades-de-actividades | N103: Servicio/tema general para contribuyentes
A104: Contribuyente General | B104: Contribuyente General | D104: Regímenes tributarios | E104: ISR para negocios | F104: Régimen sobre las Utilidades de Actividades Lucrativas | G104: Curso: régimen sobre las utilidades | H104: Capacitación virtual de la SAT sobre régimen sobre las utilidades. | J104: Análisis | K104: Régimen General del IVA e ISR | L104: CAPACITACIÓN | M104: https://sites.google.com/capacitacionessat.page/cultura-tributariad/cursos-virtuales-sat/impuesto-sobre-la-renta-isr/12-r%C3%A9gimen-sobre-utilidades-de-rentas-de-actividades-lucrativa | N104: Servicio/tema general para contribuyentes
A105: Contribuyente General | B105: Contribuyente General | D105: Regímenes tributarios | E105: Régimen General del IVA | F105: Régimen General del IVA | G105: Curso: Régimen General del IVA | H105: Capacitación virtual de la SAT sobre Régimen General del IVA. | J105: Análisis | K105: Régimen General del IVA e ISR | L105: CAPACITACIÓN | M105: https://sites.google.com/capacitacionessat.page/cultura-tributariad/cursos-virtuales-sat/impuesto-al-valor-agregado/r%C3%A9gimen-general-del-iva | N105: Servicio/tema general para contribuyentes
A106: Contribuyente General | B106: Contribuyente General | D106: Regímenes tributarios | E106: Régimen General del IVA | F106: Principales errores e inconsistencias detectadas en la declaración mensual del IVA, régimen general | G106: Curso: errores comunes en la declaración mensual del IVA | H106: Capacitación virtual de la SAT sobre errores comunes en la declaración mensual del IVA. | J106: Análisis | K106: Régimen General del IVA e ISR | L106: CAPACITACIÓN | M106: https://sites.google.com/capacitacionessat.page/cultura-tributariad/cursos-virtuales-sat/impuesto-al-valor-agregado-iva/principales-errores-e-inconsistencias-detectadas-en-la-declaraci%C3%B3n-mensual | N106: Servicio/tema general para contribuyentes
A107: Contribuyente General | B107: Contribuyente General | D107: Regímenes tributarios | E107: Régimen General del IVA | F107: Régimen general del IVA (Principales obligaciones tributarias) | G107: Curso: obligaciones del Régimen General del IVA | H107: Capacitación virtual de la SAT sobre obligaciones del Régimen General del IVA. | J107: Análisis | K107: Régimen General del IVA e ISR | L107: CAPACITACIÓN | M107: https://sites.google.com/capacitacionessat.page/cultura-tributariad/cursos-virtuales-sat/impuesto-al-valor-agregado-iva/r%C3%A9gimen-general-del-iva-principales-obligaciones-tributarias | N107: Servicio/tema general para contribuyentes
... A110: Contribuyentes Especiales | B110: Todos los grupos | D110: Cultura tributaria y capacitación | E110: Cursos por impuesto | F110: Agentes de retención del ISR | G110: Curso: agentes de retención del ISR | H110: Capacitación virtual de la SAT sobre agentes de retención del ISR. | J110: Análisis | K110: Agentes de retención | L110: CAPACITACIÓN | M110: https://sites.google.com/capacitacionessat.page/cultura-tributariad/cursos-virtuales-sat/impuesto-sobre-la-renta-isr/21-agentes-de-retenci%C3%B3n-de-isr | N110: Servicio/tema general para contribuyentes
A111: Contribuyentes Especiales | B111: Todos los grupos | D111: Cultura tributaria y capacitación | E111: Preguntas frecuentes | F111: Contribuyentes Especiales | G111: Preguntas frecuentes: contribuyentes especiales | H111: Respuestas a las preguntas más comunes sobre contribuyentes especiales. | I111: Contribuyentes Especiales | J111: Grupos y categorías | K111: Marcada «SI» en el archivo Grupos y categorías | L111: CAPACITACIÓN | M111: https://portal.sat.gob.gt/portal/preguntas-frecuentes/contribuyentes-especiales/ | N111: Servicio/tema general para contribuyentes
A112: Contribuyentes Especiales | B112: Todos los grupos | D112: Declaraciones, pagos y solvencias | E112: Declaraciones | F112: Informe Electrónico de Compras y Ventas | G112: Informe electrónico de compras y ventas | H112: Información sobre: Informe electrónico de compras y ventas. | J112: Análisis | K112: Informe electrónico de compras y ventas | L112: SERVICIOS TRIBUTARIOS | M112: https://portal.sat.gob.gt/portal/informe-electronico-de-compras-y-venta/ | N112: Servicio/tema general para contribuyentes
A113: Contribuyentes Especiales | B113: Todos los grupos | D113: Gobierno y gestión institucional | E113: Información de referencia | F113: Tasas e Intereses | G113: Tasas e intereses vigentes | H113: Información sobre: Tasas e intereses vigentes. | I113: Contribuyentes Especiales | J113: Grupos y categorías | K113: Marcada «SI» en el archivo Grupos y categorías | L113: INSTITUCIONAL | M113: https://portal.sat.gob.gt/portal/tasas-e-intereses/ | N113: Contenido institucional/corporativo general (excluido por decisión del usuario)
A114: Contribuyentes Especiales | B114: Todos los grupos | D114: Inscripción y actualización en el RTU | E114: Registros especiales | F114: Solicitud de Inscripción como Agente de Retención del IVA | G114: Solicitar ser agente de retención del IVA | H114: Requisitos, pasos y documentos para solicitar ser agente de retención del IVA. | J114: Análisis | K114: Agentes de retención del IVA, designados en su mayoría entre contribuyentes especiales | L114: SERVICIOS TRIBUTARIOS | M114: https://portal.sat.gob.gt/portal/requisitos-tramites-agencias/solicitud-de-inscripcion-como-agente-de-retencion-del-iva/ | N114: Servicio/tema general para contribuyentes
A115: Contribuyentes Especiales | B115: Todos los grupos | D115: Otros servicios al contribuyente | E115: Constancias y gestiones del RTU | F115: RTU Digital | G115: RTU Digital: gestiones de tu registro en línea | H115: Información sobre: RTU Digital: gestiones de tu registro en línea. | I115: Contribuyentes Especiales | J115: Grupos y categorías | K115: Marcada «SI» en el archivo Grupos y categorías | L115: SERVICIOS TRIBUTARIOS | M115: https://portal.sat.gob.gt/portal/rtu-digital/ | N115: Servicio/tema general para contribuyentes
A116: Contribuyentes Especiales | B116: Todos los grupos | D116: Otros servicios al contribuyente | E116: Constancias y gestiones del RTU | F116: Requisitos de persona/empresa | G116: Requisitos para despacho de Distintivos | H116: Requisitos para despacho de distintivos de control de productos importados a los fabricantes o importadores domiciliados en el país y a las personas individuales y jurídicas que no sean fabricantes ni importadores | I116: Contribuyentes Especiales | J116: Grupos y categorías | K116: Marcada «SI» en el archivo Grupos y categorías | L116: SERVICIOS TRIBUTARIOS | M116: https://portal.sat.gob.gt/portal/requisitos-de-personas-empresas/ | N116: Servicio/tema general para contribuyentes
A117: Contribuyentes Especiales | B117: Todos los grupos | D117: Otros servicios al contribuyente | E117: Constancias y gestiones del RTU | F117: Requisitos de persona/empresa | G117: Requisitos sobre Trámites en Gerencias Especiales | H117: Requisitos para el registro y emisión de autorización de la SAT al impuesto a la distribución de petróleo crudo y combustible derivados del petróleo. | I117: Contribuyentes Especiales | J117: Grupos y categorías | K117: Marcada «SI» en el archivo Grupos y categorías | L117: SERVICIOS TRIBUTARIOS | M117: https://portal.sat.gob.gt/portal/requisitos-de-personas-empresas/ | N117: Servicio/tema general para contribuyentes
A118: Contribuyentes Especiales | B118: Todos los grupos | D118: Otros servicios al contribuyente | E118: Sistemas de retención | F118: Agentes de Retención IVA | G118: Información para agentes de retención del IVA | H118: Información sobre: Información para agentes de retención del IVA. | J118: Análisis | K118: Agentes de retención de IVA e ISR | L118: SERVICIOS TRIBUTARIOS | M118: https://portal.sat.gob.gt/portal/project/agentes-de-retencion-iva-2/ | N118: Servicio/tema general para contribuyentes
A119: Contribuyentes Especiales | B119: Todos los grupos | D119: Otros servicios al contribuyente | E119: Sistemas de retención | F119: Sistema Retenciones Web -ISR- | G119: Sistema de retenciones del ISR | H119: Información sobre: Sistema de retenciones del ISR. | I119: Contribuyentes Especiales | J119: Grupos y categorías | K119: Marcada «SI» en el archivo Grupos y categorías | L119: SERVICIOS TRIBUTARIOS | M119: https://portal.sat.gob.gt/portal/sistemas-web/retencioneswebisr/ | N119: Servicio/tema general para contribuyentes
A120: Contribuyentes Especiales | B120: Todos los grupos | D120: Agregada desde «Grupos y categorías» | G120: AsisteLight | H120: Información relacionada con la herramienta web, descarga y forma de uso. | I120: Contribuyentes Especiales | J120: Grupos y categorías | K120: Marcada «SI» en el archivo Grupos y categorías | M120: https://portal.sat.gob.gt/portal/biblioteca-en-linea-sat/software/asistelight/
A121: Contribuyentes Especiales | B121: Todos los grupos | D121: Agregada desde «Grupos y categorías» | G121: Precios de Transferencia | H121: Información relacionada a la declaración jurada anual del impuesto sobre la renta sobre partes relacionadas, guías técnicas y anexos. | I121: Contribuyentes Especiales | J121: Grupos y categorías | K121: Marcada «SI» en el archivo Grupos y categorías | M121: https://portal.sat.gob.gt/portal/precios-de-transferencia/
A122: Contribuyentes Especiales | B122: Grandes | D122: Devoluciones y créditos fiscales | E122: Otros impuestos | F122: Devolución o Compensación del Impuesto a la Distribución de Bebidas Alcohólicas y Otras, SAT-3035 | G122: Devolución del impuesto a bebidas alcohólicas | H122: Información sobre: Devolución del impuesto a bebidas alcohólicas. | J122: Análisis | K122: Fabricantes de bebidas alcohólicas | L122: SERVICIOS TRIBUTARIOS | M122: https://portal.sat.gob.gt/portal/requisitos-tramites-agencias/devolucion-acreditamiento-o-compensacion-del-impuesto-de-bebidas-alcoholicas/ | N122: Servicio/tema general para contribuyentes
A123: Contribuyentes Especiales | B123: Grandes | D123: Facturación electrónica y documentos tributarios | E123: Guías para llenar formularios | F123: Llenado del formulario de declaración anual del ISR, para contribuyentes que desarrollan actividades de transporte aéreo internacional | G123: Cómo llenar la declaración anual de ISR (transporte aéreo internacional) | H123: Guía paso a paso: cómo llenar la declaración anual de ISR (transporte aéreo internacional). | J123: Análisis | K123: Declaración anual de transporte aéreo internacional | L123: CAPACITACIÓN | M123: https://sites.google.com/capacitacionessat.page/eventosenvivo/p%C3%A1gina-principal/llenado-del-formulario-de-declaraci%C3%B3n-anual-del-isr-para-contribuyentes-qu | N123: Servicio/tema general para contribuyentes
A124: Contribuyentes Especiales | B124: Grandes | D124: Otros servicios al contribuyente | E124: Alcohol y combustibles | F124: Autorización de Fabricas de Alcohol y Bebidas Alcohólicas | G124: Autorizar una fábrica de alcohol o bebidas alcohólicas | H124: Requisitos, pasos y documentos para autorizar una fábrica de alcohol o bebidas alcohólicas. | J124: Análisis | K124: Fábricas de alcohol y bebidas alcohólicas | L124: SERVICIOS TRIBUTARIOS | M124: https://portal.sat.gob.gt/portal/requisitos-tramites-agencias/fabricas-de-alcoholes-y-bebidas-alcoholicas-y-fermentadas/ | N124: Servicio/tema general para contribuyentes
A125: Contribuyentes Especiales | B125: Grandes | D125: Otros servicios al contribuyente | E125: Alcohol y combustibles | F125: Solicitud de Alcoholes, Bebidas Alcohólicas y Fermentadas | G125: Solicitud para alcoholes y bebidas alcohólicas o fermentadas | H125: Información sobre: Solicitud para alcoholes y bebidas alcohólicas o fermentadas. | J125: Análisis | K125: Fábricas de alcohol y bebidas alcohólicas | L125: SERVICIOS TRIBUTARIOS | M125: https://portal.sat.gob.gt/portal/requisitos-tramites-agencias/solicitud-de-alcoholes-bebidas-alcoholicas-y-fermentadas/ | N125: Servicio/tema general para contribuyentes
A126: Contribuyentes Especiales | B126: Rep. Legales | D126: Inscripción y actualización en el RTU | E126: Representante legal | F126: Cancelación de Representante Legal solicitado por persona individual que finalizó relación laboral con la entidad | G126: Dejar de ser representante legal al terminar tu relación laboral | H126: Requisitos, pasos y documentos para dejar de ser representante legal al terminar tu relación laboral. | J126: Análisis | K126: Representación de personas jurídicas | L126: SERVICIOS TRIBUTARIOS | M126: https://portal.sat.gob.gt/portal/requisitos-tramites-agencias/requisitos-de-cancelacion-de-rl-solicitado-por-pi-que-finalizo-relacion-laboral/ | N126: Servicio/tema general para contribuyentes
A127: Contribuyentes Especiales | B127: Rep. Legales | D127: Inscripción y actualización en el RTU | E127: Representante legal | F127: Actualización o Cancelación de Representante Legal | G127: Nombrar, cambiar o cancelar al representante legal | H127: Información sobre: Nombrar, cambiar o cancelar al representante legal. | J127: Análisis | K127: Representación de personas jurídicas | L127: SERVICIOS TRIBUTARIOS | M127: https://portal.sat.gob.gt/portal/requisitos-tramites-agencias/actualizacion-o-cancelacion-de-representante-legal/ | N127: Servicio/tema general para contribuyentes
A128: Trámites comunes | B128: Todos los grupos | D128: Atención, quejas y denuncias | E128: Chat | F128: Chat en línea | G128: Chatear con la SAT | H128: Requisitos, pasos y documentos para chatear con la SAT. | I128: Varias categorías de contribuyentes | J128: Análisis | K128: Atención, quejas y denuncias | L128: CONTÁCTANOS | M128: https://portal.sat.gob.gt/portal/soporte-chat/ | N128: Servicio/tema general para contribuyentes
A129: Trámites comunes | B129: Todos los grupos | D129: Atención, quejas y denuncias | E129: Información pública | F129: Solicitud de Información Pública | G129: Solicitar información pública | H129: Requisitos, pasos y documentos para solicitar información pública. | I129: Varias categorías de contribuyentes | J129: Análisis | K129: Atención, quejas y denuncias | L129: CONTÁCTANOS | M129: https://portal.sat.gob.gt/portal/solicitud-informacion-publica/ | N129: Servicio/tema general para contribuyentes
A130: Trámites comunes | B130: Todos los grupos | D130: Atención, quejas y denuncias | E130: Quejas y denuncias | F130: Denuncias Tributarias | G130: Denunciar a quien no da factura | H130: Requisitos, pasos y documentos para denunciar a quien no da factura. | I130: Varias categorías de contribuyentes | J130: Análisis | K130: Atención, quejas y denuncias | L130: CONTÁCTANOS | M130: https://portal.sat.gob.gt/portal/contacto/denuncias-no-facturacion/ | N130: Servicio/tema general para contribuyentes
A131: Trámites comunes | B131: Todos los grupos | D131: Atención, quejas y denuncias | E131: Quejas y denuncias | F131: Corrupción e incumplimiento ético | G131: Denunciar corrupción o falta de ética | H131: Requisitos, pasos y documentos para denunciar corrupción o falta de ética. | I131: Varias categorías de contribuyentes | J131: Análisis | K131: Atención, quejas y denuncias | L131: CONTÁCTANOS | M131: https://portal.sat.gob.gt/portal/contacto/denuncias-por-corrupcion/ | N131: Servicio/tema general para contribuyentes
A132: Trámites comunes | B132: Todos los grupos | D132: Atención, quejas y denuncias | E132: Quejas y denuncias | F132: Quejas por mal servicio | G132: Presentar una queja por mal servicio | H132: Requisitos, pasos y documentos para presentar una queja por mal servicio. | I132: Varias categorías de contribuyentes | J132: Análisis | K132: Atención, quejas y denuncias | L132: CONTÁCTANOS | M132: https://portal.sat.gob.gt/portal/contacto/quejas-por-mal-servicio-o-servicio-no-conforme/ | N132: Servicio/tema general para contribuyentes
A133: Trámites comunes | B133: Todos los grupos | D133: Capacitación y orientación aduanera | E133: Legislación aduanera | F133: Legislación Aduanera | G133: Leyes aduaneras | H133: Información sobre: Leyes aduaneras. | I133: Contribuyente General, Contribuyentes Especiales | J133: Grupos y categorías | K133: Marcada «SI» en el archivo Grupos y categorías | L133: CAPACITACIÓN | M133: https://portal.sat.gob.gt/portal/biblioteca-en-linea-sat/legislacion-aduanera/ | N133: Coincide con palabra clave de comercio exterior/aduanas
A134: Trámites comunes | B134: Todos los grupos | D134: Consultas y verificadores | E134: Agencia Virtual | F134: Solicitud de Usuario Agencia Virtual | G134: Solicitar usuario de Agencia Virtual | H134: Requisitos, pasos y documentos para solicitar usuario de Agencia Virtual. | I134: Varias categorías de contribuyentes | J134: Análisis | K134: Consultas y verificadores | L134: SERVICIOS TRIBUTARIOS | M134: https://portal.sat.gob.gt/portal/solicitud-usuario-agencia-virtual/ | N134: Servicio/tema general para contribuyentes
A135: Trámites comunes | B135: Todos los grupos | D135: Consultas y verificadores | E135: Agencia Virtual | F135: Consulta Estado de Gestión de Agencia Virtual | G135: Ver el estado de tu gestión en Agencia Virtual | H135: Servicio en línea para ver el estado de tu gestión en Agencia Virtual. | I135: NIT sin Obligaciones, Contribuyente General | J135: Grupos y categorías | K135: Marcada «SI» en el archivo Grupos y categorías | L135: SERVICIOS TRIBUTARIOS | M135: https://portal.sat.gob.gt/portal/consulta-de-gestion-del-contribuyente/ | N135: Servicio/tema general para contribuyentes
A136: Trámites comunes | B136: Todos los grupos | D136: Consultas y verificadores | E136: Citas y quejas | F136: Consulta estado de cita | G136: Ver el estado de tu cita | H136: Servicio en línea para ver el estado de tu cita. | I136: Pequeños Contribuyentes, Contribuyente General | J136: Grupos y categorías | K136: Marcada «SI» en el archivo Grupos y categorías | L136: SERVICIOS TRIBUTARIOS | M136: https://portal.sat.gob.gt/portal/consulta-estado-de-cita/ | N136: Servicio/tema general para contribuyentes
A137: Trámites comunes | B137: Todos los grupos | D137: Consultas y verificadores | E137: Citas y quejas | F137: Consultar estado de la queja | G137: Ver el estado de tu queja | H137: Servicio en línea para ver el estado de tu queja. | I137: Varias categorías de contribuyentes | J137: Análisis | K137: Consultas y verificadores | L137: CONTÁCTANOS | M137: https://portal.sat.gob.gt/portal/contacto/consulta-estado-de-queja/ | N137: Servicio/tema general para contribuyentes
A138: Trámites comunes | B138: Todos los grupos | D138: Consultas y verificadores | E138: NIT y RTU | F138: Actualización de Datos | G138: Actualizar tus datos | H138: Requisitos, pasos y documentos para actualizar tus datos. | I138: Varias categorías de contribuyentes | J138: Análisis | K138: Consultas y verificadores | L138: SERVICIOS TRIBUTARIOS | M138: https://portal.sat.gob.gt/portal/project/actualizacion-de-datos/ | N138: Servicio/tema general para contribuyentes
A139: Trámites comunes | B139: Todos los grupos | D139: Consultas y verificadores | E139: NIT y RTU | F139: Consulta CUI / NIT | G139: Consultar tu NIT con tu DPI (CUI) | H139: Servicio en línea para consultar tu NIT con tu DPI (CUI). | I139: Varias categorías de contribuyentes | J139: Análisis | K139: Consultas y verificadores | L139: SERVICIOS TRIBUTARIOS | M139: https://portal.sat.gob.gt/portal/consulta-cui-nit/ | N139: Servicio/tema general para contribuyentes
... A357: Trámites comunes | B357: Todos los grupos | D357: Vehículos (como propietario) | E357: Título y tarjeta de circulación | F357: Reposición de Tarjeta de Circulación | G357: Reponer la tarjeta de circulación | H357: Requisitos, pasos y documentos para reponer la tarjeta de circulación. | I357: Varias categorías de contribuyentes | J357: Análisis | K357: Trámites de vehículos que usan todas las categorías | L357: SERVICIOS TRIBUTARIOS | M357: https://portal.sat.gob.gt/portal/requisitos-tramites-agencias/reposicion-de-tarjeta-de-circulacion-con-formulario-electronico-sat-8933/ | N357: Servicio/tema general para contribuyentes

Sheet Operadores de comercio exterior
A1: Operadores de comercio exterior
A2: Importadores, exportadores y auxiliares de la función pública aduanera que intervienen en operaciones de comercio exterior. Orden: Categoría › Grupo › Tema › Página. «Todos los grupos» = la usan todos los grupos de la categoría. «Trámites comunes» = la usan varias categorías.
A4: Categoría | B4: Grupo | C4: Tema | D4: Subtema | E4: Página / Trámite (nombre actual) | F4: Nombre de trámite sugerido | G4: Descripción de la página | H4: Usado por (según Grupos y categorías) | I4: Origen de la clasificación | J4: Motivo / referencia | K4: Sección actual del menú | L4: URL | M4: Nota / Revisar
A5: Importadores y Exportadores | B5: Todos los grupos | C5: Exportación | D5: Declaraciones y sanciones | E5: Importación y Exportación Menor con Declaración de Oficio | F5: Importación y exportación menor con declaración de oficio | G5: Información sobre: Importación y exportación menor con declaración de oficio. | I5: Análisis | J5: Aplica a importación y exportación | K5: ADUANAS | L5: https://portal.sat.gob.gt/portal/requisitos-tramites-aduanas/importacion-y-exportacion-menor-con-declaracion-de-oficio/ | M5: Bajo menú Aduanas
A6: Importadores y Exportadores | B6: Todos los grupos | C6: Exportación | D6: Declaraciones y sanciones | E6: Sanciones Aplicables a la Importación, Exportación o Tránsito | F6: Sanciones en importación, exportación o tránsito | G6: Información sobre: Sanciones en importación, exportación o tránsito. | I6: Análisis | J6: Aplica a importación y exportación | K6: ADUANAS | L6: https://portal.sat.gob.gt/portal/sanciones-aplicables-a-la-importacion-exportacion-o-transito/ | M6: Bajo menú Aduanas
A7: Importadores y Exportadores | B7: Todos los grupos | C7: Gestiones y consultas aduaneras | D7: Aranceles y permisos | E7: Catálogo de Permisos No arancelarios. | F7: Catálogo de permisos no arancelarios | G7: Información sobre: Catálogo de permisos no arancelarios. | I7: Análisis | J7: Declaración y clasificación de mercancías | K7: ADUANAS | L7: https://portal.sat.gob.gt/portal/catalogo-de-permisos-no-arancelarios/ | M7: Bajo menú Aduanas
A8: Importadores y Exportadores | B8: Todos los grupos | C8: Gestiones y consultas aduaneras | D8: Aranceles y permisos | E8: Arancel Integrado | F8: Consultar el arancel integrado | G8: Servicio en línea para consultar el arancel integrado. | I8: Análisis | J8: Declaración y clasificación de mercancías | K8: ADUANAS | L8: https://portal.sat.gob.gt/portal/arancel-integrado/ | M8: Bajo menú Aduanas
A9: Importadores y Exportadores | B9: Todos los grupos | C9: Gestiones y consultas aduaneras | D9: Aranceles y permisos | E9: Criterio de Clasificación Arancelaria No. 01-2002, Partida Arancelaria 4011 | F9: Criterio de clasificación arancelaria 01-2002 | G9: Información sobre: Criterio de clasificación arancelaria 01-2002. | I9: Análisis | J9: Declaración y clasificación de mercancías | K9: ADUANAS | L9: https://portal.sat.gob.gt/portal/valoracion-clasificacion-y-origen-de-la-mercancia/criterio-de-clasificacion-arancelaria-no-01-2002-partida-arancelaria-4011/ | M9: Bajo menú Aduanas
A10: Importadores y Exportadores | B10: Todos los grupos | C10: Gestiones y consultas aduaneras | D10: Aranceles y permisos | E10: Notas explicativas del SAC | F10: Notas explicativas del SAC | G10: Información sobre: Notas explicativas del SAC. | I10: Análisis | J10: Declaración y clasificación de mercancías | K10: ADUANAS | L10: https://portal.sat.gob.gt/portal/aduanas/notas-explicativas-del-sistema-armonizado/ | M10: Bajo menú Aduanas
A11: Importadores y Exportadores | B11: Todos los grupos | C11: Gestiones y consultas aduaneras | D11: Aranceles y permisos | E11: Sistema Arancelario Centroamericano (SAC) | F11: Sistema Arancelario Centroamericano (SAC) | G11: Información sobre: Sistema Arancelario Centroamericano (SAC). | I11: Análisis | J11: Declaración y clasificación de mercancías | K11: ADUANAS | L11: https://portal.sat.gob.gt/portal/valoracion-clasificacion-y-origen-de-la-mercancia/sistema-arancelario-centroamericano-sac/ | M11: Bajo menú Aduanas
A12: Importadores y Exportadores | B12: Todos los grupos | C12: Gestiones y consultas aduaneras | D12: Consultas de declaraciones | E12: Consultas de FAUCAS/DUCA F | F12: Consultar FAUCA / DUCA-F | G12: Servicio en línea para consultar FAUCA / DUCA-F. | I12: Análisis | J12: Declaración y clasificación de mercancías | K12: ADUANAS | L12: https://portal.sat.gob.gt/portal/consultas-de-faucas-duca-f/ | M12: Bajo menú Aduanas
A13: Importadores y Exportadores | B13: Todos los grupos | C13: Gestiones y consultas aduaneras | D13: Consultas de declaraciones | E13: Consulta de manifiestos/ Documentos de transporte pantalla externa/ Unión Aduanera Guatemala-Honduras | F13: Consultar manifiestos de la Unión Aduanera | G13: Servicio en línea para consultar manifiestos de la Unión Aduanera. | I13: Análisis | J13: Declaración y clasificación de mercancías | K13: ADUANAS | L13: https://portal.sat.gob.gt/portal/consulta-de-manifiestos-documentos-de-transporte-pantalla-externa-union-aduanera-guatemala-honduras/ | M13: Bajo menú Aduanas
A14: Importadores y Exportadores | B14: Todos los grupos | C14: Gestiones y consultas aduaneras | D14: Consultas de declaraciones | E14: Consulta Pública Retención/Liberación | F14: Consultar mercancías retenidas o liberadas | G14: Servicio en línea para consultar mercancías retenidas o liberadas. | I14: Análisis | J14: Declaración y clasificación de mercancías | K14: ADUANAS | L14: https://portal.sat.gob.gt/portal/consulta-publica-retencion-liberacion/ | M14: Bajo menú Aduanas
A15: Importadores y Exportadores | B15: Todos los grupos | C15: Gestiones y consultas aduaneras | D15: Consultas de declaraciones | E15: Consultas Pago DUCA-F país Destino | F15: Consultar pago de DUCA-F en país de destino | G15: Servicio en línea para consultar pago de DUCA-F en país de destino. | I15: Análisis | J15: Declaración y clasificación de mercancías | K15: ADUANAS | L15: https://portal.sat.gob.gt/portal/consultas-pago-duca-f-pais-destino/ | M15: Bajo menú Aduanas
A16: Importadores y Exportadores | B16: Todos los grupos | C16: Gestiones y consultas aduaneras | D16: Consultas de declaraciones | E16: Consultas Declaración de Mercancías | F16: Consultar una declaración de mercancías | G16: Servicio en línea para consultar una declaración de mercancías. | I16: Análisis | J16: Declaración y clasificación de mercancías | K16: ADUANAS | L16: https://portal.sat.gob.gt/portal/consulta-declaracion-unica-aduanera/ | M16: Bajo menú Aduanas
... A22: Importadores y Exportadores | B22: Todos los grupos | C22: Gestiones y consultas aduaneras | D22: Declaraciones (DUA / DUCA) | E22: Presentación de la Declaración de Mercancías (DUA/FAUCA/DUT) para el proceso de análisis de riesgo | F22: Presentar la declaración para análisis de riesgo | G22: Requisitos, pasos y documentos para presentar la declaración para análisis de riesgo. | I22: Análisis | J22: Declaración y clasificación de mercancías | K22: ADUANAS | L22: https://portal.sat.gob.gt/portal/requisitos-tramites-aduanas/presentacion-de-la-declaracion-de-mercancias-dua-fauca-dut-para-el-proceso-de-analisis-de-riesgo/ | M22: Bajo menú Aduanas
A23: Importadores y Exportadores | B23: Todos los grupos | C23: Gestiones y consultas aduaneras | D23: Declaraciones (DUA / DUCA) | E23: Declaración de mercancías | F23: Programa de Modernización Integral Aduanera | G23: Información sobre el proceso de solicitud, colocación y funcionamiento del marchamo electrónico, inventario de áreas de activación y desactivación y entidades prestadoras del servicio autorizadas. | H23: Importadores y Exportadores | I23: Grupos y categorías | J23: Marcada «SI» en el archivo Grupos y categorías | K23: ADUANAS | L23: https://portal.sat.gob.gt/portal/procedimientos-aduanas/#1555105635499-a4507e58-10e9 | M23: Bajo menú Aduanas
A24: Importadores y Exportadores | B24: Todos los grupos | C24: Gestiones y consultas aduaneras | D24: Requisitos, recursos y sistemas | E24: Recursos Aduaneros | F24: Recursos aduaneros (impugnaciones) | G24: Información sobre: Recursos aduaneros (impugnaciones). | I24: Análisis | J24: Recursos y mercancías en abandono | K24: ADUANAS | L24: https://portal.sat.gob.gt/portal/recursos-aduaneros/ | M24: Bajo menú Aduanas
A25: Importadores y Exportadores | B25: Todos los grupos | C25: Gestiones y consultas aduaneras | D25: Requisitos, recursos y sistemas | E25: Rescate de Mercancías Caídas en Abandono | F25: Rescatar mercancías en abandono | G25: Requisitos, pasos y documentos para rescatar mercancías en abandono. | I25: Análisis | J25: Recursos y mercancías en abandono | K25: ADUANAS | L25: https://portal.sat.gob.gt/portal/requisitos-tramites-aduanas/rescate-de-mercancias-caidas-en-abandono/ | M25: Bajo menú Aduanas
A26: Importadores y Exportadores | B26: Todos los grupos | C26: Inscripción y actualización en el RTU | D26: Actualizar tus datos | E26: Actualización de Datos, por medio de Agencia Virtual | F26: Actualizar tus datos en Agencia Virtual | G26: Requisitos, pasos y documentos para actualizar tus datos en Agencia Virtual. | H26: Importadores y Exportadores | I26: Grupos y categorías | J26: Marcada «SI» en el archivo Grupos y categorías | K26: SERVICIOS TRIBUTARIOS | L26: https://farm3.sat.gob.gt/menu/login.jsf | M26: Servicio/tema general para contribuyentes
A27: Importadores y Exportadores | B27: Importadores | C27: Capacitación y orientación aduanera | D27: Cursos | E27: Sistema de Franquicias Electrónicas | F27: Curso: sistema de franquicias electrónicas | G27: Capacitación virtual de la SAT sobre sistema de franquicias electrónicas. | I27: Análisis | J27: Franquicias | K27: CAPACITACIÓN | L27: https://sites.google.com/capacitacionessat.page/eventosenvivo/p%C3%A1gina-principal/sistema-de-franquicias-electr%C3%B3nicas | M27: Coincide con palabra clave de comercio exterior/aduanas
A28: Importadores y Exportadores | B28: Importadores | C28: Gestiones y consultas aduaneras | D28: Declaraciones (DUA / DUCA) | E28: Declaración de mercancías | F28: Sistema de Franquicias Electrónicas | G28: Información sobre documentación técnica de orientación al usuario externo para solicitudes de Franquicia Electrónica y videos informativos. | H28: Importadores y Exportadores: Importadores, OEA | I28: Grupos y categorías | J28: Marcada «SI» en el archivo Grupos y categorías | K28: ADUANAS | L28: https://portal.sat.gob.gt/portal/procedimientos-aduanas/#1555105635499-a4507e58-10e9 | M28: Bajo menú Aduanas
A29: Importadores y Exportadores | B29: Importadores | C29: Gestiones y consultas aduaneras | D29: Requisitos, recursos y sistemas | E29: Requisitos Gestiones en Aduanas | F29: Requisitos sobre documentos para Importación y Admisión Temporal | G29: Información y requisitos sobre recepción de seguro de caución de importacion y admisión temporal, presentación de mercancia de importación y admisiones temporales para cargos y fianzas y requisitos para la importación temporal de vehículos de turismo. | H29: Importadores y Exportadores: Importadores, OEA | I29: Grupos y categorías | J29: Marcada «SI» en el archivo Grupos y categorías | K29: ADUANAS | L29: https://portal.sat.gob.gt/portal/requisitos-de-aduanas/ | M29: Bajo menú Aduanas
A30: Importadores y Exportadores | B30: Importadores | C30: Importación | D30: Compras en el extranjero | E30: Pasos Previos a tu Importacion de Mercacias Via Aerea | F30: Pasos antes de importar por vía aérea | G30: Información sobre: Pasos antes de importar por vía aérea. | I30: Análisis | J30: Importación de mercancías y vehículos | K30: ADUANAS | L30: https://portal.sat.gob.gt/portal/programa-miad/componente-procesos-2/#1623281274865-df599d08-4b3c | M30: Bajo menú Aduanas
A31: Importadores y Exportadores | B31: Importadores | C31: Importación | D31: Compras en el extranjero | E31: Consideraciones para hacer tu envio via Aerea | F31: Qué considerar al enviar por vía aérea | G31: Información general: Qué considerar al enviar por vía aérea | I31: Análisis | J31: Importación de mercancías y vehículos | K31: ADUANAS | L31: https://portal.sat.gob.gt/portal/programa-miad/componente-procesos-2/#1623281275085-8c3227fc-5354 | M31: Bajo menú Aduanas
A32: Importadores y Exportadores | B32: Importadores | C32: Importación | D32: Compras en el extranjero | E32: Consideraciones para hacer tu Compra | F32: Qué considerar antes de comprar en el extranjero | G32: Información general: Qué considerar antes de comprar en el extranjero | I32: Análisis | J32: Importación de mercancías y vehículos | K32: ADUANAS | L32: https://portal.sat.gob.gt/portal/programa-miad/componente-procesos-2/#1623281275316-efbcfcd7-9f48 | M32: Bajo menú Aduanas
A33: Importadores y Exportadores | B33: Importadores | C33: Importación | D33: Importación de vehículos | E33: Alza de importación de vehículos | F33: Alza e importación de vehículos | G33: Información sobre: Alza e importación de vehículos. | I33: Análisis | J33: Importación de mercancías y vehículos | K33: ADUANAS | L33: https://portal.sat.gob.gt/portal/alza-e-importacion-vehiculos/#1510763502627-ec3a24b4-76f4 | M33: Bajo menú Aduanas
A34: Importadores y Exportadores | B34: Importadores | C34: Importación | D34: Importación de vehículos | E34: Comprobación del valor en la importación de vehículos automotores terrestres usados | F34: Comprobar el valor de un vehículo usado importado | G34: Requisitos, pasos y documentos para comprobar el valor de un vehículo usado importado. | I34: Análisis | J34: Importación de mercancías y vehículos | K34: SERVICIOS TRIBUTARIOS | L34: https://portal.sat.gob.gt/portal/comprobacion-valor-de-importacion/ | M34: Coincide con palabra clave de comercio exterior/aduanas
A35: Importadores y Exportadores | B35: Importadores | C35: Importación | D35: Importación de vehículos | E35: Importación de Vehículos | F35: Importar un vehículo | G35: Requisitos, pasos y documentos para importar un vehículo. | I35: Análisis | J35: Importación de mercancías y vehículos | K35: ADUANAS | L35: https://portal.sat.gob.gt/portal/alza-e-importacion-vehiculos/#1510763502681-dff4b62b-fd76 | M35: Bajo menú Aduanas
A36: Importadores y Exportadores | B36: Importadores | C36: Importación | D36: Importación de vehículos | E36: Inscripción de Vehículos para Importadores de Vehículos Nuevos | F36: Inscribir vehículos nuevos (importadores) | G36: Requisitos, pasos y documentos para inscribir vehículos nuevos (importadores). | I36: Análisis | J36: Importación de mercancías y vehículos | K36: SERVICIOS TRIBUTARIOS | L36: https://portal.sat.gob.gt/portal/requisitos-tramites-agencias/inscripcion-de-vehiculos-para-importadores-de-vehiculos-nuevos/ | M36: Coincide con palabra clave de comercio exterior/aduanas
A37: Importadores y Exportadores | B37: Importadores | C37: Importación | D37: Proceso de importación | E37: Generalidades de la importación de mercancías | F37: Curso: generalidades de la importación | G37: Capacitación virtual de la SAT sobre generalidades de la importación. | I37: Análisis | J37: Importación de mercancías y vehículos | K37: CAPACITACIÓN | L37: https://sites.google.com/capacitacionessat.page/cultura-tributariad/cursos-virtuales-sat/aduanas/20-generalidades-de-la-importaci%C3%B3n-de-mercanc%C3%Adas | M37: Coincide con palabra clave de comercio exterior/aduanas
A38: Importadores y Exportadores | B38: Importadores | C38: Importación | D38: Proceso de importación | E38: Requisitos para Inscripccion en el Registro de importadores | F38: Inscribirte como importador | G38: Requisitos, pasos y documentos para inscribirte como importador. | I38: Análisis | J38: Importación de mercancías y vehículos | K38: ADUANAS | L38: https://portal.sat.gob.gt/portal/requisitos-para-inscripccion-en-el-registro-de-importadores/ | M38: Bajo menú Aduanas
A39: Importadores y Exportadores | B39: Importadores | C39: Importación | D39: Proceso de importación | E39: Presentación de Declaración de Mercancías de Importación y Admisiones Temporales para Cargos y Fianza | F39: Presentar declaración de importación con fianza | G39: Requisitos, pasos y documentos para presentar declaración de importación con fianza. | I39: Análisis | J39: Importación de mercancías y vehículos | K39: ADUANAS | L39: https://portal.sat.gob.gt/portal/requisitos-tramites-aduanas/presentacion-de-declaracion-de-mercancias-de-importacion-y-admisiones-temporales-para-cargos-y-fianza/ | M39: Bajo menú Aduanas
A40: Importadores y Exportadores | B40: Importadores | C40: Importación | D40: Proceso de importación | E40: Pólizas de Importación | F40: Pólizas de importación | G40: Información sobre: Pólizas de importación. | I40: Análisis | J40: Importación de mercancías y vehículos | K40: ADUANAS | L40: https://portal.sat.gob.gt/portal/polizas-de-importacion/ | M40: Bajo menú Aduanas
A41: Importadores y Exportadores | B41: Importadores | C41: Importación | D41: Tablas de valores de vehículos | E41: Acuerdo de Directorio Número 24-2024 que aprueba la Tabla de Valores Imponibles del Impuesto Específico a la Primera Matrícula para la Importación de Vehículos Automotores Terrestre Usados para el año 2025. | F41: Acuerdo que aprueba la tabla de IPRIMA de vehículos usados | G41: Información sobre: Acuerdo que aprueba la tabla de IPRIMA de vehículos usados. | I41: Análisis | J41: Importación de mercancías y vehículos | K41: SERVICIOS TRIBUTARIOS | L41: https://portal.sat.gob.gt/portal/descarga/1895/legislacion-aduanera/82515/acuerdo-de-directorio-numero-24-2024-que-aprueba-la-tabla-de-valores-imponibles-del-impuesto-especifico-a-la-primera-matricula-para-la-importacion-de-vehiculos-automotores-terrestre-usados-para.pdf | M41: Coincide con palabra clave de comercio exterior/aduanas
... A51: Importadores y Exportadores | B51: Importadores | C51: Vehículos (como propietario) | D51: Placas de distribuidor | E51: Asignación de Placas de Uso Distribuidor | F51: Solicitar placas de distribuidor | G51: Requisitos, pasos y documentos para solicitar placas de distribuidor. | I51: Análisis | J51: Placas de distribuidor para importadores y distribuidores de vehículos | K51: SERVICIOS TRIBUTARIOS | L51: https://portal.sat.gob.gt/portal/requisitos-tramites-agencias/asignacion-de-placas-de-uso-distribuidor/ | M51: Servicio/tema general para contribuyentes
A52: Importadores y Exportadores | B52: Importadores | C52: Agregada desde «Grupos y categorías» | F52: Importación | G52: Conceptos generales sobre importación de mercancias y buenas practicas sugeridas desde la Modernización Integral Aduanera. | H52: Importadores y Exportadores: Importadores, OEA | I52: Grupos y categorías | J52: Marcada «SI» en el archivo Grupos y categorías | L52: https://portal.sat.gob.gt/portal/programa-miad/componente-procesos/importacion/#1623281268015-fb939ea7-9dfb
A53: Importadores y Exportadores | B53: Importadores | C53: Agregada desde «Grupos y categorías» | F53: Página | G53: Pasos previos a tu importación de mercancías vía aérea Información sobre requisitos, consideraciones, documentos necesarios y procesos con los pasos previos a una importación definitiva desde el marco de la Modernización Integral Aduanera. | H53: Importadores y Exportadores: Importadores, OEA | I53: Grupos y categorías | J53: Marcada «SI» en el archivo Grupos y categorías | L53: https://portal.sat.gob.gt/portal/programa-miad/componente-procesos/importacion/#1623281274865-df599d08-4b3c
A54: Importadores y Exportadores | B54: OEA | C54: Exportación | D54: Cambio de régimen | E54: Cambio de Régimen Optativo al Régimen Especial de Devolución de Crédito Fiscal de IVA por Exportaciones | F54: Pasar del Régimen Optativo al Especial | G54: Requisitos, pasos y documentos para pasar del Régimen Optativo al Especial. | H54: Importadores y Exportadores: OEA, Exportadores | I54: Grupos y categorías | J54: Marcada «SI» en el archivo Grupos y categorías | K54: SERVICIOS TRIBUTARIOS | L54: https://portal.sat.gob.gt/portal/requisitos-tramites-agencias/cambio-de-regimen-optativo-al-regimen-especial-de-devolucion-de-credito-fiscal-de-iva-por-exportaciones/ | M54: Coincide con palabra clave de comercio exterior/aduanas
A55: Importadores y Exportadores | B55: OEA | C55: Gestiones y consultas aduaneras | D55: Declaraciones (DUA / DUCA) | E55: Declaración de mercancías | F55: Sistema de Franquicias Electrónicas | G55: Información sobre documentación técnica de orientación al usuario externo para solicitudes de Franquicia Electrónica y videos informativos. | H55: Importadores y Exportadores: Importadores, OEA | I55: Grupos y categorías | J55: Marcada «SI» en el archivo Grupos y categorías | K55: ADUANAS | L55: https://portal.sat.gob.gt/portal/procedimientos-aduanas/#1555105635499-a4507e58-10e9 | M55: Bajo menú Aduanas
A56: Importadores y Exportadores | B56: OEA | C56: Gestiones y consultas aduaneras | D56: Requisitos, recursos y sistemas | E56: Requisitos Gestiones en Aduanas | F56: Requisitos sobre documentos para Importación y Admisión Temporal | G56: Información y requisitos sobre recepción de seguro de caución de importacion y admisión temporal, presentación de mercancia de importación y admisiones temporales para cargos y fianzas y requisitos para la importación temporal de vehículos de turismo. | H56: Importadores y Exportadores: Importadores, OEA | I56: Grupos y categorías | J56: Marcada «SI» en el archivo Grupos y categorías | K56: ADUANAS | L56: https://portal.sat.gob.gt/portal/requisitos-de-aduanas/ | M56: Bajo menú Aduanas
A57: Importadores y Exportadores | B57: OEA | C57: MIAD | D57: Programa de Modernización Integral Aduanera | F57: Importación | G57: Conceptos generales sobre importación de mercancias y buenas practicas sugeridas desde la Modernización Integral Aduanera. | H57: Importadores y Exportadores: Importadores, OEA | I57: Grupos y categorías | J57: Marcada «SI» en el archivo Grupos y categorías | L57: https://portal.sat.gob.gt/portal/programa-miad/componente-procesos/importacion/#1623281268015-fb939ea7-9dfb
A58: Importadores y Exportadores | B58: OEA | C58: MIAD | D58: Programa de Modernización Integral Aduanera | F58: Página | G58: Pasos previos a tu importación de mercancías vía aérea Información sobre requisitos, consideraciones, documentos necesarios y procesos con los pasos previos a una importación definitiva desde el marco de la Modernización Integral Aduanera. | H58: Importadores y Exportadores: Importadores, OEA | I58: Grupos y categorías | J58: Marcada «SI» en el archivo Grupos y categorías | L58: https://portal.sat.gob.gt/portal/programa-miad/componente-procesos/importacion/#1623281274865-df599d08-4b3c
A59: Importadores y Exportadores | B59: Exportadores | C59: Devoluciones y créditos fiscales | D59: Solicitudes y seguimiento | E59: Consulta de Solicitudes de Devolución de Crédito Fiscal Régimen General | F59: Consultar tu solicitud de devolución de crédito fiscal | G59: Servicio en línea para consultar tu solicitud de devolución de crédito fiscal. | H59: Importadores y Exportadores: Exportadores | I59: Grupos y categorías | J59: Marcada «SI» en el archivo Grupos y categorías | K59: SERVICIOS TRIBUTARIOS | L59: https://portal.sat.gob.gt/portal/consulta-de-solicitudes-de-devolucion-de-credito-fiscal-regimen-general/ | M59: Servicio/tema general para contribuyentes
A60: Importadores y Exportadores | B60: Exportadores | C60: Devoluciones y créditos fiscales | D60: Solicitudes y seguimiento | E60: Régimen Electrónico de Devolución de Crédito Fiscal | F60: Curso: régimen electrónico de devolución de crédito fiscal | G60: Capacitación virtual de la SAT sobre régimen electrónico de devolución de crédito fiscal. | I60: Análisis | J60: Devolución de crédito fiscal a exportadores (Ley del IVA, arts. 23-25) | K60: CAPACITACIÓN | L60: https://sites.google.com/capacitacionessat.page/eventosenvivo/p%C3%A1gina-principal/r%C3%A9gimen-electr%C3%B3nico-de-devoluci%C3%B3n-de-cr%C3%A9dito-fiscal | M60: Servicio/tema general para contribuyentes
A61: Importadores y Exportadores | B61: Exportadores | C61: Devoluciones y créditos fiscales | D61: Solicitudes y seguimiento | E61: Devolución del Impuesto al Valor Agregado, SAT-2237 | F61: Solicitar devolución de crédito fiscal del IVA | G61: Requisitos, pasos y documentos para solicitar devolución de crédito fiscal del IVA. | I61: Análisis | J61: Devolución de crédito fiscal a exportadores (Ley del IVA, arts. 23-25) | K61: SERVICIOS TRIBUTARIOS | L61: https://portal.sat.gob.gt/portal/requisitos-tramites-agencias/devolucion-del-impuesto-al-valor-agregadosat-2157-sat-2237/ | M61: Servicio/tema general para contribuyentes
A62: Importadores y Exportadores | B62: Exportadores | C62: Exportación | D62: Cambio de régimen | E62: Cambio de Régimen Especial al Régimen Optativo de Devolución de Crédito Fiscal de IVA por Exportaciones | F62: Pasar del Régimen Especial al Optativo | G62: Requisitos, pasos y documentos para pasar del Régimen Especial al Optativo. | I62: Análisis | J62: Exportadores (registro, declaraciones y devolución de IVA) | K62: SERVICIOS TRIBUTARIOS | L62: https://portal.sat.gob.gt/portal/requisitos-tramites-agencias/cambio-de-regimen-especial-al-regimen-optativo-de-devolucion-de-credito-fiscal-de-iva-por-exportaciones/ | M62: Coincide con palabra clave de comercio exterior/aduanas
A63: Importadores y Exportadores | B63: Exportadores | C63: Exportación | D63: Cambio de régimen | E63: Cambio de Régimen Optativo al Régimen Especial de Devolución de Crédito Fiscal de IVA por Exportaciones | F63: Pasar del Régimen Optativo al Especial | G63: Requisitos, pasos y documentos para pasar del Régimen Optativo al Especial. | H63: Importadores y Exportadores: OEA, Exportadores | I63: Grupos y categorías | J63: Marcada «SI» en el archivo Grupos y categorías | K63: SERVICIOS TRIBUTARIOS | L63: https://portal.sat.gob.gt/portal/requisitos-tramites-agencias/cambio-de-regimen-optativo-al-regimen-especial-de-devolucion-de-credito-fiscal-de-iva-por-exportaciones/ | M63: Coincide con palabra clave de comercio exterior/aduanas
A64: Importadores y Exportadores | B64: Exportadores | C64: Exportación | D64: Declaraciones y sanciones | E64: Declaraciones de Exportación Simplificadas, Provisionales y Complementarias | F64: Declaraciones de exportación simplificadas, provisionales y complementarias | G64: Información sobre: Declaraciones de exportación simplificadas, provisionales y complementarias. | I64: Análisis | J64: Exportadores (registro, declaraciones y devolución de IVA) | K64: ADUANAS | L64: https://portal.sat.gob.gt/portal/dec-expo-sim-prov-com/ | M64: Bajo menú Aduanas
A65: Importadores y Exportadores | B65: Exportadores | C65: Exportación | D65: Declaraciones y sanciones | E65: Presentación y Análisis de Declaración Complementarias de Exportación | F65: Presentar declaración complementaria de exportación | G65: Requisitos, pasos y documentos para presentar declaración complementaria de exportación. | I65: Análisis | J65: Exportadores (registro, declaraciones y devolución de IVA) | K65: ADUANAS | L65: https://portal.sat.gob.gt/portal/requisitos-tramites-aduanas/presentacion-y-analisis-de-declaracion-complementarias-de-exportacion/ | M65: Bajo menú Aduanas
A66: Importadores y Exportadores | B66: Exportadores | C66: Exportación | D66: Declaraciones y sanciones | E66: Selectivo de Declaraciones de Exportación | F66: Selectivo de declaraciones de exportación | G66: Información sobre: Selectivo de declaraciones de exportación. | I66: Análisis | J66: Exportadores (registro, declaraciones y devolución de IVA) | K66: ADUANAS | L66: https://portal.sat.gob.gt/portal/requisitos-tramites-aduanas/selectivo-de-declaraciones-de-exportacion/ | M66: Bajo menú Aduanas
A67: Importadores y Exportadores | B67: Exportadores | C67: Exportación | D67: Exportador habitual | E67: Inscripción al Régimen Habitual de Exportaciones | F67: Inscribirte como exportador habitual | G67: Requisitos, pasos y documentos para inscribirte como exportador habitual. | I67: Análisis | J67: Exportadores (registro, declaraciones y devolución de IVA) | K67: SERVICIOS TRIBUTARIOS | L67: https://portal.sat.gob.gt/portal/requisitos-tramites-agencias/inscripcion-al-regimen-habitual-de-exportaciones/ | M67: Coincide con palabra clave de comercio exterior/aduanas
A68: Importadores y Exportadores | B68: Exportadores | C68: Exportación | D68: Registro de exportadores | E68: Requisitos para la Actualización en el Registro de Exportadores | F68: Actualizar tus datos como exportador | G68: Requisitos, pasos y documentos para actualizar tus datos como exportador. | I68: Análisis | J68: Exportadores (registro, declaraciones y devolución de IVA) | K68: SERVICIOS TRIBUTARIOS | L68: https://portal.sat.gob.gt/portal/requisitos-tramites-agencias/requisitos-para-la-actualizacion-en-el-registro-de-exportadores/ | M68: Coincide con palabra clave de comercio exterior/aduanas
A69: Importadores y Exportadores | B69: Exportadores | C69: Exportación | D69: Registro de exportadores | E69: Requisitos para la Inactivación en el Registro de Exportadores | F69: Darte de baja como exportador | G69: Requisitos, pasos y documentos para darte de baja como exportador. | I69: Análisis | J69: Exportadores (registro, declaraciones y devolución de IVA) | K69: SERVICIOS TRIBUTARIOS | L69: https://portal.sat.gob.gt/portal/requisitos-tramites-agencias/requisitos-para-la-inactivacion-en-el-registro-de-exportadores/ | M69: Coincide con palabra clave de comercio exterior/aduanas
A70: Importadores y Exportadores | B70: Exportadores | C70: Exportación | D70: Registro de exportadores | E70: Requisitos para la Inscripción en el Registro de Exportadores | F70: Inscribirte como exportador | G70: Requisitos, pasos y documentos para inscribirte como exportador. | I70: Análisis | J70: Exportadores (registro, declaraciones y devolución de IVA) | K70: SERVICIOS TRIBUTARIOS | L70: https://portal.sat.gob.gt/portal/requisitos-tramites-agencias/requisitos-para-la-inscripcion-en-el-registro-de-exportadores/ | M70: Coincide con palabra clave de comercio exterior/aduanas
A71: Importadores y Exportadores | B71: Exportadores | C71: Exportación | D71: Registro de exportadores | E71: Registro de Exportadores En Agencia Virtual | F71: Registrarte como exportador en Agencia Virtual | G71: Requisitos, pasos y documentos para registrarte como exportador en Agencia Virtual. | I71: Análisis | J71: Exportadores (registro, declaraciones y devolución de IVA) | K71: SERVICIOS TRIBUTARIOS | L71: https://portal.sat.gob.gt/portal/registro-de-exportadores-en-agencia-virtual/ | M71: Coincide con palabra clave de comercio exterior/aduanas
A72: Importadores y Exportadores | B72: Exportadores | C72: Exportación | D72: Registro de exportadores | E72: Requisitos para Solicitud de Permiso Temporal en el Registro de Exportadores | F72: Solicitar permiso temporal como exportador | G72: Requisitos, pasos y documentos para solicitar permiso temporal como exportador. | I72: Análisis | J72: Exportadores (registro, declaraciones y devolución de IVA) | K72: SERVICIOS TRIBUTARIOS | L72: https://portal.sat.gob.gt/portal/requisitos-tramites-agencias/requisitos-para-solicitud-de-permiso-temporal-en-el-registro-de-exportadores/ | M72: Coincide con palabra clave de comercio exterior/aduanas
A73: Importadores y Exportadores | B73: Exportadores | C73: Exportación | D73: Régimen Especial | E73: Actualización al Régimen Especial de Devolución de Crédito Fiscal a los Exportadores desde Agencia Virtual | F73: Actualizar tus datos en el Régimen Especial | G73: Requisitos, pasos y documentos para actualizar tus datos en el Régimen Especial. | I73: Análisis | J73: Exportadores (registro, declaraciones y devolución de IVA) | K73: SERVICIOS TRIBUTARIOS | L73: https://portal.sat.gob.gt/portal/requisitos-tramites-agencias/actualizacion-al-regimen-especial-de-devolucion-de-credito-fiscal-a-los-exportadores-desde-agencia-virtual/ | M73: Coincide con palabra clave de comercio exterior/aduanas
A74: Importadores y Exportadores | B74: Exportadores | C74: Exportación | D74: Régimen Especial | E74: Actualización de exportadores en el Régimen Especial por Agencia Virtual | F74: Curso: actualización de exportadores en el Régimen Especial | G74: Capacitación virtual de la SAT sobre actualización de exportadores en el Régimen Especial. | I74: Análisis | J74: Exportadores (registro, declaraciones y devolución de IVA) | K74: CAPACITACIÓN | L74: https://sites.google.com/capacitacionessat.page/eventosenvivo/p%C3%A1gina-principal/actualizaci%C3%B3n-de-exportadores-en-el-r%C3%A9gimen-especial-por-agencia-virtual | M74: Coincide con palabra clave de comercio exterior/aduanas
A75: Importadores y Exportadores | B75: Exportadores | C75: Exportación | D75: Régimen Especial | E75: Inscripción al Régimen Especial de Devolución de Crédito Fiscal de IVA por Exportación | F75: Inscribirte al Régimen Especial de devolución de IVA | G75: Requisitos, pasos y documentos para inscribirte al Régimen Especial de devolución de IVA. | I75: Análisis | J75: Exportadores (registro, declaraciones y devolución de IVA) | K75: SERVICIOS TRIBUTARIOS | L75: https://portal.sat.gob.gt/portal/requisitos-tramites-agencias/inscripcion-al-regimen-especial-de-devolucion-de-credito-fiscal-de-iva-por-exportaciones/ | M75: Coincide con palabra clave de comercio exterior/aduanas
... A78: Importadores y Exportadores | B78: Exportadores | C78: Gestiones y consultas aduaneras | D78: Manifiestos, marchamos y tránsito | E78: Autorización de Lista de Embarque | F78: Autorizar lista de embarque | G78: Requisitos, pasos y documentos para autorizar lista de embarque. | I78: Análisis | J78: Lista de embarque de exportación | K78: ADUANAS | L78: https://portal.sat.gob.gt/portal/requisitos-tramites-aduanas/autorizacion-de-lista-de-embarque/ | M78: Bajo menú Aduanas
A79: Importadores y Exportadores | B79: Exportadores | C79: Otros servicios al contribuyente | D79: Constancias y gestiones del RTU | E79: Requisitos de persona/empresa | F79: Requisitos para el Cambio de Regímenes | G79: Información sobre los requisitos para el registro exportadores en Agencia Virtual, inscripción al régimen habitual de exportación, actualización, inscripción, inactivación, permisos temporales y devolución de crédito fiscal en el registro de exportadores. | H79: Importadores y Exportadores: Exportadores | I79: Grupos y categorías | J79: Marcada «SI» en el archivo Grupos y categorías | K79: SERVICIOS TRIBUTARIOS | L79: https://portal.sat.gob.gt/portal/requisitos-de-personas-empresas/ | M79: Servicio/tema general para contribuyentes
A80: Auxiliares de la Función Pública Aduanera | B80: Todos los grupos | C80: Cultura tributaria y capacitación | D80: Biblioteca virtual y descargas | E80: Repositorio Virtual | F80: Repositorio de documentos | G80: Información sobre: Repositorio de documentos. | H80: Auxiliares de la Función Pública Aduanera | I80: Grupos y categorías | J80: Marcada «SI» en el archivo Grupos y categorías | K80: CAPACITACIÓN | L80: https://portal.sat.gob.gt/portal/biblioteca-en-linea-sat/archivo-de-documentos/ | M80: Servicio/tema general para contribuyentes
A81: Auxiliares de la Función Pública Aduanera | B81: Todos los grupos | C81: Cultura tributaria y capacitación | D81: Información institucional | E81: Memoria de Labores SAT | F81: Memoria de labores | G81: Información sobre: Memoria de labores. | H81: Auxiliares de la Función Pública Aduanera | I81: Grupos y categorías | J81: Marcada «SI» en el archivo Grupos y categorías | K81: CAPACITACIÓN | L81: https://portal.sat.gob.gt/portal/memoria-de-labores/ | M81: Servicio/tema general para contribuyentes
A82: Auxiliares de la Función Pública Aduanera | B82: Todos los grupos | C82: Estadísticas y estudios | D82: Estadísticas e indicadores | E82: Estadísticas Tributarias SAT | F82: Estadísticas tributarias | G82: Información sobre: Estadísticas tributarias. | H82: Auxiliares de la Función Pública Aduanera | I82: Grupos y categorías | J82: Marcada «SI» en el archivo Grupos y categorías | K82: ESTADÍSTICAS | L82: https://portal.sat.gob.gt/portal/estadisticas-tributarias-sat/ | M82: Contenido institucional/corporativo general (excluido por decisión del usuario)
A83: Auxiliares de la Función Pública Aduanera | B83: Todos los grupos | C83: Gestiones y consultas aduaneras | D83: Declaraciones (DUA / DUCA) | E83: Declaración de mercancías | F83: Auxiliares de la Función Pública Aduanera | G83: Información sobre quienes se consideran Auxiliares de la Función Pública Aduanera, información y diseño del carné de identificación y maual de usuario para registro, consulta y actualización. Componente ActiveX PKI/DUA. | H83: Auxiliares de la Función Pública Aduanera | I83: Grupos y categorías | J83: Marcada «SI» en el archivo Grupos y categorías | K83: ADUANAS | L83: https://portal.sat.gob.gt/portal/procedimientos-aduanas/#1555105635499-a4507e58-10e9 | M83: Bajo menú Aduanas
A84: Auxiliares de la Función Pública Aduanera | B84: Todos los grupos | C84: Gestiones y consultas aduaneras | D84: Programas aduaneros | E84: Auxiliares de la Función Pública Aduanera | F84: Auxiliares de la función pública aduanera | G84: Información sobre: Auxiliares de la función pública aduanera. | I84: Análisis | J84: Auxiliares de la función pública aduanera | K84: ADUANAS | L84: https://portal.sat.gob.gt/portal/auxiliares-de-la-funcion-publica/ | M84: Bajo menú Aduanas
A85: Auxiliares de la Función Pública Aduanera | B85: Todos los grupos | C85: Gestiones y consultas aduaneras | D85: Requisitos, recursos y sistemas | E85: Requisitos Gestiones en Aduanas | F85: Requisitos para la Renovación de Operación de Auxiliares de la Función Publica | G85: Información sobre la solicitud de renovación de Auxiliares de la Función Pública. | H85: Auxiliares de la Función Pública Aduanera | I85: Grupos y categorías | J85: Marcada «SI» en el archivo Grupos y categorías | K85: ADUANAS | L85: https://portal.sat.gob.gt/portal/requisitos-de-aduanas/ | M85: Bajo menú Aduanas
A86: Auxiliares de la Función Pública Aduanera | B86: Todos los grupos | C86: Gobierno y gestión institucional | D86: Opina sobre los procedimientos | E86: Objeciones y Recomendaciones a los procedimientos de la Intendencia de Asuntos Jurídicos | F86: Opinar sobre procedimientos de Asuntos Jurídicos | G86: Espacio para opinar sobre procedimientos de Asuntos Jurídicos y enviar tus recomendaciones. | H86: Auxiliares de la Función Pública Aduanera | I86: Grupos y categorías | J86: Marcada «SI» en el archivo Grupos y categorías | K86: INSTITUCIONAL | L86: https://portal.sat.gob.gt/portal/recepcion-de-objeciones-y-recomendaciones-procedimientos-de-la-sat/objeciones-y-recomendaciones-a-los-procedimientos-de-la-intendencia-de-asuntos-juridicos/ | M86: Contenido institucional/corporativo general (excluido por decisión del usuario)
A87: Auxiliares de la Función Pública Aduanera | B87: Todos los grupos | C87: Otros servicios al contribuyente | D87: Calculadoras y listados | E87: Económico Coactivo: Listado de Contribuyentes Morosos | F87: Consultar listado de contribuyentes morosos | G87: Servicio en línea para consultar listado de contribuyentes morosos. | H87: Auxiliares de la Función Pública Aduanera | I87: Grupos y categorías | J87: Marcada «SI» en el archivo Grupos y categorías | K87: SERVICIOS TRIBUTARIOS | L87: https://portal.sat.gob.gt/portal/listado-de-contribuyentes-morosos/ | M87: Servicio/tema general para contribuyentes
A88: Auxiliares de la Función Pública Aduanera | B88: Courier | C88: Gestiones y consultas aduaneras | D88: Franquicias y viajeros | E88: Sistema de Franquicias Electrónicas | F88: Sistema de franquicias electrónicas | G88: Información sobre: Sistema de franquicias electrónicas. | H88: Auxiliares de la Función Pública Aduanera: Courier, Consolidadores y Desconsolidadores de Carga, Agentes Aduaneros, Transportistas | I88: Grupos y categorías | J88: Marcada «SI» en el archivo Grupos y categorías | K88: ADUANAS | L88: https://portal.sat.gob.gt/portal/franquicias-electronicas/ | M88: Bajo menú Aduanas
A89: Auxiliares de la Función Pública Aduanera | B89: Courier | C89: Importación | D89: Proceso de importación | E89: Conceptos Generales | F89: Conceptos generales de importación | G89: Información sobre: Conceptos generales de importación. | H89: Auxiliares de la Función Pública Aduanera: Courier, Consolidadores y Desconsolidadores de Carga, Agentes Aduaneros | I89: Grupos y categorías | J89: Marcada «SI» en el archivo Grupos y categorías | K89: ADUANAS | L89: https://portal.sat.gob.gt/portal/programa-miad/componente-procesos-2/importacion/ | M89: Bajo menú Aduanas
A90: Auxiliares de la Función Pública Aduanera | B90: Courier | C90: Importación | D90: Proceso de importación | E90: Recepción de Seguro de Caución Importación y Admisión Temporal | F90: Entregar seguro de caución para importación | G90: Requisitos, pasos y documentos para entregar seguro de caución para importación. | H90: Auxiliares de la Función Pública Aduanera: Courier, Agentes Aduaneros | I90: Grupos y categorías | J90: Marcada «SI» en el archivo Grupos y categorías | K90: ADUANAS | L90: https://portal.sat.gob.gt/portal/requisitos-tramites-agencias/recepcion-de-seguro-de-caucion-importacion-y-admision-temporal/ | M90: Bajo menú Aduanas
A91: Auxiliares de la Función Pública Aduanera | B91: Consolidadores y Desconsolidadores de Carga | C91: Gestiones y consultas aduaneras | D91: Franquicias y viajeros | E91: Sistema de Franquicias Electrónicas | F91: Sistema de franquicias electrónicas | G91: Información sobre: Sistema de franquicias electrónicas. | H91: Auxiliares de la Función Pública Aduanera: Courier, Consolidadores y Desconsolidadores de Carga, Agentes Aduaneros, Transportistas | I91: Grupos y categorías | J91: Marcada «SI» en el archivo Grupos y categorías | K91: ADUANAS | L91: https://portal.sat.gob.gt/portal/franquicias-electronicas/ | M91: Bajo menú Aduanas
A92: Auxiliares de la Función Pública Aduanera | B92: Consolidadores y Desconsolidadores de Carga | C92: Importación | D92: Proceso de importación | E92: Conceptos Generales | F92: Conceptos generales de importación | G92: Información sobre: Conceptos generales de importación. | H92: Auxiliares de la Función Pública Aduanera: Courier, Consolidadores y Desconsolidadores de Carga, Agentes Aduaneros | I92: Grupos y categorías | J92: Marcada «SI» en el archivo Grupos y categorías | K92: ADUANAS | L92: https://portal.sat.gob.gt/portal/programa-miad/componente-procesos-2/importacion/ | M92: Bajo menú Aduanas
A93: Auxiliares de la Función Pública Aduanera | B93: Almacenes Fiscales | C93: Gestiones y consultas aduaneras | D93: Manifiestos, marchamos y tránsito | E93: Sistema de Cobro Por Permanencia -SCP- | F93: Cobro por permanencia de mercancías | G93: Información sobre: Cobro por permanencia de mercancías. | I93: Análisis | J93: Depositarios aduaneros | K93: ADUANAS | L93: https://portal.sat.gob.gt/portal/sistema-de-cobro-por-permanencia/ | M93: Bajo menú Aduanas
A94: Auxiliares de la Función Pública Aduanera | B94: Almacenadoras | C94: Gestiones y consultas aduaneras | D94: Manifiestos, marchamos y tránsito | E94: Sistema de Cobro Por Permanencia -SCP- | F94: Cobro por permanencia de mercancías | G94: Información sobre: Cobro por permanencia de mercancías. | I94: Análisis | J94: Depositarios aduaneros | K94: ADUANAS | L94: https://portal.sat.gob.gt/portal/sistema-de-cobro-por-permanencia/ | M94: Bajo menú Aduanas
A95: Auxiliares de la Función Pública Aduanera | B95: Depósitos Aduaneros | C95: Gestiones y consultas aduaneras | D95: Manifiestos, marchamos y tránsito | E95: Sistema de Cobro Por Permanencia -SCP- | F95: Cobro por permanencia de mercancías | G95: Información sobre: Cobro por permanencia de mercancías. | I95: Análisis | J95: Depositarios aduaneros | K95: ADUANAS | L95: https://portal.sat.gob.gt/portal/sistema-de-cobro-por-permanencia/ | M95: Bajo menú Aduanas
A96: Auxiliares de la Función Pública Aduanera | B96: Agentes Aduaneros | C96: Gestiones y consultas aduaneras | D96: Cursos | E96: Generalidades de la Declaración Única Centroamericana -DUCA- | F96: Curso: generalidades de la DUCA | G96: Capacitación virtual de la SAT sobre generalidades de la DUCA. | I96: Análisis | J96: Elaboración de la DUCA | K96: CAPACITACIÓN | L96: https://sites.google.com/capacitacionessat.page/cultura-tributariad/cursos-virtuales-sat/aduanas/declaraci%C3%B3n-%C3%BAnica-centroamericana-duca | M96: Coincide con palabra clave de comercio exterior/aduanas
A97: Auxiliares de la Función Pública Aduanera | B97: Agentes Aduaneros | C97: Gestiones y consultas aduaneras | D97: Franquicias y viajeros | E97: Sistema de Franquicias Electrónicas | F97: Sistema de franquicias electrónicas | G97: Información sobre: Sistema de franquicias electrónicas. | H97: Auxiliares de la Función Pública Aduanera: Courier, Consolidadores y Desconsolidadores de Carga, Agentes Aduaneros, Transportistas | I97: Grupos y categorías | J97: Marcada «SI» en el archivo Grupos y categorías | K97: ADUANAS | L97: https://portal.sat.gob.gt/portal/franquicias-electronicas/ | M97: Bajo menú Aduanas
A98: Auxiliares de la Función Pública Aduanera | B98: Agentes Aduaneros | C98: Gestiones y consultas aduaneras | D98: Requisitos, recursos y sistemas | E98: Componente ActiveX PKI/DUA | F98: Componente ActiveX PKI/DUA | G98: Información sobre: Componente ActiveX PKI/DUA. | I98: Análisis | J98: Firma de declaraciones (agentes aduaneros) | K98: ADUANAS | L98: https://portal.sat.gob.gt/portal/componente-activex-pki-dua/ | M98: Bajo menú Aduanas
A99: Auxiliares de la Función Pública Aduanera | B99: Agentes Aduaneros | C99: Importación | D99: Proceso de importación | E99: Conceptos Generales | F99: Conceptos generales de importación | G99: Información sobre: Conceptos generales de importación. | H99: Auxiliares de la Función Pública Aduanera: Courier, Consolidadores y Desconsolidadores de Carga, Agentes Aduaneros | I99: Grupos y categorías | J99: Marcada «SI» en el archivo Grupos y categorías | K99: ADUANAS | L99: https://portal.sat.gob.gt/portal/programa-miad/componente-procesos-2/importacion/ | M99: Bajo menú Aduanas
A100: Auxiliares de la Función Pública Aduanera | B100: Agentes Aduaneros | C100: Importación | D100: Proceso de importación | E100: Recepción de Seguro de Caución Importación y Admisión Temporal | F100: Entregar seguro de caución para importación | G100: Requisitos, pasos y documentos para entregar seguro de caución para importación. | H100: Auxiliares de la Función Pública Aduanera: Courier, Agentes Aduaneros | I100: Grupos y categorías | J100: Marcada «SI» en el archivo Grupos y categorías | K100: ADUANAS | L100: https://portal.sat.gob.gt/portal/requisitos-tramites-agencias/recepcion-de-seguro-de-caucion-importacion-y-admision-temporal/ | M100: Bajo menú Aduanas
A101: Auxiliares de la Función Pública Aduanera | B101: Agentes Aduaneros | C101: Infraestructura y modernización aduanera | D101: Infraestructura | E101: Puesto Fronterizo Pedro de Alvarado – La Hachadura | F101: Videovigilancia Pedro de Alvarado – La Hachadura | G101: Información sobre: Videovigilancia Pedro de Alvarado – La Hachadura. | H101: Auxiliares de la Función Pública Aduanera: Agentes Aduaneros, Transportistas | I101: Grupos y categorías | J101: Marcada «SI» en el archivo Grupos y categorías | K101: ADUANAS | L101: https://portal.sat.gob.gt/portal/programa-miad/sistemas-de-video-vigilancia-cctv/ | M101: Bajo menú Aduanas
A102: Auxiliares de la Función Pública Aduanera | B102: Transportistas | C102: Devoluciones y créditos fiscales | D102: Otros impuestos | E102: Devolución del Impuesto de Admisión Temporal de Equipos de Carga (ATC) | F102: Devolución de impuestos por admisión temporal de equipo de carga | G102: Información sobre: Devolución de impuestos por admisión temporal de equipo de carga. | I102: Análisis | J102: Equipo de carga en admisión temporal | K102: SERVICIOS TRIBUTARIOS | L102: https://portal.sat.gob.gt/portal/requisitos-tramites-agencias/devolucion-de-impuestos-de-admision-temporal-de-equipo-de-carga-atc/ | M102: Servicio/tema general para contribuyentes
A103: Auxiliares de la Función Pública Aduanera | B103: Transportistas | C103: Gestiones y consultas aduaneras | D103: Equipo de carga en admisión temporal (ATC) | E103: Registro de Ampliación ATC | F103: Ampliar el plazo del equipo de carga (ATC) | G103: Requisitos, pasos y documentos para ampliar el plazo del equipo de carga (ATC). | I103: Análisis | J103: Manifiesto, marchamo, tránsito y equipo de carga (transportistas aduaneros) | K103: ADUANAS | L103: https://portal.sat.gob.gt/portal/registro-ampliacion-atc/ | M103: Bajo menú Aduanas
A104: Auxiliares de la Función Pública Aduanera | B104: Transportistas | C104: Gestiones y consultas aduaneras | D104: Equipo de carga en admisión temporal (ATC) | E104: Culminación de Admisión Temporal de Equipo de Carga | F104: Finalizar la admisión temporal de equipo de carga | G104: Requisitos, pasos y documentos para finalizar la admisión temporal de equipo de carga. | I104: Análisis | J104: Manifiesto, marchamo, tránsito y equipo de carga (transportistas aduaneros) | K104: ADUANAS | L104: https://portal.sat.gob.gt/portal/requisitos-tramites-aduanas/culminacion-de-admision-temporal-de-equipo-de-carga/ | M104: Bajo menú Aduanas
A105: Auxiliares de la Función Pública Aduanera | B105: Transportistas | C105: Gestiones y consultas aduaneras | D105: Equipo de carga en admisión temporal (ATC) | E105: Registro ATC Terrestre | F105: Registrar equipo de carga terrestre (ATC) | G105: Requisitos, pasos y documentos para registrar equipo de carga terrestre (ATC). | I105: Análisis | J105: Manifiesto, marchamo, tránsito y equipo de carga (transportistas aduaneros) | K105: ADUANAS | L105: https://portal.sat.gob.gt/portal/registro-atc-terrestre/ | M105: Bajo menú Aduanas
A106: Auxiliares de la Función Pública Aduanera | B106: Transportistas | C106: Gestiones y consultas aduaneras | D106: Franquicias y viajeros | E106: Sistema de Franquicias Electrónicas | F106: Sistema de franquicias electrónicas | G106: Información sobre: Sistema de franquicias electrónicas. | H106: Auxiliares de la Función Pública Aduanera: Courier, Consolidadores y Desconsolidadores de Carga, Agentes Aduaneros, Transportistas | I106: Grupos y categorías | J106: Marcada «SI» en el archivo Grupos y categorías | K106: ADUANAS | L106: https://portal.sat.gob.gt/portal/franquicias-electronicas/ | M106: Bajo menú Aduanas
A107: Auxiliares de la Función Pública Aduanera | B107: Transportistas | C107: Gestiones y consultas aduaneras | D107: Manifiestos, marchamos y tránsito | E107: Asignación de Rampa | F107: Asignación de rampa | G107: Información sobre: Asignación de rampa. | I107: Análisis | J107: Manifiesto, marchamo, tránsito y equipo de carga (transportistas aduaneros) | K107: ADUANAS | L107: https://portal.sat.gob.gt/portal/asignacion-rampa-pq/ | M107: Bajo menú Aduanas
A108: Auxiliares de la Función Pública Aduanera | B108: Transportistas | C108: Gestiones y consultas aduaneras | D108: Manifiestos, marchamos y tránsito | E108: Asignación de Revisores | F108: Asignación de revisores | G108: Información sobre: Asignación de revisores. | I108: Análisis | J108: Manifiesto, marchamo, tránsito y equipo de carga (transportistas aduaneros) | K108: ADUANAS | L108: https://portal.sat.gob.gt/portal/asignacion-de-revisores/ | M108: Bajo menú Aduanas
A109: Auxiliares de la Función Pública Aduanera | B109: Transportistas | C109: Gestiones y consultas aduaneras | D109: Manifiestos, marchamos y tránsito | E109: Autorización de Cartas de Ingreso a Zona Primaria | F109: Autorizar cartas de ingreso a zona primaria | G109: Requisitos, pasos y documentos para autorizar cartas de ingreso a zona primaria. | I109: Análisis | J109: Manifiesto, marchamo, tránsito y equipo de carga (transportistas aduaneros) | K109: ADUANAS | L109: https://portal.sat.gob.gt/portal/requisitos-tramites-aduanas/autorizacion-de-cartas-de-ingreso-a-zona-primaria/ | M109: Bajo menú Aduanas
A110: Auxiliares de la Función Pública Aduanera | B110: Transportistas | C110: Gestiones y consultas aduaneras | D110: Manifiestos, marchamos y tránsito | E110: Tránsito Pendiente | F110: Consultar tránsitos pendientes | G110: Servicio en línea para consultar tránsitos pendientes. | I110: Análisis | J110: Manifiesto, marchamo, tránsito y equipo de carga (transportistas aduaneros) | K110: ADUANAS | L110: https://portal.sat.gob.gt/portal/transito-pendiente/ | M110: Bajo menú Aduanas
A111: Auxiliares de la Función Pública Aduanera | B111: Transportistas | C111: Gestiones y consultas aduaneras | D111: Manifiestos, marchamos y tránsito | E111: Documentos Manifiesto | F111: Documentos del manifiesto de carga | G111: Información sobre: Documentos del manifiesto de carga. | I111: Análisis | J111: Manifiesto, marchamo, tránsito y equipo de carga (transportistas aduaneros) | K111: ADUANAS | L111: https://portal.sat.gob.gt/portal/documentos-manifiesto/ | M111: Bajo menú Aduanas
A112: Auxiliares de la Función Pública Aduanera | B112: Transportistas | C112: Gestiones y consultas aduaneras | D112: Manifiestos, marchamos y tránsito | E112: Marchamo Electrónico | F112: Marchamo electrónico | G112: Información sobre: Marchamo electrónico. | I112: Análisis | J112: Manifiesto, marchamo, tránsito y equipo de carga (transportistas aduaneros) | K112: ADUANAS | L112: https://portal.sat.gob.gt/portal/marchamo-electronico/ | M112: Bajo menú Aduanas
A113: Auxiliares de la Función Pública Aduanera | B113: Transportistas | C113: Gestiones y consultas aduaneras | D113: Manifiestos, marchamos y tránsito | E113: Mensaje de Carga Aduanera (CUSCAR) | F113: Mensaje de carga aduanera (CUSCAR) | G113: Información sobre: Mensaje de carga aduanera (CUSCAR). | I113: Análisis | J113: Manifiesto, marchamo, tránsito y equipo de carga (transportistas aduaneros) | K113: ADUANAS | L113: https://portal.sat.gob.gt/portal/mensaje-carga-aduanera-cuscar/ | M113: Bajo menú Aduanas
A114: Auxiliares de la Función Pública Aduanera | B114: Transportistas | C114: Infraestructura y modernización aduanera | D114: Infraestructura | E114: Puesto Fronterizo Pedro de Alvarado – La Hachadura | F114: Videovigilancia Pedro de Alvarado – La Hachadura | G114: Información sobre: Videovigilancia Pedro de Alvarado – La Hachadura. | H114: Auxiliares de la Función Pública Aduanera: Agentes Aduaneros, Transportistas | I114: Grupos y categorías | J114: Marcada «SI» en el archivo Grupos y categorías | K114: ADUANAS | L114: https://portal.sat.gob.gt/portal/programa-miad/sistemas-de-video-vigilancia-cctv/ | M114: Bajo menú Aduanas
A115: Trámites comunes | B115: Todos los grupos | C115: Capacitación y orientación aduanera | D115: Cursos | E115: Comercio Exterior | F115: Curso: comercio exterior | G115: Capacitación virtual de la SAT sobre comercio exterior. | H115: Varias categorías de operadores de comercio exterior | I115: Análisis | J115: Capacitación aduanera | K115: CAPACITACIÓN | L115: https://sites.google.com/capacitacionessat.page/cultura-tributariad/cursos-virtuales-sat/comercio-exterior | M115: Coincide con palabra clave de comercio exterior/aduanas
A116: Trámites comunes | B116: Todos los grupos | C116: Capacitación y orientación aduanera | D116: Cursos | E116: Aspectos Importantes del Equipaje de Viajero | F116: Curso: equipaje del viajero | G116: Capacitación virtual de la SAT sobre equipaje del viajero. | H116: Varias categorías de operadores de comercio exterior | I116: Análisis | J116: Capacitación aduanera | K116: CAPACITACIÓN | L116: https://sites.google.com/capacitacionessat.page/cultura-tributariad/cursos-virtuales-sat/aduanas/13-aspectos-importantes-del-equipaje-de-viajero | M116: Coincide con palabra clave de comercio exterior/aduanas
A117: Trámites comunes | B117: Todos los grupos | C117: Capacitación y orientación aduanera | D117: Cursos | E117: Temas Aduaneros | F117: Preguntas Frecuentes sobre Temas Aduaneros | G117: Preguntas frecuentes y respuestas sobre la declaración jurada del viajero, operador economico autorizado, DUCA, declaración anticipada, manifiestos de carga, despacho de mercancías, aduanas sin papeles, clasificación arancelaria, marchamo electrónico, defraudación y contrabando aduanero, laboratorio químico fiscal, franquicias aduaneras, exportaciones temporales, reimportación y sustitución de mercancías, auxiliares de la función pública aduanera y el régimen de admisión temporal de perfeccionamiento activo. | H117: Importadores y Exportadores, Auxiliares de la Función Pública Aduanera | I117: Grupos y categorías | J117: Marcada «SI» en el archivo Grupos y categorías | K117: CAPACITACIÓN | L117: https://portal.sat.gob.gt/portal/preguntas-frecuentes/temas-aduaneros/ | M117: Coincide con palabra clave de comercio exterior/aduanas
...

Sheet Profesionales
A1: Profesionales
A2: Terceras personas que hacen gestiones ante la SAT en nombre de otros: gestores, abogados y notarios, contadores y auditores. Orden: Categoría › Grupo › Tema › Página. «Todos los grupos» = la usan todos los grupos de la categoría. «Trámites comunes» = la usan varias categorías.
A4: Categoría | B4: Grupo | C4: Tema | D4: Subtema | E4: Página / Trámite (nombre actual) | F4: Nombre de trámite sugerido | G4: Descripción de la página | H4: Usado por (según Grupos y categorías) | I4: Origen de la clasificación | J4: Motivo / referencia | K4: Sección actual del menú | L4: URL | M4: Nota / Revisar
A5: Terceras Personas | B5: Todos los grupos | C5: Consultas legales | D5: Consultas | E5: Consultas Legales | F5: Hacer una consulta legal | G5: Requisitos, pasos y documentos para hacer una consulta legal. | H5: Terceras Personas | I5: Grupos y categorías | J5: Marcada «SI» en el archivo Grupos y categorías | K5: CONTÁCTANOS | L5: https://portal.sat.gob.gt/portal/contacto/consultas-legales/ | M5: Rol profesional (agente aduanero, notario, abogado, gestor, tercero autorizado)
A6: Terceras Personas | B6: Todos los grupos | C6: Cultura tributaria y capacitación | D6: Biblioteca virtual y descargas | E6: Descarga de Aplicaciones | F6: Descargar aplicaciones de la SAT | G6: Requisitos, pasos y documentos para descargar aplicaciones de la SAT. | H6: Terceras Personas | I6: Grupos y categorías | J6: Marcada «SI» en el archivo Grupos y categorías | K6: CAPACITACIÓN | L6: https://portal.sat.gob.gt/portal/biblioteca-en-linea-sat/software/ | M6: Servicio/tema general para contribuyentes
A7: Terceras Personas | B7: Todos los grupos | C7: Cultura tributaria y capacitación | D7: Información institucional | E7: Memoria de Labores SAT | F7: Memoria de labores | G7: Información sobre: Memoria de labores. | H7: Terceras Personas | I7: Grupos y categorías | J7: Marcada «SI» en el archivo Grupos y categorías | K7: CAPACITACIÓN | L7: https://portal.sat.gob.gt/portal/memoria-de-labores/ | M7: Servicio/tema general para contribuyentes
A8: Terceras Personas | B8: Todos los grupos | C8: Cultura tributaria y capacitación | D8: Leyes y normativa | E8: Criterios Institucionales | F8: Criterios institucionales | G8: Información sobre: Criterios institucionales. | H8: Terceras Personas | I8: Grupos y categorías | J8: Marcada «SI» en el archivo Grupos y categorías | K8: CAPACITACIÓN | L8: https://portal.sat.gob.gt/portal/criterios-institucionales/ | M8: Servicio/tema general para contribuyentes
A9: Terceras Personas | B9: Todos los grupos | C9: Cultura tributaria y capacitación | D9: Leyes y normativa | E9: Legislación | F9: Legislación | G9: Información sobre: Legislación. | H9: Terceras Personas | I9: Grupos y categorías | J9: Marcada «SI» en el archivo Grupos y categorías | K9: CAPACITACIÓN | L9: https://portal.sat.gob.gt/portal/biblioteca-en-linea-sat/legislacion/ | M9: Servicio/tema general para contribuyentes
A10: Terceras Personas | B10: Todos los grupos | C10: Cultura tributaria y capacitación | D10: Leyes y normativa | E10: Orientacion Legal | F10: Orientación legal | G10: Información sobre: Orientación legal. | H10: Terceras Personas | I10: Grupos y categorías | J10: Marcada «SI» en el archivo Grupos y categorías | K10: CAPACITACIÓN | L10: https://portal.sat.gob.gt/portal/orientacion-legal/ | M10: Servicio/tema general para contribuyentes
A11: Terceras Personas | B11: Todos los grupos | C11: Cultura tributaria y capacitación | D11: Preguntas frecuentes | E11: Preguntas Frecuentes | F11: Preguntas frecuentes | G11: Respuestas a las preguntas más comunes sobre preguntas frecuentes. | H11: Terceras Personas | I11: Grupos y categorías | J11: Marcada «SI» en el archivo Grupos y categorías | K11: CAPACITACIÓN | L11: https://portal.sat.gob.gt/portal/preguntas-frecuentes/ | M11: Servicio/tema general para contribuyentes
A12: Terceras Personas | B12: Todos los grupos | C12: Declaraciones, pagos y solvencias | D12: Formas de pago y convenios | E12: Consulta Movimiento de Pago: Facilidades de pago | F12: Consultar pagos de tu convenio | G12: Servicio en línea para consultar pagos de tu convenio. | H12: Terceras Personas | I12: Grupos y categorías | J12: Marcada «SI» en el archivo Grupos y categorías | K12: SERVICIOS TRIBUTARIOS | L12: https://portal.sat.gob.gt/portal/consulta-movimiento-convenio/ | M12: Servicio/tema general para contribuyentes
A13: Terceras Personas | B13: Todos los grupos | C13: Declaraciones, pagos y solvencias | D13: Formas de pago y convenios | E13: Otras Formas de Pago | F13: Formas de pago de impuestos | G13: Información sobre: Formas de pago de impuestos. | H13: Terceras Personas | I13: Grupos y categorías | J13: Marcada «SI» en el archivo Grupos y categorías | K13: SERVICIOS TRIBUTARIOS | L13: https://portal.sat.gob.gt/portal/forma-de-pago/ | M13: Servicio/tema general para contribuyentes
A14: Terceras Personas | B14: Todos los grupos | C14: Declaraciones, pagos y solvencias | D14: Solvencia fiscal | E14: Falta Solvencia Fiscal | F14: ¿Por qué no tengo solvencia fiscal? | G14: Información general: ¿Por qué no tengo solvencia fiscal? | H14: Terceras Personas | I14: Grupos y categorías | J14: Marcada «SI» en el archivo Grupos y categorías | K14: SERVICIOS TRIBUTARIOS | L14: https://portal.sat.gob.gt/portal/solvencia-fiscal/ | M14: Servicio/tema general para contribuyentes
A15: Terceras Personas | B15: Todos los grupos | C15: Estadísticas y estudios | D15: Estadísticas e indicadores | E15: Estadísticas Tributarias SAT | F15: Estadísticas tributarias | G15: Información sobre: Estadísticas tributarias. | H15: Terceras Personas | I15: Grupos y categorías | J15: Marcada «SI» en el archivo Grupos y categorías | K15: ESTADÍSTICAS | L15: https://portal.sat.gob.gt/portal/estadisticas-tributarias-sat/ | M15: Contenido institucional/corporativo general (excluido por decisión del usuario)
... A57: Terceras Personas | B57: Todos los grupos | C57: Vehículos (como propietario) | D57: Requisitos y representantes | E57: Requisitos Gestiones Vehículos para Propietarios: Requisitos de Vehiculos | F57: Requisitos sobre Traspaso Electrónico de Vehículos a través de Notarios | G57: Información sobre traspaso electrónico de vehículos por notario con anexo del certificado de propiedad emitido vía Declaraguate en Agencia Virtual, entrega de documentos de traspaso electrónico en Agencia Virtual y Requisitos para remitir documentación electrónica o digital de TEV. | H57: Terceras Personas | I57: Grupos y categorías | J57: Marcada «SI» en el archivo Grupos y categorías | K57: SERVICIOS TRIBUTARIOS | L57: https://portal.sat.gob.gt/portal/requisitos-de-vehiculos/ | M57: Servicio/tema general para contribuyentes
A58: Terceras Personas | B58: Gestores Tributarios | C58: Gestores tributarios y terceros autorizados | D58: Registro y gafete | E58: Actualización de Información y Renovación del Gafete de Gestor Tributario y/o Auxiliar de Gestor Tributario | F58: Actualizar tus datos y renovar tu gafete de gestor | G58: Requisitos, pasos y documentos para actualizar tus datos y renovar tu gafete de gestor. | I58: Análisis | J58: Gestores tributarios y sus auxiliares | K58: SERVICIOS TRIBUTARIOS | L58: https://portal.sat.gob.gt/portal/requisitos-tramites-agencias/actualizacion-de-informacion-y-renovacion-del-gafete-de-gestor-tributario-y-o-auxiliar-de-gestor-tributario/ | M58: Rol profesional (agente aduanero, notario, abogado, gestor, tercero autorizado)
A59: Terceras Personas | B59: Gestores Tributarios | C59: Gestores tributarios y terceros autorizados | D59: Registro y gafete | E59: Terceros Autorizados: Consulta de Datos del Gestor Tributario o Auxiliar de Gestor Tributario | F59: Consultar los datos de un gestor tributario | G59: Servicio en línea para consultar los datos de un gestor tributario. | I59: Análisis | J59: Gestores tributarios | K59: SERVICIOS TRIBUTARIOS | L59: https://portal.sat.gob.gt/portal/consulta-de-datos-del-gestor-tributario-o-auxiliar-de-gestor-tributario/ | M59: Rol profesional (agente aduanero, notario, abogado, gestor, tercero autorizado)
A60: Terceras Personas | B60: Gestores Tributarios | C60: Gestores tributarios y terceros autorizados | D60: Registro y gafete | E60: Habilitación e Inhabilitación Temporal o Permanente de Gestor Tributario y/o Auxiliar de Gestor Tributario | F60: Habilitar o inhabilitar a un gestor tributario | G60: Requisitos, pasos y documentos para habilitar o inhabilitar a un gestor tributario. | I60: Análisis | J60: Gestores tributarios | K60: SERVICIOS TRIBUTARIOS | L60: https://portal.sat.gob.gt/portal/requisitos-tramites-agencias/habilitacion-e-inhabilitacion-temporal-o-permanente-de-gestor-tributario-y-o-auxiliar-de-gestor-tributario/ | M60: Rol profesional (agente aduanero, notario, abogado, gestor, tercero autorizado)
A61: Terceras Personas | B61: Gestores Tributarios | C61: Gestores tributarios y terceros autorizados | D61: Registro y gafete | E61: Reposición del Gafete de Gestor Tributario y/o Auxiliares de Gestor Tributario por Extravió, Robo, Hurto o Deterioro | F61: Reponer tu gafete de gestor tributario | G61: Requisitos, pasos y documentos para reponer tu gafete de gestor tributario. | I61: Análisis | J61: Gestores tributarios y sus auxiliares | K61: SERVICIOS TRIBUTARIOS | L61: https://portal.sat.gob.gt/portal/requisitos-tramites-agencias/reposicion-del-gafete-de-gestor-tributario-y-o-auxiliares-de-gestor-tributario-por-extravio-robo-hurto-o-deterioro/ | M61: Rol profesional (agente aduanero, notario, abogado, gestor, tercero autorizado)
A62: Terceras Personas | B62: Gestores Tributarios | C62: Gestores tributarios y terceros autorizados | D62: Registro y gafete | E62: Requisitos para las solicitudes de Gestor Tributario o Auxiliar de Gestor Tributario | F62: Requisitos para ser gestor tributario o auxiliar | G62: Lista de requisitos y documentos: requisitos para ser gestor tributario o auxiliar. | I62: Análisis | J62: Gestores tributarios y sus auxiliares | K62: SERVICIOS TRIBUTARIOS | L62: https://portal.sat.gob.gt/portal/requisitos-tramites-agencias/requisitos-para-las-solicitudes-de-gestor-tributario-o-auxiliar-de-gestor-tributario/ | M62: Rol profesional (agente aduanero, notario, abogado, gestor, tercero autorizado)
A63: Terceras Personas | B63: Auxiliar Tributario | C63: Gestores tributarios y terceros autorizados | D63: Registro y gafete | E63: Actualización de Información y Renovación del Gafete de Gestor Tributario y/o Auxiliar de Gestor Tributario | F63: Actualizar tus datos y renovar tu gafete de gestor | G63: Requisitos, pasos y documentos para actualizar tus datos y renovar tu gafete de gestor. | I63: Análisis | J63: Gestores tributarios y sus auxiliares | K63: SERVICIOS TRIBUTARIOS | L63: https://portal.sat.gob.gt/portal/requisitos-tramites-agencias/actualizacion-de-informacion-y-renovacion-del-gafete-de-gestor-tributario-y-o-auxiliar-de-gestor-tributario/ | M63: Rol profesional (agente aduanero, notario, abogado, gestor, tercero autorizado)
A64: Terceras Personas | B64: Auxiliar Tributario | C64: Gestores tributarios y terceros autorizados | D64: Registro y gafete | E64: Reposición del Gafete de Gestor Tributario y/o Auxiliares de Gestor Tributario por Extravió, Robo, Hurto o Deterioro | F64: Reponer tu gafete de gestor tributario | G64: Requisitos, pasos y documentos para reponer tu gafete de gestor tributario. | I64: Análisis | J64: Gestores tributarios y sus auxiliares | K64: SERVICIOS TRIBUTARIOS | L64: https://portal.sat.gob.gt/portal/requisitos-tramites-agencias/reposicion-del-gafete-de-gestor-tributario-y-o-auxiliares-de-gestor-tributario-por-extravio-robo-hurto-o-deterioro/ | M64: Rol profesional (agente aduanero, notario, abogado, gestor, tercero autorizado)
A65: Terceras Personas | B65: Auxiliar Tributario | C65: Gestores tributarios y terceros autorizados | D65: Registro y gafete | E65: Requisitos para las solicitudes de Gestor Tributario o Auxiliar de Gestor Tributario | F65: Requisitos para ser gestor tributario o auxiliar | G65: Lista de requisitos y documentos: requisitos para ser gestor tributario o auxiliar. | I65: Análisis | J65: Gestores tributarios y sus auxiliares | K65: SERVICIOS TRIBUTARIOS | L65: https://portal.sat.gob.gt/portal/requisitos-tramites-agencias/requisitos-para-las-solicitudes-de-gestor-tributario-o-auxiliar-de-gestor-tributario/ | M65: Rol profesional (agente aduanero, notario, abogado, gestor, tercero autorizado)
A66: Terceras Personas | B66: Abogados y Notarios | C66: Cultura tributaria y capacitación | D66: Preguntas frecuentes | E66: Contribuyentes Especiales | F66: Preguntas frecuentes: contribuyentes especiales | G66: Respuestas a las preguntas más comunes sobre contribuyentes especiales. | H66: Terceras Personas: Abogados y Notarios, Peritos Contadores, Auditores | I66: Grupos y categorías | J66: Marcada «SI» en el archivo Grupos y categorías | K66: CAPACITACIÓN | L66: https://portal.sat.gob.gt/portal/preguntas-frecuentes/contribuyentes-especiales/ | M66: Servicio/tema general para contribuyentes
A67: Terceras Personas | B67: Abogados y Notarios | C67: Notarios | D67: Especies fiscales | E67: Venta de Especies Fiscales a Notarios y Patentados | F67: Comprar especies fiscales (notarios y patentados) | G67: Requisitos, pasos y documentos para comprar especies fiscales (notarios y patentados). | I67: Análisis | J67: Abogados y notarios (Código de Notariado; Ley de Timbres Fiscales) | K67: SERVICIOS TRIBUTARIOS | L67: https://portal.sat.gob.gt/portal/requisitos-tramites-agencias/venta-de-especies-fiscales-a-notarios-y-patentados/ | M67: Rol profesional (agente aduanero, notario, abogado, gestor, tercero autorizado)
A68: Terceras Personas | B68: Abogados y Notarios | C68: Notarios | D68: Registro | E68: Activacion de abogados | F68: Activarte como abogado | G68: Requisitos, pasos y documentos para activarte como abogado. | I68: Análisis | J68: Abogados y notarios (Código de Notariado; Ley de Timbres Fiscales) | K68: SERVICIOS TRIBUTARIOS | L68: https://portal.sat.gob.gt/portal/requisitos-tramites-agencias/activacion-de-abogados/ | M68: Rol profesional (agente aduanero, notario, abogado, gestor, tercero autorizado)
A69: Terceras Personas | B69: Abogados y Notarios | C69: Notarios | D69: Registro | E69: Confirmación de Huella en el Registro de Abogados y Notarios | F69: Confirmar tu huella en el registro de abogados y notarios | G69: Requisitos, pasos y documentos para confirmar tu huella en el registro de abogados y notarios. | I69: Análisis | J69: Abogados y notarios (Código de Notariado; Ley de Timbres Fiscales) | K69: SERVICIOS TRIBUTARIOS | L69: https://portal.sat.gob.gt/portal/sin-categoria/requisitos-de-actualizacion-de-impresion-dactilar-para-abogados-y-notarios-que-realizan-traspasos-electronicos-a-traves-de-agencia-virtual/ | M69: Rol profesional (agente aduanero, notario, abogado, gestor, tercero autorizado)
A70: Terceras Personas | B70: Abogados y Notarios | C70: Notarios | D70: Registro | E70: Confirmación de Huella en el Registro de Abogados y Notarios | F70: Confirmar tu huella en el registro de abogados y notarios | G70: Requisitos, pasos y documentos para confirmar tu huella en el registro de abogados y notarios. | I70: Análisis | J70: Abogados y notarios (Código de Notariado; Ley de Timbres Fiscales) | K70: SERVICIOS TRIBUTARIOS | L70: https://portal.sat.gob.gt/portal/requisitos-tramites-agencias/requisitos-de-actualizacion-de-impresion-dactilar-para-abogados-y-notarios-que-realizan-traspasos-electronicos-a-traves-de-agencia-virtual/ | M70: Rol profesional (agente aduanero, notario, abogado, gestor, tercero autorizado)
A71: Terceras Personas | B71: Abogados y Notarios | C71: Notarios | D71: Registro | E71: Inscripción / Actualización de Abogado y Notario | F71: Inscribirte o actualizar tus datos como abogado y notario | G71: Requisitos, pasos y documentos para inscribirte o actualizar tus datos como abogado y notario. | I71: Análisis | J71: Abogados y notarios (Código de Notariado; Ley de Timbres Fiscales) | K71: SERVICIOS TRIBUTARIOS | L71: https://portal.sat.gob.gt/portal/requisitos-tramites-agencias/inscripcion-actualizacion-de-abogado-y-notario/ | M71: Rol profesional (agente aduanero, notario, abogado, gestor, tercero autorizado)
A72: Terceras Personas | B72: Abogados y Notarios | C72: Notarios | D72: Traspasos y avisos | E72: Tercera Persona Autorizada en el Registro Fiscal de Vehículos | F72: Autorizar a otra persona en el registro de vehículos | G72: Requisitos, pasos y documentos para autorizar a otra persona en el registro de vehículos. | I72: Análisis | J72: Abogados y notarios (Código de Notariado; Ley de Timbres Fiscales) | K72: SERVICIOS TRIBUTARIOS | L72: https://portal.sat.gob.gt/portal/requisitos-tramites-agencias/tercera-persona-autorizada-en-el-registro-fiscal-de-vehiculos/ | M72: Rol profesional (agente aduanero, notario, abogado, gestor, tercero autorizado)
A73: Terceras Personas | B73: Abogados y Notarios | C73: Notarios | D73: Traspasos y avisos | E73: Aviso de Legalización de Firmas en Certificado de Propiedad de Vehículos | F73: Avisar la legalización de firmas en un título de propiedad | G73: Requisitos, pasos y documentos para avisar la legalización de firmas en un título de propiedad. | I73: Análisis | J73: Abogados y notarios (Código de Notariado; Ley de Timbres Fiscales) | K73: SERVICIOS TRIBUTARIOS | L73: https://portal.sat.gob.gt/portal/requisitos-tramites-agencias/aviso-de-legalizacion-de-firmas-en-certificado-de-propiedad-de-vehiculos/ | M73: Rol profesional (agente aduanero, notario, abogado, gestor, tercero autorizado)
A74: Terceras Personas | B74: Abogados y Notarios | C74: Notarios | D74: Traspasos y avisos | E74: Aviso de Transferencia de Dominio de Vehículos | F74: Avisar una transferencia de dominio de vehículo | G74: Requisitos, pasos y documentos para avisar una transferencia de dominio de vehículo. | I74: Análisis | J74: Abogados y notarios (Código de Notariado; Ley de Timbres Fiscales) | K74: SERVICIOS TRIBUTARIOS | L74: https://portal.sat.gob.gt/portal/requisitos-tramites-agencias/aviso-de-transferencia-de-dominio-de-vehiculos/ | M74: Rol profesional (agente aduanero, notario, abogado, gestor, tercero autorizado)
A75: Terceras Personas | B75: Abogados y Notarios | C75: Notarios | D75: Traspasos y avisos | E75: Registro en la Modalidad de Traspaso Electrónico por Notario | F75: Registrarte para hacer traspasos electrónicos | G75: Requisitos, pasos y documentos para registrarte para hacer traspasos electrónicos. | I75: Análisis | J75: Abogados y notarios (Código de Notariado; Ley de Timbres Fiscales) | K75: SERVICIOS TRIBUTARIOS | L75: https://portal.sat.gob.gt/portal/requisitos-tramites-agencias/registro-en-la-modalidad-de-traspaso-electronico-por-notario/ | M75: Rol profesional (agente aduanero, notario, abogado, gestor, tercero autorizado)
A76: Terceras Personas | B76: Abogados y Notarios | C76: Notarios | D76: Traspasos y avisos | E76: Requisitos Gestiones Vehículos para Notarios: Requisitos para Trámites de Notarios | F76: Requisitos de trámites de vehículos para notarios | G76: Requisitos gestiones vehículos para Notarios Verifica los requisitos indispensables como notario para realizar tus gestiones | H76: Terceras Personas: Abogados y Notarios | I76: Grupos y categorías | J76: Marcada «SI» en el archivo Grupos y categorías | K76: SERVICIOS TRIBUTARIOS | L76: https://portal.sat.gob.gt/portal/requisitos-tramites-notarios/ | M76: Rol profesional (agente aduanero, notario, abogado, gestor, tercero autorizado)
A77: Terceras Personas | B77: Abogados y Notarios | C77: Otros servicios al contribuyente | D77: Alcohol y combustibles | E77: Requisitos para el Registro y Emisión de Autorización de la Superintendencia de Administración Tributaria al Impuesto a la Distribución de Petróleo Crudo y Combustible Derivados del Petróleo | F77: Registro de exentos del impuesto a combustibles | G77: Información sobre: Registro de exentos del impuesto a combustibles. | H77: Terceras Personas: Abogados y Notarios, Peritos Contadores, Auditores | I77: Grupos y categorías | J77: Marcada «SI» en el archivo Grupos y categorías | K77: SERVICIOS TRIBUTARIOS | L77: https://portal.sat.gob.gt/portal/requisitos-tramites-agencias/solicitud-de-registro-de-personas-exentas-del-impuesto-a-la-distribucion-de-petroleo-crudo-y-combustibles-derivados-del-petroleo/ | M77: Servicio/tema general para contribuyentes
A78: Terceras Personas | B78: Abogados y Notarios | C78: Otros servicios al contribuyente | D78: Constancias y gestiones del RTU | E78: RTU Digital | F78: RTU Digital: gestiones de tu registro en línea | G78: Información sobre: RTU Digital: gestiones de tu registro en línea. | H78: Terceras Personas: Abogados y Notarios, Peritos Contadores, Auditores | I78: Grupos y categorías | J78: Marcada «SI» en el archivo Grupos y categorías | K78: SERVICIOS TRIBUTARIOS | L78: https://portal.sat.gob.gt/portal/rtu-digital/ | M78: Servicio/tema general para contribuyentes
A79: Terceras Personas | B79: Abogados y Notarios | C79: Agregada desde «Grupos y categorías» | F79: Sistema Retenciones Web -ICT- | G79: Información y documentación de soporte sobre el sistema que tienen a disposición todas las personas individuales o jurídicas afiliadas al Impuesto a la Confianza Tributaria. | H79: Terceras Personas: Abogados y Notarios, Peritos Contadores, Auditores | I79: Grupos y categorías | J79: Marcada «SI» en el archivo Grupos y categorías | L79: https://portal.sat.gob.gt/portal/sistemas-web/retencioneswebict/
A80: Terceras Personas | B80: Peritos Contadores | C80: Cultura tributaria y capacitación | D80: Preguntas frecuentes | E80: Contribuyentes Especiales | F80: Preguntas frecuentes: contribuyentes especiales | G80: Respuestas a las preguntas más comunes sobre contribuyentes especiales. | H80: Terceras Personas: Abogados y Notarios, Peritos Contadores, Auditores | I80: Grupos y categorías | J80: Marcada «SI» en el archivo Grupos y categorías | K80: CAPACITACIÓN | L80: https://portal.sat.gob.gt/portal/preguntas-frecuentes/contribuyentes-especiales/ | M80: Servicio/tema general para contribuyentes
A81: Terceras Personas | B81: Peritos Contadores | C81: Inscripción y actualización en el RTU | D81: Contadores, auditores y gestores | E81: Actualización de Peritos Contadores | F81: Actualizar tus datos como perito contador | G81: Requisitos, pasos y documentos para actualizar tus datos como perito contador. | I81: Análisis | J81: Registro de contadores | K81: SERVICIOS TRIBUTARIOS | L81: https://portal.sat.gob.gt/portal/requisitos-tramites-agencias/actualizacion-al-registro-de-peritos-contadores-o-contadores-publicos-y-auditores/ | M81: Servicio/tema general para contribuyentes
A82: Terceras Personas | B82: Peritos Contadores | C82: Inscripción y actualización en el RTU | D82: Contadores, auditores y gestores | E82: Aviso de Baja como Contador Registrado en Agencia Virtual | F82: Darte de baja como contador en Agencia Virtual | G82: Requisitos, pasos y documentos para darte de baja como contador en Agencia Virtual. | I82: Análisis | J82: Registro de contadores | K82: SERVICIOS TRIBUTARIOS | L82: https://portal.sat.gob.gt/portal/aviso-de-baja-como-contador-registrado-en-agencia-virtual/ | M82: Servicio/tema general para contribuyentes
A83: Terceras Personas | B83: Peritos Contadores | C83: Inscripción y actualización en el RTU | D83: Contadores, auditores y gestores | E83: Inscripción de Peritos Contadores | F83: Inscribirte como perito contador | G83: Requisitos, pasos y documentos para inscribirte como perito contador. | I83: Análisis | J83: Registro de contadores | K83: SERVICIOS TRIBUTARIOS | L83: https://portal.sat.gob.gt/portal/requisitos-tramites-agencias/inscripcion-de-peritos-contadores/ | M83: Servicio/tema general para contribuyentes
A84: Terceras Personas | B84: Peritos Contadores | C84: Inscripción y actualización en el RTU | D84: Contadores, auditores y gestores | E84: Registro de Contadores En Agencia Virtual | F84: Registrarte como contador en Agencia Virtual | G84: Requisitos, pasos y documentos para registrarte como contador en Agencia Virtual. | I84: Análisis | J84: Registro de contadores | K84: SERVICIOS TRIBUTARIOS | L84: https://portal.sat.gob.gt/portal/registro-de-contadores-en-agencia-virtual/ | M84: Servicio/tema general para contribuyentes
A85: Terceras Personas | B85: Peritos Contadores | C85: Otros servicios al contribuyente | D85: Alcohol y combustibles | E85: Requisitos para el Registro y Emisión de Autorización de la Superintendencia de Administración Tributaria al Impuesto a la Distribución de Petróleo Crudo y Combustible Derivados del Petróleo | F85: Registro de exentos del impuesto a combustibles | G85: Información sobre: Registro de exentos del impuesto a combustibles. | H85: Terceras Personas: Abogados y Notarios, Peritos Contadores, Auditores | I85: Grupos y categorías | J85: Marcada «SI» en el archivo Grupos y categorías | K85: SERVICIOS TRIBUTARIOS | L85: https://portal.sat.gob.gt/portal/requisitos-tramites-agencias/solicitud-de-registro-de-personas-exentas-del-impuesto-a-la-distribucion-de-petroleo-crudo-y-combustibles-derivados-del-petroleo/ | M85: Servicio/tema general para contribuyentes
A86: Terceras Personas | B86: Peritos Contadores | C86: Otros servicios al contribuyente | D86: Constancias y gestiones del RTU | E86: RTU Digital | F86: RTU Digital: gestiones de tu registro en línea | G86: Información sobre: RTU Digital: gestiones de tu registro en línea. | H86: Terceras Personas: Abogados y Notarios, Peritos Contadores, Auditores | I86: Grupos y categorías | J86: Marcada «SI» en el archivo Grupos y categorías | K86: SERVICIOS TRIBUTARIOS | L86: https://portal.sat.gob.gt/portal/rtu-digital/ | M86: Servicio/tema general para contribuyentes
A87: Terceras Personas | B87: Peritos Contadores | C87: Agregada desde «Grupos y categorías» | F87: Sistema Retenciones Web -ICT- | G87: Información y documentación de soporte sobre el sistema que tienen a disposición todas las personas individuales o jurídicas afiliadas al Impuesto a la Confianza Tributaria. | H87: Terceras Personas: Abogados y Notarios, Peritos Contadores, Auditores | I87: Grupos y categorías | J87: Marcada «SI» en el archivo Grupos y categorías | L87: https://portal.sat.gob.gt/portal/sistemas-web/retencioneswebict/
A88: Terceras Personas | B88: Auditores | C88: Cultura tributaria y capacitación | D88: Preguntas frecuentes | E88: Contribuyentes Especiales | F88: Preguntas frecuentes: contribuyentes especiales | G88: Respuestas a las preguntas más comunes sobre contribuyentes especiales. | H88: Terceras Personas: Abogados y Notarios, Peritos Contadores, Auditores | I88: Grupos y categorías | J88: Marcada «SI» en el archivo Grupos y categorías | K88: CAPACITACIÓN | L88: https://portal.sat.gob.gt/portal/preguntas-frecuentes/contribuyentes-especiales/ | M88: Servicio/tema general para contribuyentes
A89: Terceras Personas | B89: Auditores | C89: Devoluciones y créditos fiscales | D89: Contador que emite el dictamen | E89: Actualización de Contador Público y Auditor para emisión de Dictámenes de Devolución de Crédito Fiscal Régimen Optativo | F89: Actualizar tus datos como contador que emite dictámenes de devolución | G89: Requisitos, pasos y documentos para actualizar tus datos como contador que emite dictámenes de devolución. | I89: Análisis | J89: Dictamen de contador público y auditor | K89: SERVICIOS TRIBUTARIOS | L89: https://portal.sat.gob.gt/portal/requisitos-tramites-agencias/actualizacion-de-contador-publico-y-auditor-para-emision-de-dictamenes-de-devolucion-de-credito-fiscal-regimen-optativo/ | M89: Servicio/tema general para contribuyentes
A90: Terceras Personas | B90: Auditores | C90: Devoluciones y créditos fiscales | D90: Contador que emite el dictamen | E90: Inscripción de Contador Público y Auditor para emisión de Dictámenes de Devolución de Crédito Fiscal Régimen Optativo | F90: Inscribirte como contador para emitir dictámenes de devolución | G90: Requisitos, pasos y documentos para inscribirte como contador para emitir dictámenes de devolución. | I90: Análisis | J90: Dictamen de contador público y auditor | K90: SERVICIOS TRIBUTARIOS | L90: https://portal.sat.gob.gt/portal/requisitos-tramites-agencias/inscripcion-de-contador-publico-y-auditor-emisor-de-dictamenes/ | M90: Servicio/tema general para contribuyentes
A91: Terceras Personas | B91: Auditores | C91: Inscripción y actualización en el RTU | D91: Contadores, auditores y gestores | E91: Actualización de Auditores | F91: Actualizar tus datos como auditor | G91: Requisitos, pasos y documentos para actualizar tus datos como auditor. | I91: Análisis | J91: Registro de auditores | K91: SERVICIOS TRIBUTARIOS | L91: https://portal.sat.gob.gt/portal/requisitos-tramites-agencias/actualizacion-de-auditores/ | M91: Servicio/tema general para contribuyentes
A92: Terceras Personas | B92: Auditores | C92: Inscripción y actualización en el RTU | D92: Contadores, auditores y gestores | E92: Inscripcion de Auditores | F92: Inscribirte como auditor | G92: Requisitos, pasos y documentos para inscribirte como auditor. | I92: Análisis | J92: Registro de auditores | K92: SERVICIOS TRIBUTARIOS | L92: https://portal.sat.gob.gt/portal/requisitos-tramites-agencias/inscripcion-de-auditores/ | M92: Servicio/tema general para contribuyentes
A93: Terceras Personas | B93: Auditores | C93: Otros servicios al contribuyente | D93: Alcohol y combustibles | E93: Requisitos para el Registro y Emisión de Autorización de la Superintendencia de Administración Tributaria al Impuesto a la Distribución de Petróleo Crudo y Combustible Derivados del Petróleo | F93: Registro de exentos del impuesto a combustibles | G93: Información sobre: Registro de exentos del impuesto a combustibles. | H93: Terceras Personas: Abogados y Notarios, Peritos Contadores, Auditores | I93: Grupos y categorías | J93: Marcada «SI» en el archivo Grupos y categorías | K93: SERVICIOS TRIBUTARIOS | L93: https://portal.sat.gob.gt/portal/requisitos-tramites-agencias/solicitud-de-registro-de-personas-exentas-del-impuesto-a-la-distribucion-de-petroleo-crudo-y-combustibles-derivados-del-petroleo/ | M93: Servicio/tema general para contribuyentes
A94: Terceras Personas | B94: Auditores | C94: Otros servicios al contribuyente | D94: Constancias y gestiones del RTU | E94: RTU Digital | F94: RTU Digital: gestiones de tu registro en línea | G94: Información sobre: RTU Digital: gestiones de tu registro en línea. | H94: Terceras Personas: Abogados y Notarios, Peritos Contadores, Auditores | I94: Grupos y categorías | J94: Marcada «SI» en el archivo Grupos y categorías | K94: SERVICIOS TRIBUTARIOS | L94: https://portal.sat.gob.gt/portal/rtu-digital/ | M94: Servicio/tema general para contribuyentes
A95: Terceras Personas | B95: Auditores | C95: Agregada desde «Grupos y categorías» | F95: Sistema Retenciones Web -ICT- | G95: Información y documentación de soporte sobre el sistema que tienen a disposición todas las personas individuales o jurídicas afiliadas al Impuesto a la Confianza Tributaria. | H95: Terceras Personas: Abogados y Notarios, Peritos Contadores, Auditores | I95: Grupos y categorías | J95: Marcada «SI» en el archivo Grupos y categorías | L95: https://portal.sat.gob.gt/portal/sistemas-web/retencioneswebict/

Sheet Organismos especiales
A1: Organismos especiales
A2: Entidades exentas y entidades del Estado que se relacionan con la SAT por régimen especial o por coordinación institucional. Orden: Categoría › Grupo › Tema › Página. «Todos los grupos» = la usan todos los grupos de la categoría. «Trámites comunes» = la usan varias categorías.
A4: Categoría | B4: Grupo | C4: Tema | D4: Subtema | E4: Página / Trámite (nombre actual) | F4: Nombre de trámite sugerido | G4: Descripción de la página | H4: Usado por (según Grupos y categorías) | I4: Origen de la clasificación | J4: Motivo / referencia | K4: Sección actual del menú | L4: URL | M4: Nota / Revisar
A5: Exentos | B5: Todos los grupos | C5: Facturación electrónica y documentos tributarios | D5: Constancias de exención (CIVA y CAIS) | E5: Habilitación para emisión de CIVA | F5: Habilitarte para emitir constancias de exención de IVA (CIVA) | G5: Requisitos, pasos y documentos para habilitarte para emitir constancias de exención de IVA (CIVA). | I5: Análisis | J5: Constancias de exención de IVA que emiten los entes exentos | K5: SERVICIOS TRIBUTARIOS | L5: https://portal.sat.gob.gt/portal/requisitos-tramites-agencias/habilitacion-para-la-emision-de-constancias-de-exencion-de-iva-civa/ | M5: Servicio/tema general para contribuyentes
A6: Exentos | B6: Constitucionales | C6: Declaraciones, pagos y solvencias | D6: Formas de pago y convenios | E6: Consulta Movimiento de Pago: Facilidades de pago | F6: Consultar pagos de tu convenio | G6: Servicio en línea para consultar pagos de tu convenio. | H6: Exentos: Constitucionales, No Lucrativos, Decreto, Municipalidades | I6: Grupos y categorías | J6: Marcada «SI» en el archivo Grupos y categorías | K6: SERVICIOS TRIBUTARIOS | L6: https://portal.sat.gob.gt/portal/consulta-movimiento-convenio/ | M6: Servicio/tema general para contribuyentes
A7: Exentos | B7: Constitucionales | C7: Declaraciones, pagos y solvencias | D7: Solvencia fiscal | E7: Bitácora de Solvencia Fiscal | F7: Historial de solvencias fiscales | G7: Información sobre: Historial de solvencias fiscales. | H7: Exentos: Constitucionales, No Lucrativos, Decreto, Municipalidades | I7: Grupos y categorías | J7: Marcada «SI» en el archivo Grupos y categorías | K7: SERVICIOS TRIBUTARIOS | L7: https://portal.sat.gob.gt/portal/bitacora-de-solvencia-fiscal/ | M7: Servicio/tema general para contribuyentes
A8: Exentos | B8: Constitucionales | C8: Declaraciones, pagos y solvencias | D8: Solvencia fiscal | E8: Falta Solvencia Fiscal | F8: ¿Por qué no tengo solvencia fiscal? | G8: Información general: ¿Por qué no tengo solvencia fiscal? | H8: Exentos: Constitucionales, No Lucrativos, Decreto, Municipalidades | I8: Grupos y categorías | J8: Marcada «SI» en el archivo Grupos y categorías | K8: SERVICIOS TRIBUTARIOS | L8: https://portal.sat.gob.gt/portal/solvencia-fiscal/ | M8: Servicio/tema general para contribuyentes
A9: Exentos | B9: Constitucionales | C9: Gestiones y consultas aduaneras | D9: Centros educativos | E9: Actualización Centros Educativos, Centros Educativos Públicos Comunitarios | F9: Actualizar los datos de un centro educativo | G9: Requisitos, pasos y documentos para actualizar los datos de un centro educativo. | I9: Análisis | J9: Centros educativos (Constitución, art. 88) | K9: SERVICIOS TRIBUTARIOS | L9: https://portal.sat.gob.gt/portal/requisitos-tramites-agencias/actualizacion-centros-educativos-centros-educativos-publicos-comunitarios/ | M9: Coincide con palabra clave de comercio exterior/aduanas
A10: Exentos | B10: Constitucionales | C10: Gestiones y consultas aduaneras | D10: Centros educativos | E10: Obligaciones Tributarias para Centros Educativos | F10: Curso: obligaciones tributarias de centros educativos | G10: Capacitación virtual de la SAT sobre obligaciones tributarias de centros educativos. | I10: Análisis | J10: Centros educativos (Constitución, art. 88) | K10: CAPACITACIÓN | L10: https://sites.google.com/capacitacionessat.page/cultura-tributariad/cursos-virtuales-sat/temas-varios/28-obligaciones-tributarias-para-los-centros-educativos | M10: Coincide con palabra clave de comercio exterior/aduanas
A11: Exentos | B11: Constitucionales | C11: Gestiones y consultas aduaneras | D11: Centros educativos | E11: Inscripción de Centros Educativos, Centros Educativos Públicos Comunitarios | F11: Inscribir un centro educativo | G11: Requisitos, pasos y documentos para inscribir un centro educativo. | I11: Análisis | J11: Centros educativos (Constitución, art. 88) | K11: SERVICIOS TRIBUTARIOS | L11: https://portal.sat.gob.gt/portal/requisitos-tramites-agencias/inscripcion-centros-educativos-centros-educativos-publicos-comunitarios-asociacion-educativa/ | M11: Coincide con palabra clave de comercio exterior/aduanas
A12: Exentos | B12: Constitucionales | C12: Gestiones y consultas aduaneras | D12: Centros educativos | E12: Solicitud de Actividades: Solicitud para llevar a cabo en centros educativos actividades de Cultura Tributaria | F12: Solicitar actividades de cultura tributaria en tu centro educativo | G12: Requisitos, pasos y documentos para solicitar actividades de cultura tributaria en tu centro educativo. | I12: Análisis | J12: Centros educativos (Constitución, art. 88) | K12: CAPACITACIÓN | L12: https://docs.google.com/forms/d/e/1FAIpQLScCxvGsehcWigqXjUu4yH5KwFZF-HDCrOwY-zL8SqwWhuZ-fQ/viewform | M12: Coincide con palabra clave de comercio exterior/aduanas
A13: Exentos | B13: Constitucionales | C13: Inscripción y actualización en el RTU | D13: Clubes y federaciones deportivas | E13: Actualización de Federaciones Deportivas | F13: Actualizar los datos de una federación deportiva | G13: Requisitos, pasos y documentos para actualizar los datos de una federación deportiva. | I13: Análisis | J13: Deporte federado autónomo (Constitución, arts. 91-92) | K13: SERVICIOS TRIBUTARIOS | L13: https://portal.sat.gob.gt/portal/requisitos-tramites-agencias/actualizacion-de-federaciones-deportivas/ | M13: Servicio/tema general para contribuyentes
A14: Exentos | B14: Constitucionales | C14: Inscripción y actualización en el RTU | D14: Iglesia Católica | E14: Actualización Iglesia Católica | F14: Actualizar los datos de una entidad de la Iglesia Católica | G14: Requisitos, pasos y documentos para actualizar los datos de una entidad de la Iglesia Católica. | I14: Análisis | J14: Exención constitucional (Constitución, arts. 37 y 88) | K14: SERVICIOS TRIBUTARIOS | L14: https://portal.sat.gob.gt/portal/requisitos-tramites-agencias/actualizacion-iglesia-catolica/ | M14: Servicio/tema general para contribuyentes
A15: Exentos | B15: Constitucionales | C15: Inscripción y actualización en el RTU | D15: Iglesia Católica | E15: Cancelación de nombramiento de representante legal de iglesia católica | F15: Cancelar al representante legal de una entidad de la Iglesia Católica | G15: Requisitos, pasos y documentos para cancelar al representante legal de una entidad de la Iglesia Católica. | I15: Análisis | J15: Exención constitucional (Constitución, arts. 37 y 88) | K15: SERVICIOS TRIBUTARIOS | L15: https://portal.sat.gob.gt/portal/requisitos-tramites-agencias/cancelacion-de-nombramiento-de-representante-legal-de-iglesia-catolica/ | M15: Servicio/tema general para contribuyentes
A16: Exentos | B16: Constitucionales | C16: Inscripción y actualización en el RTU | D16: Iglesia Católica | E16: Inscripción de Iglesia Católica | F16: Inscribir una entidad de la Iglesia Católica | G16: Requisitos, pasos y documentos para inscribir una entidad de la Iglesia Católica. | I16: Análisis | J16: Exención constitucional (Constitución, arts. 37 y 88) | K16: SERVICIOS TRIBUTARIOS | L16: https://portal.sat.gob.gt/portal/requisitos-tramites-agencias/inscripcion-iglesia-catolica/ | M16: Servicio/tema general para contribuyentes
A17: Exentos | B17: Constitucionales | C17: Inscripción y actualización en el RTU | D17: Universidades privadas | E17: Actualización Universidad Privada Empresa/Organización (Persona Jurídica) | F17: Actualizar los datos de una universidad privada | G17: Requisitos, pasos y documentos para actualizar los datos de una universidad privada. | I17: Análisis | J17: Exención constitucional (Constitución, arts. 37 y 88) | K17: SERVICIOS TRIBUTARIOS | L17: https://portal.sat.gob.gt/portal/requisitos-tramites-agencias/actualizacion-universidad-privada-empresa-organizacion-persona-juridica/ | M17: Servicio/tema general para contribuyentes
A18: Exentos | B18: Constitucionales | C18: Inscripción y actualización en el RTU | D18: Universidades privadas | E18: Inscripción de Universidad Privada | F18: Inscribir una universidad privada | G18: Requisitos, pasos y documentos para inscribir una universidad privada. | I18: Análisis | J18: Exención constitucional (Constitución, arts. 37 y 88) | K18: SERVICIOS TRIBUTARIOS | L18: https://portal.sat.gob.gt/portal/requisitos-tramites-agencias/inscripcion-universidad-privada/ | M18: Servicio/tema general para contribuyentes
A19: Exentos | B19: Constitucionales | C19: Notarios | D19: Traspasos y avisos | E19: Requisitos Gestiones Vehículos para Notarios: Requisitos para Trámites de Notarios | F19: Requisitos para Avisos de Notarios | G19: Requisitos para el aviso de legalización de firmas en certificado de propiedad de vehículos y aviso de transferencia de dominio de vehículos. | H19: Exentos: Constitucionales, No Lucrativos, Decreto, Municipalidades | I19: Grupos y categorías | J19: Marcada «SI» en el archivo Grupos y categorías | K19: SERVICIOS TRIBUTARIOS | L19: https://portal.sat.gob.gt/portal/requisitos-tramites-notarios/ | M19: Rol profesional (agente aduanero, notario, abogado, gestor, tercero autorizado)
A20: Exentos | B20: Constitucionales | C20: Otros servicios al contribuyente | D20: Calculadoras y listados | E20: Económico Coactivo: Listado de Contribuyentes Morosos | F20: Consultar listado de contribuyentes morosos | G20: Servicio en línea para consultar listado de contribuyentes morosos. | H20: Exentos: Constitucionales, No Lucrativos, Decreto, Municipalidades | I20: Grupos y categorías | J20: Marcada «SI» en el archivo Grupos y categorías | K20: SERVICIOS TRIBUTARIOS | L20: https://portal.sat.gob.gt/portal/listado-de-contribuyentes-morosos/ | M20: Servicio/tema general para contribuyentes
A21: Exentos | B21: Constitucionales | C21: Otros servicios al contribuyente | D21: Constancias y gestiones del RTU | E21: Tercera Persona Autorizada en Gestiones de RTU | F21: Autorizar a otra persona para gestiones del RTU | G21: Requisitos, pasos y documentos para autorizar a otra persona para gestiones del RTU. | H21: Exentos: Constitucionales, No Lucrativos, Decreto, Municipalidades | I21: Grupos y categorías | J21: Marcada «SI» en el archivo Grupos y categorías | K21: SERVICIOS TRIBUTARIOS | L21: https://portal.sat.gob.gt/portal/requisitos-tramites-agencias/tercera-persona-autorizada-rtu/ | M21: Servicio/tema general para contribuyentes
A22: Exentos | B22: Constitucionales | C22: Otros servicios al contribuyente | D22: Constancias y gestiones del RTU | E22: Requisitos de persona/empresa | F22: Requisitos para la Actualización RTU | G22: Requisitos sobre actualización de actividad economica, afiliaciones, cooperativa, datos de identificación, domicilio fiscal, entidades del estado, federaciones deportivas, datos de establecimiento, cambio de regimenes, nombramiento o cambio de peritos contadores y representantes legales. | H22: Exentos: Constitucionales, No Lucrativos, ZOLIC | I22: Grupos y categorías | J22: Marcada «SI» en el archivo Grupos y categorías | K22: SERVICIOS TRIBUTARIOS | L22: https://portal.sat.gob.gt/portal/requisitos-de-personas-empresas/ | M22: Servicio/tema general para contribuyentes
A23: Exentos | B23: Constitucionales | C23: Otros servicios al contribuyente | D23: Constancias y gestiones del RTU | E23: Confederación Deportiva Autónoma de Guatemala | F23: Trámites de la Confederación Deportiva Autónoma (CDAG) | G23: Información sobre: Trámites de la Confederación Deportiva Autónoma (CDAG). | I23: Análisis | J23: Deporte federado (Constitución, arts. 91-92) | K23: SERVICIOS TRIBUTARIOS | L23: https://portal.sat.gob.gt/portal/requisitos-tramites-agencias/confederacion-deportiva-autonoma-de-guatemala/ | M23: Servicio/tema general para contribuyentes
A24: Exentos | B24: Constitucionales | C24: Vehículos (como propietario) | D24: Requisitos y representantes | E24: Requisitos Gestiones Vehículos para Propietarios: Requisitos de Vehiculos | F24: Requisitos para el Registro de Marca y Código de Fabricante | G24: Requisitos listado de pasos y casos especiales; para el Registro de Marca y Código de Fabricante del vehículo. | H24: Exentos: Constitucionales, No Lucrativos, Decreto, Municipalidades | I24: Grupos y categorías | J24: Marcada «SI» en el archivo Grupos y categorías | K24: SERVICIOS TRIBUTARIOS | L24: https://portal.sat.gob.gt/portal/requisitos-de-vehiculos/ | M24: Servicio/tema general para contribuyentes
A25: Exentos | B25: Constitucionales | C25: Vehículos (como propietario) | D25: Requisitos y representantes | E25: Requisitos Gestiones Vehículos para Propietarios: Requisitos de Vehiculos | F25: Requisitos para los Cambios, Rectificaciones o Transformaciones de Vehículos | G25: Requisitos sobre Cambios, Rectificaciones o Transformaciones a los datos de vehículos. | H25: Exentos: Constitucionales, No Lucrativos, Decreto, Municipalidades | I25: Grupos y categorías | J25: Marcada «SI» en el archivo Grupos y categorías | K25: SERVICIOS TRIBUTARIOS | L25: https://portal.sat.gob.gt/portal/requisitos-de-vehiculos/ | M25: Servicio/tema general para contribuyentes
A26: Exentos | B26: Constitucionales | C26: Vehículos (como propietario) | D26: Requisitos y representantes | E26: Requisitos Gestiones Vehículos para Propietarios: Requisitos de Vehiculos | F26: Requisitos sobre Traspaso Electrónico de Vehículos a través de Notarios | G26: Información sobre traspaso electrónico de vehículos por notario con anexo del certificado de propiedad emitido vía Declaraguate en Agencia Virtual, entrega de documentos de traspaso electrónico en Agencia Virtual y Requisitos para remitir documentación electrónica o digital de TEV. | H26: Exentos: Constitucionales, No Lucrativos, Decreto | I26: Grupos y categorías | J26: Marcada «SI» en el archivo Grupos y categorías | K26: SERVICIOS TRIBUTARIOS | L26: https://portal.sat.gob.gt/portal/requisitos-de-vehiculos/ | M26: Servicio/tema general para contribuyentes
A27: Exentos | B27: Constitucionales | C27: Vehículos (como propietario) | D27: Título y tarjeta de circulación | E27: Actualización de Distintivos | F27: Actualizar el título y la tarjeta de circulación | G27: Requisitos, pasos y documentos para actualizar el título y la tarjeta de circulación. | H27: Exentos: Constitucionales, No Lucrativos, Decreto, Municipalidades | I27: Grupos y categorías | J27: Marcada «SI» en el archivo Grupos y categorías | K27: SERVICIOS TRIBUTARIOS | L27: https://portal.sat.gob.gt/portal/requisitos-tramites-agencias/actualizacion-de-distintivos/ | M27: Servicio/tema general para contribuyentes
A28: Exentos | B28: No Lucrativos | C28: Declaraciones, pagos y solvencias | D28: Formas de pago y convenios | E28: Consulta Movimiento de Pago: Facilidades de pago | F28: Consultar pagos de tu convenio | G28: Servicio en línea para consultar pagos de tu convenio. | H28: Exentos: Constitucionales, No Lucrativos, Decreto, Municipalidades | I28: Grupos y categorías | J28: Marcada «SI» en el archivo Grupos y categorías | K28: SERVICIOS TRIBUTARIOS | L28: https://portal.sat.gob.gt/portal/consulta-movimiento-convenio/ | M28: Servicio/tema general para contribuyentes
A29: Exentos | B29: No Lucrativos | C29: Declaraciones, pagos y solvencias | D29: Solvencia fiscal | E29: Bitácora de Solvencia Fiscal | F29: Historial de solvencias fiscales | G29: Información sobre: Historial de solvencias fiscales. | H29: Exentos: Constitucionales, No Lucrativos, Decreto, Municipalidades | I29: Grupos y categorías | J29: Marcada «SI» en el archivo Grupos y categorías | K29: SERVICIOS TRIBUTARIOS | L29: https://portal.sat.gob.gt/portal/bitacora-de-solvencia-fiscal/ | M29: Servicio/tema general para contribuyentes
A30: Exentos | B30: No Lucrativos | C30: Declaraciones, pagos y solvencias | D30: Solvencia fiscal | E30: Falta Solvencia Fiscal | F30: ¿Por qué no tengo solvencia fiscal? | G30: Información general: ¿Por qué no tengo solvencia fiscal? | H30: Exentos: Constitucionales, No Lucrativos, Decreto, Municipalidades | I30: Grupos y categorías | J30: Marcada «SI» en el archivo Grupos y categorías | K30: SERVICIOS TRIBUTARIOS | L30: https://portal.sat.gob.gt/portal/solvencia-fiscal/ | M30: Servicio/tema general para contribuyentes
A31: Exentos | B31: No Lucrativos | C31: Inscripción y actualización en el RTU | D31: Asociaciones, fundaciones y ONG | E31: Actualización Persona Jurídica no Lucrativa | F31: Actualizar los datos de una entidad sin fines de lucro | G31: Requisitos, pasos y documentos para actualizar los datos de una entidad sin fines de lucro. | I31: Análisis | J31: Entidad no lucrativa (ISR, Decreto 10-2012, art. 11) | K31: SERVICIOS TRIBUTARIOS | L31: https://portal.sat.gob.gt/portal/requisitos-tramites-agencias/actualizacion-persona-juridica-no-lucrativa/ | M31: Servicio/tema general para contribuyentes
A32: Exentos | B32: No Lucrativos | C32: Inscripción y actualización en el RTU | D32: Asociaciones, fundaciones y ONG | E32: Cese de Actividades Persona Jurídica No Lucrativa | F32: Cerrar una entidad sin fines de lucro | G32: Requisitos, pasos y documentos para cerrar una entidad sin fines de lucro. | I32: Análisis | J32: Entidad no lucrativa (ISR, Decreto 10-2012, art. 11) | K32: SERVICIOS TRIBUTARIOS | L32: https://portal.sat.gob.gt/portal/requisitos-tramites-agencias/cese-de-actividades-persona-juridica-no-lucrativa/ | M32: Servicio/tema general para contribuyentes
A33: Exentos | B33: No Lucrativos | C33: Inscripción y actualización en el RTU | D33: Asociaciones, fundaciones y ONG | E33: Inscripción de Organización No Gubernamental –ONG- inscritas en el Registro de Personas Jurídicas –REPEJU- antes del 3 de agosto 2022 | F33: Inscribir una ONG registrada antes del 3 de agosto de 2022 | G33: Requisitos, pasos y documentos para inscribir una ONG registrada antes del 3 de agosto de 2022. | I33: Análisis | J33: Entidad no lucrativa (ISR, Decreto 10-2012, art. 11) | K33: SERVICIOS TRIBUTARIOS | L33: https://portal.sat.gob.gt/portal/requisitos-tramites-agencias/inscripcion-de-organizacion-no-gubernamental-ong-inscritas-en-el-registro-de-personas-juridicas-repeju-antes-del-3-de-agosto-2022/ | M33: Servicio/tema general para contribuyentes
A34: Exentos | B34: No Lucrativos | C34: Inscripción y actualización en el RTU | D34: Asociaciones, fundaciones y ONG | E34: Inscripción de Organización No Gubernamental –ONG- inscritas en el Registro de Personas Jurídicas –REPEJU- a partir del 3 de agosto 2022 | F34: Inscribir una ONG registrada desde el 3 de agosto de 2022 | G34: Requisitos, pasos y documentos para inscribir una ONG registrada desde el 3 de agosto de 2022. | I34: Análisis | J34: Entidad no lucrativa (ISR, Decreto 10-2012, art. 11) | K34: SERVICIOS TRIBUTARIOS | L34: https://portal.sat.gob.gt/portal/requisitos-tramites-agencias/inscripcion-de-organizacion-no-gubernamental-ong-inscritas-en-el-registro-de-personas-juridicas-repeju-a-partir-del-3-de-agosto-2022/ | M34: Servicio/tema general para contribuyentes
A35: Exentos | B35: No Lucrativos | C35: Inscripción y actualización en el RTU | D35: Asociaciones, fundaciones y ONG | E35: Inscripción de: Fundación, Otra Entidad Religiosa, Asociación | F35: Inscribir una fundación, asociación o entidad religiosa | G35: Requisitos, pasos y documentos para inscribir una fundación, asociación o entidad religiosa. | I35: Análisis | J35: Entidad no lucrativa (ISR, Decreto 10-2012, art. 11) | K35: SERVICIOS TRIBUTARIOS | L35: https://portal.sat.gob.gt/portal/requisitos-tramites-agencias/inscripcion-de-fundacion-otra-entidad-religiosa-asociacion/ | M35: Servicio/tema general para contribuyentes
A36: Exentos | B36: No Lucrativos | C36: Inscripción y actualización en el RTU | D36: Asociaciones, fundaciones y ONG | E36: Inscripción de: Fundación, Otra Entidad Religiosa, Asociación Extranjeras | F36: Inscribir una fundación, asociación o entidad religiosa extranjera | G36: Requisitos, pasos y documentos para inscribir una fundación, asociación o entidad religiosa extranjera. | I36: Análisis | J36: Entidad no lucrativa (ISR, Decreto 10-2012, art. 11) | K36: SERVICIOS TRIBUTARIOS | L36: https://portal.sat.gob.gt/portal/requisitos-tramites-agencias/inscripcion-de-fundacion-otra-entidad-religiosa-asociacion-extranjeras/ | M36: Servicio/tema general para contribuyentes
A37: Exentos | B37: No Lucrativos | C37: Inscripción y actualización en el RTU | D37: Organizaciones comunitarias | E37: Actualización de Organizaciones Comunitarias | F37: Actualizar los datos de una organización comunitaria | G37: Requisitos, pasos y documentos para actualizar los datos de una organización comunitaria. | I37: Análisis | J37: Entidad no lucrativa (ISR, Decreto 10-2012, art. 11) | K37: SERVICIOS TRIBUTARIOS | L37: https://portal.sat.gob.gt/portal/requisitos-tramites-agencias/actualizacion-de-organizaciones-comunitarias/ | M37: Servicio/tema general para contribuyentes
A38: Exentos | B38: No Lucrativos | C38: Inscripción y actualización en el RTU | D38: Organizaciones comunitarias | E38: Inscripción de Organizaciones Comunitarias | F38: Inscribir una organización comunitaria | G38: Requisitos, pasos y documentos para inscribir una organización comunitaria. | I38: Análisis | J38: Entidad no lucrativa (ISR, Decreto 10-2012, art. 11) | K38: SERVICIOS TRIBUTARIOS | L38: https://portal.sat.gob.gt/portal/requisitos-tramites-agencias/inscripcion-organizaciones-comunitarias/ | M38: Servicio/tema general para contribuyentes
A39: Exentos | B39: No Lucrativos | C39: Inscripción y actualización en el RTU | D39: Organizaciones de Padres de Familia (OPF) | E39: Actualización de Organización de Padres de Familia | F39: Actualizar los datos de una OPF | G39: Requisitos, pasos y documentos para actualizar los datos de una OPF. | I39: Análisis | J39: Entidad no lucrativa (ISR, Decreto 10-2012, art. 11) | K39: SERVICIOS TRIBUTARIOS | L39: https://portal.sat.gob.gt/portal/requisitos-tramites-agencias/actualizacion-de-organizaciones-de-padres-familia/ | M39: Servicio/tema general para contribuyentes
A40: Exentos | B40: No Lucrativos | C40: Inscripción y actualización en el RTU | D40: Organizaciones de Padres de Familia (OPF) | E40: Inscripción de Organización de Padres de Familia -OPF- | F40: Inscribir una Organización de Padres de Familia (OPF) | G40: Requisitos, pasos y documentos para inscribir una Organización de Padres de Familia (OPF). | I40: Análisis | J40: Entidad no lucrativa (ISR, Decreto 10-2012, art. 11) | K40: SERVICIOS TRIBUTARIOS | L40: https://portal.sat.gob.gt/portal/requisitos-tramites-agencias/organizacion-de-padres-de-familia-opf/ | M40: Servicio/tema general para contribuyentes
A41: Exentos | B41: No Lucrativos | C41: Inscripción y actualización en el RTU | D41: Sindicatos | E41: Inscripción de Sindicato | F41: Inscribir un sindicato | G41: Requisitos, pasos y documentos para inscribir un sindicato. | I41: Análisis | J41: Entidad no lucrativa (ISR, Decreto 10-2012, art. 11) | K41: SERVICIOS TRIBUTARIOS | L41: https://portal.sat.gob.gt/portal/requisitos-tramites-agencias/inscripcion-sindicato/ | M41: Servicio/tema general para contribuyentes
A42: Exentos | B42: No Lucrativos | C42: Notarios | D42: Traspasos y avisos | E42: Requisitos Gestiones Vehículos para Notarios: Requisitos para Trámites de Notarios | F42: Requisitos para Avisos de Notarios | G42: Requisitos para el aviso de legalización de firmas en certificado de propiedad de vehículos y aviso de transferencia de dominio de vehículos. | H42: Exentos: Constitucionales, No Lucrativos, Decreto, Municipalidades | I42: Grupos y categorías | J42: Marcada «SI» en el archivo Grupos y categorías | K42: SERVICIOS TRIBUTARIOS | L42: https://portal.sat.gob.gt/portal/requisitos-tramites-notarios/ | M42: Rol profesional (agente aduanero, notario, abogado, gestor, tercero autorizado)
A43: Exentos | B43: No Lucrativos | C43: Otros servicios al contribuyente | D43: Calculadoras y listados | E43: Económico Coactivo: Listado de Contribuyentes Morosos | F43: Consultar listado de contribuyentes morosos | G43: Servicio en línea para consultar listado de contribuyentes morosos. | H43: Exentos: Constitucionales, No Lucrativos, Decreto, Municipalidades | I43: Grupos y categorías | J43: Marcada «SI» en el archivo Grupos y categorías | K43: SERVICIOS TRIBUTARIOS | L43: https://portal.sat.gob.gt/portal/listado-de-contribuyentes-morosos/ | M43: Servicio/tema general para contribuyentes
A44: Exentos | B44: No Lucrativos | C44: Otros servicios al contribuyente | D44: Constancias y gestiones del RTU | E44: Tercera Persona Autorizada en Gestiones de RTU | F44: Autorizar a otra persona para gestiones del RTU | G44: Requisitos, pasos y documentos para autorizar a otra persona para gestiones del RTU. | H44: Exentos: Constitucionales, No Lucrativos, Decreto, Municipalidades | I44: Grupos y categorías | J44: Marcada «SI» en el archivo Grupos y categorías | K44: SERVICIOS TRIBUTARIOS | L44: https://portal.sat.gob.gt/portal/requisitos-tramites-agencias/tercera-persona-autorizada-rtu/ | M44: Servicio/tema general para contribuyentes
A45: Exentos | B45: No Lucrativos | C45: Otros servicios al contribuyente | D45: Constancias y gestiones del RTU | E45: Requisitos de persona/empresa | F45: Requisitos para Cancelación de Negocios | G45: Requisitos para cese por prescripción, cese de negocios inscritos bajo diferentes modalidades, Cese de NIT administrativo jurídico y habilitación de actividades con cancelación temporal. | H45: Exentos: No Lucrativos | I45: Grupos y categorías | J45: Marcada «SI» en el archivo Grupos y categorías | K45: SERVICIOS TRIBUTARIOS | L45: https://portal.sat.gob.gt/portal/requisitos-de-personas-empresas/ | M45: Servicio/tema general para contribuyentes
A46: Exentos | B46: No Lucrativos | C46: Otros servicios al contribuyente | D46: Constancias y gestiones del RTU | E46: Requisitos de persona/empresa | F46: Requisitos para la Actualización RTU | G46: Requisitos sobre actualización de actividad economica, afiliaciones, cooperativa, datos de identificación, domicilio fiscal, entidades del estado, federaciones deportivas, datos de establecimiento, cambio de regimenes, nombramiento o cambio de peritos contadores y representantes legales. | H46: Exentos: Constitucionales, No Lucrativos, ZOLIC | I46: Grupos y categorías | J46: Marcada «SI» en el archivo Grupos y categorías | K46: SERVICIOS TRIBUTARIOS | L46: https://portal.sat.gob.gt/portal/requisitos-de-personas-empresas/ | M46: Servicio/tema general para contribuyentes
A47: Exentos | B47: No Lucrativos | C47: Otros servicios al contribuyente | D47: Constancias y gestiones del RTU | E47: Requisitos de persona/empresa | F47: Requisitos para la Inscripción RTU | G47: Requisitos para la solicitud electronica de NIT, incripción de NIT con y sin obligaciones, inscripción de copropiedad, sociedades, cooperativas, fideicomiso, sindicato, entidad estatal, univerisidad privada, iglesia católica e inscripción de organizaciones no gubernamentales. | H47: Exentos: No Lucrativos, Decreto | I47: Grupos y categorías | J47: Marcada «SI» en el archivo Grupos y categorías | K47: SERVICIOS TRIBUTARIOS | L47: https://portal.sat.gob.gt/portal/requisitos-de-personas-empresas/ | M47: Servicio/tema general para contribuyentes
A48: Exentos | B48: No Lucrativos | C48: Vehículos (como propietario) | D48: Requisitos y representantes | E48: Requisitos Gestiones Vehículos para Propietarios: Requisitos de Vehiculos | F48: Requisitos para el Registro de Marca y Código de Fabricante | G48: Requisitos listado de pasos y casos especiales; para el Registro de Marca y Código de Fabricante del vehículo. | H48: Exentos: Constitucionales, No Lucrativos, Decreto, Municipalidades | I48: Grupos y categorías | J48: Marcada «SI» en el archivo Grupos y categorías | K48: SERVICIOS TRIBUTARIOS | L48: https://portal.sat.gob.gt/portal/requisitos-de-vehiculos/ | M48: Servicio/tema general para contribuyentes
A49: Exentos | B49: No Lucrativos | C49: Vehículos (como propietario) | D49: Requisitos y representantes | E49: Requisitos Gestiones Vehículos para Propietarios: Requisitos de Vehiculos | F49: Requisitos para los Cambios, Rectificaciones o Transformaciones de Vehículos | G49: Requisitos sobre Cambios, Rectificaciones o Transformaciones a los datos de vehículos. | H49: Exentos: Constitucionales, No Lucrativos, Decreto, Municipalidades | I49: Grupos y categorías | J49: Marcada «SI» en el archivo Grupos y categorías | K49: SERVICIOS TRIBUTARIOS | L49: https://portal.sat.gob.gt/portal/requisitos-de-vehiculos/ | M49: Servicio/tema general para contribuyentes
A50: Exentos | B50: No Lucrativos | C50: Vehículos (como propietario) | D50: Requisitos y representantes | E50: Requisitos Gestiones Vehículos para Propietarios: Requisitos de Vehiculos | F50: Requisitos sobre Traspaso Electrónico de Vehículos a través de Notarios | G50: Información sobre traspaso electrónico de vehículos por notario con anexo del certificado de propiedad emitido vía Declaraguate en Agencia Virtual, entrega de documentos de traspaso electrónico en Agencia Virtual y Requisitos para remitir documentación electrónica o digital de TEV. | H50: Exentos: Constitucionales, No Lucrativos, Decreto | I50: Grupos y categorías | J50: Marcada «SI» en el archivo Grupos y categorías | K50: SERVICIOS TRIBUTARIOS | L50: https://portal.sat.gob.gt/portal/requisitos-de-vehiculos/ | M50: Servicio/tema general para contribuyentes
A51: Exentos | B51: No Lucrativos | C51: Vehículos (como propietario) | D51: Título y tarjeta de circulación | E51: Actualización de Distintivos | F51: Actualizar el título y la tarjeta de circulación | G51: Requisitos, pasos y documentos para actualizar el título y la tarjeta de circulación. | H51: Exentos: Constitucionales, No Lucrativos, Decreto, Municipalidades | I51: Grupos y categorías | J51: Marcada «SI» en el archivo Grupos y categorías | K51: SERVICIOS TRIBUTARIOS | L51: https://portal.sat.gob.gt/portal/requisitos-tramites-agencias/actualizacion-de-distintivos/ | M51: Servicio/tema general para contribuyentes
A52: Exentos | B52: Decreto | C52: Agentes y agencias aduaneras | D52: Renovación | E52: Solicitud de Renovación de Auxiliar de la Función Pública en Unidad de Calificación Registro y Control de Auxiliares de la Función Pública | F52: Renovar tu registro como auxiliar de la función pública aduanera | G52: Requisitos, pasos y documentos para renovar tu registro como auxiliar de la función pública aduanera. | H52: Exentos: Decreto | I52: Grupos y categorías | J52: Marcada «SI» en el archivo Grupos y categorías | K52: ADUANAS | L52: https://portal.sat.gob.gt/portal/requisitos-tramites-aduanas/solicitud-de-renovacion-de-auxiliares-de-la-funcion-publica-en-unidad-de-calificacion-registro-y-control-de-auxiliares-de-la-funcion-publica/ | M52: Rol profesional (agente aduanero, notario, abogado, gestor, tercero autorizado)
A53: Exentos | B53: Decreto | C53: Declaraciones, pagos y solvencias | D53: Formas de pago y convenios | E53: Consulta Movimiento de Pago: Facilidades de pago | F53: Consultar pagos de tu convenio | G53: Servicio en línea para consultar pagos de tu convenio. | H53: Exentos: Constitucionales, No Lucrativos, Decreto, Municipalidades | I53: Grupos y categorías | J53: Marcada «SI» en el archivo Grupos y categorías | K53: SERVICIOS TRIBUTARIOS | L53: https://portal.sat.gob.gt/portal/consulta-movimiento-convenio/ | M53: Servicio/tema general para contribuyentes
... A57: Exentos | B57: Decreto | C57: Facilitación de comercio | D57: Programas | E57: Acuerdo de Facilitación del Comercio OMC: Facilitación de Comercio | F57: Facilitación de Comercio | G57: Información sobre Acuerdos, Estudios, Valoración de Mercancias, Procedimientos, Unión Aduanera, Consulta Pública, Declaración Anticipada y la No Exigibilidad de la declaraciones sobre las mismas, para la Facilitación de Comercio. | H57: Exentos: Decreto | I57: Grupos y categorías | J57: Marcada «SI» en el archivo Grupos y categorías | K57: ADUANAS | L57: https://portal.sat.gob.gt/portal/facilitacion-de-comercio/ | M57: Bajo menú Aduanas
A58: Exentos | B58: Decreto | C58: Facturación electrónica y documentos tributarios | D58: Constancias de exención (CIVA y CAIS) | E58: Habilitación para emision de CAIS | F58: Habilitarte para emitir constancias CAIS | G58: Requisitos, pasos y documentos para habilitarte para emitir constancias CAIS. | I58: Análisis | J58: CAIS: régimen de maquila (Decreto 29-89) | K58: SERVICIOS TRIBUTARIOS | L58: https://portal.sat.gob.gt/portal/requisitos-tramites-agencia-virtual/habilitacion-emision-cais/ | M58: Servicio/tema general para contribuyentes
A59: Exentos | B59: Decreto | C59: Gestiones y consultas aduaneras | D59: Consultas de declaraciones | E59: Monitoreo Histórico de Selectivo en Aduanas | F59: Historial del selectivo en aduanas | G59: Información sobre: Historial del selectivo en aduanas. | H59: Exentos: Decreto | I59: Grupos y categorías | J59: Marcada «SI» en el archivo Grupos y categorías | K59: ADUANAS | L59: https://portal.sat.gob.gt/portal/consultas-aduanas/#1507054761278-36cb86bc-8c2d:~:text=Monitoreo%20Hist%C3%B3rico%20de%20Selectivo%20en%20Aduanas | M59: Bajo menú Aduanas
A60: Exentos | B60: Decreto | C60: Gestiones y consultas aduaneras | D60: Declaraciones (DUA / DUCA) | E60: Declaración de mercancías | F60: Declaración de mercancías | G60: Información sobre la declaración única centroamericana DUCA, declaración única aduanera, aduana sin papeles y su instructivo, codificación de documentos digitalizados y la declaración de valor. | H60: Exentos: Decreto, ZOLIC | I60: Grupos y categorías | J60: Marcada «SI» en el archivo Grupos y categorías | K60: ADUANAS | L60: https://portal.sat.gob.gt/portal/procedimientos-aduanas/#1555105635499-a4507e58-10e9 | M60: Bajo menú Aduanas
