Workbook

Sheet Resumen
H3: SUBGRUPOS
D4: MACROGRUPOS | E4: No. | F4: Grupo | G4: Cantidad Temas | H4: Categoria 1 | I4: Categoria2 | J4: Categoria3 | K4: Categoria4 | L4: Categoria5 | M4: Categoria6 | N4: Categoria7 | O4: Categoria8 | P4: Categoria9
D5: Contribuyentes | E5: 1 | F5: NIT sin Obligaciones | G5: =COUNTIF(NITsinObligaciones[URL],"*") -> 23
E6: 2 | F6: Pequeños Contribuyentes | G6: ='Pequeños Contribuyentes'!D3 -> 39 | H6: Pequeño Contribuyente | I6: Primario | J6: Pecuario
H7: ='Pequeños Contribuyentes'!$D$4 -> 39 | I7: ='Pequeños Contribuyentes'!$D$4 -> 39 | J7: ='Pequeños Contribuyentes'!$D$4 -> 39
E8: 3 | F8: Contribuyente General | G8: =+'Contribuyente General'!$D$3 -> 37 | H8: Contribuyente General | I8: Rep. Legales
H9: =+'Contribuyente General'!$D$7 -> 37 | I9: =+'Contribuyente General'!$E$7 -> 36
E10: 4 | F10: Contribuyentes Especiales | G10: 36 | H10: Medianos | I10: Grandes | J10: Rep. Legales
H11: =COUNTIF(ContribuyentesEspeciales[Medianos], "SI") -> 32 | I11: =COUNTIF(ContribuyentesEspeciales[Grandes], "SI") -> 32 | J11: 36
D12: Operadores de Comercio Exterior | E12: 5 | F12: Importadores y Exportadores | G12: 48 | H12: Importadores | I12: OEA | J12: Exportadores
H13: =+'Importadores y Exportadores'!$D$8 -> 45 | I13: =+'Importadores y Exportadores'!$E$8 -> 46 | J13: =+'Importadores y Exportadores'!$F$8 -> 44
D14: Operadores de Comercio Exterior | E14: 8 | F14: Auxiliares de la Función Públic | G14: =+'Auxiliares Función Pública'!$D$3 -> 50 | H14: Courier | I14: Consolidadores y Desconsolidadores de Carga | J14: Almacenes Fiscales | K14: Almacenadoras | L14: Depósitos Aduaneros | M14: ZDEEP | N14: Agentes Aduaneros | O14: Transportistas | P14: Apoderado Especial Aduanero
H15: =+'Auxiliares Función Pública'!$D$10 -> 48 | I15: =+'Auxiliares Función Pública'!$E$10 -> 47 | J15: =+'Auxiliares Función Pública'!F10 -> 45 | K15: =+'Auxiliares Función Pública'!G10 -> 45 | L15: =+'Auxiliares Función Pública'!$H$10 -> 45 | M15: =+'Auxiliares Función Pública'!$I$10 -> 45 | N15: =+'Auxiliares Función Pública'!$J$10 -> 50 | O15: =+'Auxiliares Función Pública'!$K$10 -> 48 | P15: =+'Auxiliares Función Pública'!L10 -> 45
D16: Profesionales | E16: 7 | F16: Terceras Personas | G16: =+'Terceras Personas'!$D$3 -> 62 | H16: Gestores Tributarios | I16: Auxiliar Tributario | J16: Abogados y Notarios | K16: Peritos Contadores | L16: Auditores
H17: =+'Terceras Personas'!$D$10 -> 53 | I17: =+'Terceras Personas'!$E$10 -> 53 | J17: =+'Terceras Personas'!$F$10 -> 61 | K17: =+'Terceras Personas'!$G$10 -> 61 | L17: =+'Terceras Personas'!$H$10 -> 59
C18: Entes exentos | D18: Entes exentos | E18: 6 | F18: Exentos | G18: =+Exentos!$D$4 -> 49 | H18: Constitucionales | I18: No Lucrativos | J18: Decreto | K18: ZOLIC | L18: Municipalidades
H19: =+Exentos!$D$25 -> 29 | I19: =+Exentos!$E$25 -> 28 | J19: =+Exentos!$F$25 -> 39 | K19: =+Exentos!$G$25 -> 6 | L19: =+Exentos!$H$25 -> 33
C20: Entes exentos | D20: Entes exentos | E20: 9 | F20: Entidades del Estado | G20: =+'Entidades del Estado'!$D$3 -> 26 | H20: Organismo Judicial | I20: Ministerio Público | J20: SENABED / CONABED | K20: PDH
H21: =+'Entidades del Estado'!$D$5 -> 26 | I21: =+'Entidades del Estado'!$E$5 -> 26 | J21: =+'Entidades del Estado'!$F$5 -> 26 | K21: =+'Entidades del Estado'!$G$5 -> 26

Sheet Calidad
A2: Pequeños Contribuyentes | B2: 40 | E2: Informacion Clasificada | F2: Informacion Contactos
A3: ICT Régimen primarios | B3: 40
A4: ICT Régimen pecuario | B4: 40
A5: Contribuyentes Inscritos en Régimen General | B5: 37
A6: Representantes Legales de Contribuyentes Generales | B6: 36
A7: Régimen opcional simplificado
A8: Régimen Sobre Utilidades Lucrativas
A9: Contribuyentes Especiales Medianos (incluye los Especiales Regionales) | B9: 33
A10: Contribuyentes Especiales Grandes (incluye los Especiales Regionales) | B10: 33
A11: Asalariados
A12: Profesionales liberales
A13: Contribuyentes Exentos | B13: 60
A14: Centros Educativos
A15: Estado y Municipalidades | B15: 39
A16: Organizaciones No Gubernamentales (ONG)
A17: Organizaciones Padres de Familia (OPF)
A18: Cooperativas
A19: ZOLIC | B19: 6
A20: Terceras Personas Relacionadas con la Tributación | B20: 72
A21: Gestores Tributarios | B21: 55
A22: Auxiliares Tributarios | B22: 54
A23: Abogados y Notarios | B23: 66
A24: Peritos Contadores | B24: 67
A25: Contadores Públicos y Auditores | B25: 61
A26: Importadores y Exportadores | B26: 49
A27: Importadores | B27: 46
A28: Exportadores | B28: 45
A29: Operador Económico Autorizado | B29: 46
A30: Contribuyentes Bajo Decreto Específico | B30: 46
A31: Empresas Maquiladoras (Decreto 29-89)
A32: Empresas en Zonas Francas (Decreto 65-89)
A33: Empresas en Zonas de Desarrollo Económico Especial Público (ZDEEP) | B33: 45
A34: Auxiliares de la Función Pública Aduanera | B34: 50
A35: Empresas de Courier (69 según informe de los auxiliares en estado activo) | B35: 48
A36: Consolidadoras y Desconsolidadoras de Carga (315) | B36: 47
A37: Depósitos Aduaneros (9) | B37: 45
A38: Agentes Aduaneros (133) | B38: 50
A39: Transportistas (1362) | B39: 48
A40: Entidades del Estado | B40: 28
A41: Organismo Judicial | B41: 28
A42: Ministerio Público | B42: 28
A43: Secretaría Nacional de Bienes en Extinción de Dominio (SENABED) / Consejo Nacional de Bienes en Extinción de Dominio (CONABED) | B43: 28
A44: Procuraduría de los Derechos Humanos | B44: 28

Sheet NIT sin Obligaciones
C2: RESUMEN | D2: NIT sin Obligaciones
C3: Total de Páginas consumidas por interesado | D3: =+C5 -> 23
C5: =COUNTIF(NITsinObligaciones[URL],"*") -> 23
B6: No. | C6: URL | D6: Descripción
B7: 1 | C7: https://farm3.sat.gob.gt/menu/login.jsf | D7: Agencia Virtual Para solicitar acceso, ingresar y realizar gestiones en linea, reinicio de contraseña, cambio de correo electrónico.
B8: 2 | C8: https://portal.sat.gob.gt/portal/consulta-de-gestion-del-contribuyente/ | D8: Estado de Gestión de Agencia Virtual Para verificar el estado de la gestión sobre la solicitud de Agencia Virtual, recuperación de contraseña o cambio de correo electrónico
B9: 3 | C9: https://portal.sat.gob.gt/portal/libre-acceso-la-informacion-publica/ | D9: Acceso a la Información Pública Información relacionada para el cumplimiento de la Ley de Información Pública, así como la solicitud en idiomas español, Kaqchikel, Q'eqchi' y K'iche' y la Unidad de SAT que gestiona las solicitudes.
B10: 4 | C10: https://portal.sat.gob.gt/portal/#capacitacion | D10: Capacitaciones Capacitaciones en diferentes modalidades y Cultura Tributaria sobre temas relacionados al NIT sin Obligaciones
B11: 5 | C11: https://portal.sat.gob.gt/portal/consulta-de-titulos-qr/ | D11: Consulta de Títulos QR Para verificar Títulos Universitarios escaneando el QR
B12: 6 | C12: https://portal.sat.gob.gt/portal/distintivos-electronicos/ | D12: Distintivos Electrónicos (Título de propiedad y Tarjeta de Circulación) Requisitos y guias para obtener Tarjeta de Circulación y Certificado de Propiedad de Vehículo de forma electrónica.
B13: 7 | C13: https://portal.sat.gob.gt/portal/efactura/ | D13: Factura Electrónica Todo lo relacionado con la emisión, la documentación técnica, los certificadores y auditores del certificadores del Régimen de Factura Electrónica en Línea.
B14: 8 | C14: https://portal.sat.gob.gt/portal/planilla-iva-fel/ | D14: Planilla IVA-FEL Información sobre los pasos para presentar tu Planilla de IVA – FEL y manual de uso.
B15: 9 | C15: https://portal.sat.gob.gt/portal/sistemas-web/retencioneswebiva/ | D15: Sistema Retenciones Web -IVA- Información sobre el uso de la herramienta, porcentajes de retención, listado de agentes de retención del impuesto y canales de consultas.
B16: 10 | C16: https://portal.sat.gob.gt/portal/solvencia-fiscal/ | D16: Solvencia Fiscal Consultas de la gestión y el pago de la solicitud.
B17: 11 | C17: https://portal.sat.gob.gt/portal/preguntas-frecuentes/cumplimiento-tributario/ | D17: Preguntas Frecuentes sobre Cumplimiento Tributario Preguntas Frecuentes y respuestas, sobre incumplimientos, ceses de actividades, formularios de pago, emisiones de documentos tributarios, facilidades de pago e impuestos especificos.
B18: 14 | C18: https://portal.sat.gob.gt/portal/preguntas-frecuentes/temas-de-vehiculos/ | D18: Preguntas Frecuentes sobre Vehículos Preguntas frecuentes y respuestas sobre vehículos, impuesto de circulación, terceros autorizados y traspaso por notario.
... B29: 23 | C29: https://portal.sat.gob.gt/portal/libro-electronico-tributario/pequeno-contribuyente/ | D29: Libro Electrónico Tributario Pequeño Contribuyente

Sheet Pequeños Contribuyentes
C2: RESUMEN | D2: PEQUEÑO CONTRIBUYENTE | E2: PRIMARIO | F2: PECUARIOS
C3: Total de Páginas consumidas por interesado | D3: =+D7 -> 39
C4: Cantidad de páginas que consumen por igual todos los interesados | D4: =+D7 -> 39 | E4: =+E7 -> 39 | F4: =+F7 -> 39
D7: =COUNTIF('Pequeños Contribuyentes'!$D$9:$D$48,"*") -> 39 | E7: =COUNTIF('Pequeños Contribuyentes'!$E$9:$E$48,"*") -> 39 | F7: =COUNTIF('Pequeños Contribuyentes'!$F$9:$F$48,"*") -> 39
B8: No | C8: URL | D8: PEQUEÑO CONTRIBUYENTE | E8: PRIMARIO | F8: PECUARIOS | G8: Descripción
B9: 1 | C9: https://farm3.sat.gob.gt/menu/login.jsf | D9: SI | E9: SI | F9: SI | G9: Agencia Virtual Para solicitar acceso, ingresar y realizar gestiones en linea, reinicio de contraseña, cambio de correo electrónico.
B10: 2 | C10: https://portal.sat.gob.gt/portal/libre-acceso-la-informacion-publica/ | D10: SI | E10: SI | F10: SI | G10: Acceso a la Información Pública Información relacionada para el cumplimiento de la Ley de Información Pública, así como la solicitud en idiomas español, Kaqchikel, Q'eqchi' y K'iche' y la Unidad de SAT que gestiona las solicitudes.
B11: 3 | C11: https://portal.sat.gob.gt/portal/tablas-y-acuerdos-vehiculos/ | D11: SI | E11: SI | F11: SI | G11: Acuerdos y Tablas de Valores de Vehículos Información relacionada a tablas y acuerdos de valores imponibles del Impuesto al Valor Agregado para la importación de vehículos.
B12: 4 | C12: https://portal.sat.gob.gt/portal/sistemas-web/asistehospitalesweb/ | D12: SI | E12: SI | F12: SI | G12: Asiste Hospitales Web Información sobre el sistema para registrar los pagos a profesionales que brindan asistencias médicas en instituciónes, de parte de terceros.
B13: 5 | C13: https://portal.sat.gob.gt/portal/autoliquidacion/ | D13: SI | E13: SI | F13: SI | G13: Autoliquidación Cálculo de las sanciones a pagar por presentación y pago extemporáneo o rectificaciones.
B14: 6 | C14: https://portal.sat.gob.gt/portal/#capacitacion | D14: SI | E14: SI | F14: SI | G14: Capacitaciones Capacitaciones en diferentes modalidades y Cultura Tributaria sobre temas relacionados a Pequeño Contribuyente.
B15: 7 | C15: https://portal.sat.gob.gt/portal/consulta-de-titulos-qr/ | D15: SI | E15: SI | F15: SI | G15: Consulta de Títulos QR Para verificar Títulos Universitarios escaneando el QR
B16: 8 | C16: https://portal.sat.gob.gt/portal/consulta-estado-de-cita/ | D16: SI | E16: SI | F16: SI | G16: Consulta estado de cita Realizar la verificación por NIT, Número de Cita o CUI/Pasaporte de tu cita
B17: 9 | C17: https://portal.sat.gob.gt/portal/consulta-movimiento-convenio/ | D17: SI | E17: SI | F17: SI | G17: Consulta Facilidades de Pago Información sobre requisitos, consultas movimiento convenio y preguntas frecuentes.
B18: 10 | C18: https://portal.sat.gob.gt/portal/retenciones-del-iva-consulta-de-constancias-de-retencion-del-iva-recibidas/ | D18: SI | E18: SI | F18: SI | G18: Consulta de constancias de retención del IVA e ISR recibidas Consulta para verificar la validez de las Constancias de Retención de IVA e ISR emitidas por el Agente Retenedor.
B19: 11 | C19: https://portal.sat.gob.gt/portal/declaracion-valor-cero/ | D19: SI | E19: SI | F19: SI | G19: Declaración Valor Cero Para resentar la declaración, en donde no se registraron movimientos en el mes
B20: 12 | C20: https://portal.sat.gob.gt/portal/efactura/ | D20: SI | E20: SI | F20: SI | G20: Factura Electrónica Todo lo relacionado con la emisión, la documentación técnica, los certificadores y auditores del certificadores del Régimen de Factura Electrónica en Línea.
... B47: 39 | C47: https://portal.sat.gob.gt/portal/requisitos-tramites-agencias/despacho-de-distintivos-de-control-de-productos-importados-a-los-fabricantes-o-importadores-domiciliados-en-el-pais-y-a-las-personas-individuales-y-juridicas/ | D47: SI | E47: SI | F47: SI | G47: Requisitos para el Despacho de distintivos de control de productos importados a los fabricantes o importadores domiciliados en el país y a las personas individuales y jurídicas que no sean fabricantes ni importadores Requisitos y listado de pasos.
B48: 23 | C48: https://portal.sat.gob.gt/portal/libro-electronico-tributario/pequeno-contribuyente/ | G48: Libro Electrónico Tributario Pequeño Contribuyente

Sheet Contribuyente General
C2: RESUMEN | D2: Contribuyente General | E2: Rep. Legales
C3: Total de Páginas consumidas por grupos de interés | D3: =+C7 -> 37
C4: Cantidad de páginas que consumen por igual todos los grupos de interés | D4: =COUNTIF(D9:D44,"*") -> 36 | E4: =COUNTIF(E9:E44,"*") -> 36
C5: Cantidad de páginas que consumen individualmente 1/2 de los grupos de interés | D5: =COUNTIF(D46:D46,"*") -> 1
C7: =COUNTIF(C9:C46,"*") -> 37 | D7: =COUNTIF(D9:D46,"*") -> 37 | E7: =COUNTIF(E9:E46,"*") -> 36
B8: No. | C8: URL | D8: Contribuyente General | E8: Rep. Legales | F8: Descripción
B9: 1 | C9: https://portal.sat.gob.gt/portal/libre-acceso-la-informacion-publica/ | D9: SI | E9: SI | F9: Acceso a la Información Pública Información relacionada para el cumplimiento de la Ley de Información Pública, así como la solicitud en idiomas español, Kaqchikel, Q'eqchi' y K'iche' y la Unidad de SAT que gestiona las solicitudes.
B10: 2 | C10: https://portal.sat.gob.gt/portal/autoliquidacion/ | D10: SI | E10: SI | F10: Autoliquidación Cálculo de las sanciones a pagar por presentación y pago extemporáneo o rectificaciones.
B11: 3 | C11: https://portal.sat.gob.gt/portal/#capacitacion | D11: SI | E11: SI | F11: Capacitaciones Capacitaciones en diferentes modalidades y Cultura Tributaria sobre temas relacionados a Contribuyente General.
B12: 4 | C12: https://portal.sat.gob.gt/portal/consulta-estado-de-cita/ | D12: SI | E12: SI | F12: Consulta estado de cita Realizar la verificación por NIT, Número de Cita o CUI/Pasaporte de tu cita
B13: 5 | C13: https://portal.sat.gob.gt/portal/consulta-de-titulos-qr/ | D13: SI | E13: SI | F13: Consulta de Títulos QR Para verificar Títulos Universitarios escaneando el QR
B14: 6 | C14: https://portal.sat.gob.gt/portal/consulta-movimiento-convenio/ | D14: SI | E14: SI | F14: Consulta Facilidades de Pago Información sobre requisitos, consultas movimiento convenio y preguntas frecuentes.
B15: 7 | C15: https://portal.sat.gob.gt/portal/declaracion-valor-cero/ | D15: SI | E15: SI | F15: Declaración Valor Cero Para resentar la declaración, en donde no se registraron movimientos en el mes
B16: 8 | C16: https://portal.sat.gob.gt/portal/emision-constancias-de-adquisicion-de-insumos-y-servicios-cais/ | D16: SI | E16: SI | F16: Emisión Constancias de Adquisición Insumos y Servicios -CAIS- Información para contribuyentes (calificado bajo el Decreto No. 29-89) sobre la generación de -CAIS-.
B17: 9 | C17: https://portal.sat.gob.gt/portal/emision-constancias-de-exencion-de-iva-civa/ | D17: SI | E17: SI | F17: Emisión Constancias de Exención de IVA -CIVA- Información para que contribuyentes exentos (artículo 8 Ley del IVA) generen -CIVA-.
B18: 10 | C18: https://portal.sat.gob.gt/portal/consulta-de-gestion-del-contribuyente/ | D18: SI | E18: SI | F18: Estado de Gestión de Agencia Virtual Para verificar el estado de la gestión sobre la solicitud de Agencia Virtual, recuperación de contraseña o cambio de correo electrónico
B19: 11 | C19: https://portal.sat.gob.gt/portal/efactura/ | D19: SI | E19: SI | F19: Factura Electrónica Todo lo relacionado con la emisión, la documentación técnica, los certificadores y auditores del certificadores del Régimen de Factura Electrónica en Línea.
B20: 12 | C20: https://portal.sat.gob.gt/portal/forma-de-pago/ | D20: SI | E20: SI | F20: Formas de Pago Información sobre los bancos y otras formas de pago para realizar los mismos a SAT.
... B44: 36 | C44: https://portal.sat.gob.gt/portal/requisitos-de-vehiculos/#1541722263997-e0d7cba3-7daf | D44: SI | E44: SI | F44: Requisitos para el Traspaso de Vehículos ante la SAT Requisitos, listado de pasos y casos especiales, para el traspaso de vehículo en diferentes modalidades.
B46: 1 | C46: https://portal.sat.gob.gt/portal/requisitos-de-personas-empresas/#1573597244944-61668ad5-acf7 | D46: SI | F46: Requisitos sobre Formularios Electrónicos Solicitud Dev. C.F. Régimen Especial Electrónico y Régimen General Requisitos, listado de pasos, y casos especiales; para los formularios SAT-2125, SAT-2251 y SAT-2390.

Sheet Contribuyentes Especiales
C2: RESUMEN | D2: Medianos | E2: Grandes
C3: Total de Páginas consumidas por grupos de interés | D3: =+C6 -> 32
C4: Cantidad de páginas que consumen por igual todos los grupos de interés | D4: =+D6 -> 32 | E4: =+E6 -> 32
C6: =COUNTIF(C8:C39,"*") -> 32 | D6: =COUNTIF(D8:D39,"*") -> 32 | E6: =COUNTIF(E8:E39,"*") -> 32
B7: No. | C7: URL | D7: Medianos | E7: Grandes | F7: Descripción
B8: 1 | C8: https://farm3.sat.gob.gt/menu/login.jsf | D8: SI | E8: SI | F8: Agencia Virtual Para solicitar acceso, ingresar y realizar gestiones en linea, reinicio de contraseña, cambio de correo electrónico.
B9: 2 | C9: https://portal.sat.gob.gt/portal/libre-acceso-la-informacion-publica/ | D9: SI | E9: SI | F9: Acceso a la Información Pública Información relacionada para el cumplimiento de la Ley de Información Pública, así como la solicitud en idiomas español, Kaqchikel, Q'eqchi' y K'iche' y la Unidad de SAT que gestiona las solicitudes.
B10: 3 | C10: https://portal.sat.gob.gt/portal/tablas-y-acuerdos-vehiculos/ | D10: SI | E10: SI | F10: Acuerdos y Tablas de Valores de Vehículos Información relacionada a tablas y acuerdos de valores imponibles del Impuesto al Valor Agregado para la importación de vehículos.
B11: 4 | C11: https://portal.sat.gob.gt/portal/biblioteca-en-linea-sat/software/asistelight/ | D11: SI | E11: SI | F11: AsisteLight Información relacionada con la herramienta web, descarga y forma de uso.
B12: 5 | C12: https://portal.sat.gob.gt/portal/autoliquidacion/ | D12: SI | E12: SI | F12: Autoliquidación Cálculo de las sanciones a pagar por presentación y pago extemporáneo o rectificaciones.
B13: 6 | C13: https://portal.sat.gob.gt/portal/#capacitacion | D13: SI | E13: SI | F13: Capacitaciones Capacitaciones en diferentes modalidades y Cultura Tributaria sobre temas relacionados a Contribuyentes Especiales.
B14: 7 | C14: https://portal.sat.gob.gt/portal/consulta-movimiento-convenio/ | D14: SI | E14: SI | F14: Consulta Facilidades de Pago Información sobre requisitos, consultas movimiento convenio y preguntas frecuentes.
B15: 8 | C15: https://portal.sat.gob.gt/portal/efactura/ | D15: SI | E15: SI | F15: Factura Electrónica Todo lo relacionado con la emisión, la documentación técnica, los certificadores y auditores del certificadores del Régimen de Factura Electrónica en Línea.
B16: 9 | C16: https://portal.sat.gob.gt/portal/biblioteca-en-linea-sat/legislacion-aduanera/ | D16: SI | E16: SI | F16: Legislación Aduanera Información sobre Acuerdos y Resoluciones en materia aduanera.
B17: 10 | C17: https://portal.sat.gob.gt/portal/biblioteca-en-linea-sat/legislacion-tributaria/ | D17: SI | E17: SI | F17: Legislación Tributaria Información sobre Acuerdos y Resoluciones en materia tributaria.
B18: 11 | C18: https://portal.sat.gob.gt/portal/precios-de-transferencia/ | D18: SI | E18: SI | F18: Precios de Transferencia Información relacionada a la declaración jurada anual del impuesto sobre la renta sobre partes relacionadas, guías técnicas y anexos.
B19: 12 | C19: https://portal.sat.gob.gt/portal/rtu-digital/ | D19: SI | E19: SI | F19: RTU Digital Información para realizar la inscripción o solicitud de NIT, actualización de datos y cese de actividades comerciales y/o de servicios.
... B39: 32 | C39: https://portal.sat.gob.gt/portal/requisitos-tramites-agencias/actualizacion-de-distintivos/ | D39: SI | E39: SI | F39: Requisitos para el Cambio de Placas Temporales Requisitos para el cambio de placa temporal del vehículo.

Sheet Importadores y Exportadores
C2: RESUMEN | D2: Importadores | E2: OEA | F2: Exportadores
C3: Total de Páginas consumidas por grupos de interés | D3: =COUNTIF(C10:C59,"*") -> 48
C4: Cantidad de páginas que consumen por igual todos los grupos de interés | D4: =COUNTIF(D10:D50,"*") -> 41 | E4: =COUNTIF(E10:E50,"*") -> 41 | F4: =COUNTIF(F10:F50,"*") -> 41
C5: Cantidad de páginas que consumen individualmente 2/3 de los grupos de interés | D5: 4 | E5: 4
E6: 1 | F6: 1
C7: Cantidad de páginas que consumen individualmente 1/3 de los grupos de interés | F7: =COUNTIF(F58:F59,"*") -> 2
C8: =COUNTIF(C10:C59,"*") -> 48 | D8: =COUNTIF(D10:D59,"*") -> 45 | E8: =COUNTIF(E10:E59,"*") -> 46 | F8: =COUNTIF(F10:F59,"*") -> 44
B9: No. | C9: URL | D9: Importadores | E9: OEA | F9: Exportadores | G9: Descripción
B10: 1 | C10: https://farm3.sat.gob.gt/menu/login.jsf | D10: SI | E10: SI | F10: SI | G10: Agencia Virtual Para solicitar acceso, ingresar y realizar gestiones en linea, reinicio de contraseña, cambio de correo electrónico.
B11: 2 | C11: https://portal.sat.gob.gt/portal/libre-acceso-la-informacion-publica/ | D11: SI | E11: SI | F11: SI | G11: Acceso a la Información Pública Información relacionada para el cumplimiento de la Ley de Información Pública, así como la solicitud en idiomas español, Kaqchikel, Q'eqchi' y K'iche' y la Unidad de SAT que gestiona las solicitudes.
B12: 3 | C12: https://portal.sat.gob.gt/portal/autoliquidacion/ | D12: SI | E12: SI | F12: SI | G12: Autoliquidación Cálculo de las sanciones a pagar por presentación y pago extemporáneo o rectificaciones.
B13: 4 | C13: https://portal.sat.gob.gt/portal/tablas-y-acuerdos-vehiculos/ | D13: SI | E13: SI | F13: SI | G13: Acuerdos y Tablas de Valores de Vehículos Información relacionada a tablas y acuerdos de valores imponibles del Impuesto al Valor Agregado para la importación de vehículos.
B14: 5 | C14: https://portal.sat.gob.gt/portal/#capacitacion | D14: SI | E14: SI | F14: SI | G14: Capacitaciones Capacitaciones en diferentes modalidades y Cultura Tributaria sobre temas relacionados a Importadores y Exportadores.
B15: 6 | C15: https://portal.sat.gob.gt/portal/consulta-movimiento-convenio/ | D15: SI | E15: SI | F15: SI | G15: Consulta Facilidades de Pago Información sobre requisitos, consultas movimiento convenio y preguntas frecuentes.
B16: 7 | C16: https://portal.sat.gob.gt/portal/consultas-aduanas/ | D16: SI | E16: SI | F16: SI | G16: Consultas de Aduanas Consultas sobre retención/liberación de documentos, manifiestos y contenedores; Documentos de transporte con Honduras y Sistema de cobro por Permanencia en el pais. Asignaciones a Rampa de revisión y Revisores, Arancel Integrado, Declaraciones de Mercancías. Registro de Admisión Temporal de Contenedores Terrestres y su ampliación. Transito pendiente. Monitoreo de Sistemas Informáticos de Aduanas.
B17: 8 | C17: https://portal.sat.gob.gt/portal/facilitacion-de-comercio/#1559325573466-1284efd5-2d1b | D17: SI | E17: SI | F17: SI | G17: Declaración Anticipada Información, resoluciones y procedimiento de orientación para la implementación de la declaración anticipada. Preguntas frecuentes.
B18: 9 | C18: https://portal.sat.gob.gt/portal/efactura/ | D18: SI | E18: SI | F18: SI | G18: Factura Electrónica Todo lo relacionado con la emisión, la documentación técnica, los certificadores y auditores del certificadores del Régimen de Factura Electrónica en Línea.
B19: 10 | C19: https://portal.sat.gob.gt/portal/biblioteca-en-linea-sat/legislacion-aduanera/ | D19: SI | E19: SI | F19: SI | G19: Legislación Aduanera Información sobre Acuerdos y Resoluciones en materia aduanera.
B20: 11 | C20: https://portal.sat.gob.gt/portal/biblioteca-en-linea-sat/legislacion-tributaria/ | D20: SI | E20: SI | F20: SI | G20: Legislación Tributaria Información sobre Acuerdos y Resoluciones en materia tributaria.
B21: 12 | C21: https://portal.sat.gob.gt/portal/programa-miad/ | D21: SI | E21: SI | F21: SI | G21: Programa MIAD Información sobre los componentes de procesos, infraestructura, tecnología, seguridad y recursos de la Modernización Integral Aduanera.
... B50: 41 | C50: https://portal.sat.gob.gt/portal/requisitos-de-vehiculos/#1662393570133-d90819b2-32d3 | D50: SI | E50: SI | F50: SI | G50: Requisitos para el Cambio de Placas Temporales Requisitos para el cambio de placa temporal del vehículo.
B52: 1 | C52: https://portal.sat.gob.gt/portal/programa-miad/componente-procesos/importacion/#1623281268015-fb939ea7-9dfb | D52: SI | E52: SI | G52: Importación Conceptos generales sobre importación de mercancias y buenas practicas sugeridas desde la Modernización Integral Aduanera.
B53: 2 | C53: https://portal.sat.gob.gt/portal/programa-miad/componente-procesos/importacion/#1623281274865-df599d08-4b3c | D53: SI | E53: SI | G53: Pasos previos a tu importación de mercancías vía aérea Información sobre requisitos, consideraciones, documentos necesarios y procesos con los pasos previos a una importación definitiva desde el marco de la Modernización Integral Aduanera.
B54: 3 | C54: https://portal.sat.gob.gt/portal/procedimientos-aduanas/#1555105576411-b2abec85-7665 | D54: SI | E54: SI | G54: Sistema de Franquicias Electrónicas Información sobre documentación técnica de orientación al usuario externo para solicitudes de Franquicia Electrónica y videos informativos.
B55: 4 | C55: https://portal.sat.gob.gt/portal/requisitos-de-aduanas/#1542142298663-bee160b4-5362 | D55: SI | E55: SI | G55: Requisitos sobre documentos para Importación y Admisión Temporal Información y requisitos sobre recepción de seguro de caución de importacion y admisión temporal, presentación de mercancia de importación y admisiones temporales para cargos y fianzas y requisitos para la importación temporal de vehículos de turismo.
B56: 5 | C56: https://portal.sat.gob.gt/portal/requisitos-tramites-agencias/cambio-de-regimen-optativo-al-regimen-especial-de-devolucion-de-credito-fiscal-de-iva-por-exportaciones/ | E56: SI | F56: SI | G56: Requisitos para el Cambio de Regímenes Requisitos, listado de pasos, y casos especiales; para el cambio de régimen optativo al régimen especial de devolución de crédito fiscal de IVA por exportaciones.
B58: 1 | C58: https://portal.sat.gob.gt/portal/consulta-de-solicitudes-de-devolucion-de-credito-fiscal-regimen-general/ | F58: SI | G58: Consulta de Devolucion de Crédito Fiscal Régimen General Información sobre solicitudes de crédito fiscal de régimen general pendientes de atención.
B59: 2 | C59: https://portal.sat.gob.gt/portal/requisitos-de-personas-empresas/#1541710775060-c48ed303-d21d | F59: SI | G59: Requisitos para el Cambio de Regímenes Información sobre los requisitos para el registro exportadores en Agencia Virtual, inscripción al régimen habitual de exportación, actualización, inscripción, inactivación, permisos temporales y devolución de crédito fiscal en el registro de exportadores.

Sheet Exentos
C3: RESUMEN | D3: Constitucionales | E3: No Lucrativos | F3: Decreto | G3: ZOLIC | H3: Municipalidades
C4: Total de Páginas consumidas por grupo de interés | D4: =COUNTIF(Exentos16[URL],"*") -> 49
C5: Cantidad de páginas que consumen por igual 4/5 de los grupos de interés | D5: 24 | E5: 24 | F5: 24 | H5: 24
C6: Cantidad de páginas que consumen por igual 3/5 de los grupos de interés | D6: 3 | F6: 3 | H6: 3
D7: 1 | E7: 1 | G7: 1
D8: 1 | E8: 1 | F8: 1
C9: Cantidad de páginas que consumen individualmente 2/5 de los grupos de interés | F9: 1 | H9: 1
F10: 2 | G10: 2
E11: 1 | F11: 1
C12: Cantidad de páginas que consumen individualmente 1/5 de los grupos de interés | F12: 1
G13: 1
F14: 1
H15: 2
F16: 1
H17: 2
G18: 1
F19: 1
H20: 1
G21: 1
F22: 3
E23: 1
C25: =COUNTIF(Exentos16[URL],"*") -> 49 | D25: =COUNTIF(Exentos16[Constitucionales],"SI") -> 29 | E25: =COUNTIF(Exentos16[No Lucrativos],"SI") -> 28 | F25: =COUNTIF(Exentos16[Decreto],"SI") -> 39 | G25: =COUNTIF(Exentos16[ZOLIC],"SI") -> 6 | H25: =COUNTIF(Exentos16[Municipalidades],"SI") -> 33
B26: No. | C26: URL | D26: Constitucionales | E26: No Lucrativos | F26: Decreto | G26: ZOLIC | H26: Municipalidades | I26: Descripción
B27: 1 | C27: https://portal.sat.gob.gt/portal/libre-acceso-la-informacion-publica/ | D27: SI | E27: SI | F27: SI | H27: SI | I27: Acceso a la Información Pública Información relacionada para el cumplimiento de la Ley de Información Pública, así como la solicitud en idiomas español, Kaqchikel, Q'eqchi' y K'iche' y la Unidad de SAT que gestiona las solicitudes.
B28: 2 | C28: https://portal.sat.gob.gt/portal/autoliquidacion/ | D28: SI | E28: SI | F28: SI | H28: SI | I28: Autoliquidación Cálculo de las sanciones a pagar por presentación y pago extemporáneo o rectificaciones.
B29: 3 | C29: https://portal.sat.gob.gt/portal/#capacitacion | D29: SI | E29: SI | F29: SI | H29: SI | I29: Capacitaciones Capacitaciones en diferentes modalidades y Cultura Tributaria sobre temas relacionados a Contribuyentes Exentos.
B30: 4 | C30: https://portal.sat.gob.gt/portal/consulta-movimiento-convenio/ | D30: SI | E30: SI | F30: SI | H30: SI | I30: Consulta Facilidades de Pago Información sobre requisitos, consultas movimiento convenio y preguntas frecuentes.
B31: 5 | C31: https://portal.sat.gob.gt/portal/listado-de-contribuyentes-morosos/ | D31: SI | E31: SI | F31: SI | H31: SI | I31: Listado de Contribuyentes Morosos Expedientes con adeudo tributario en fase judicial, Intendencia de Asuntos Jurídicos
B32: 6 | C32: https://portal.sat.gob.gt/portal/bitacora-de-solvencia-fiscal/ | D32: SI | E32: SI | F32: SI | H32: SI | I32: Solvencia Fiscal Para consultar la gestión de la Solvencia Fiscal en línea.
B33: 7 | C33: https://portal.sat.gob.gt/portal/solvencia-fiscal/ | D33: SI | E33: SI | F33: SI | H33: SI | I33: Solvencia Fiscal Consultas de la gestión y el pago de la solicitud.
B34: 8 | C34: https://portal.sat.gob.gt/portal/tasas-e-intereses/ | D34: SI | E34: SI | F34: SI | H34: SI | I34: Tasas e Intereses Información relacionada a las tasas de intereses que estipula la Junta Monetaria para cada semestre del año, y la tasa de mora correspondiente.
B35: 9 | C35: https://portal.sat.gob.gt/portal/preguntas-frecuentes/cumplimiento-tributario/#1528240031207-3ce9866a-9863 | D35: SI | E35: SI | F35: SI | H35: SI | I35: Preguntas Frecuentes sobre Facilidades de Pago Preguntas frecuentes y respuestas sobre bases legales, plazos de emisión, solicitud y formularios de facilidades de pago.
B36: 10 | C36: https://portal.sat.gob.gt/portal/preguntas-frecuentes/cumplimiento-tributario/#1652906579852-40d8e272-35bb | D36: SI | E36: SI | F36: SI | H36: SI | I36: Preguntas Frecuentes sobre Solvencia Fiscal -S0FI- Preguntas frecuentes y respuestas sobre bases legales, plazos de emisión, solicitud, oblicaciones pendientes, y formularios de solvencia fiscal.
B37: 11 | C37: https://portal.sat.gob.gt/portal/recepcion-de-objeciones-y-recomendaciones-procedimientos-de-la-sat/objeciones-y-recomendaciones-a-los-procedimientos-de-la-intendencia-de-asuntos-juridicos/ | D37: SI | E37: SI | F37: SI | H37: SI | I37: Observaciones y recomendaciones a procedimientos de la Intedencia de Asuntos Jurídicos Sección a visualizar los procedimientos de SAT en proceso de creación o actualización, donde se puede objetar y recomendar previo a su aprobación.
B38: 12 | C38: https://portal.sat.gob.gt/portal/requisitos-tramites-notarios/#1541778875468-83ddfd67-082d | D38: SI | E38: SI | F38: SI | H38: SI | I38: Requisitos para Avisos de Notarios Requisitos para el aviso de legalización de firmas en certificado de propiedad de vehículos y aviso de transferencia de dominio de vehículos.
... B50: 24 | C50: https://portal.sat.gob.gt/portal/requisitos-de-vehiculos/#1541722263997-e0d7cba3-7daf | D50: SI | E50: SI | F50: SI | H50: SI | I50: Requisitos para el Traspaso de Vehículos ante la SAT Requisitos, listado de pasos y casos especiales, para el traspaso de vehículo en diferentes modalidades.
B52: 1 | C52: https://portal.sat.gob.gt/portal/tablas-y-acuerdos-vehiculos/ | D52: SI | F52: SI | H52: SI | I52: Acuerdos y Tablas de Valores de Vehículos Información relacionada a tablas y acuerdos de valores imponibles del Impuesto al Valor Agregado para la importación de vehículos.
B53: 2 | C53: https://portal.sat.gob.gt/portal/biblioteca-en-linea-sat/legislacion-aduanera/ | D53: SI | F53: SI | H53: SI | I53: Legislación Aduanera Información sobre Acuerdos y Resoluciones en materia aduanera.
B54: 3 | C54: https://portal.sat.gob.gt/portal/biblioteca-en-linea-sat/legislacion-tributaria/ | D54: SI | F54: SI | H54: SI | I54: Legislación Tributaria Información sobre Acuerdos y Resoluciones en materia tributaria.
B55: 4 | C55: https://portal.sat.gob.gt/portal/requisitos-de-personas-empresas/#1541621044169-4198d06d-693f | D55: SI | E55: SI | G55: SI | I55: Requisitos para la Actualización RTU Requisitos sobre actualización de actividad economica, afiliaciones, cooperativa, datos de identificación, domicilio fiscal, entidades del estado, federaciones deportivas, datos de establecimiento, cambio de regimenes, nombramiento o cambio de peritos contadores y representantes legales.
B56: 5 | C56: https://portal.sat.gob.gt/portal/requisitos-de-vehiculos/#1541780077723-c74e470e-b935 | D56: SI | E56: SI | F56: SI | I56: Requisitos sobre Traspaso Electrónico de Vehículos a través de Notarios Información sobre traspaso electrónico de vehículos por notario con anexo del certificado de propiedad emitido vía Declaraguate en Agencia Virtual, entrega de documentos de traspaso electrónico en Agencia Virtual y Requisitos para remitir documentación electrónica o digital de TEV.
B58: 1 | C58: https://portal.sat.gob.gt/portal/operador-economico-autorizado/ | F58: SI | H58: SI | I58: Operador Económico Autorizado Información sobre proceso de habilitación, marco normativo, controles administrativos y operacionales, actores OEA habilitados, documentos generales, manuales e instructivos del operador económico autorizado.
B59: 2 | C59: https://portal.sat.gob.gt/portal/procedimientos-aduanas/ | F59: SI | G59: SI | I59: Declaración de mercancías Información sobre la declaración única centroamericana DUCA, declaración única aduanera, aduana sin papeles y su instructivo, codificación de documentos digitalizados y la declaración de valor.
B60: 3 | C60: https://portal.sat.gob.gt/portal/manual-de-procedimientos-de-la-intendencia-de-aduanas/ | F60: SI | G60: SI | I60: Procedimientos de la Intendencia de Aduanas (Manuales) Información aplicable en los Depósitos Aduaneros Temporales; sobre autorización, registro, gestiones o autorizaciones especiales, gestión de carga, despacho y gestión posterior.
B61: 4 | C61: https://portal.sat.gob.gt/portal/requisitos-de-personas-empresas/#1615485066841-639e67c5-51e3 | E61: SI | F61: SI | I61: Requisitos para la Inscripción RTU Requisitos para la solicitud electronica de NIT, incripción de NIT con y sin obligaciones, inscripción de copropiedad, sociedades, cooperativas, fideicomiso, sindicato, entidad estatal, univerisidad privada, iglesia católica e inscripción de organizaciones no gubernamentales.
B63: 1 | C63: https://portal.sat.gob.gt/portal/aduana-sin-papeles/ | F63: SI | I63: Aduana Sin Papeles Información sobre el objetivo, pilares y alcance de la digitalización de las Declaraciones de Mercancías para la eliminación progresiva del uso de papel.
B64: 2 | C64: https://portal.sat.gob.gt/portal/convenios-interinstitucionales-sat/ | G64: SI | I64: Convenios Interinstitucionales Información sobre convenios de SAT con otras instituciones, fecha de suscripción, finalización y estatus.
B65: 3 | C65: https://portal.sat.gob.gt/portal/consultas-aduanas/ | F65: SI | I65: Consultas de Aduanas Consultas sobre retención/liberación de documentos, manifiestos y contenedores; Documentos de transporte con Honduras y Sistema de cobro por Permanencia en el pais. Asignaciones a Rampa de revisión y Revisores, Arancel Integrado, Declaraciones de Mercancías. Registro de Admisión Temporal de Contenedores Terrestres y su ampliación. Transito pendiente. Monitoreo de Sistemas Informáticos de Aduanas.
B66: 4 | C66: https://portal.sat.gob.gt/portal/emision-constancias-de-exencion-de-iva-civa/ | H66: SI | I66: Emisión Constancias de Exención de IVA -CIVA- Información para que contribuyentes exentos (artículo 8 Ley del IVA) generen -CIVA-.
B67: 5 | C67: https://portal.sat.gob.gt/portal/efactura/ | H67: SI | I67: Factura Electrónica Todo lo relacionado con la emisión, la documentación técnica, los certificadores y auditores del certificadores del Régimen de Factura Electrónica en Línea.
B68: 6 | C68: https://portal.sat.gob.gt/portal/facilitacion-de-comercio/ | F68: SI | I68: Facilitación de Comercio Información sobre Acuerdos, Estudios, Valoración de Mercancias, Procedimientos, Unión Aduanera, Consulta Pública, Declaración Anticipada y la No Exigibilidad de la declaraciones sobre las mismas, para la Facilitación de Comercio.
B69: 7 | C69: https://portal.sat.gob.gt/portal/sistemas-web/retencioneswebisr/ | H69: SI | I69: Sistema Retenciones Web -ISR- Información sobre el uso de la herramienta, incorporación, delegación de permisos y manuales de usuario para usuarios del sector público.
B70: 8 | C70: https://portal.sat.gob.gt/portal/sistemas-web/retencioneswebiva/ | H70: SI | I70: Sistema Retenciones Web -IVA- Información sobre el uso de la herramienta, porcentajes de retención, listado de agentes de retención del impuesto y canales de consultas.
B71: 9 | C71: https://portal.sat.gob.gt/portal/ubicacion-y-horario-de-aduanas/ | G71: SI | I71: Ubicación y horario de Aduanas Ubicaciones, contacto teléfono, horarios y servicios que prestan las diferentes aduanas a nivel nacional.
B72: 10 | C72: https://portal.sat.gob.gt/portal/union-aduanera/ | F72: SI | I72: Unión Aduanera Información sobre la historia, resoluciones y procedimientos de la Unión Aduanera entre Guatemala y Honduras.
B73: 11 | C73: https://portal.sat.gob.gt/portal/preguntas-frecuentes/cumplimiento-tributario/#1674938805376-f6c4abc5-cfda | H73: SI | I73: Preguntas Frecuentes sobre Factura Electrónica -FEL- Preguntas frecuentes y respuestas sobre el régimen de factura electrónica en línea, documentos tribuarios electrónicos y la aplicacion FEL.
B74: 12 | C74: https://portal.sat.gob.gt/portal/preguntas-frecuentes/temas-aduaneros/#1712605946821-b4e512b4-6c69 | G74: SI | I74: Preguntas Frecuentes sobre el Marchamo Electrónico Preguntas frecuentes y respuestas sobre marchamo electrónico y en que aduanas lo utilizan.
B75: 13 | C75: https://portal.sat.gob.gt/portal/recepcion-de-objeciones-y-recomendaciones-procedimientos-de-la-sat/objeciones-y-recomendaciones-a-los-procedimientos-de-la-intendencia-de-aduanas/ | F75: SI | I75: Objeciones y Recomendaciones a los procedimientos de la Intendencia de Aduanas Sección a visualizar los procedimientos de SAT en proceso de creación o actualización, donde se puede objetar y recomendar previo a su aprobación.
B76: 14 | C76: https://portal.sat.gob.gt/portal/documentacion-a-presentar-ante-la-aduana-de-vehiculos-trifoliar/ | F76: SI | I76: Documentación a presentar ante la Aduana de Vehículos para la revisión de los vehículos según solicitud Información sobre quienes pueden solicitar la revisión de vehículos, que deben presentar y como comprobar el valor de la transacción.
B77: 15 | C77: https://portal.sat.gob.gt/portal/requisitos-tramites-aduanas/solicitud-de-renovacion-de-auxiliares-de-la-funcion-publica-en-unidad-de-calificacion-registro-y-control-de-auxiliares-de-la-funcion-publica/ | F77: SI | I77: Requisitos para la Solicitud de Renovación de Auxiliar de la Función Pública en la Unidad de Administración de Auxiliares de la Función Pública Aduanera Requisitos para auxiliares de la función pública aduanera y su representante legal, lista de pasos y casos especiales.
B78: 16 | C78: https://portal.sat.gob.gt/portal/requisitos-de-personas-empresas/#1541698042332-5a32c823-6bb4 | E78: SI | I78: Requisitos para Cancelación de Negocios Requisitos para cese por prescripción, cese de negocios inscritos bajo diferentes modalidades, Cese de NIT administrativo jurídico y habilitación de actividades con cancelación temporal.

Sheet Terceras Personas
C2: RESUMEN | D2: Gestores Tributarios | E2: Auxiliar Tributario | F2: Abogados y Notarios | G2: Peritos Contadores | H2: Auditores
C3: Total de Páginas consumidas por grupo de interés | D3: =+C10 -> 62
C4: Cantidad de páginas que consumen por igual todos los grupos de interés | D4: 53 | E4: 53 | F4: 53 | G4: 53 | H4: 53
C5: Cantidad de páginas que consumen por igual 3/5 de los grupos de interés | F5: 6 | G5: 6 | H5: 6
C6: Cantidad de páginas que consumen por igual 2/5 de los grupos de interés | F6: 1 | G6: 1
C7: Cantidad de páginas que consumen individualmente 1/5 de los grupos de interés | G7: 1
F8: 1
C10: =COUNTA(C12:C76) -> 62 | D10: =COUNTIF(D12:D76,"SI") -> 53 | E10: =COUNTIF(E12:E76,"SI") -> 53 | F10: =COUNTIF(F12:F76,"SI") -> 61 | G10: =COUNTIF(G12:G76,"SI") -> 61 | H10: =COUNTIF(H12:H76,"SI") -> 59
B11: No. | C11: URL | D11: Gestores Tributarios | E11: Auxiliar Tributario | F11: Abogados y Notarios | G11: Peritos Contadores | H11: Auditores | I11: Descripción
B12: 1 | C12: https://farm3.sat.gob.gt/menu/login.jsf | D12: SI | E12: SI | F12: SI | G12: SI | H12: SI | I12: Agencia Virtual Para solicitar acceso, ingresar y realizar gestiones en linea, reinicio de contraseña, cambio de correo electrónico.
B13: 2 | C13: https://portal.sat.gob.gt/portal/libre-acceso-la-informacion-publica/ | D13: SI | E13: SI | F13: SI | G13: SI | H13: SI | I13: Acceso a la Información Pública Información relacionada para el cumplimiento de la Ley de Información Pública, así como la solicitud en idiomas español, Kaqchikel, Q'eqchi' y K'iche' y la Unidad de SAT que gestiona las solicitudes.
B14: 3 | C14: https://portal.sat.gob.gt/portal/tablas-y-acuerdos-vehiculos/ | D14: SI | E14: SI | F14: SI | G14: SI | H14: SI | I14: Acuerdos y Tablas de Valores de Vehículos Información relacionada a tablas y acuerdos de valores imponibles del Impuesto al Valor Agregado para la importación de vehículos.
B15: 4 | C15: https://portal.sat.gob.gt/portal/sistemas-web/asistehospitalesweb/ | D15: SI | E15: SI | F15: SI | G15: SI | H15: SI | I15: Asiste Hospitales Web Información sobre el sistema para registrar los pagos a profesionales que brindan asistencias médicas en instituciónes, de parte de terceros.
B16: 5 | C16: https://portal.sat.gob.gt/portal/autoliquidacion/ | D16: SI | E16: SI | F16: SI | G16: SI | H16: SI | I16: Autoliquidación Cálculo de las sanciones a pagar por presentación y pago extemporáneo o rectificaciones.
B17: 6 | C17: https://portal.sat.gob.gt/portal/#capacitacion | D17: SI | E17: SI | F17: SI | G17: SI | H17: SI | I17: Capacitaciones Capacitaciones en diferentes modalidades y Cultura Tributaria sobre temas relacionados a Terceras Personas.
B18: 7 | C18: https://portal.sat.gob.gt/portal/consulta-movimiento-convenio/ | D18: SI | E18: SI | F18: SI | G18: SI | H18: SI | I18: Consulta Facilidades de Pago Información sobre requisitos, consultas movimiento convenio y preguntas frecuentes.
B19: 8 | C19: https://portal.sat.gob.gt/portal/consultas-aduanas/ | D19: SI | E19: SI | F19: SI | G19: SI | H19: SI | I19: Consultas de Aduanas Consultas sobre retención/liberación de documentos, manifiestos y contenedores; Documentos de transporte con Honduras y Sistema de cobro por Permanencia en el pais. Asignaciones a Rampa de revisión y Revisores, Arancel Integrado, Declaraciones de Mercancías. Registro de Admisión Temporal de Contenedores Terrestres y su ampliación. Transito pendiente. Monitoreo de Sistemas Informáticos de Aduanas.
B20: 9 | C20: https://portal.sat.gob.gt/portal/contacto/consultas-legales/ | D20: SI | E20: SI | F20: SI | G20: SI | H20: SI | I20: Consultas Legales Formulario y documentos para obtener orientación legal de la SAT
B21: 10 | C21: https://portal.sat.gob.gt/portal/retenciones-del-iva-consulta-de-constancias-de-retencion-del-iva-recibidas/ | D21: SI | E21: SI | F21: SI | G21: SI | H21: SI | I21: Consulta de constancias de retención del IVA e ISR recibidas Consulta para verificar la validez de las Constancias de Retención de IVA e ISR emitidas por el Agente Retenedor.
B22: 11 | C22: https://portal.sat.gob.gt/portal/criterios-institucionales/ | D22: SI | E22: SI | F22: SI | G22: SI | H22: SI | I22: Criterios Institucionales Histórico y normativa que crea y regula el funcionamiento de la Junta de Criterios Tributarios de la Superintendencia de Administración Tributaria.
B23: 12 | C23: https://portal.sat.gob.gt/portal/facilitacion-de-comercio/#1559325573466-1284efd5-2d1b | D23: SI | E23: SI | F23: SI | G23: SI | H23: SI | I23: Declaración Anticipada Información, resoluciones y procedimiento de orientación para la implementación de la declaración anticipada, así como peguntas frecuentes.
... B64: 53 | C64: https://portal.sat.gob.gt/portal/requisitos-tramites-agencias/despacho-de-distintivos-de-control-de-productos-importados-a-los-fabricantes-o-importadores-domiciliados-en-el-pais-y-a-las-personas-individuales-y-juridicas/ | D64: SI | E64: SI | F64: SI | G64: SI | H64: SI | I64: Requisitos para el Despacho de distintivos de control de productos importados a los fabricantes o importadores domiciliados en el país y a las personas individuales y jurídicas que no sean fabricantes ni importadores Requisitos y listado de pasos.
B66: 1 | C66: https://portal.sat.gob.gt/portal/efactura/ | F66: SI | G66: SI | H66: SI | I66: Factura Electrónica Todo lo relacionado con la emisión, certificador, documentación técnica, auditor del certificador, gráficos y preguntas frecuentes del Régimen de Factura Electrónica en Línea.
B67: 2 | C67: https://portal.sat.gob.gt/portal/sistemas-web/retencioneswebict/ | F67: SI | G67: SI | H67: SI | I67: Sistema Retenciones Web -ICT- Información y documentación de soporte sobre el sistema que tienen a disposición todas las personas individuales o jurídicas afiliadas al Impuesto a la Confianza Tributaria.
B68: 3 | C68: https://portal.sat.gob.gt/portal/sistemas-web/retencioneswebiva/ | F68: SI | G68: SI | H68: SI | I68: Sistema Retenciones Web -IVA- Información sobre el uso de la herramienta, porcentajes de retención, listado de agentes de retención del impuesto y canales de consultas.
B69: 4 | C69: https://portal.sat.gob.gt/portal/rtu-digital/ | F69: SI | G69: SI | H69: SI | I69: RTU Digital Información para realizar la inscripción o solicitud de NIT, actualización de datos y cese de actividades comerciales y/o de servicios.
B70: 5 | C70: https://portal.sat.gob.gt/portal/preguntas-frecuentes/contribuyentes-especiales/ | F70: SI | G70: SI | H70: SI | I70: Preguntas Frecuentes sobre Gestiones de Contribuyentes Especiales Preguntas frecuentes y respuestas sobre obligaciones de contribuyentes especiales, calificacion de agentes de retención del IVA, retenciones WEB, retenciones del ISR e IVA, sistema Reten ISR WEB 2, Herramienta informe electrónico de compras y ventas, entre otras.
B71: 6 | C71: https://portal.sat.gob.gt/portal/requisitos-tramites-agencias/solicitud-de-registro-de-personas-exentas-del-impuesto-a-la-distribucion-de-petroleo-crudo-y-combustibles-derivados-del-petroleo/ | F71: SI | G71: SI | H71: SI | I71: Requisitos para el Registro y Emisión de Autorización de la Superintendencia de Administración Tributaria al Impuesto a la Distribución de Petróleo Crudo y Combustible Derivados del Petróleo Requisitos, listado de pasos y casos especiales.
B73: 1 | C73: https://portal.sat.gob.gt/portal/biblioteca-en-linea-sat/software/ | F73: SI | G73: SI | I73: Descarga de Aplicaciones Información y descarga de AsisteLight, AsisteLibros2, RetenISR, Traspaso Electrónico por Notario y Reporte Semestral de Inventario. Informes del Impuesto Sobre la Renta anual de maquilas.
B75: 1 | C75: https://portal.sat.gob.gt/portal/consultas-aduanas/ | G75: SI | I75: Consultas de Aduanas Consultas sobre retención/liberación de documentos, manifiestos y contenedores; Documentos de transporte con Honduras y Sistema de cobro por Permanencia en el pais. Asignaciones a Rampa de revisión y Revisores, Arancel Integrado, Declaraciones de Mercancías. Registro de Admisión Temporal de Contenedores Terrestres y su ampliación. Transito pendiente. Monitoreo de Sistemas Informáticos de Aduanas.
B76: 2 | C76: https://portal.sat.gob.gt/portal/requisitos-tramites-notarios/ | F76: SI | I76: Requisitos gestiones vehículos para Notarios Verifica los requisitos indispensables como notario para realizar tus gestiones

Sheet Auxiliares Función Pública
C2: RESUMEN | D2: Courier | E2: Consolidadores y Desconsolidadores de Carga | F2: Almacenes Fiscales | G2: Almacenadoras | H2: Depósitos Aduaneros | I2: ZDEEP | J2: Agentes Aduaneros | K2: Transportistas | L2: Apoderado Especial Aduanero
C3: Total de Páginas consumidas por grupo de interés | D3: 50
C4: Cantidad de páginas que consumen por igual todos los grupos de interés | D4: 45 | E4: 45 | F4: 45 | G4: 45 | H4: 45 | I4: 45 | J4: 45 | K4: 45 | L4: 45
C5: Cantidad de páginas que consumen por igual 4/6 de los grupos de interés | D5: 1 | E5: 1 | J5: 1 | K5: 1
C6: Cantidad de páginas que consumen por igual 3/6 de los grupos de interés | D6: 1 | E6: 1 | J6: 1
C7: Cantidad de páginas que consumen por igual 2/6 de los grupos de interés | J7: 2 | K7: 2
D8: 1 | J8: 1
C10: =COUNTIF(AuxiliaresFunciónPública15[URL],"*") -> 50 | D10: =COUNTIF(AuxiliaresFunciónPública15[Courier],"*") -> 48 | E10: =COUNTIF(AuxiliaresFunciónPública15[Consolidadores y Desconsolidadores de Carga],"*") -> 47 | F10: =COUNTIF(AuxiliaresFunciónPública15[Almacenes Fiscales],"*") -> 45 | G10: =COUNTIF(AuxiliaresFunciónPública15[Almacenadoras],"*") -> 45 | H10: =COUNTIF(AuxiliaresFunciónPública15[Depósitos Aduaneros],"*") -> 45 | I10: =COUNTIF(AuxiliaresFunciónPública15[ZDEEP],"*") -> 45 | J10: =COUNTIF(AuxiliaresFunciónPública15[Agentes Aduaneros],"*") -> 50 | K10: =COUNTIF(AuxiliaresFunciónPública15[Transportistas],"*") -> 48 | L10: =COUNTIF(AuxiliaresFunciónPública15[Apoderado Especial Aduanero],"*") -> 45
B11: No. | C11: URL | D11: Courier | E11: Consolidadores y Desconsolidadores de Carga | F11: Almacenes Fiscales | G11: Almacenadoras | H11: Depósitos Aduaneros | I11: ZDEEP | J11: Agentes Aduaneros | K11: Transportistas | L11: Apoderado Especial Aduanero | M11: Descripción
B12: 1 | C12: https://portal.sat.gob.gt/portal/libre-acceso-la-informacion-publica/ | D12: SI | E12: SI | F12: SI | G12: SI | H12: SI | I12: SI | J12: SI | K12: SI | L12: SI | M12: Acceso a la Información Pública Información relacionada para el cumplimiento de la Ley de Información Pública, así como la solicitud en idiomas español, Kaqchikel, Q'eqchi' y K'iche' y la Unidad de SAT que gestiona las solicitudes.
B13: 2 | C13: https://portal.sat.gob.gt/portal/tablas-y-acuerdos-vehiculos/ | D13: SI | E13: SI | F13: SI | G13: SI | H13: SI | I13: SI | J13: SI | K13: SI | L13: SI | M13: Acuerdos y Tablas de Valores de Vehículos Información relacionada a tablas y acuerdos de valores imponibles del Impuesto al Valor Agregado para la importación de vehículos.
B14: 3 | C14: https://portal.sat.gob.gt/portal/autoliquidacion/ | D14: SI | E14: SI | F14: SI | G14: SI | H14: SI | I14: SI | J14: SI | K14: SI | L14: SI | M14: Autoliquidación Cálculo de las sanciones a pagar por presentación y pago extemporáneo o rectificaciones.
B15: 4 | C15: https://portal.sat.gob.gt/portal/#capacitacion | D15: SI | E15: SI | F15: SI | G15: SI | H15: SI | I15: SI | J15: SI | K15: SI | L15: SI | M15: Capacitaciones Capacitaciones en diferentes modalidades y Cultura Tributaria sobre temas relacionados a Auxiliares de la Función Pública.
B16: 5 | C16: https://portal.sat.gob.gt/portal/consulta-movimiento-convenio/ | D16: SI | E16: SI | F16: SI | G16: SI | H16: SI | I16: SI | J16: SI | K16: SI | L16: SI | M16: Consulta Facilidades de Pago Información sobre requisitos, consultas movimiento convenio y preguntas frecuentes.
B17: 6 | C17: https://portal.sat.gob.gt/portal/consultas-aduanas/ | D17: SI | E17: SI | F17: SI | G17: SI | H17: SI | I17: SI | J17: SI | K17: SI | L17: SI | M17: Consultas de Aduanas Consultas sobre retención/liberación de documentos, manifiestos y contenedores; Documentos de transporte con Honduras y Sistema de cobro por Permanencia en el pais. Asignaciones a Rampa de revisión y Revisores, Arancel Integrado, Declaraciones de Mercancías. Registro de Admisión Temporal de Contenedores Terrestres y su ampliación. Transito pendiente. Monitoreo de Sistemas Informáticos de Aduanas.
B18: 7 | C18: https://portal.sat.gob.gt/portal/facilitacion-de-comercio/#1559325573466-1284efd5-2d1b | D18: SI | E18: SI | F18: SI | G18: SI | H18: SI | I18: SI | J18: SI | K18: SI | L18: SI | M18: Declaración Anticipada Información, resoluciones y procedimiento de orientación para la implementación de la declaración anticipada. Preguntas frecuentes.
B19: 8 | C19: https://portal.sat.gob.gt/portal/estadisticas-tributarias-sat/ | D19: SI | E19: SI | F19: SI | G19: SI | H19: SI | I19: SI | J19: SI | K19: SI | L19: SI | M19: Estadísticas Tributarias SAT Información de carácter estadístico y puede ser utilizada con fines de análisis tributario;
B20: 9 | C20: https://portal.sat.gob.gt/portal/efactura/ | D20: SI | E20: SI | F20: SI | G20: SI | H20: SI | I20: SI | J20: SI | K20: SI | L20: SI | M20: Factura Electrónica Todo lo relacionado con la emisión, la documentación técnica, los certificadores y auditores del certificadores del Régimen de Factura Electrónica en Línea.
B21: 10 | C21: https://portal.sat.gob.gt/portal/biblioteca-en-linea-sat/legislacion-aduanera/ | D21: SI | E21: SI | F21: SI | G21: SI | H21: SI | I21: SI | J21: SI | K21: SI | L21: SI | M21: Legislación Aduanera Información sobre Acuerdos y Resoluciones en materia aduanera
B22: 11 | C22: https://portal.sat.gob.gt/portal/biblioteca-en-linea-sat/legislacion-tributaria/ | D22: SI | E22: SI | F22: SI | G22: SI | H22: SI | I22: SI | J22: SI | K22: SI | L22: SI | M22: Legislación Tributaria Información sobre Acuerdos y Resoluciones en materia tributaria
B23: 12 | C23: https://portal.sat.gob.gt/portal/listado-de-contribuyentes-morosos/ | D23: SI | E23: SI | F23: SI | G23: SI | H23: SI | I23: SI | J23: SI | K23: SI | L23: SI | M23: Listado de Contribuyentes Morosos Expedientes con adeudo tributario en fase judicial, Intendencia de Asuntos Jurídicos
... B56: 45 | C56: https://portal.sat.gob.gt/portal/requisitos-de-vehiculos/#1662393570133-d90819b2-32d3 | D56: SI | E56: SI | F56: SI | G56: SI | H56: SI | I56: SI | J56: SI | K56: SI | L56: SI | M56: Requisitos para el Cambio de Placas Temporales Requisitos para el cambio de placa temporal del vehículo.
B58: 1 | C58: https://portal.sat.gob.gt/portal/franquicias-electronicas/ | D58: SI | E58: SI | J58: SI | K58: SI | M58: Sistema de Franquicias Electrónicas Información sobre documentación técnica de orientación al usuario externo para solicitudes de Franquicia Electrónica y videos informativos.
B60: 1 | C60: https://portal.sat.gob.gt/portal/programa-miad/componente-procesos-2/importacion/ | D60: SI | E60: SI | J60: SI | M60: Importación Conceptos Generales sobre importación de mercancias y buenas practicas sugeridas desde la Modernización Integral Aduanera.
B62: 1 | C62: https://portal.sat.gob.gt/portal/puestos-de-control-interinstitucional-pci/ | J62: SI | K62: SI | M62: Puestos de Control Interinstitucional -PCI- Información sobre Puestos de Control Interinstitucional y sus ubicaciones.
B63: 2 | C63: https://portal.sat.gob.gt/portal/programa-miad/sistemas-de-video-vigilancia-cctv/ | J63: SI | K63: SI | M63: Visualización de operaciones en el Puesto Fronterizo Pedro de Alvarado – La Hachadura Movimiento de transporte en las aduanas en el marco de la Estrategia Centroamericana de Facilitación de Comercio.
B64: 3 | C64: https://portal.sat.gob.gt/portal/requisitos-tramites-agencias/recepcion-de-seguro-de-caucion-importacion-y-admision-temporal/ | D64: SI | J64: SI | M64: Recepción de seguro de caución importacion y admisión temporal Requisitos, listado de pasos y casos especiales para Contribuyente, Agente Aduanero, Representante Legal y Mandatario.

Sheet Entidades del Estado
C2: RESUMEN | D2: Organismo Judicial | E2: Ministerio Público | F2: SENABED / CONABED | G2: Procuraduría de los Derechos Humanos
C3: Total de Páginas consumidas por grupo de interés | D3: =+C5 -> 26
C5: =COUNTIF(C7:C32,"*") -> 26 | D5: =COUNTIF(D7:D32,"*") -> 26 | E5: =COUNTIF(E7:E32,"*") -> 26 | F5: =COUNTIF(F7:F32,"*") -> 26 | G5: =COUNTIF(G7:G32,"*") -> 26
B6: No. | C6: URL | D6: Organismo Judicial | E6: Ministerio Público | F6: SENABED / CONABED | G6: Procuraduría de los Derechos Humanos | H6: Descripción
B7: 1 | C7: https://portal.sat.gob.gt/portal/libre-acceso-la-informacion-publica/ | D7: SI | E7: SI | F7: SI | G7: SI | H7: Acceso a la Información Pública Información relacionada para el cumplimiento de la Ley de Información Pública, así como la solicitud en idiomas español, Kaqchikel, Q'eqchi' y K'iche' y la Unidad de SAT que gestiona las solicitudes.
B8: 2 | C8: https://portal.sat.gob.gt/portal/tablas-y-acuerdos-vehiculos/ | D8: SI | E8: SI | F8: SI | G8: SI | H8: Acuerdos y Tablas de Valores de Vehículos Información relacionada a tablas y acuerdos de valores imponibles del Impuesto al Valor Agregado para la importación de vehículos.
B9: 3 | C9: https://portal.sat.gob.gt/portal/autoliquidacion/ | D9: SI | E9: SI | F9: SI | G9: SI | H9: Autoliquidación Cálculo de las sanciones a pagar por presentación y pago extemporáneo o rectificaciones.
B10: 4 | C10: https://portal.sat.gob.gt/portal/#capacitacion | D10: SI | E10: SI | F10: SI | G10: SI | H10: Capacitaciones Capacitaciones en diferentes modalidades y Cultura Tributaria sobre temas relacionados a Entidad del Estado.
B11: 5 | C11: https://portal.sat.gob.gt/portal/emision-constancias-de-eSIencion-de-iva-civa/ | D11: SI | E11: SI | F11: SI | G11: SI | H11: Emisión Constancias de Exención de IVA -CIVA- Información para contribuyentes exentos (artículo 8 Ley del IVA) generen -CIVA- a través de la Agencia Virtual SAT en Factura Electrónica en Línea -FEL-.
B12: 6 | C12: https://portal.sat.gob.gt/portal/efactura/ | D12: SI | E12: SI | F12: SI | G12: SI | H12: Factura Electrónica Todo lo relacionado con la emisión, la documentación técnica, los certificadores y auditores del certificadores del Régimen de Factura Electrónica en Línea.
B13: 7 | C13: https://portal.sat.gob.gt/portal/biblioteca-en-linea-sat/legislacion-tributaria/ | D13: SI | E13: SI | F13: SI | G13: SI | H13: Legislación Tributaria Información sobre Acuerdos y Resoluciones en materia tributaria
B14: 8 | C14: https://portal.sat.gob.gt/portal/biblioteca-en-linea-sat/legislacion-aduanera/ | D14: SI | E14: SI | F14: SI | G14: SI | H14: Legislación Aduanera Información sobre Acuerdos y Resoluciones en materia aduanera.
B15: 9 | C15: https://portal.sat.gob.gt/portal/planilla-iva-fel/ | D15: SI | E15: SI | F15: SI | G15: SI | H15: Planilla IVA-FEL Información sobre los pasos para presentar tu Planilla de IVA – FEL y manual de uso.
B16: 10 | C16: https://portal.sat.gob.gt/portal/sistemas-web/retencioneswebisr/ | D16: SI | E16: SI | F16: SI | G16: SI | H16: Sistema Retenciones Web -ISR- Información sobre el uso de la herramienta, incorporación, delegación de permisos y manuales de usuario para usuarios del sector público.
B17: 11 | C17: https://portal.sat.gob.gt/portal/sistemas-web/retencioneswebiva/ | D17: SI | E17: SI | F17: SI | G17: SI | H17: Sistema Retenciones Web -IVA- Información sobre el uso de la herramienta, porcentajes de retención, listado de agentes de retención del impuesto y canales de consultas.
B18: 12 | C18: https://portal.sat.gob.gt/portal/tasas-e-intereses/ | D18: SI | E18: SI | F18: SI | G18: SI | H18: Tasas e Intereses Información relacionada a las tasas de intereses que estipula la Junta Monetaria para cada semestre del año, y la tasa de mora correspondiente.
... B32: 26 | C32: https://portal.sat.gob.gt/portal/requisitos-de-vehiculos/#1541722263997-e0d7cba3-7daf | D32: SI | E32: SI | F32: SI | G32: SI | H32: Requisitos para el Traspaso de Vehículos ante la SAT Requisitos, listado de pasos y casos especiales, para el traspaso de vehículo en diferentes modalidades.
